Workbook

Sheet EERR RODEO
A2: ESTADO DE RESULTADOS
A3: PARTIDAS | B3: =IF(ISBLANK(A2),"",YEAR(TODAY())-1) -> 2025 | C3: % Vtas | D3: % Gastos | E3: ENE | F3: % Vtas | G3: % Gastos | H3: FEB | I3: % Vtas | J3: % Gastos | K3: Vari Rel. | L3: ACUM EJEC | M3: % Vtas | N3: % Gastos | O3: MAR | P3: % Vtas | Q3: % Gastos | R3: Vari Rel. | S3: ACUM EJEC | T3: % Vtas | U3: % Gastos | V3: ACUM PPTO | W3: % Vtas | X3: Var PPTO | Y3: ABR | Z3: % Vtas | AA3: % Gastos | AB3: Vari Rel. | AC3: ACUM EJEC | AD3: % Vtas | AE3: % Gastos | AF3: MAY | AG3: % Vtas | AH3: % Gastos | AI3: Vari Rel. | AJ3: ACUM EJEC | AK3: % Vtas | AL3: % Gastos | AM3: JUN | AN3: % Vtas | AO3: % Gastos | AP3: Vari Rel. | AQ3: ACUM EJEC | AR3: % Vtas | AS3: % Gastos | AT3: ACUM PPTO | AU3: % Vtas | AV3: Var PPTO | AW3: PROM 6 EJEC | AX3: % Vtas | AY3: % Gastos | AZ3: PROM 6 PPTO | BA3: % Vtas | BB3: Var PPTO | BC3: JUL | BD3: % Vtas | BE3: % Gastos | BF3: Vari Rel. | BG3: ACUM EJEC | BH3: % Vtas | BI3: % Gastos | BJ3: AGO | BK3: % Vtas | BL3: % Gastos | BM3: Vari Rel. | BN3: ACUM EJEC | BO3: % Vtas | BP3: % Gastos | BQ3: SEPT | BR3: % Vtas | BS3: % Gastos | BT3: Vari Rel. | BU3: ACUM EJEC | BV3: % Vtas | BW3: % Gastos | BX3: ACUM PPTO | BY3: % Vtas | BZ3: Var PPTO | CA3: OCT | CB3: % Vtas | CC3: % Gastos | CD3: Vari Rel. | CE3: ACUM EJEC | CF3: % Vtas | CG3: % Gastos | CH3: NOV | CI3: % Vtas | CJ3: % Gastos | CK3: Vari Rel. | CL3: ACUM EJEC | CM3: % Vtas | CN3: % Gastos | CO3: DIC | CP3: % Vtas | CQ3: % Gastos | CR3: Vari Rel. | CS3: 2025 | CT3: % Vtas | CU3: % Gastos | CV3: ACUM PPTO | CW3: % Vtas | CX3: Var PPTO
A4: Total Ingresos | B4: =+B5+B10+B15+B18 -> 0 | C4: =IF(AND(B4=0,B4>=0), "",B4/B4) | E4: =+E5+E10+E15+E18 -> 47933.03 | F4: =IF(AND(E4=0,E4>=0), "",E4/E4) -> 1 | H4: =+H5+H10+H15+H18 -> 51483.04 | I4: =IF(AND(H4=0,H4>=0), "",H4/H4) -> 1 | K4: =IF(AND(E4=0,H4>0),100%,IF(AND(E4<0,H4=0),(E4-H4)/E4,IF(AND(E4>0,H4>0),(H4-E4)/E4,IF(AND(E4=0,H4=0),"",(H4-E4)/E4)))) -> 0.074061873 | L4: =+L5+L10+L15+L18 -> 99416.07 | M4: =IF(AND(L4=0,L4>=0), "",L4/L4) -> 1 | O4: =+O5+O10+O15+O18 -> 64106.18 | P4: =IF(AND(O4=0,O4>=0), "",O4/O4) -> 1 | R4: =IF(AND(H4=0,O4>0),100%,IF(AND(H4<0,O4=0),(H4-O4)/H4,IF(AND(H4>0,O4>0),(O4-H4)/H4,IF(AND(H4=0,O4=0),"",(O4-H4)/H4)))) -> 0.24519026 | S4: =+S5+S10+S15+S18 -> 163522.25 | T4: =IF(AND(S4=0,S4>=0), "",S4/S4) -> 1 | V4: =+V5+V10+V15+V18 -> 0 | W4: =IF(AND(V4=0,V4>=0), "",V4/V4) | X4: =IF(AND(V4=0,S4>0),100%,IF(AND(V4<0,S4=0),(V4-S4)/V4,IF(AND(V4>0,S4>0),(S4-V4)/V4,IF(AND(V4=0,S4=0),"",(S4-V4)/V4)))) -> 1 | Y4: =+Y5+Y10+Y15+Y18 -> 0 | Z4: =IF(AND(Y4=0,Y4>=0), "",Y4/Y4) | AB4: =IF(AND(O4=0,Y4>0),100%,IF(AND(O4<0,Y4=0),(O4-Y4)/O4,IF(AND(O4>0,Y4>0),(Y4-O4)/O4,IF(AND(O4=0,Y4=0),"",(Y4-O4)/O4)))) -> -1 | AC4: =+AC5+AC10+AC15+AC18 -> 163522.25 | AD4: =IF(AND(AC4=0,AC4>=0), "",AC4/AC4) -> 1 | AF4: =+AF5+AF10+AF15+AF18 -> 0 | AG4: =IF(AND(AF4=0,AF4>=0), "",AF4/AF4) | AI4: =IF(AND(Y4=0,AF4>0),100%,IF(AND(Y4<0,AF4=0),(Y4-AF4)/Y4,IF(AND(Y4>0,AF4>0),(AF4-Y4)/Y4,IF(AND(Y4=0,AF4=0),"",(AF4-Y4)/Y4)))) | AJ4: =+AJ5+AJ10+AJ15+AJ18 -> 163522.25 | AK4: =IF(AND(AJ4=0,AJ4>=0), "",AJ4/AJ4) -> 1 | AM4: =+AM5+AM10+AM15+AM18 -> 0 | AN4: =IF(AND(AM4=0,AM4>=0), "",AM4/AM4) | AP4: =IF(AND(AF4=0,AM4>0),100%,IF(AND(AF4<0,AM4=0),(AF4-AM4)/AF4,IF(AND(AF4>0,AM4>0),(AM4-AF4)/AF4,IF(AND(AF4=0,AM4=0),"",(AM4-AF4)/AF4)))) | AQ4: =+AQ5+AQ10+AQ15+AQ18 -> 163522.25 | AR4: =IF(AND(AQ4=0,AQ4>=0), "",AQ4/AQ4) -> 1 | AT4: =+AT5+AT10+AT15+AT18 -> 0 | AU4: =IF(AND(AT4=0,AT4>=0), "",AT4/AT4) | AV4: =IF(AND(AT4=0,AQ4>0),100%,IF(AND(AT4<0,AQ4=0),(AT4-AQ4)/AT4,IF(AND(AT4>0,AQ4>0),(AQ4-AT4)/AT4,IF(AND(AT4=0,AQ4=0),"",(AQ4-AT4)/AT4)))) -> 1 | AW4: =+AW5+AW10+AW15+AW18 -> 27253.708 | AX4: =IF(AND(AW4=0,AW4>=0), "",AW4/AW4) -> 1 | AZ4: =+AZ5+AZ10+AZ15+AZ18 -> 0 | BA4: =IF(AND(AZ4=0,AZ4>=0), "",AZ4/AZ4) | BB4: =IF(AND(AZ4=0,AW4>0),100%,IF(AND(AZ4<0,AW4=0),(AZ4-AW4)/AZ4,IF(AND(AZ4>0,AW4>0),(AW4-AZ4)/AZ4,IF(AND(AZ4=0,AW4=0),"",(AW4-AZ4)/AZ4)))) -> 1 | BC4: =+BC5+BC10+BC15+BC18 -> 0 | BD4: =IF(AND(BC4=0,BC4>=0), "",BC4/BC4) | BF4: =IF(AND(AM4=0,BC4>0),100%,IF(AND(AM4<0,BC4=0),(AM4-BC4)/AM4,IF(AND(AM4>0,BC4>0),(BC4-AM4)/AM4,IF(AND(AM4=0,BC4=0),"",(BC4-AM4)/AM4)))) | BG4: =+BG5+BG10+BG15+BG18 -> 163522.25 | BH4: =IF(AND(BG4=0,BG4>=0), "",BG4/BG4) -> 1 | BJ4: =+BJ5+BJ10+BJ15+BJ18 -> 0 | BK4: =IF(AND(BJ4=0,BJ4>=0), "",BJ4/BJ4) | BM4: =IF(AND(BC4=0,BJ4>0),100%,IF(AND(BC4<0,BJ4=0),(BC4-BJ4)/BC4,IF(AND(BC4>0,BJ4>0),(BJ4-BC4)/BC4,IF(AND(BC4=0,BJ4=0),"",(BJ4-BC4)/BC4)))) | BN4: =+BN5+BN10+BN15+BN18 -> 163522.25 | BO4: =IF(AND(BN4=0,BN4>=0), "",BN4/BN4) -> 1 | BQ4: =+BQ5+BQ10+BQ15+BQ18 -> 0 | BR4: =IF(AND(BQ4=0,BQ4>=0), "",BQ4/BQ4) | BT4: =IF(AND(BJ4=0,BQ4>0),100%,IF(AND(BJ4<0,BQ4=0),(BJ4-BQ4)/BJ4,IF(AND(BJ4>0,BQ4>0),(BQ4-BJ4)/BJ4,IF(AND(BJ4=0,BQ4=0),"",(BQ4-BJ4)/BJ4)))) | BU4: =+BU5+BU10+BU15+BU18 -> 163522.25 | BV4: =IF(AND(BU4=0,BU4>=0), "",BU4/BU4) -> 1 | BX4: =+BX5+BX10+BX15+BX18 -> 0 | BY4: =IF(AND(BX4=0,BX4>=0), "",BX4/BX4) | BZ4: =IF(AND(BX4=0,BU4>0),100%,IF(AND(BX4<0,BU4=0),(BX4-BU4)/BX4,IF(AND(BX4>0,BU4>0),(BU4-BX4)/BX4,IF(AND(BX4=0,BU4=0),"",(BU4-BX4)/BX4)))) -> 1 | CA4: =+CA5+CA10+CA15+CA18 -> 0 | CB4: =IF(AND(CA4=0,CA4>=0), "",CA4/CA4) | CD4: =IF(AND(BQ4=0,CA4>0),100%,IF(AND(BQ4<0,CA4=0),(BQ4-CA4)/BQ4,IF(AND(BQ4>0,CA4>0),(CA4-BQ4)/BQ4,IF(AND(BQ4=0,CA4=0),"",(CA4-BQ4)/BQ4)))) | CE4: =+CE5+CE10+CE15+CE18 -> 163522.25 | CF4: =IF(AND(CE4=0,CE4>=0), "",CE4/CE4) -> 1 | CH4: =+CH5+CH10+CH15+CH18 -> 0 | CI4: =IF(AND(CH4=0,CH4>=0), "",CH4/CH4) | CK4: =IF(AND(CA4=0,CH4>0),100%,IF(AND(CA4<0,CH4=0),(CA4-CH4)/CA4,IF(AND(CA4>0,CH4>0),(CH4-CA4)/CA4,IF(AND(CA4=0,CH4=0),"",(CH4-CA4)/CA4)))) | CL4: =+CL5+CL10+CL15+CL18 -> 163522.25 | CM4: =IF(AND(CL4=0,CL4>=0), "",CL4/CL4) -> 1 | CO4: =+CO5+CO10+CO15+CO18 -> 0 | CP4: =IF(AND(CO4=0,CO4>=0), "",CO4/CO4) | CR4: =IF(AND(CH4=0,CO4>0),100%,IF(AND(CH4<0,CO4=0),(CH4-CO4)/CH4,IF(AND(CH4>0,CO4>0),(CO4-CH4)/CH4,IF(AND(CH4=0,CO4=0),"",(CO4-CH4)/CH4)))) | CS4: =+CS5+CS10+CS15+CS18 -> 163522.25 | CT4: =IF(AND(CS4=0,CS4>=0), "",CS4/CS4) -> 1 | CV4: =+CV5+CV10+CV15+CV18 -> 0 | CW4: =IF(AND(CV4=0,CV4>=0), "",CV4/CV4) | CX4: =IF(AND(CV4=0,CS4>0),100%,IF(AND(CV4<0,CS4=0),(CV4-CS4)/CV4,IF(AND(CV4>0,CS4>0),(CS4-CV4)/CV4,IF(AND(CV4=0,CS4=0),"",(CS4-CV4)/CV4)))) -> 1
A5: Subtotal Ingresos por Venta de Mercancia | B5: =+B6-B7-B8 -> 0 | C5: =IF(AND(B4=0,B5>=0), "",B5/B4) | E5: =+E6-E7-E8 -> 47933.03 | F5: =IF(AND(E4=0,E5>=0), "",E5/E4) -> 1 | H5: =+H6-H7-H8 -> 51483.04 | I5: =IF(AND(H4=0,H5>=0), "",H5/H4) -> 1 | K5: =IF(AND(E5=0,H5>0),100%,IF(AND(E5<0,H5=0),(E5-H5)/E5,IF(AND(E5>0,H5>0),(H5-E5)/E5,IF(AND(E5=0,H5=0),"",(H5-E5)/E5)))) -> 0.074061873 | L5: =+L6-L7-L8 -> 99416.07 | M5: =IF(AND(L4=0,L5>=0), "",L5/L4) -> 1 | O5: =+O6-O7-O8 -> 64106.18 | P5: =IF(AND(O4=0,O5>=0), "",O5/O4) -> 1 | R5: =IF(AND(H5=0,O5>0),100%,IF(AND(H5<0,O5=0),(H5-O5)/H5,IF(AND(H5>0,O5>0),(O5-H5)/H5,IF(AND(H5=0,O5=0),"",(O5-H5)/H5)))) -> 0.24519026 | S5: =+S6-S7-S8 -> 163522.25 | T5: =IF(AND(S4=0,S5>=0), "",S5/S4) -> 1 | V5: =+V6-V7-V8 -> 0 | W5: =IF(AND(V4=0,V5>=0), "",V5/V4) | X5: =IF(AND(V5=0,S5>0),100%,IF(AND(V5<0,S5=0),(V5-S5)/V5,IF(AND(V5>0,S5>0),(S5-V5)/V5,IF(AND(V5=0,S5=0),"",(S5-V5)/V5)))) -> 1 | Y5: =+Y6-Y7-Y8 -> 0 | Z5: =IF(AND(Y4=0,Y5>=0), "",Y5/Y4) | AB5: =IF(AND(O5=0,Y5>0),100%,IF(AND(O5<0,Y5=0),(O5-Y5)/O5,IF(AND(O5>0,Y5>0),(Y5-O5)/O5,IF(AND(O5=0,Y5=0),"",(Y5-O5)/O5)))) -> -1 | AC5: =+AC6-AC7-AC8 -> 163522.25 | AD5: =IF(AND(AC4=0,AC5>=0), "",AC5/AC4) -> 1 | AF5: =+AF6-AF7-AF8 -> 0 | AG5: =IF(AND(AF4=0,AF5>=0), "",AF5/AF4) | AI5: =IF(AND(Y5=0,AF5>0),100%,IF(AND(Y5<0,AF5=0),(Y5-AF5)/Y5,IF(AND(Y5>0,AF5>0),(AF5-Y5)/Y5,IF(AND(Y5=0,AF5=0),"",(AF5-Y5)/Y5)))) | AJ5: =+AJ6-AJ7-AJ8 -> 163522.25 | AK5: =IF(AND(AJ4=0,AJ5>=0), "",AJ5/AJ4) -> 1 | AM5: =+AM6-AM7-AM8 -> 0 | AN5: =IF(AND(AM4=0,AM5>=0), "",AM5/AM4) | AP5: =IF(AND(AF5=0,AM5>0),100%,IF(AND(AF5<0,AM5=0),(AF5-AM5)/AF5,IF(AND(AF5>0,AM5>0),(AM5-AF5)/AF5,IF(AND(AF5=0,AM5=0),"",(AM5-AF5)/AF5)))) | AQ5: =+AQ6-AQ7-AQ8 -> 163522.25 | AR5: =IF(AND(AQ4=0,AQ5>=0), "",AQ5/AQ4) -> 1 | AT5: =+AT6-AT7-AT8 -> 0 | AU5: =IF(AND(AT4=0,AT5>=0), "",AT5/AT4) | AV5: =IF(AND(AT5=0,AQ5>0),100%,IF(AND(AT5<0,AQ5=0),(AT5-AQ5)/AT5,IF(AND(AT5>0,AQ5>0),(AQ5-AT5)/AT5,IF(AND(AT5=0,AQ5=0),"",(AQ5-AT5)/AT5)))) -> 1 | AW5: =+AW6-AW7-AW8 -> 27253.708 | AX5: =IF(AND(AW4=0,AW5>=0), "",AW5/AW4) -> 1 | AZ5: =+AZ6-AZ7-AZ8 -> 0 | BA5: =IF(AND(AZ4=0,AZ5>=0), "",AZ5/AZ4) | BB5: =IF(AND(AZ5=0,AW5>0),100%,IF(AND(AZ5<0,AW5=0),(AZ5-AW5)/AZ5,IF(AND(AZ5>0,AW5>0),(AW5-AZ5)/AZ5,IF(AND(AZ5=0,AW5=0),"",(AW5-AZ5)/AZ5)))) -> 1 | BC5: =+BC6-BC7-BC8 -> 0 | BD5: =IF(AND(BC4=0,BC5>=0), "",BC5/BC4) | BF5: =IF(AND(AM5=0,BC5>0),100%,IF(AND(AM5<0,BC5=0),(AM5-BC5)/AM5,IF(AND(AM5>0,BC5>0),(BC5-AM5)/AM5,IF(AND(AM5=0,BC5=0),"",(BC5-AM5)/AM5)))) | BG5: =+BG6-BG7-BG8 -> 163522.25 | BH5: =IF(AND(BG4=0,BG5>=0), "",BG5/BG4) -> 1 | BJ5: =+BJ6-BJ7-BJ8 -> 0 | BK5: =IF(AND(BJ4=0,BJ5>=0), "",BJ5/BJ4) | BM5: =IF(AND(BC5=0,BJ5>0),100%,IF(AND(BC5<0,BJ5=0),(BC5-BJ5)/BC5,IF(AND(BC5>0,BJ5>0),(BJ5-BC5)/BC5,IF(AND(BC5=0,BJ5=0),"",(BJ5-BC5)/BC5)))) | BN5: =+BN6-BN7-BN8 -> 163522.25 | BO5: =IF(AND(BN4=0,BN5>=0), "",BN5/BN4) -> 1 | BQ5: =+BQ6-BQ7-BQ8 -> 0 | BR5: =IF(AND(BQ4=0,BQ5>=0), "",BQ5/BQ4) | BT5: =IF(AND(BJ5=0,BQ5>0),100%,IF(AND(BJ5<0,BQ5=0),(BJ5-BQ5)/BJ5,IF(AND(BJ5>0,BQ5>0),(BQ5-BJ5)/BJ5,IF(AND(BJ5=0,BQ5=0),"",(BQ5-BJ5)/BJ5)))) | BU5: =+BU6-BU7-BU8 -> 163522.25 | BV5: =IF(AND(BU4=0,BU5>=0), "",BU5/BU4) -> 1 | BX5: =+BX6-BX7-BX8 -> 0 | BY5: =IF(AND(BX4=0,BX5>=0), "",BX5/BX4) | BZ5: =IF(AND(BX5=0,BU5>0),100%,IF(AND(BX5<0,BU5=0),(BX5-BU5)/BX5,IF(AND(BX5>0,BU5>0),(BU5-BX5)/BX5,IF(AND(BX5=0,BU5=0),"",(BU5-BX5)/BX5)))) -> 1 | CA5: =+CA6-CA7-CA8 -> 0 | CB5: =IF(AND(CA4=0,CA5>=0), "",CA5/CA4) | CD5: =IF(AND(BQ5=0,CA5>0),100%,IF(AND(BQ5<0,CA5=0),(BQ5-CA5)/BQ5,IF(AND(BQ5>0,CA5>0),(CA5-BQ5)/BQ5,IF(AND(BQ5=0,CA5=0),"",(CA5-BQ5)/BQ5)))) | CE5: =+CE6-CE7-CE8 -> 163522.25 | CF5: =IF(AND(CE4=0,CE5>=0), "",CE5/CE4) -> 1 | CH5: =+CH6-CH7-CH8 -> 0 | CI5: =IF(AND(CH4=0,CH5>=0), "",CH5/CH4) | CK5: =IF(AND(CA5=0,CH5>0),100%,IF(AND(CA5<0,CH5=0),(CA5-CH5)/CA5,IF(AND(CA5>0,CH5>0),(CH5-CA5)/CA5,IF(AND(CA5=0,CH5=0),"",(CH5-CA5)/CA5)))) | CL5: =+CL6-CL7-CL8 -> 163522.25 | CM5: =IF(AND(CL4=0,CL5>=0), "",CL5/CL4) -> 1 | CO5: =+CO6-CO7-CO8 -> 0 | CP5: =IF(AND(CO4=0,CO5>=0), "",CO5/CO4) | CR5: =IF(AND(CH5=0,CO5>0),100%,IF(AND(CH5<0,CO5=0),(CH5-CO5)/CH5,IF(AND(CH5>0,CO5>0),(CO5-CH5)/CH5,IF(AND(CH5=0,CO5=0),"",(CO5-CH5)/CH5)))) | CS5: =+CS6-CS7-CS8 -> 163522.25 | CT5: =IF(AND(CS4=0,CS5>=0), "",CS5/CS4) -> 1 | CV5: =+CV6-CV7-CV8 -> 0 | CW5: =IF(AND(CV4=0,CV5>=0), "",CV5/CV4) | CX5: =IF(AND(CV5=0,CS5>0),100%,IF(AND(CV5<0,CS5=0),(CV5-CS5)/CV5,IF(AND(CV5>0,CS5>0),(CS5-CV5)/CV5,IF(AND(CV5=0,CS5=0),"",(CS5-CV5)/CV5)))) -> 1
A6: Ingresos por venta de mercancía | B6: =+'N EERR RODEO'!B6 -> 0 | C6: =IF(AND(B4=0,B6>=0), "",B6/B4) | E6: =+'N EERR RODEO'!C6 -> 47933.03 | F6: =IF(AND(E4=0,E6>=0), "",E6/E4) -> 1 | H6: =+'N EERR RODEO'!D6 -> 51483.04 | I6: =IF(AND(H4=0,H6>=0), "",H6/H4) -> 1 | K6: =IF(AND(E6=0,H6>0),100%,IF(AND(E6<0,H6=0),(E6-H6)/E6,IF(AND(E6>0,H6>0),(H6-E6)/E6,IF(AND(E6=0,H6=0),"",(H6-E6)/E6)))) -> 0.074061873 | L6: =+E6+H6 -> 99416.07 | M6: =IF(AND(L4=0,L6>=0), "",L6/L4) -> 1 | O6: =+'N EERR RODEO'!E6 -> 64106.18 | P6: =IF(AND(O4=0,O6>=0), "",O6/O4) -> 1 | R6: =IF(AND(H6=0,O6>0),100%,IF(AND(H6<0,O6=0),(H6-O6)/H6,IF(AND(H6>0,O6>0),(O6-H6)/H6,IF(AND(H6=0,O6=0),"",(O6-H6)/H6)))) -> 0.24519026 | S6: =+L6+O6 -> 163522.25 | T6: =IF(AND(S4=0,S6>=0), "",S6/S4) -> 1 | W6: =IF(AND(V4=0,V6>=0), "",V6/V4) | X6: =IF(AND(V6=0,S6>0),100%,IF(AND(V6<0,S6=0),(V6-S6)/V6,IF(AND(V6>0,S6>0),(S6-V6)/V6,IF(AND(V6=0,S6=0),"",(S6-V6)/V6)))) -> 1 | Y6: =+'N EERR RODEO'!F6 -> 0 | Z6: =IF(AND(Y4=0,Y6>=0), "",Y6/Y4) | AB6: =IF(AND(O6=0,Y6>0),100%,IF(AND(O6<0,Y6=0),(O6-Y6)/O6,IF(AND(O6>0,Y6>0),(Y6-O6)/O6,IF(AND(O6=0,Y6=0),"",(Y6-O6)/O6)))) -> -1 | AC6: =+S6+Y6 -> 163522.25 | AD6: =IF(AND(AC4=0,AC6>=0), "",AC6/AC4) -> 1 | AF6: =+'N EERR RODEO'!G6 -> 0 | AG6: =IF(AND(AF4=0,AF6>=0), "",AF6/AF4) | AI6: =IF(AND(Y6=0,AF6>0),100%,IF(AND(Y6<0,AF6=0),(Y6-AF6)/Y6,IF(AND(Y6>0,AF6>0),(AF6-Y6)/Y6,IF(AND(Y6=0,AF6=0),"",(AF6-Y6)/Y6)))) | AJ6: =+AC6+AF6 -> 163522.25 | AK6: =IF(AND(AJ4=0,AJ6>=0), "",AJ6/AJ4) -> 1 | AM6: =+'N EERR RODEO'!H6 -> 0 | AN6: =IF(AND(AM4=0,AM6>=0), "",AM6/AM4) | AP6: =IF(AND(AF6=0,AM6>0),100%,IF(AND(AF6<0,AM6=0),(AF6-AM6)/AF6,IF(AND(AF6>0,AM6>0),(AM6-AF6)/AF6,IF(AND(AF6=0,AM6=0),"",(AM6-AF6)/AF6)))) | AQ6: =+AJ6+AM6 -> 163522.25 | AR6: =IF(AND(AQ4=0,AQ6>=0), "",AQ6/AQ4) -> 1 | AT6: =+V6*2 -> 0 | AU6: =IF(AND(AT4=0,AT6>=0), "",AT6/AT4) | AV6: =IF(AND(AT6=0,AQ6>0),100%,IF(AND(AT6<0,AQ6=0),(AT6-AQ6)/AT6,IF(AND(AT6>0,AQ6>0),(AQ6-AT6)/AT6,IF(AND(AT6=0,AQ6=0),"",(AQ6-AT6)/AT6)))) -> 1 | AW6: =+AQ6/6 -> 27253.708 | AX6: =IF(AND(AW4=0,AW6>=0), "",AW6/AW4) -> 1 | AZ6: =+AT6/6 -> 0 | BA6: =IF(AND(AZ4=0,AZ6>=0), "",AZ6/AZ4) | BB6: =IF(AND(AZ6=0,AW6>0),100%,IF(AND(AZ6<0,AW6=0),(AZ6-AW6)/AZ6,IF(AND(AZ6>0,AW6>0),(AW6-AZ6)/AZ6,IF(AND(AZ6=0,AW6=0),"",(AW6-AZ6)/AZ6)))) -> 1 | BC6: =+'N EERR RODEO'!I6 -> 0 | BD6: =IF(AND(BC4=0,BC6>=0), "",BC6/BC4) | BF6: =IF(AND(AM6=0,BC6>0),100%,IF(AND(AM6<0,BC6=0),(AM6-BC6)/AM6,IF(AND(AM6>0,BC6>0),(BC6-AM6)/AM6,IF(AND(AM6=0,BC6=0),"",(BC6-AM6)/AM6)))) | BG6: =+AQ6+BC6 -> 163522.25 | BH6: =IF(AND(BG4=0,BG6>=0), "",BG6/BG4) -> 1 | BJ6: =+'N EERR RODEO'!J6 -> 0 | BK6: =IF(AND(BJ4=0,BJ6>=0), "",BJ6/BJ4) | BM6: =IF(AND(BC6=0,BJ6>0),100%,IF(AND(BC6<0,BJ6=0),(BC6-BJ6)/BC6,IF(AND(BC6>0,BJ6>0),(BJ6-BC6)/BC6,IF(AND(BC6=0,BJ6=0),"",(BJ6-BC6)/BC6)))) | BN6: =+BG6+BJ6 -> 163522.25 | BO6: =IF(AND(BN4=0,BN6>=0), "",BN6/BN4) -> 1 | BQ6: =+'N EERR RODEO'!K6 -> 0 | BR6: =IF(AND(BQ4=0,BQ6>=0), "",BQ6/BQ4) | BT6: =IF(AND(BJ6=0,BQ6>0),100%,IF(AND(BJ6<0,BQ6=0),(BJ6-BQ6)/BJ6,IF(AND(BJ6>0,BQ6>0),(BQ6-BJ6)/BJ6,IF(AND(BJ6=0,BQ6=0),"",(BQ6-BJ6)/BJ6)))) | BU6: =+BN6+BQ6 -> 163522.25 | BV6: =IF(AND(BU4=0,BU6>=0), "",BU6/BU4) -> 1 | BX6: =+AZ6*9 -> 0 | BY6: =IF(AND(BX4=0,BX6>=0), "",BX6/BX4) | BZ6: =IF(AND(BX6=0,BU6>0),100%,IF(AND(BX6<0,BU6=0),(BX6-BU6)/BX6,IF(AND(BX6>0,BU6>0),(BU6-BX6)/BX6,IF(AND(BX6=0,BU6=0),"",(BU6-BX6)/BX6)))) -> 1 | CA6: =+'N EERR RODEO'!L6 -> 0 | CB6: =IF(AND(CA4=0,CA6>=0), "",CA6/CA4) | CD6: =IF(AND(BQ6=0,CA6>0),100%,IF(AND(BQ6<0,CA6=0),(BQ6-CA6)/BQ6,IF(AND(BQ6>0,CA6>0),(CA6-BQ6)/BQ6,IF(AND(BQ6=0,CA6=0),"",(CA6-BQ6)/BQ6)))) | CE6: =+BU6+CA6 -> 163522.25 | CF6: =IF(AND(CE4=0,CE6>=0), "",CE6/CE4) -> 1 | CH6: =+'N EERR RODEO'!M6 -> 0 | CI6: =IF(AND(CH4=0,CH6>=0), "",CH6/CH4) | CK6: =IF(AND(CA6=0,CH6>0),100%,IF(AND(CA6<0,CH6=0),(CA6-CH6)/CA6,IF(AND(CA6>0,CH6>0),(CH6-CA6)/CA6,IF(AND(CA6=0,CH6=0),"",(CH6-CA6)/CA6)))) | CL6: =+CE6+CH6 -> 163522.25 | CM6: =IF(AND(CL4=0,CL6>=0), "",CL6/CL4) -> 1 | CO6: =+'N EERR RODEO'!N6 -> 0 | CP6: =IF(AND(CO4=0,CO6>=0), "",CO6/CO4) | CR6: =IF(AND(CH6=0,CO6>0),100%,IF(AND(CH6<0,CO6=0),(CH6-CO6)/CH6,IF(AND(CH6>0,CO6>0),(CO6-CH6)/CH6,IF(AND(CH6=0,CO6=0),"",(CO6-CH6)/CH6)))) | CS6: =+CL6+CO6 -> 163522.25 | CT6: =IF(AND(CS4=0,CS6>=0), "",CS6/CS4) -> 1 | CV6: =+AZ6*12 -> 0 | CW6: =IF(AND(CV4=0,CV6>=0), "",CV6/CV4) | CX6: =IF(AND(CV6=0,CS6>0),100%,IF(AND(CV6<0,CS6=0),(CV6-CS6)/CV6,IF(AND(CV6>0,CS6>0),(CS6-CV6)/CV6,IF(AND(CV6=0,CS6=0),"",(CS6-CV6)/CV6)))) -> 1
A7: Devoluciones sobre ventas | B7: =+'N EERR RODEO'!B7 -> 0 | C7: =IF(AND(B4=0,B7>=0), "",B7/B4) | E7: =+'N EERR RODEO'!C7 -> 0 | F7: =IF(AND(E4=0,E7>=0), "",E7/E4) -> 0 | H7: =+'N EERR RODEO'!D7 -> 0 | I7: =IF(AND(H4=0,H7>=0), "",H7/H4) -> 0 | K7: =IF(AND(E7=0,H7>0),100%,IF(AND(E7<0,H7=0),(E7-H7)/E7,IF(AND(E7>0,H7>0),(H7-E7)/E7,IF(AND(E7=0,H7=0),"",(H7-E7)/E7)))) | L7: =+E7+H7 -> 0 | M7: =IF(AND(L4=0,L7>=0), "",L7/L4) -> 0 | O7: =+'N EERR RODEO'!E7 -> 0 | P7: =IF(AND(O4=0,O7>=0), "",O7/O4) -> 0 | R7: =IF(AND(H7=0,O7>0),100%,IF(AND(H7<0,O7=0),(H7-O7)/H7,IF(AND(H7>0,O7>0),(O7-H7)/H7,IF(AND(H7=0,O7=0),"",(O7-H7)/H7)))) | S7: =+L7+O7 -> 0 | T7: =IF(AND(S4=0,S7>=0), "",S7/S4) -> 0 | W7: =IF(AND(V4=0,V7>=0), "",V7/V4) | X7: =IF(AND(V7=0,S7>0),100%,IF(AND(V7<0,S7=0),(V7-S7)/V7,IF(AND(V7>0,S7>0),(S7-V7)/V7,IF(AND(V7=0,S7=0),"",(S7-V7)/V7)))) | Y7: =+'N EERR RODEO'!F7 -> 0 | Z7: =IF(AND(Y4=0,Y7>=0), "",Y7/Y4) | AB7: =IF(AND(O7=0,Y7>0),100%,IF(AND(O7<0,Y7=0),(O7-Y7)/O7,IF(AND(O7>0,Y7>0),(Y7-O7)/O7,IF(AND(O7=0,Y7=0),"",(Y7-O7)/O7)))) | AC7: =+S7+Y7 -> 0 | AD7: =IF(AND(AC4=0,AC7>=0), "",AC7/AC4) -> 0 | AF7: =+'N EERR RODEO'!G7 -> 0 | AG7: =IF(AND(AF4=0,AF7>=0), "",AF7/AF4) | AI7: =IF(AND(Y7=0,AF7>0),100%,IF(AND(Y7<0,AF7=0),(Y7-AF7)/Y7,IF(AND(Y7>0,AF7>0),(AF7-Y7)/Y7,IF(AND(Y7=0,AF7=0),"",(AF7-Y7)/Y7)))) | AJ7: =+AC7+AF7 -> 0 | AK7: =IF(AND(AJ4=0,AJ7>=0), "",AJ7/AJ4) -> 0 | AM7: =+'N EERR RODEO'!H7 -> 0 | AN7: =IF(AND(AM4=0,AM7>=0), "",AM7/AM4) | AP7: =IF(AND(AF7=0,AM7>0),100%,IF(AND(AF7<0,AM7=0),(AF7-AM7)/AF7,IF(AND(AF7>0,AM7>0),(AM7-AF7)/AF7,IF(AND(AF7=0,AM7=0),"",(AM7-AF7)/AF7)))) | AQ7: =+AJ7+AM7 -> 0 | AR7: =IF(AND(AQ4=0,AQ7>=0), "",AQ7/AQ4) -> 0 | AT7: =+V7*2 -> 0 | AU7: =IF(AND(AT4=0,AT7>=0), "",AT7/AT4) | AV7: =IF(AND(AT7=0,AQ7>0),100%,IF(AND(AT7<0,AQ7=0),(AT7-AQ7)/AT7,IF(AND(AT7>0,AQ7>0),(AQ7-AT7)/AT7,IF(AND(AT7=0,AQ7=0),"",(AQ7-AT7)/AT7)))) | AW7: =+AQ7/6 -> 0 | AX7: =IF(AND(AW4=0,AW7>=0), "",AW7/AW4) -> 0 | AZ7: =+AT7/6 -> 0 | BA7: =IF(AND(AZ4=0,AZ7>=0), "",AZ7/AZ4) | BB7: =IF(AND(AZ7=0,AW7>0),100%,IF(AND(AZ7<0,AW7=0),(AZ7-AW7)/AZ7,IF(AND(AZ7>0,AW7>0),(AW7-AZ7)/AZ7,IF(AND(AZ7=0,AW7=0),"",(AW7-AZ7)/AZ7)))) | BC7: =+'N EERR RODEO'!I7 -> 0 | BD7: =IF(AND(BC4=0,BC7>=0), "",BC7/BC4) | BF7: =IF(AND(AM7=0,BC7>0),100%,IF(AND(AM7<0,BC7=0),(AM7-BC7)/AM7,IF(AND(AM7>0,BC7>0),(BC7-AM7)/AM7,IF(AND(AM7=0,BC7=0),"",(BC7-AM7)/AM7)))) | BG7: =+AQ7+BC7 -> 0 | BH7: =IF(AND(BG4=0,BG7>=0), "",BG7/BG4) -> 0 | BJ7: =+'N EERR RODEO'!J7 -> 0 | BK7: =IF(AND(BJ4=0,BJ7>=0), "",BJ7/BJ4) | BM7: =IF(AND(BC7=0,BJ7>0),100%,IF(AND(BC7<0,BJ7=0),(BC7-BJ7)/BC7,IF(AND(BC7>0,BJ7>0),(BJ7-BC7)/BC7,IF(AND(BC7=0,BJ7=0),"",(BJ7-BC7)/BC7)))) | BN7: =+BG7+BJ7 -> 0 | BO7: =IF(AND(BN4=0,BN7>=0), "",BN7/BN4) -> 0 | BQ7: =+'N EERR RODEO'!K7 -> 0 | BR7: =IF(AND(BQ4=0,BQ7>=0), "",BQ7/BQ4) | BT7: =IF(AND(BJ7=0,BQ7>0),100%,IF(AND(BJ7<0,BQ7=0),(BJ7-BQ7)/BJ7,IF(AND(BJ7>0,BQ7>0),(BQ7-BJ7)/BJ7,IF(AND(BJ7=0,BQ7=0),"",(BQ7-BJ7)/BJ7)))) | BU7: =+BN7+BQ7 -> 0 | BV7: =IF(AND(BU4=0,BU7>=0), "",BU7/BU4) -> 0 | BX7: =+AZ7*9 -> 0 | BY7: =IF(AND(BX4=0,BX7>=0), "",BX7/BX4) | BZ7: =IF(AND(BX7=0,BU7>0),100%,IF(AND(BX7<0,BU7=0),(BX7-BU7)/BX7,IF(AND(BX7>0,BU7>0),(BU7-BX7)/BX7,IF(AND(BX7=0,BU7=0),"",(BU7-BX7)/BX7)))) | CA7: =+'N EERR RODEO'!L7 -> 0 | CB7: =IF(AND(CA4=0,CA7>=0), "",CA7/CA4) | CD7: =IF(AND(BQ7=0,CA7>0),100%,IF(AND(BQ7<0,CA7=0),(BQ7-CA7)/BQ7,IF(AND(BQ7>0,CA7>0),(CA7-BQ7)/BQ7,IF(AND(BQ7=0,CA7=0),"",(CA7-BQ7)/BQ7)))) | CE7: =+BU7+CA7 -> 0 | CF7: =IF(AND(CE4=0,CE7>=0), "",CE7/CE4) -> 0 | CH7: =+'N EERR RODEO'!M7 -> 0 | CI7: =IF(AND(CH4=0,CH7>=0), "",CH7/CH4) | CK7: =IF(AND(CA7=0,CH7>0),100%,IF(AND(CA7<0,CH7=0),(CA7-CH7)/CA7,IF(AND(CA7>0,CH7>0),(CH7-CA7)/CA7,IF(AND(CA7=0,CH7=0),"",(CH7-CA7)/CA7)))) | CL7: =+CE7+CH7 -> 0 | CM7: =IF(AND(CL4=0,CL7>=0), "",CL7/CL4) -> 0 | CO7: =+'N EERR RODEO'!N7 -> 0 | CP7: =IF(AND(CO4=0,CO7>=0), "",CO7/CO4) | CR7: =IF(AND(CH7=0,CO7>0),100%,IF(AND(CH7<0,CO7=0),(CH7-CO7)/CH7,IF(AND(CH7>0,CO7>0),(CO7-CH7)/CH7,IF(AND(CH7=0,CO7=0),"",(CO7-CH7)/CH7)))) | CS7: =+CL7+CO7 -> 0 | CT7: =IF(AND(CS4=0,CS7>=0), "",CS7/CS4) -> 0 | CV7: =+AZ7*12 -> 0 | CW7: =IF(AND(CV4=0,CV7>=0), "",CV7/CV4) | CX7: =IF(AND(CV7=0,CS7>0),100%,IF(AND(CV7<0,CS7=0),(CV7-CS7)/CV7,IF(AND(CV7>0,CS7>0),(CS7-CV7)/CV7,IF(AND(CV7=0,CS7=0),"",(CS7-CV7)/CV7))))
A8: Descuentos sobre ventas | B8: =+'N EERR RODEO'!B8+'N EERR RODEO'!B9 -> 0 | C8: =IF(AND(B5=0,B8>=0), "",B8/B5) | E8: =+'N EERR RODEO'!C8+'N EERR RODEO'!C9 -> 0 | F8: =IF(AND(E5=0,E8>=0), "",E8/E5) -> 0 | H8: =+'N EERR RODEO'!D8+'N EERR RODEO'!D9 -> 0 | I8: =IF(AND(H5=0,H8>=0), "",H8/H5) -> 0 | K8: =IF(AND(E8=0,H8>0),100%,IF(AND(E8<0,H8=0),(E8-H8)/E8,IF(AND(E8>0,H8>0),(H8-E8)/E8,IF(AND(E8=0,H8=0),"",(H8-E8)/E8)))) | L8: =+E8+H8 -> 0 | M8: =IF(AND(L5=0,L8>=0), "",L8/L5) -> 0 | O8: =+'N EERR RODEO'!E8+'N EERR RODEO'!E9 -> 0 | P8: =IF(AND(O5=0,O8>=0), "",O8/O5) -> 0 | R8: =IF(AND(H8=0,O8>0),100%,IF(AND(H8<0,O8=0),(H8-O8)/H8,IF(AND(H8>0,O8>0),(O8-H8)/H8,IF(AND(H8=0,O8=0),"",(O8-H8)/H8)))) | S8: =+L8+O8 -> 0 | T8: =IF(AND(S5=0,S8>=0), "",S8/S5) -> 0 | W8: =IF(AND(V5=0,V8>=0), "",V8/V5) | X8: =IF(AND(V8=0,S8>0),100%,IF(AND(V8<0,S8=0),(V8-S8)/V8,IF(AND(V8>0,S8>0),(S8-V8)/V8,IF(AND(V8=0,S8=0),"",(S8-V8)/V8)))) | Y8: =+'N EERR RODEO'!F8+'N EERR RODEO'!F9 -> 0 | Z8: =IF(AND(Y5=0,Y8>=0), "",Y8/Y5) | AB8: =IF(AND(O8=0,Y8>0),100%,IF(AND(O8<0,Y8=0),(O8-Y8)/O8,IF(AND(O8>0,Y8>0),(Y8-O8)/O8,IF(AND(O8=0,Y8=0),"",(Y8-O8)/O8)))) | AC8: =+S8+Y8 -> 0 | AD8: =IF(AND(AC5=0,AC8>=0), "",AC8/AC5) -> 0 | AF8: =+'N EERR RODEO'!G8+'N EERR RODEO'!G9 -> 0 | AG8: =IF(AND(AF5=0,AF8>=0), "",AF8/AF5) | AI8: =IF(AND(Y8=0,AF8>0),100%,IF(AND(Y8<0,AF8=0),(Y8-AF8)/Y8,IF(AND(Y8>0,AF8>0),(AF8-Y8)/Y8,IF(AND(Y8=0,AF8=0),"",(AF8-Y8)/Y8)))) | AJ8: =+AC8+AF8 -> 0 | AK8: =IF(AND(AJ5=0,AJ8>=0), "",AJ8/AJ5) -> 0 | AM8: =+'N EERR RODEO'!H8+'N EERR RODEO'!H9 -> 0 | AN8: =IF(AND(AM5=0,AM8>=0), "",AM8/AM5) | AP8: =IF(AND(AF8=0,AM8>0),100%,IF(AND(AF8<0,AM8=0),(AF8-AM8)/AF8,IF(AND(AF8>0,AM8>0),(AM8-AF8)/AF8,IF(AND(AF8=0,AM8=0),"",(AM8-AF8)/AF8)))) | AQ8: =+AJ8+AM8 -> 0 | AR8: =IF(AND(AQ5=0,AQ8>=0), "",AQ8/AQ5) -> 0 | AT8: =+V8*2 -> 0 | AU8: =IF(AND(AT5=0,AT8>=0), "",AT8/AT5) | AV8: =IF(AND(AT8=0,AQ8>0),100%,IF(AND(AT8<0,AQ8=0),(AT8-AQ8)/AT8,IF(AND(AT8>0,AQ8>0),(AQ8-AT8)/AT8,IF(AND(AT8=0,AQ8=0),"",(AQ8-AT8)/AT8)))) | AW8: =+AQ8/6 -> 0 | AX8: =IF(AND(AW5=0,AW8>=0), "",AW8/AW5) -> 0 | AZ8: =+AT8/6 -> 0 | BA8: =IF(AND(AZ5=0,AZ8>=0), "",AZ8/AZ5) | BB8: =IF(AND(AZ8=0,AW8>0),100%,IF(AND(AZ8<0,AW8=0),(AZ8-AW8)/AZ8,IF(AND(AZ8>0,AW8>0),(AW8-AZ8)/AZ8,IF(AND(AZ8=0,AW8=0),"",(AW8-AZ8)/AZ8)))) | BC8: =+'N EERR RODEO'!I8+'N EERR RODEO'!I9 -> 0 | BD8: =IF(AND(BC5=0,BC8>=0), "",BC8/BC5) | BF8: =IF(AND(AM8=0,BC8>0),100%,IF(AND(AM8<0,BC8=0),(AM8-BC8)/AM8,IF(AND(AM8>0,BC8>0),(BC8-AM8)/AM8,IF(AND(AM8=0,BC8=0),"",(BC8-AM8)/AM8)))) | BG8: =+AQ8+BC8 -> 0 | BH8: =IF(AND(BG5=0,BG8>=0), "",BG8/BG5) -> 0 | BJ8: =+'N EERR RODEO'!J8+'N EERR RODEO'!J9 -> 0 | BK8: =IF(AND(BJ5=0,BJ8>=0), "",BJ8/BJ5) | BM8: =IF(AND(BC8=0,BJ8>0),100%,IF(AND(BC8<0,BJ8=0),(BC8-BJ8)/BC8,IF(AND(BC8>0,BJ8>0),(BJ8-BC8)/BC8,IF(AND(BC8=0,BJ8=0),"",(BJ8-BC8)/BC8)))) | BN8: =+BG8+BJ8 -> 0 | BO8: =IF(AND(BN5=0,BN8>=0), "",BN8/BN5) -> 0 | BQ8: =+'N EERR RODEO'!K8+'N EERR RODEO'!K9 -> 0 | BR8: =IF(AND(BQ5=0,BQ8>=0), "",BQ8/BQ5) | BT8: =IF(AND(BJ8=0,BQ8>0),100%,IF(AND(BJ8<0,BQ8=0),(BJ8-BQ8)/BJ8,IF(AND(BJ8>0,BQ8>0),(BQ8-BJ8)/BJ8,IF(AND(BJ8=0,BQ8=0),"",(BQ8-BJ8)/BJ8)))) | BU8: =+BN8+BQ8 -> 0 | BV8: =IF(AND(BU5=0,BU8>=0), "",BU8/BU5) -> 0 | BX8: =+AZ8*9 -> 0 | BY8: =IF(AND(BX5=0,BX8>=0), "",BX8/BX5) | BZ8: =IF(AND(BX8=0,BU8>0),100%,IF(AND(BX8<0,BU8=0),(BX8-BU8)/BX8,IF(AND(BX8>0,BU8>0),(BU8-BX8)/BX8,IF(AND(BX8=0,BU8=0),"",(BU8-BX8)/BX8)))) | CA8: =+'N EERR RODEO'!L8+'N EERR RODEO'!L9 -> 0 | CB8: =IF(AND(CA5=0,CA8>=0), "",CA8/CA5) | CD8: =IF(AND(BQ8=0,CA8>0),100%,IF(AND(BQ8<0,CA8=0),(BQ8-CA8)/BQ8,IF(AND(BQ8>0,CA8>0),(CA8-BQ8)/BQ8,IF(AND(BQ8=0,CA8=0),"",(CA8-BQ8)/BQ8)))) | CE8: =+BU8+CA8 -> 0 | CF8: =IF(AND(CE5=0,CE8>=0), "",CE8/CE5) -> 0 | CH8: =+'N EERR RODEO'!M8+'N EERR RODEO'!M9 -> 0 | CI8: =IF(AND(CH5=0,CH8>=0), "",CH8/CH5) | CK8: =IF(AND(CA8=0,CH8>0),100%,IF(AND(CA8<0,CH8=0),(CA8-CH8)/CA8,IF(AND(CA8>0,CH8>0),(CH8-CA8)/CA8,IF(AND(CA8=0,CH8=0),"",(CH8-CA8)/CA8)))) | CL8: =+CE8+CH8 -> 0 | CM8: =IF(AND(CL5=0,CL8>=0), "",CL8/CL5) -> 0 | CO8: =+'N EERR RODEO'!N8+'N EERR RODEO'!N9 -> 0 | CP8: =IF(AND(CO5=0,CO8>=0), "",CO8/CO5) | CR8: =IF(AND(CH8=0,CO8>0),100%,IF(AND(CH8<0,CO8=0),(CH8-CO8)/CH8,IF(AND(CH8>0,CO8>0),(CO8-CH8)/CH8,IF(AND(CH8=0,CO8=0),"",(CO8-CH8)/CH8)))) | CS8: =+CL8+CO8 -> 0 | CT8: =IF(AND(CS5=0,CS8>=0), "",CS8/CS5) -> 0 | CV8: =+AZ8*12 -> 0 | CW8: =IF(AND(CV5=0,CV8>=0), "",CV8/CV5) | CX8: =IF(AND(CV8=0,CS8>0),100%,IF(AND(CV8<0,CS8=0),(CV8-CS8)/CV8,IF(AND(CV8>0,CS8>0),(CS8-CV8)/CV8,IF(AND(CV8=0,CS8=0),"",(CS8-CV8)/CV8))))
K9: =IF(AND(E9=0,H9>0),100%,IF(AND(E9<0,H9=0),(E9-H9)/E9,IF(AND(E9>0,H9>0),(H9-E9)/E9,IF(AND(E9=0,H9=0),"",(H9-E9)/E9)))) | R9: =IF(AND(H9=0,O9>0),100%,IF(AND(H9<0,O9=0),(H9-O9)/H9,IF(AND(H9>0,O9>0),(O9-H9)/H9,IF(AND(H9=0,O9=0),"",(O9-H9)/H9)))) | X9: =IF(AND(V9=0,S9>0),100%,IF(AND(V9<0,S9=0),(V9-S9)/V9,IF(AND(V9>0,S9>0),(S9-V9)/V9,IF(AND(V9=0,S9=0),"",(S9-V9)/V9)))) | AB9: =IF(AND(O9=0,Y9>0),100%,IF(AND(O9<0,Y9=0),(O9-Y9)/O9,IF(AND(O9>0,Y9>0),(Y9-O9)/O9,IF(AND(O9=0,Y9=0),"",(Y9-O9)/O9)))) | AI9: =IF(AND(Y9=0,AF9>0),100%,IF(AND(Y9<0,AF9=0),(Y9-AF9)/Y9,IF(AND(Y9>0,AF9>0),(AF9-Y9)/Y9,IF(AND(Y9=0,AF9=0),"",(AF9-Y9)/Y9)))) | AJ9: =+AC9+AF9 -> 0 | AP9: =IF(AND(AF9=0,AM9>0),100%,IF(AND(AF9<0,AM9=0),(AF9-AM9)/AF9,IF(AND(AF9>0,AM9>0),(AM9-AF9)/AF9,IF(AND(AF9=0,AM9=0),"",(AM9-AF9)/AF9)))) | AQ9: =+AJ9+AM9 -> 0 | AT9: =+V9*2 -> 0 | AV9: =IF(AND(AT9=0,AQ9>0),100%,IF(AND(AT9<0,AQ9=0),(AT9-AQ9)/AT9,IF(AND(AT9>0,AQ9>0),(AQ9-AT9)/AT9,IF(AND(AT9=0,AQ9=0),"",(AQ9-AT9)/AT9)))) | AZ9: =+AT9/6 -> 0 | BB9: =IF(AND(AZ9=0,AW9>0),100%,IF(AND(AZ9<0,AW9=0),(AZ9-AW9)/AZ9,IF(AND(AZ9>0,AW9>0),(AW9-AZ9)/AZ9,IF(AND(AZ9=0,AW9=0),"",(AW9-AZ9)/AZ9)))) | BF9: =IF(AND(AM9=0,BC9>0),100%,IF(AND(AM9<0,BC9=0),(AM9-BC9)/AM9,IF(AND(AM9>0,BC9>0),(BC9-AM9)/AM9,IF(AND(AM9=0,BC9=0),"",(BC9-AM9)/AM9)))) | BG9: =+AQ9+BC9 -> 0 | BM9: =IF(AND(BC9=0,BJ9>0),100%,IF(AND(BC9<0,BJ9=0),(BC9-BJ9)/BC9,IF(AND(BC9>0,BJ9>0),(BJ9-BC9)/BC9,IF(AND(BC9=0,BJ9=0),"",(BJ9-BC9)/BC9)))) | BN9: =+BG9+BJ9 -> 0 | BT9: =IF(AND(BJ9=0,BQ9>0),100%,IF(AND(BJ9<0,BQ9=0),(BJ9-BQ9)/BJ9,IF(AND(BJ9>0,BQ9>0),(BQ9-BJ9)/BJ9,IF(AND(BJ9=0,BQ9=0),"",(BQ9-BJ9)/BJ9)))) | BU9: =+BN9+BQ9 -> 0 | BX9: =+AZ9*9 -> 0 | BZ9: =IF(AND(BX9=0,BU9>0),100%,IF(AND(BX9<0,BU9=0),(BX9-BU9)/BX9,IF(AND(BX9>0,BU9>0),(BU9-BX9)/BX9,IF(AND(BX9=0,BU9=0),"",(BU9-BX9)/BX9)))) | CD9: =IF(AND(BQ9=0,CA9>0),100%,IF(AND(BQ9<0,CA9=0),(BQ9-CA9)/BQ9,IF(AND(BQ9>0,CA9>0),(CA9-BQ9)/BQ9,IF(AND(BQ9=0,CA9=0),"",(CA9-BQ9)/BQ9)))) | CK9: =IF(AND(CA9=0,CH9>0),100%,IF(AND(CA9<0,CH9=0),(CA9-CH9)/CA9,IF(AND(CA9>0,CH9>0),(CH9-CA9)/CA9,IF(AND(CA9=0,CH9=0),"",(CH9-CA9)/CA9)))) | CL9: =+CE9+CH9 -> 0 | CR9: =IF(AND(CH9=0,CO9>0),100%,IF(AND(CH9<0,CO9=0),(CH9-CO9)/CH9,IF(AND(CH9>0,CO9>0),(CO9-CH9)/CH9,IF(AND(CH9=0,CO9=0),"",(CO9-CH9)/CH9)))) | CS9: =+CL9+CO9 -> 0 | CV9: =+AZ9*12 -> 0 | CX9: =IF(AND(CV9=0,CS9>0),100%,IF(AND(CV9<0,CS9=0),(CV9-CS9)/CV9,IF(AND(CV9>0,CS9>0),(CS9-CV9)/CV9,IF(AND(CV9=0,CS9=0),"",(CS9-CV9)/CV9))))
A10: Subtotal Ingresos por Servicios | B10: =SUM(B11:B14) -> 0 | C10: =IF(AND(B4=0,B10>=0), "",B10/B4) | E10: =SUM(E11:E14) -> 0 | F10: =IF(AND(E4=0,E10>=0), "",E10/E4) -> 0 | H10: =SUM(H11:H14) -> 0 | I10: =IF(AND(H4=0,H10>=0), "",H10/H4) -> 0 | K10: =IF(AND(E10=0,H10>0),100%,IF(AND(E10<0,H10=0),(E10-H10)/E10,IF(AND(E10>0,H10>0),(H10-E10)/E10,IF(AND(E10=0,H10=0),"",(H10-E10)/E10)))) | L10: =SUM(L11:L14) -> 0 | M10: =IF(AND(L4=0,L10>=0), "",L10/L4) -> 0 | O10: =SUM(O11:O14) -> 0 | P10: =IF(AND(O4=0,O10>=0), "",O10/O4) -> 0 | R10: =IF(AND(H10=0,O10>0),100%,IF(AND(H10<0,O10=0),(H10-O10)/H10,IF(AND(H10>0,O10>0),(O10-H10)/H10,IF(AND(H10=0,O10=0),"",(O10-H10)/H10)))) | S10: =SUM(S11:S14) -> 0 | T10: =IF(AND(S4=0,S10>=0), "",S10/S4) -> 0 | V10: =SUM(V11:V14) -> 0 | W10: =IF(AND(V4=0,V10>=0), "",V10/V4) | X10: =IF(AND(V10=0,S10>0),100%,IF(AND(V10<0,S10=0),(V10-S10)/V10,IF(AND(V10>0,S10>0),(S10-V10)/V10,IF(AND(V10=0,S10=0),"",(S10-V10)/V10)))) | Y10: =SUM(Y11:Y14) -> 0 | Z10: =IF(AND(Y4=0,Y10>=0), "",Y10/Y4) | AB10: =IF(AND(O10=0,Y10>0),100%,IF(AND(O10<0,Y10=0),(O10-Y10)/O10,IF(AND(O10>0,Y10>0),(Y10-O10)/O10,IF(AND(O10=0,Y10=0),"",(Y10-O10)/O10)))) | AC10: =SUM(AC11:AC14) -> 0 | AD10: =IF(AND(AC4=0,AC10>=0), "",AC10/AC4) -> 0 | AF10: =SUM(AF11:AF14) -> 0 | AG10: =IF(AND(AF4=0,AF10>=0), "",AF10/AF4) | AI10: =IF(AND(Y10=0,AF10>0),100%,IF(AND(Y10<0,AF10=0),(Y10-AF10)/Y10,IF(AND(Y10>0,AF10>0),(AF10-Y10)/Y10,IF(AND(Y10=0,AF10=0),"",(AF10-Y10)/Y10)))) | AJ10: =SUM(AJ11:AJ14) -> 0 | AK10: =IF(AND(AJ4=0,AJ10>=0), "",AJ10/AJ4) -> 0 | AM10: =SUM(AM11:AM14) -> 0 | AN10: =IF(AND(AM4=0,AM10>=0), "",AM10/AM4) | AP10: =IF(AND(AF10=0,AM10>0),100%,IF(AND(AF10<0,AM10=0),(AF10-AM10)/AF10,IF(AND(AF10>0,AM10>0),(AM10-AF10)/AF10,IF(AND(AF10=0,AM10=0),"",(AM10-AF10)/AF10)))) | AQ10: =SUM(AQ11:AQ14) -> 0 | AR10: =IF(AND(AQ4=0,AQ10>=0), "",AQ10/AQ4) -> 0 | AT10: =SUM(AT11:AT14) -> 0 | AU10: =IF(AND(AT4=0,AT10>=0), "",AT10/AT4) | AV10: =IF(AND(AT10=0,AQ10>0),100%,IF(AND(AT10<0,AQ10=0),(AT10-AQ10)/AT10,IF(AND(AT10>0,AQ10>0),(AQ10-AT10)/AT10,IF(AND(AT10=0,AQ10=0),"",(AQ10-AT10)/AT10)))) | AW10: =SUM(AW11:AW14) -> 0 | AX10: =IF(AND(AW4=0,AW10>=0), "",AW10/AW4) -> 0 | AZ10: =SUM(AZ11:AZ14) -> 0 | BA10: =IF(AND(AZ4=0,AZ10>=0), "",AZ10/AZ4) | BB10: =IF(AND(AZ10=0,AW10>0),100%,IF(AND(AZ10<0,AW10=0),(AZ10-AW10)/AZ10,IF(AND(AZ10>0,AW10>0),(AW10-AZ10)/AZ10,IF(AND(AZ10=0,AW10=0),"",(AW10-AZ10)/AZ10)))) | BC10: =SUM(BC11:BC14) -> 0 | BD10: =IF(AND(BC4=0,BC10>=0), "",BC10/BC4) | BF10: =IF(AND(AM10=0,BC10>0),100%,IF(AND(AM10<0,BC10=0),(AM10-BC10)/AM10,IF(AND(AM10>0,BC10>0),(BC10-AM10)/AM10,IF(AND(AM10=0,BC10=0),"",(BC10-AM10)/AM10)))) | BG10: =SUM(BG11:BG14) -> 0 | BH10: =IF(AND(BG4=0,BG10>=0), "",BG10/BG4) -> 0 | BJ10: =SUM(BJ11:BJ14) -> 0 | BK10: =IF(AND(BJ4=0,BJ10>=0), "",BJ10/BJ4) | BM10: =IF(AND(BC10=0,BJ10>0),100%,IF(AND(BC10<0,BJ10=0),(BC10-BJ10)/BC10,IF(AND(BC10>0,BJ10>0),(BJ10-BC10)/BC10,IF(AND(BC10=0,BJ10=0),"",(BJ10-BC10)/BC10)))) | BN10: =SUM(BN11:BN14) -> 0 | BO10: =IF(AND(BN4=0,BN10>=0), "",BN10/BN4) -> 0 | BQ10: =SUM(BQ11:BQ14) -> 0 | BR10: =IF(AND(BQ4=0,BQ10>=0), "",BQ10/BQ4) | BT10: =IF(AND(BJ10=0,BQ10>0),100%,IF(AND(BJ10<0,BQ10=0),(BJ10-BQ10)/BJ10,IF(AND(BJ10>0,BQ10>0),(BQ10-BJ10)/BJ10,IF(AND(BJ10=0,BQ10=0),"",(BQ10-BJ10)/BJ10)))) | BU10: =SUM(BU11:BU14) -> 0 | BV10: =IF(AND(BU4=0,BU10>=0), "",BU10/BU4) -> 0 | BX10: =SUM(BX11:BX14) -> 0 | BY10: =IF(AND(BX4=0,BX10>=0), "",BX10/BX4) | BZ10: =IF(AND(BX10=0,BU10>0),100%,IF(AND(BX10<0,BU10=0),(BX10-BU10)/BX10,IF(AND(BX10>0,BU10>0),(BU10-BX10)/BX10,IF(AND(BX10=0,BU10=0),"",(BU10-BX10)/BX10)))) | CA10: =SUM(CA11:CA14) -> 0 | CB10: =IF(AND(CA4=0,CA10>=0), "",CA10/CA4) | CD10: =IF(AND(BQ10=0,CA10>0),100%,IF(AND(BQ10<0,CA10=0),(BQ10-CA10)/BQ10,IF(AND(BQ10>0,CA10>0),(CA10-BQ10)/BQ10,IF(AND(BQ10=0,CA10=0),"",(CA10-BQ10)/BQ10)))) | CE10: =SUM(CE11:CE14) -> 0 | CF10: =IF(AND(CE4=0,CE10>=0), "",CE10/CE4) -> 0 | CH10: =SUM(CH11:CH14) -> 0 | CI10: =IF(AND(CH4=0,CH10>=0), "",CH10/CH4) | CK10: =IF(AND(CA10=0,CH10>0),100%,IF(AND(CA10<0,CH10=0),(CA10-CH10)/CA10,IF(AND(CA10>0,CH10>0),(CH10-CA10)/CA10,IF(AND(CA10=0,CH10=0),"",(CH10-CA10)/CA10)))) | CL10: =SUM(CL11:CL14) -> 0 | CM10: =IF(AND(CL4=0,CL10>=0), "",CL10/CL4) -> 0 | CO10: =SUM(CO11:CO14) -> 0 | CP10: =IF(AND(CO4=0,CO10>=0), "",CO10/CO4) | CR10: =IF(AND(CH10=0,CO10>0),100%,IF(AND(CH10<0,CO10=0),(CH10-CO10)/CH10,IF(AND(CH10>0,CO10>0),(CO10-CH10)/CH10,IF(AND(CH10=0,CO10=0),"",(CO10-CH10)/CH10)))) | CS10: =SUM(CS11:CS14) -> 0 | CT10: =IF(AND(CS4=0,CS10>=0), "",CS10/CS4) -> 0 | CV10: =SUM(CV11:CV14) -> 0 | CW10: =IF(AND(CV4=0,CV10>=0), "",CV10/CV4) | CX10: =IF(AND(CV10=0,CS10>0),100%,IF(AND(CV10<0,CS10=0),(CV10-CS10)/CV10,IF(AND(CV10>0,CS10>0),(CS10-CV10)/CV10,IF(AND(CV10=0,CS10=0),"",(CS10-CV10)/CV10))))
A11: Ingresos por servicios del café | B11: =+'N EERR RODEO'!B10 -> 0 | C11: =IF(AND(B4=0,B11>=0), "",B11/B4) | E11: =+'N EERR RODEO'!C10 -> 0 | F11: =IF(AND(E4=0,E11>=0), "",E11/E4) -> 0 | H11: =+'N EERR RODEO'!D10 -> 0 | I11: =IF(AND(H4=0,H11>=0), "",H11/H4) -> 0 | K11: =IF(AND(E11=0,H11>0),100%,IF(AND(E11<0,H11=0),(E11-H11)/E11,IF(AND(E11>0,H11>0),(H11-E11)/E11,IF(AND(E11=0,H11=0),"",(H11-E11)/E11)))) | L11: =+E11+H11 -> 0 | M11: =IF(AND(L4=0,L11>=0), "",L11/L4) -> 0 | O11: =+'N EERR RODEO'!E10 -> 0 | P11: =IF(AND(O4=0,O11>=0), "",O11/O4) -> 0 | R11: =IF(AND(H11=0,O11>0),100%,IF(AND(H11<0,O11=0),(H11-O11)/H11,IF(AND(H11>0,O11>0),(O11-H11)/H11,IF(AND(H11=0,O11=0),"",(O11-H11)/H11)))) | S11: =+L11+O11 -> 0 | T11: =IF(AND(S4=0,S11>=0), "",S11/S4) -> 0 | W11: =IF(AND(V4=0,V11>=0), "",V11/V4) | X11: =IF(AND(V11=0,S11>0),100%,IF(AND(V11<0,S11=0),(V11-S11)/V11,IF(AND(V11>0,S11>0),(S11-V11)/V11,IF(AND(V11=0,S11=0),"",(S11-V11)/V11)))) | Y11: =+'N EERR RODEO'!F10 -> 0 | Z11: =IF(AND(Y4=0,Y11>=0), "",Y11/Y4) | AB11: =IF(AND(O11=0,Y11>0),100%,IF(AND(O11<0,Y11=0),(O11-Y11)/O11,IF(AND(O11>0,Y11>0),(Y11-O11)/O11,IF(AND(O11=0,Y11=0),"",(Y11-O11)/O11)))) | AC11: =+S11+Y11 -> 0 | AD11: =IF(AND(AC4=0,AC11>=0), "",AC11/AC4) -> 0 | AF11: =+'N EERR RODEO'!G10 -> 0 | AG11: =IF(AND(AF4=0,AF11>=0), "",AF11/AF4) | AI11: =IF(AND(Y11=0,AF11>0),100%,IF(AND(Y11<0,AF11=0),(Y11-AF11)/Y11,IF(AND(Y11>0,AF11>0),(AF11-Y11)/Y11,IF(AND(Y11=0,AF11=0),"",(AF11-Y11)/Y11)))) | AJ11: =+AC11+AF11 -> 0 | AK11: =IF(AND(AJ4=0,AJ11>=0), "",AJ11/AJ4) -> 0 | AM11: =+'N EERR RODEO'!H10 -> 0 | AN11: =IF(AND(AM4=0,AM11>=0), "",AM11/AM4) | AP11: =IF(AND(AF11=0,AM11>0),100%,IF(AND(AF11<0,AM11=0),(AF11-AM11)/AF11,IF(AND(AF11>0,AM11>0),(AM11-AF11)/AF11,IF(AND(AF11=0,AM11=0),"",(AM11-AF11)/AF11)))) | AQ11: =+AJ11+AM11 -> 0 | AR11: =IF(AND(AQ4=0,AQ11>=0), "",AQ11/AQ4) -> 0 | AT11: =+V11*2 -> 0 | AU11: =IF(AND(AT4=0,AT11>=0), "",AT11/AT4) | AV11: =IF(AND(AT11=0,AQ11>0),100%,IF(AND(AT11<0,AQ11=0),(AT11-AQ11)/AT11,IF(AND(AT11>0,AQ11>0),(AQ11-AT11)/AT11,IF(AND(AT11=0,AQ11=0),"",(AQ11-AT11)/AT11)))) | AW11: =+AQ11/6 -> 0 | AX11: =IF(AND(AW4=0,AW11>=0), "",AW11/AW4) -> 0 | AZ11: =+AT11/6 -> 0 | BA11: =IF(AND(AZ4=0,AZ11>=0), "",AZ11/AZ4) | BB11: =IF(AND(AZ11=0,AW11>0),100%,IF(AND(AZ11<0,AW11=0),(AZ11-AW11)/AZ11,IF(AND(AZ11>0,AW11>0),(AW11-AZ11)/AZ11,IF(AND(AZ11=0,AW11=0),"",(AW11-AZ11)/AZ11)))) | BC11: =+'N EERR RODEO'!I10 -> 0 | BD11: =IF(AND(BC4=0,BC11>=0), "",BC11/BC4) | BF11: =IF(AND(AM11=0,BC11>0),100%,IF(AND(AM11<0,BC11=0),(AM11-BC11)/AM11,IF(AND(AM11>0,BC11>0),(BC11-AM11)/AM11,IF(AND(AM11=0,BC11=0),"",(BC11-AM11)/AM11)))) | BG11: =+AQ11+BC11 -> 0 | BH11: =IF(AND(BG4=0,BG11>=0), "",BG11/BG4) -> 0 | BJ11: =+'N EERR RODEO'!J10 -> 0 | BK11: =IF(AND(BJ4=0,BJ11>=0), "",BJ11/BJ4) | BM11: =IF(AND(BC11=0,BJ11>0),100%,IF(AND(BC11<0,BJ11=0),(BC11-BJ11)/BC11,IF(AND(BC11>0,BJ11>0),(BJ11-BC11)/BC11,IF(AND(BC11=0,BJ11=0),"",(BJ11-BC11)/BC11)))) | BN11: =+BG11+BJ11 -> 0 | BO11: =IF(AND(BN4=0,BN11>=0), "",BN11/BN4) -> 0 | BQ11: =+'N EERR RODEO'!K10 -> 0 | BR11: =IF(AND(BQ4=0,BQ11>=0), "",BQ11/BQ4) | BT11: =IF(AND(BJ11=0,BQ11>0),100%,IF(AND(BJ11<0,BQ11=0),(BJ11-BQ11)/BJ11,IF(AND(BJ11>0,BQ11>0),(BQ11-BJ11)/BJ11,IF(AND(BJ11=0,BQ11=0),"",(BQ11-BJ11)/BJ11)))) | BU11: =+BN11+BQ11 -> 0 | BV11: =IF(AND(BU4=0,BU11>=0), "",BU11/BU4) -> 0 | BX11: =+AZ11*9 -> 0 | BY11: =IF(AND(BX4=0,BX11>=0), "",BX11/BX4) | BZ11: =IF(AND(BX11=0,BU11>0),100%,IF(AND(BX11<0,BU11=0),(BX11-BU11)/BX11,IF(AND(BX11>0,BU11>0),(BU11-BX11)/BX11,IF(AND(BX11=0,BU11=0),"",(BU11-BX11)/BX11)))) | CA11: =+'N EERR RODEO'!L10 -> 0 | CB11: =IF(AND(CA4=0,CA11>=0), "",CA11/CA4) | CD11: =IF(AND(BQ11=0,CA11>0),100%,IF(AND(BQ11<0,CA11=0),(BQ11-CA11)/BQ11,IF(AND(BQ11>0,CA11>0),(CA11-BQ11)/BQ11,IF(AND(BQ11=0,CA11=0),"",(CA11-BQ11)/BQ11)))) | CE11: =+BU11+CA11 -> 0 | CF11: =IF(AND(CE4=0,CE11>=0), "",CE11/CE4) -> 0 | CH11: =+'N EERR RODEO'!M10 -> 0 | CI11: =IF(AND(CH4=0,CH11>=0), "",CH11/CH4) | CK11: =IF(AND(CA11=0,CH11>0),100%,IF(AND(CA11<0,CH11=0),(CA11-CH11)/CA11,IF(AND(CA11>0,CH11>0),(CH11-CA11)/CA11,IF(AND(CA11=0,CH11=0),"",(CH11-CA11)/CA11)))) | CL11: =+CE11+CH11 -> 0 | CM11: =IF(AND(CL4=0,CL11>=0), "",CL11/CL4) -> 0 | CO11: =+'N EERR RODEO'!N10 -> 0 | CP11: =IF(AND(CO4=0,CO11>=0), "",CO11/CO4) | CR11: =IF(AND(CH11=0,CO11>0),100%,IF(AND(CH11<0,CO11=0),(CH11-CO11)/CH11,IF(AND(CH11>0,CO11>0),(CO11-CH11)/CH11,IF(AND(CH11=0,CO11=0),"",(CO11-CH11)/CH11)))) | CS11: =+CL11+CO11 -> 0 | CT11: =IF(AND(CS4=0,CS11>=0), "",CS11/CS4) -> 0 | CV11: =+AZ11*12 -> 0 | CW11: =IF(AND(CV4=0,CV11>=0), "",CV11/CV4) | CX11: =IF(AND(CV11=0,CS11>0),100%,IF(AND(CV11<0,CS11=0),(CV11-CS11)/CV11,IF(AND(CV11>0,CS11>0),(CS11-CV11)/CV11,IF(AND(CV11=0,CS11=0),"",(CS11-CV11)/CV11))))
A12: Ingresos por zona FIT | B12: =+'N EERR RODEO'!B11 -> 0 | C12: =IF(AND(B4=0,B12>=0), "",B12/B4) | E12: =+'N EERR RODEO'!C11 -> 0 | F12: =IF(AND(E4=0,E12>=0), "",E12/E4) -> 0 | H12: =+'N EERR RODEO'!D11 -> 0 | I12: =IF(AND(H4=0,H12>=0), "",H12/H4) -> 0 | K12: =IF(AND(E12=0,H12>0),100%,IF(AND(E12<0,H12=0),(E12-H12)/E12,IF(AND(E12>0,H12>0),(H12-E12)/E12,IF(AND(E12=0,H12=0),"",(H12-E12)/E12)))) | L12: =+E12+H12 -> 0 | M12: =IF(AND(L4=0,L12>=0), "",L12/L4) -> 0 | O12: =+'N EERR RODEO'!E11 -> 0 | P12: =IF(AND(O4=0,O12>=0), "",O12/O4) -> 0 | R12: =IF(AND(H12=0,O12>0),100%,IF(AND(H12<0,O12=0),(H12-O12)/H12,IF(AND(H12>0,O12>0),(O12-H12)/H12,IF(AND(H12=0,O12=0),"",(O12-H12)/H12)))) | S12: =+L12+O12 -> 0 | T12: =IF(AND(S4=0,S12>=0), "",S12/S4) -> 0 | W12: =IF(AND(V4=0,V12>=0), "",V12/V4) | X12: =IF(AND(V12=0,S12>0),100%,IF(AND(V12<0,S12=0),(V12-S12)/V12,IF(AND(V12>0,S12>0),(S12-V12)/V12,IF(AND(V12=0,S12=0),"",(S12-V12)/V12)))) | Y12: =+'N EERR RODEO'!F11 -> 0 | Z12: =IF(AND(Y4=0,Y12>=0), "",Y12/Y4) | AB12: =IF(AND(O12=0,Y12>0),100%,IF(AND(O12<0,Y12=0),(O12-Y12)/O12,IF(AND(O12>0,Y12>0),(Y12-O12)/O12,IF(AND(O12=0,Y12=0),"",(Y12-O12)/O12)))) | AC12: =+S12+Y12 -> 0 | AD12: =IF(AND(AC4=0,AC12>=0), "",AC12/AC4) -> 0 | AF12: =+'N EERR RODEO'!G11 -> 0 | AG12: =IF(AND(AF4=0,AF12>=0), "",AF12/AF4) | AI12: =IF(AND(Y12=0,AF12>0),100%,IF(AND(Y12<0,AF12=0),(Y12-AF12)/Y12,IF(AND(Y12>0,AF12>0),(AF12-Y12)/Y12,IF(AND(Y12=0,AF12=0),"",(AF12-Y12)/Y12)))) | AJ12: =+AC12+AF12 -> 0 | AK12: =IF(AND(AJ4=0,AJ12>=0), "",AJ12/AJ4) -> 0 | AM12: =+'N EERR RODEO'!H11 -> 0 | AN12: =IF(AND(AM4=0,AM12>=0), "",AM12/AM4) | AP12: =IF(AND(AF12=0,AM12>0),100%,IF(AND(AF12<0,AM12=0),(AF12-AM12)/AF12,IF(AND(AF12>0,AM12>0),(AM12-AF12)/AF12,IF(AND(AF12=0,AM12=0),"",(AM12-AF12)/AF12)))) | AQ12: =+AJ12+AM12 -> 0 | AR12: =IF(AND(AQ4=0,AQ12>=0), "",AQ12/AQ4) -> 0 | AT12: =+V12*2 -> 0 | AU12: =IF(AND(AT4=0,AT12>=0), "",AT12/AT4) | AV12: =IF(AND(AT12=0,AQ12>0),100%,IF(AND(AT12<0,AQ12=0),(AT12-AQ12)/AT12,IF(AND(AT12>0,AQ12>0),(AQ12-AT12)/AT12,IF(AND(AT12=0,AQ12=0),"",(AQ12-AT12)/AT12)))) | AW12: =+AQ12/6 -> 0 | AX12: =IF(AND(AW4=0,AW12>=0), "",AW12/AW4) -> 0 | AZ12: =+AT12/6 -> 0 | BA12: =IF(AND(AZ4=0,AZ12>=0), "",AZ12/AZ4) | BB12: =IF(AND(AZ12=0,AW12>0),100%,IF(AND(AZ12<0,AW12=0),(AZ12-AW12)/AZ12,IF(AND(AZ12>0,AW12>0),(AW12-AZ12)/AZ12,IF(AND(AZ12=0,AW12=0),"",(AW12-AZ12)/AZ12)))) | BC12: =+'N EERR RODEO'!I11 -> 0 | BD12: =IF(AND(BC4=0,BC12>=0), "",BC12/BC4) | BF12: =IF(AND(AM12=0,BC12>0),100%,IF(AND(AM12<0,BC12=0),(AM12-BC12)/AM12,IF(AND(AM12>0,BC12>0),(BC12-AM12)/AM12,IF(AND(AM12=0,BC12=0),"",(BC12-AM12)/AM12)))) | BG12: =+AQ12+BC12 -> 0 | BH12: =IF(AND(BG4=0,BG12>=0), "",BG12/BG4) -> 0 | BJ12: =+'N EERR RODEO'!J11 -> 0 | BK12: =IF(AND(BJ4=0,BJ12>=0), "",BJ12/BJ4) | BM12: =IF(AND(BC12=0,BJ12>0),100%,IF(AND(BC12<0,BJ12=0),(BC12-BJ12)/BC12,IF(AND(BC12>0,BJ12>0),(BJ12-BC12)/BC12,IF(AND(BC12=0,BJ12=0),"",(BJ12-BC12)/BC12)))) | BN12: =+BG12+BJ12 -> 0 | BO12: =IF(AND(BN4=0,BN12>=0), "",BN12/BN4) -> 0 | BQ12: =+'N EERR RODEO'!K11 -> 0 | BR12: =IF(AND(BQ4=0,BQ12>=0), "",BQ12/BQ4) | BT12: =IF(AND(BJ12=0,BQ12>0),100%,IF(AND(BJ12<0,BQ12=0),(BJ12-BQ12)/BJ12,IF(AND(BJ12>0,BQ12>0),(BQ12-BJ12)/BJ12,IF(AND(BJ12=0,BQ12=0),"",(BQ12-BJ12)/BJ12)))) | BU12: =+BN12+BQ12 -> 0 | BV12: =IF(AND(BU4=0,BU12>=0), "",BU12/BU4) -> 0 | BX12: =+AZ12*9 -> 0 | BY12: =IF(AND(BX4=0,BX12>=0), "",BX12/BX4) | BZ12: =IF(AND(BX12=0,BU12>0),100%,IF(AND(BX12<0,BU12=0),(BX12-BU12)/BX12,IF(AND(BX12>0,BU12>0),(BU12-BX12)/BX12,IF(AND(BX12=0,BU12=0),"",(BU12-BX12)/BX12)))) | CA12: =+'N EERR RODEO'!L11 -> 0 | CB12: =IF(AND(CA4=0,CA12>=0), "",CA12/CA4) | CD12: =IF(AND(BQ12=0,CA12>0),100%,IF(AND(BQ12<0,CA12=0),(BQ12-CA12)/BQ12,IF(AND(BQ12>0,CA12>0),(CA12-BQ12)/BQ12,IF(AND(BQ12=0,CA12=0),"",(CA12-BQ12)/BQ12)))) | CE12: =+BU12+CA12 -> 0 | CF12: =IF(AND(CE4=0,CE12>=0), "",CE12/CE4) -> 0 | CH12: =+'N EERR RODEO'!M11 -> 0 | CI12: =IF(AND(CH4=0,CH12>=0), "",CH12/CH4) | CK12: =IF(AND(CA12=0,CH12>0),100%,IF(AND(CA12<0,CH12=0),(CA12-CH12)/CA12,IF(AND(CA12>0,CH12>0),(CH12-CA12)/CA12,IF(AND(CA12=0,CH12=0),"",(CH12-CA12)/CA12)))) | CL12: =+CE12+CH12 -> 0 | CM12: =IF(AND(CL4=0,CL12>=0), "",CL12/CL4) -> 0 | CO12: =+'N EERR RODEO'!N11 -> 0 | CP12: =IF(AND(CO4=0,CO12>=0), "",CO12/CO4) | CR12: =IF(AND(CH12=0,CO12>0),100%,IF(AND(CH12<0,CO12=0),(CH12-CO12)/CH12,IF(AND(CH12>0,CO12>0),(CO12-CH12)/CH12,IF(AND(CH12=0,CO12=0),"",(CO12-CH12)/CH12)))) | CS12: =+CL12+CO12 -> 0 | CT12: =IF(AND(CS4=0,CS12>=0), "",CS12/CS4) -> 0 | CV12: =+AZ12*12 -> 0 | CW12: =IF(AND(CV4=0,CV12>=0), "",CV12/CV4) | CX12: =IF(AND(CV12=0,CS12>0),100%,IF(AND(CV12<0,CS12=0),(CV12-CS12)/CV12,IF(AND(CV12>0,CS12>0),(CS12-CV12)/CV12,IF(AND(CV12=0,CS12=0),"",(CS12-CV12)/CV12))))
A13: Ingresos por fletes | B13: =+'N EERR RODEO'!B12 -> 0 | C13: =IF(AND(B4=0,B13>=0), "",B13/B4) | E13: =+'N EERR RODEO'!C12 -> 0 | F13: =IF(AND(E4=0,E13>=0), "",E13/E4) -> 0 | H13: =+'N EERR RODEO'!D12 -> 0 | I13: =IF(AND(H4=0,H13>=0), "",H13/H4) -> 0 | K13: =IF(AND(E13=0,H13>0),100%,IF(AND(E13<0,H13=0),(E13-H13)/E13,IF(AND(E13>0,H13>0),(H13-E13)/E13,IF(AND(E13=0,H13=0),"",(H13-E13)/E13)))) | L13: =+E13+H13 -> 0 | M13: =IF(AND(L4=0,L13>=0), "",L13/L4) -> 0 | O13: =+'N EERR RODEO'!E12 -> 0 | P13: =IF(AND(O4=0,O13>=0), "",O13/O4) -> 0 | R13: =IF(AND(H13=0,O13>0),100%,IF(AND(H13<0,O13=0),(H13-O13)/H13,IF(AND(H13>0,O13>0),(O13-H13)/H13,IF(AND(H13=0,O13=0),"",(O13-H13)/H13)))) | S13: =+L13+O13 -> 0 | T13: =IF(AND(S4=0,S13>=0), "",S13/S4) -> 0 | W13: =IF(AND(V4=0,V13>=0), "",V13/V4) | X13: =IF(AND(V13=0,S13>0),100%,IF(AND(V13<0,S13=0),(V13-S13)/V13,IF(AND(V13>0,S13>0),(S13-V13)/V13,IF(AND(V13=0,S13=0),"",(S13-V13)/V13)))) | Y13: =+'N EERR RODEO'!F12 -> 0 | Z13: =IF(AND(Y4=0,Y13>=0), "",Y13/Y4) | AB13: =IF(AND(O13=0,Y13>0),100%,IF(AND(O13<0,Y13=0),(O13-Y13)/O13,IF(AND(O13>0,Y13>0),(Y13-O13)/O13,IF(AND(O13=0,Y13=0),"",(Y13-O13)/O13)))) | AC13: =+S13+Y13 -> 0 | AD13: =IF(AND(AC4=0,AC13>=0), "",AC13/AC4) -> 0 | AF13: =+'N EERR RODEO'!G12 -> 0 | AG13: =IF(AND(AF4=0,AF13>=0), "",AF13/AF4) | AI13: =IF(AND(Y13=0,AF13>0),100%,IF(AND(Y13<0,AF13=0),(Y13-AF13)/Y13,IF(AND(Y13>0,AF13>0),(AF13-Y13)/Y13,IF(AND(Y13=0,AF13=0),"",(AF13-Y13)/Y13)))) | AJ13: =+AC13+AF13 -> 0 | AK13: =IF(AND(AJ4=0,AJ13>=0), "",AJ13/AJ4) -> 0 | AM13: =+'N EERR RODEO'!H12 -> 0 | AN13: =IF(AND(AM4=0,AM13>=0), "",AM13/AM4) | AP13: =IF(AND(AF13=0,AM13>0),100%,IF(AND(AF13<0,AM13=0),(AF13-AM13)/AF13,IF(AND(AF13>0,AM13>0),(AM13-AF13)/AF13,IF(AND(AF13=0,AM13=0),"",(AM13-AF13)/AF13)))) | AQ13: =+AJ13+AM13 -> 0 | AR13: =IF(AND(AQ4=0,AQ13>=0), "",AQ13/AQ4) -> 0 | AT13: =+V13*2 -> 0 | AU13: =IF(AND(AT4=0,AT13>=0), "",AT13/AT4) | AV13: =IF(AND(AT13=0,AQ13>0),100%,IF(AND(AT13<0,AQ13=0),(AT13-AQ13)/AT13,IF(AND(AT13>0,AQ13>0),(AQ13-AT13)/AT13,IF(AND(AT13=0,AQ13=0),"",(AQ13-AT13)/AT13)))) | AW13: =+AQ13/6 -> 0 | AX13: =IF(AND(AW4=0,AW13>=0), "",AW13/AW4) -> 0 | AZ13: =+AT13/6 -> 0 | BA13: =IF(AND(AZ4=0,AZ13>=0), "",AZ13/AZ4) | BB13: =IF(AND(AZ13=0,AW13>0),100%,IF(AND(AZ13<0,AW13=0),(AZ13-AW13)/AZ13,IF(AND(AZ13>0,AW13>0),(AW13-AZ13)/AZ13,IF(AND(AZ13=0,AW13=0),"",(AW13-AZ13)/AZ13)))) | BC13: =+'N EERR RODEO'!I12 -> 0 | BD13: =IF(AND(BC4=0,BC13>=0), "",BC13/BC4) | BF13: =IF(AND(AM13=0,BC13>0),100%,IF(AND(AM13<0,BC13=0),(AM13-BC13)/AM13,IF(AND(AM13>0,BC13>0),(BC13-AM13)/AM13,IF(AND(AM13=0,BC13=0),"",(BC13-AM13)/AM13)))) | BG13: =+AQ13+BC13 -> 0 | BH13: =IF(AND(BG4=0,BG13>=0), "",BG13/BG4) -> 0 | BJ13: =+'N EERR RODEO'!J12 -> 0 | BK13: =IF(AND(BJ4=0,BJ13>=0), "",BJ13/BJ4) | BM13: =IF(AND(BC13=0,BJ13>0),100%,IF(AND(BC13<0,BJ13=0),(BC13-BJ13)/BC13,IF(AND(BC13>0,BJ13>0),(BJ13-BC13)/BC13,IF(AND(BC13=0,BJ13=0),"",(BJ13-BC13)/BC13)))) | BN13: =+BG13+BJ13 -> 0 | BO13: =IF(AND(BN4=0,BN13>=0), "",BN13/BN4) -> 0 | BQ13: =+'N EERR RODEO'!K12 -> 0 | BR13: =IF(AND(BQ4=0,BQ13>=0), "",BQ13/BQ4) | BT13: =IF(AND(BJ13=0,BQ13>0),100%,IF(AND(BJ13<0,BQ13=0),(BJ13-BQ13)/BJ13,IF(AND(BJ13>0,BQ13>0),(BQ13-BJ13)/BJ13,IF(AND(BJ13=0,BQ13=0),"",(BQ13-BJ13)/BJ13)))) | BU13: =+BN13+BQ13 -> 0 | BV13: =IF(AND(BU4=0,BU13>=0), "",BU13/BU4) -> 0 | BX13: =+AZ13*9 -> 0 | BY13: =IF(AND(BX4=0,BX13>=0), "",BX13/BX4) | BZ13: =IF(AND(BX13=0,BU13>0),100%,IF(AND(BX13<0,BU13=0),(BX13-BU13)/BX13,IF(AND(BX13>0,BU13>0),(BU13-BX13)/BX13,IF(AND(BX13=0,BU13=0),"",(BU13-BX13)/BX13)))) | CA13: =+'N EERR RODEO'!L12 -> 0 | CB13: =IF(AND(CA4=0,CA13>=0), "",CA13/CA4) | CD13: =IF(AND(BQ13=0,CA13>0),100%,IF(AND(BQ13<0,CA13=0),(BQ13-CA13)/BQ13,IF(AND(BQ13>0,CA13>0),(CA13-BQ13)/BQ13,IF(AND(BQ13=0,CA13=0),"",(CA13-BQ13)/BQ13)))) | CE13: =+BU13+CA13 -> 0 | CF13: =IF(AND(CE4=0,CE13>=0), "",CE13/CE4) -> 0 | CH13: =+'N EERR RODEO'!M12 -> 0 | CI13: =IF(AND(CH4=0,CH13>=0), "",CH13/CH4) | CK13: =IF(AND(CA13=0,CH13>0),100%,IF(AND(CA13<0,CH13=0),(CA13-CH13)/CA13,IF(AND(CA13>0,CH13>0),(CH13-CA13)/CA13,IF(AND(CA13=0,CH13=0),"",(CH13-CA13)/CA13)))) | CL13: =+CE13+CH13 -> 0 | CM13: =IF(AND(CL4=0,CL13>=0), "",CL13/CL4) -> 0 | CO13: =+'N EERR RODEO'!N12 -> 0 | CP13: =IF(AND(CO4=0,CO13>=0), "",CO13/CO4) | CR13: =IF(AND(CH13=0,CO13>0),100%,IF(AND(CH13<0,CO13=0),(CH13-CO13)/CH13,IF(AND(CH13>0,CO13>0),(CO13-CH13)/CH13,IF(AND(CH13=0,CO13=0),"",(CO13-CH13)/CH13)))) | CS13: =+CL13+CO13 -> 0 | CT13: =IF(AND(CS4=0,CS13>=0), "",CS13/CS4) -> 0 | CV13: =+AZ13*12 -> 0 | CW13: =IF(AND(CV4=0,CV13>=0), "",CV13/CV4) | CX13: =IF(AND(CV13=0,CS13>0),100%,IF(AND(CV13<0,CS13=0),(CV13-CS13)/CV13,IF(AND(CV13>0,CS13>0),(CS13-CV13)/CV13,IF(AND(CV13=0,CS13=0),"",(CS13-CV13)/CV13))))
K14: =IF(AND(E14=0,H14>0),100%,IF(AND(E14<0,H14=0),(E14-H14)/E14,IF(AND(E14>0,H14>0),(H14-E14)/E14,IF(AND(E14=0,H14=0),"",(H14-E14)/E14)))) | R14: =IF(AND(H14=0,O14>0),100%,IF(AND(H14<0,O14=0),(H14-O14)/H14,IF(AND(H14>0,O14>0),(O14-H14)/H14,IF(AND(H14=0,O14=0),"",(O14-H14)/H14)))) | X14: =IF(AND(V14=0,S14>0),100%,IF(AND(V14<0,S14=0),(V14-S14)/V14,IF(AND(V14>0,S14>0),(S14-V14)/V14,IF(AND(V14=0,S14=0),"",(S14-V14)/V14)))) | AB14: =IF(AND(O14=0,Y14>0),100%,IF(AND(O14<0,Y14=0),(O14-Y14)/O14,IF(AND(O14>0,Y14>0),(Y14-O14)/O14,IF(AND(O14=0,Y14=0),"",(Y14-O14)/O14)))) | AI14: =IF(AND(Y14=0,AF14>0),100%,IF(AND(Y14<0,AF14=0),(Y14-AF14)/Y14,IF(AND(Y14>0,AF14>0),(AF14-Y14)/Y14,IF(AND(Y14=0,AF14=0),"",(AF14-Y14)/Y14)))) | AJ14: =+AC14+AF14 -> 0 | AP14: =IF(AND(AF14=0,AM14>0),100%,IF(AND(AF14<0,AM14=0),(AF14-AM14)/AF14,IF(AND(AF14>0,AM14>0),(AM14-AF14)/AF14,IF(AND(AF14=0,AM14=0),"",(AM14-AF14)/AF14)))) | AQ14: =+AJ14+AM14 -> 0 | AT14: =+V14*2 -> 0 | AV14: =IF(AND(AT14=0,AQ14>0),100%,IF(AND(AT14<0,AQ14=0),(AT14-AQ14)/AT14,IF(AND(AT14>0,AQ14>0),(AQ14-AT14)/AT14,IF(AND(AT14=0,AQ14=0),"",(AQ14-AT14)/AT14)))) | AW14: =+AQ14/6 -> 0 | AZ14: =+AT14/6 -> 0 | BB14: =IF(AND(AZ14=0,AW14>0),100%,IF(AND(AZ14<0,AW14=0),(AZ14-AW14)/AZ14,IF(AND(AZ14>0,AW14>0),(AW14-AZ14)/AZ14,IF(AND(AZ14=0,AW14=0),"",(AW14-AZ14)/AZ14)))) | BF14: =IF(AND(AM14=0,BC14>0),100%,IF(AND(AM14<0,BC14=0),(AM14-BC14)/AM14,IF(AND(AM14>0,BC14>0),(BC14-AM14)/AM14,IF(AND(AM14=0,BC14=0),"",(BC14-AM14)/AM14)))) | BG14: =+AQ14+BC14 -> 0 | BM14: =IF(AND(BC14=0,BJ14>0),100%,IF(AND(BC14<0,BJ14=0),(BC14-BJ14)/BC14,IF(AND(BC14>0,BJ14>0),(BJ14-BC14)/BC14,IF(AND(BC14=0,BJ14=0),"",(BJ14-BC14)/BC14)))) | BN14: =+BG14+BJ14 -> 0 | BT14: =IF(AND(BJ14=0,BQ14>0),100%,IF(AND(BJ14<0,BQ14=0),(BJ14-BQ14)/BJ14,IF(AND(BJ14>0,BQ14>0),(BQ14-BJ14)/BJ14,IF(AND(BJ14=0,BQ14=0),"",(BQ14-BJ14)/BJ14)))) | BU14: =+BN14+BQ14 -> 0 | BX14: =+AZ14*9 -> 0 | BZ14: =IF(AND(BX14=0,BU14>0),100%,IF(AND(BX14<0,BU14=0),(BX14-BU14)/BX14,IF(AND(BX14>0,BU14>0),(BU14-BX14)/BX14,IF(AND(BX14=0,BU14=0),"",(BU14-BX14)/BX14)))) | CD14: =IF(AND(BQ14=0,CA14>0),100%,IF(AND(BQ14<0,CA14=0),(BQ14-CA14)/BQ14,IF(AND(BQ14>0,CA14>0),(CA14-BQ14)/BQ14,IF(AND(BQ14=0,CA14=0),"",(CA14-BQ14)/BQ14)))) | CK14: =IF(AND(CA14=0,CH14>0),100%,IF(AND(CA14<0,CH14=0),(CA14-CH14)/CA14,IF(AND(CA14>0,CH14>0),(CH14-CA14)/CA14,IF(AND(CA14=0,CH14=0),"",(CH14-CA14)/CA14)))) | CL14: =+CE14+CH14 -> 0 | CR14: =IF(AND(CH14=0,CO14>0),100%,IF(AND(CH14<0,CO14=0),(CH14-CO14)/CH14,IF(AND(CH14>0,CO14>0),(CO14-CH14)/CH14,IF(AND(CH14=0,CO14=0),"",(CO14-CH14)/CH14)))) | CS14: =+CL14+CO14 -> 0 | CV14: =+AZ14*12 -> 0 | CX14: =IF(AND(CV14=0,CS14>0),100%,IF(AND(CV14<0,CS14=0),(CV14-CS14)/CV14,IF(AND(CV14>0,CS14>0),(CS14-CV14)/CV14,IF(AND(CV14=0,CS14=0),"",(CS14-CV14)/CV14))))
A15: Subtotal Ingresos por Eventos | B15: =SUM(B16:B17) -> 0 | C15: =IF(AND(B4=0,B15>=0), "",B15/B4) | E15: =SUM(E16:E17) -> 0 | F15: =IF(AND(E4=0,E15>=0), "",E15/E4) -> 0 | H15: =SUM(H16:H17) -> 0 | I15: =IF(AND(H4=0,H15>=0), "",H15/H4) -> 0 | K15: =IF(AND(E15=0,H15>0),100%,IF(AND(E15<0,H15=0),(E15-H15)/E15,IF(AND(E15>0,H15>0),(H15-E15)/E15,IF(AND(E15=0,H15=0),"",(H15-E15)/E15)))) | L15: =SUM(L16:L17) -> 0 | M15: =IF(AND(L4=0,L15>=0), "",L15/L4) -> 0 | O15: =SUM(O16:O17) -> 0 | P15: =IF(AND(O4=0,O15>=0), "",O15/O4) -> 0 | R15: =IF(AND(H15=0,O15>0),100%,IF(AND(H15<0,O15=0),(H15-O15)/H15,IF(AND(H15>0,O15>0),(O15-H15)/H15,IF(AND(H15=0,O15=0),"",(O15-H15)/H15)))) | S15: =SUM(S16:S17) -> 0 | T15: =IF(AND(S4=0,S15>=0), "",S15/S4) -> 0 | V15: =SUM(V16:V17) -> 0 | W15: =IF(AND(V4=0,V15>=0), "",V15/V4) | X15: =IF(AND(V15=0,S15>0),100%,IF(AND(V15<0,S15=0),(V15-S15)/V15,IF(AND(V15>0,S15>0),(S15-V15)/V15,IF(AND(V15=0,S15=0),"",(S15-V15)/V15)))) | Y15: =SUM(Y16:Y17) -> 0 | Z15: =IF(AND(Y4=0,Y15>=0), "",Y15/Y4) | AB15: =IF(AND(O15=0,Y15>0),100%,IF(AND(O15<0,Y15=0),(O15-Y15)/O15,IF(AND(O15>0,Y15>0),(Y15-O15)/O15,IF(AND(O15=0,Y15=0),"",(Y15-O15)/O15)))) | AC15: =SUM(AC16:AC17) -> 0 | AD15: =IF(AND(AC4=0,AC15>=0), "",AC15/AC4) -> 0 | AF15: =SUM(AF16:AF17) -> 0 | AG15: =IF(AND(AF4=0,AF15>=0), "",AF15/AF4) | AI15: =IF(AND(Y15=0,AF15>0),100%,IF(AND(Y15<0,AF15=0),(Y15-AF15)/Y15,IF(AND(Y15>0,AF15>0),(AF15-Y15)/Y15,IF(AND(Y15=0,AF15=0),"",(AF15-Y15)/Y15)))) | AJ15: =SUM(AJ16:AJ17) -> 0 | AK15: =IF(AND(AJ4=0,AJ15>=0), "",AJ15/AJ4) -> 0 | AM15: =SUM(AM16:AM17) -> 0 | AN15: =IF(AND(AM4=0,AM15>=0), "",AM15/AM4) | AP15: =IF(AND(AF15=0,AM15>0),100%,IF(AND(AF15<0,AM15=0),(AF15-AM15)/AF15,IF(AND(AF15>0,AM15>0),(AM15-AF15)/AF15,IF(AND(AF15=0,AM15=0),"",(AM15-AF15)/AF15)))) | AQ15: =SUM(AQ16:AQ17) -> 0 | AR15: =IF(AND(AQ4=0,AQ15>=0), "",AQ15/AQ4) -> 0 | AT15: =SUM(AT16:AT17) -> 0 | AU15: =IF(AND(AT4=0,AT15>=0), "",AT15/AT4) | AV15: =IF(AND(AT15=0,AQ15>0),100%,IF(AND(AT15<0,AQ15=0),(AT15-AQ15)/AT15,IF(AND(AT15>0,AQ15>0),(AQ15-AT15)/AT15,IF(AND(AT15=0,AQ15=0),"",(AQ15-AT15)/AT15)))) | AW15: =SUM(AW16:AW17) -> 0 | AX15: =IF(AND(AW4=0,AW15>=0), "",AW15/AW4) -> 0 | AZ15: =SUM(AZ16:AZ17) -> 0 | BA15: =IF(AND(AZ4=0,AZ15>=0), "",AZ15/AZ4) | BB15: =IF(AND(AZ15=0,AW15>0),100%,IF(AND(AZ15<0,AW15=0),(AZ15-AW15)/AZ15,IF(AND(AZ15>0,AW15>0),(AW15-AZ15)/AZ15,IF(AND(AZ15=0,AW15=0),"",(AW15-AZ15)/AZ15)))) | BC15: =SUM(BC16:BC17) -> 0 | BD15: =IF(AND(BC4=0,BC15>=0), "",BC15/BC4) | BF15: =IF(AND(AM15=0,BC15>0),100%,IF(AND(AM15<0,BC15=0),(AM15-BC15)/AM15,IF(AND(AM15>0,BC15>0),(BC15-AM15)/AM15,IF(AND(AM15=0,BC15=0),"",(BC15-AM15)/AM15)))) | BG15: =SUM(BG16:BG17) -> 0 | BH15: =IF(AND(BG4=0,BG15>=0), "",BG15/BG4) -> 0 | BJ15: =SUM(BJ16:BJ17) -> 0 | BK15: =IF(AND(BJ4=0,BJ15>=0), "",BJ15/BJ4) | BM15: =IF(AND(BC15=0,BJ15>0),100%,IF(AND(BC15<0,BJ15=0),(BC15-BJ15)/BC15,IF(AND(BC15>0,BJ15>0),(BJ15-BC15)/BC15,IF(AND(BC15=0,BJ15=0),"",(BJ15-BC15)/BC15)))) | BN15: =SUM(BN16:BN17) -> 0 | BO15: =IF(AND(BN4=0,BN15>=0), "",BN15/BN4) -> 0 | BQ15: =SUM(BQ16:BQ17) -> 0 | BR15: =IF(AND(BQ4=0,BQ15>=0), "",BQ15/BQ4) | BT15: =IF(AND(BJ15=0,BQ15>0),100%,IF(AND(BJ15<0,BQ15=0),(BJ15-BQ15)/BJ15,IF(AND(BJ15>0,BQ15>0),(BQ15-BJ15)/BJ15,IF(AND(BJ15=0,BQ15=0),"",(BQ15-BJ15)/BJ15)))) | BU15: =SUM(BU16:BU17) -> 0 | BV15: =IF(AND(BU4=0,BU15>=0), "",BU15/BU4) -> 0 | BX15: =SUM(BX16:BX17) -> 0 | BY15: =IF(AND(BX4=0,BX15>=0), "",BX15/BX4) | BZ15: =IF(AND(BX15=0,BU15>0),100%,IF(AND(BX15<0,BU15=0),(BX15-BU15)/BX15,IF(AND(BX15>0,BU15>0),(BU15-BX15)/BX15,IF(AND(BX15=0,BU15=0),"",(BU15-BX15)/BX15)))) | CA15: =SUM(CA16:CA17) -> 0 | CB15: =IF(AND(CA4=0,CA15>=0), "",CA15/CA4) | CD15: =IF(AND(BQ15=0,CA15>0),100%,IF(AND(BQ15<0,CA15=0),(BQ15-CA15)/BQ15,IF(AND(BQ15>0,CA15>0),(CA15-BQ15)/BQ15,IF(AND(BQ15=0,CA15=0),"",(CA15-BQ15)/BQ15)))) | CE15: =SUM(CE16:CE17) -> 0 | CF15: =IF(AND(CE4=0,CE15>=0), "",CE15/CE4) -> 0 | CH15: =SUM(CH16:CH17) -> 0 | CI15: =IF(AND(CH4=0,CH15>=0), "",CH15/CH4) | CK15: =IF(AND(CA15=0,CH15>0),100%,IF(AND(CA15<0,CH15=0),(CA15-CH15)/CA15,IF(AND(CA15>0,CH15>0),(CH15-CA15)/CA15,IF(AND(CA15=0,CH15=0),"",(CH15-CA15)/CA15)))) | CL15: =SUM(CL16:CL17) -> 0 | CM15: =IF(AND(CL4=0,CL15>=0), "",CL15/CL4) -> 0 | CO15: =SUM(CO16:CO17) -> 0 | CP15: =IF(AND(CO4=0,CO15>=0), "",CO15/CO4) | CR15: =IF(AND(CH15=0,CO15>0),100%,IF(AND(CH15<0,CO15=0),(CH15-CO15)/CH15,IF(AND(CH15>0,CO15>0),(CO15-CH15)/CH15,IF(AND(CH15=0,CO15=0),"",(CO15-CH15)/CH15)))) | CS15: =SUM(CS16:CS17) -> 0 | CT15: =IF(AND(CS4=0,CS15>=0), "",CS15/CS4) -> 0 | CV15: =SUM(CV16:CV17) -> 0 | CW15: =IF(AND(CV4=0,CV15>=0), "",CV15/CV4) | CX15: =IF(AND(CV15=0,CS15>0),100%,IF(AND(CV15<0,CS15=0),(CV15-CS15)/CV15,IF(AND(CV15>0,CS15>0),(CS15-CV15)/CV15,IF(AND(CV15=0,CS15=0),"",(CS15-CV15)/CV15))))
A16: Ingresos por eventos | B16: =+'N EERR RODEO'!B14 -> 0 | C16: =IF(AND(B4=0,B16>=0), "",B16/B4) | E16: =+'N EERR RODEO'!C14 -> 0 | F16: =IF(AND(E4=0,E16>=0), "",E16/E4) -> 0 | H16: =+'N EERR RODEO'!D14 -> 0 | I16: =IF(AND(H4=0,H16>=0), "",H16/H4) -> 0 | K16: =IF(AND(E16=0,H16>0),100%,IF(AND(E16<0,H16=0),(E16-H16)/E16,IF(AND(E16>0,H16>0),(H16-E16)/E16,IF(AND(E16=0,H16=0),"",(H16-E16)/E16)))) | L16: =+E16+H16 -> 0 | M16: =IF(AND(L4=0,L16>=0), "",L16/L4) -> 0 | O16: =+'N EERR RODEO'!E14 -> 0 | P16: =IF(AND(O4=0,O16>=0), "",O16/O4) -> 0 | R16: =IF(AND(H16=0,O16>0),100%,IF(AND(H16<0,O16=0),(H16-O16)/H16,IF(AND(H16>0,O16>0),(O16-H16)/H16,IF(AND(H16=0,O16=0),"",(O16-H16)/H16)))) | S16: =+L16+O16 -> 0 | T16: =IF(AND(S4=0,S16>=0), "",S16/S4) -> 0 | W16: =IF(AND(V4=0,V16>=0), "",V16/V4) | X16: =IF(AND(V16=0,S16>0),100%,IF(AND(V16<0,S16=0),(V16-S16)/V16,IF(AND(V16>0,S16>0),(S16-V16)/V16,IF(AND(V16=0,S16=0),"",(S16-V16)/V16)))) | Y16: =+'N EERR RODEO'!F14 -> 0 | Z16: =IF(AND(Y4=0,Y16>=0), "",Y16/Y4) | AB16: =IF(AND(O16=0,Y16>0),100%,IF(AND(O16<0,Y16=0),(O16-Y16)/O16,IF(AND(O16>0,Y16>0),(Y16-O16)/O16,IF(AND(O16=0,Y16=0),"",(Y16-O16)/O16)))) | AC16: =+S16+Y16 -> 0 | AD16: =IF(AND(AC4=0,AC16>=0), "",AC16/AC4) -> 0 | AF16: =+'N EERR RODEO'!G14 -> 0 | AG16: =IF(AND(AF4=0,AF16>=0), "",AF16/AF4) | AI16: =IF(AND(Y16=0,AF16>0),100%,IF(AND(Y16<0,AF16=0),(Y16-AF16)/Y16,IF(AND(Y16>0,AF16>0),(AF16-Y16)/Y16,IF(AND(Y16=0,AF16=0),"",(AF16-Y16)/Y16)))) | AJ16: =+AC16+AF16 -> 0 | AK16: =IF(AND(AJ4=0,AJ16>=0), "",AJ16/AJ4) -> 0 | AM16: =+'N EERR RODEO'!H14 -> 0 | AN16: =IF(AND(AM4=0,AM16>=0), "",AM16/AM4) | AP16: =IF(AND(AF16=0,AM16>0),100%,IF(AND(AF16<0,AM16=0),(AF16-AM16)/AF16,IF(AND(AF16>0,AM16>0),(AM16-AF16)/AF16,IF(AND(AF16=0,AM16=0),"",(AM16-AF16)/AF16)))) | AQ16: =+AJ16+AM16 -> 0 | AR16: =IF(AND(AQ4=0,AQ16>=0), "",AQ16/AQ4) -> 0 | AT16: =+V16*2 -> 0 | AU16: =IF(AND(AT4=0,AT16>=0), "",AT16/AT4) | AV16: =IF(AND(AT16=0,AQ16>0),100%,IF(AND(AT16<0,AQ16=0),(AT16-AQ16)/AT16,IF(AND(AT16>0,AQ16>0),(AQ16-AT16)/AT16,IF(AND(AT16=0,AQ16=0),"",(AQ16-AT16)/AT16)))) | AW16: =+AQ16/6 -> 0 | AX16: =IF(AND(AW4=0,AW16>=0), "",AW16/AW4) -> 0 | AZ16: =+AT16/6 -> 0 | BA16: =IF(AND(AZ4=0,AZ16>=0), "",AZ16/AZ4) | BB16: =IF(AND(AZ16=0,AW16>0),100%,IF(AND(AZ16<0,AW16=0),(AZ16-AW16)/AZ16,IF(AND(AZ16>0,AW16>0),(AW16-AZ16)/AZ16,IF(AND(AZ16=0,AW16=0),"",(AW16-AZ16)/AZ16)))) | BC16: =+'N EERR RODEO'!I14 -> 0 | BD16: =IF(AND(BC4=0,BC16>=0), "",BC16/BC4) | BF16: =IF(AND(AM16=0,BC16>0),100%,IF(AND(AM16<0,BC16=0),(AM16-BC16)/AM16,IF(AND(AM16>0,BC16>0),(BC16-AM16)/AM16,IF(AND(AM16=0,BC16=0),"",(BC16-AM16)/AM16)))) | BG16: =+AQ16+BC16 -> 0 | BH16: =IF(AND(BG4=0,BG16>=0), "",BG16/BG4) -> 0 | BJ16: =+'N EERR RODEO'!J14 -> 0 | BK16: =IF(AND(BJ4=0,BJ16>=0), "",BJ16/BJ4) | BM16: =IF(AND(BC16=0,BJ16>0),100%,IF(AND(BC16<0,BJ16=0),(BC16-BJ16)/BC16,IF(AND(BC16>0,BJ16>0),(BJ16-BC16)/BC16,IF(AND(BC16=0,BJ16=0),"",(BJ16-BC16)/BC16)))) | BN16: =+BG16+BJ16 -> 0 | BO16: =IF(AND(BN4=0,BN16>=0), "",BN16/BN4) -> 0 | BQ16: =+'N EERR RODEO'!K14 -> 0 | BR16: =IF(AND(BQ4=0,BQ16>=0), "",BQ16/BQ4) | BT16: =IF(AND(BJ16=0,BQ16>0),100%,IF(AND(BJ16<0,BQ16=0),(BJ16-BQ16)/BJ16,IF(AND(BJ16>0,BQ16>0),(BQ16-BJ16)/BJ16,IF(AND(BJ16=0,BQ16=0),"",(BQ16-BJ16)/BJ16)))) | BU16: =+BN16+BQ16 -> 0 | BV16: =IF(AND(BU4=0,BU16>=0), "",BU16/BU4) -> 0 | BX16: =+AZ16*9 -> 0 | BY16: =IF(AND(BX4=0,BX16>=0), "",BX16/BX4) | BZ16: =IF(AND(BX16=0,BU16>0),100%,IF(AND(BX16<0,BU16=0),(BX16-BU16)/BX16,IF(AND(BX16>0,BU16>0),(BU16-BX16)/BX16,IF(AND(BX16=0,BU16=0),"",(BU16-BX16)/BX16)))) | CA16: =+'N EERR RODEO'!L14 -> 0 | CB16: =IF(AND(CA4=0,CA16>=0), "",CA16/CA4) | CD16: =IF(AND(BQ16=0,CA16>0),100%,IF(AND(BQ16<0,CA16=0),(BQ16-CA16)/BQ16,IF(AND(BQ16>0,CA16>0),(CA16-BQ16)/BQ16,IF(AND(BQ16=0,CA16=0),"",(CA16-BQ16)/BQ16)))) | CE16: =+BU16+CA16 -> 0 | CF16: =IF(AND(CE4=0,CE16>=0), "",CE16/CE4) -> 0 | CH16: =+'N EERR RODEO'!M14 -> 0 | CI16: =IF(AND(CH4=0,CH16>=0), "",CH16/CH4) | CK16: =IF(AND(CA16=0,CH16>0),100%,IF(AND(CA16<0,CH16=0),(CA16-CH16)/CA16,IF(AND(CA16>0,CH16>0),(CH16-CA16)/CA16,IF(AND(CA16=0,CH16=0),"",(CH16-CA16)/CA16)))) | CL16: =+CE16+CH16 -> 0 | CM16: =IF(AND(CL4=0,CL16>=0), "",CL16/CL4) -> 0 | CO16: =+'N EERR RODEO'!N14 -> 0 | CP16: =IF(AND(CO4=0,CO16>=0), "",CO16/CO4) | CR16: =IF(AND(CH16=0,CO16>0),100%,IF(AND(CH16<0,CO16=0),(CH16-CO16)/CH16,IF(AND(CH16>0,CO16>0),(CO16-CH16)/CH16,IF(AND(CH16=0,CO16=0),"",(CO16-CH16)/CH16)))) | CS16: =+CL16+CO16 -> 0 | CT16: =IF(AND(CS4=0,CS16>=0), "",CS16/CS4) -> 0 | CV16: =+AZ16*12 -> 0 | CW16: =IF(AND(CV4=0,CV16>=0), "",CV16/CV4) | CX16: =IF(AND(CV16=0,CS16>0),100%,IF(AND(CV16<0,CS16=0),(CV16-CS16)/CV16,IF(AND(CV16>0,CS16>0),(CS16-CV16)/CV16,IF(AND(CV16=0,CS16=0),"",(CS16-CV16)/CV16))))
K17: =IF(AND(E17=0,H17>0),100%,IF(AND(E17<0,H17=0),(E17-H17)/E17,IF(AND(E17>0,H17>0),(H17-E17)/E17,IF(AND(E17=0,H17=0),"",(H17-E17)/E17)))) | R17: =IF(AND(H17=0,O17>0),100%,IF(AND(H17<0,O17=0),(H17-O17)/H17,IF(AND(H17>0,O17>0),(O17-H17)/H17,IF(AND(H17=0,O17=0),"",(O17-H17)/H17)))) | X17: =IF(AND(V17=0,S17>0),100%,IF(AND(V17<0,S17=0),(V17-S17)/V17,IF(AND(V17>0,S17>0),(S17-V17)/V17,IF(AND(V17=0,S17=0),"",(S17-V17)/V17)))) | AB17: =IF(AND(O17=0,Y17>0),100%,IF(AND(O17<0,Y17=0),(O17-Y17)/O17,IF(AND(O17>0,Y17>0),(Y17-O17)/O17,IF(AND(O17=0,Y17=0),"",(Y17-O17)/O17)))) | AI17: =IF(AND(Y17=0,AF17>0),100%,IF(AND(Y17<0,AF17=0),(Y17-AF17)/Y17,IF(AND(Y17>0,AF17>0),(AF17-Y17)/Y17,IF(AND(Y17=0,AF17=0),"",(AF17-Y17)/Y17)))) | AJ17: =+AC17+AF17 -> 0 | AP17: =IF(AND(AF17=0,AM17>0),100%,IF(AND(AF17<0,AM17=0),(AF17-AM17)/AF17,IF(AND(AF17>0,AM17>0),(AM17-AF17)/AF17,IF(AND(AF17=0,AM17=0),"",(AM17-AF17)/AF17)))) | AQ17: =+AJ17+AM17 -> 0 | AT17: =+V17*2 -> 0 | AV17: =IF(AND(AT17=0,AQ17>0),100%,IF(AND(AT17<0,AQ17=0),(AT17-AQ17)/AT17,IF(AND(AT17>0,AQ17>0),(AQ17-AT17)/AT17,IF(AND(AT17=0,AQ17=0),"",(AQ17-AT17)/AT17)))) | AW17: =+AQ17/6 -> 0 | AZ17: =+AT17/6 -> 0 | BB17: =IF(AND(AZ17=0,AW17>0),100%,IF(AND(AZ17<0,AW17=0),(AZ17-AW17)/AZ17,IF(AND(AZ17>0,AW17>0),(AW17-AZ17)/AZ17,IF(AND(AZ17=0,AW17=0),"",(AW17-AZ17)/AZ17)))) | BF17: =IF(AND(AM17=0,BC17>0),100%,IF(AND(AM17<0,BC17=0),(AM17-BC17)/AM17,IF(AND(AM17>0,BC17>0),(BC17-AM17)/AM17,IF(AND(AM17=0,BC17=0),"",(BC17-AM17)/AM17)))) | BG17: =+AQ17+BC17 -> 0 | BM17: =IF(AND(BC17=0,BJ17>0),100%,IF(AND(BC17<0,BJ17=0),(BC17-BJ17)/BC17,IF(AND(BC17>0,BJ17>0),(BJ17-BC17)/BC17,IF(AND(BC17=0,BJ17=0),"",(BJ17-BC17)/BC17)))) | BN17: =+BG17+BJ17 -> 0 | BT17: =IF(AND(BJ17=0,BQ17>0),100%,IF(AND(BJ17<0,BQ17=0),(BJ17-BQ17)/BJ17,IF(AND(BJ17>0,BQ17>0),(BQ17-BJ17)/BJ17,IF(AND(BJ17=0,BQ17=0),"",(BQ17-BJ17)/BJ17)))) | BU17: =+BN17+BQ17 -> 0 | BX17: =+AZ17*9 -> 0 | BZ17: =IF(AND(BX17=0,BU17>0),100%,IF(AND(BX17<0,BU17=0),(BX17-BU17)/BX17,IF(AND(BX17>0,BU17>0),(BU17-BX17)/BX17,IF(AND(BX17=0,BU17=0),"",(BU17-BX17)/BX17)))) | CD17: =IF(AND(BQ17=0,CA17>0),100%,IF(AND(BQ17<0,CA17=0),(BQ17-CA17)/BQ17,IF(AND(BQ17>0,CA17>0),(CA17-BQ17)/BQ17,IF(AND(BQ17=0,CA17=0),"",(CA17-BQ17)/BQ17)))) | CK17: =IF(AND(CA17=0,CH17>0),100%,IF(AND(CA17<0,CH17=0),(CA17-CH17)/CA17,IF(AND(CA17>0,CH17>0),(CH17-CA17)/CA17,IF(AND(CA17=0,CH17=0),"",(CH17-CA17)/CA17)))) | CL17: =+CE17+CH17 -> 0 | CR17: =IF(AND(CH17=0,CO17>0),100%,IF(AND(CH17<0,CO17=0),(CH17-CO17)/CH17,IF(AND(CH17>0,CO17>0),(CO17-CH17)/CH17,IF(AND(CH17=0,CO17=0),"",(CO17-CH17)/CH17)))) | CS17: =+CL17+CO17 -> 0 | CV17: =+AZ17*12 -> 0 | CX17: =IF(AND(CV17=0,CS17>0),100%,IF(AND(CV17<0,CS17=0),(CV17-CS17)/CV17,IF(AND(CV17>0,CS17>0),(CS17-CV17)/CV17,IF(AND(CV17=0,CS17=0),"",(CS17-CV17)/CV17))))
A18: Subtotal Ingresos por Taller | B18: =SUM(B19:B20) -> 0 | C18: =IF(AND(B4=0,B18>=0), "",B18/B4) | E18: =SUM(E19:E20) -> 0 | F18: =IF(AND(E4=0,E18>=0), "",E18/E4) -> 0 | H18: =SUM(H19:H20) -> 0 | I18: =IF(AND(H4=0,H18>=0), "",H18/H4) -> 0 | K18: =IF(AND(E18=0,H18>0),100%,IF(AND(E18<0,H18=0),(E18-H18)/E18,IF(AND(E18>0,H18>0),(H18-E18)/E18,IF(AND(E18=0,H18=0),"",(H18-E18)/E18)))) | L18: =SUM(L19:L20) -> 0 | M18: =IF(AND(L4=0,L18>=0), "",L18/L4) -> 0 | O18: =SUM(O19:O20) -> 0 | P18: =IF(AND(O4=0,O18>=0), "",O18/O4) -> 0 | R18: =IF(AND(H18=0,O18>0),100%,IF(AND(H18<0,O18=0),(H18-O18)/H18,IF(AND(H18>0,O18>0),(O18-H18)/H18,IF(AND(H18=0,O18=0),"",(O18-H18)/H18)))) | S18: =SUM(S19:S20) -> 0 | T18: =IF(AND(S4=0,S18>=0), "",S18/S4) -> 0 | V18: =SUM(V19:V20) -> 0 | W18: =IF(AND(V4=0,V18>=0), "",V18/V4) | X18: =IF(AND(V18=0,S18>0),100%,IF(AND(V18<0,S18=0),(V18-S18)/V18,IF(AND(V18>0,S18>0),(S18-V18)/V18,IF(AND(V18=0,S18=0),"",(S18-V18)/V18)))) | Y18: =SUM(Y19:Y20) -> 0 | Z18: =IF(AND(Y4=0,Y18>=0), "",Y18/Y4) | AB18: =IF(AND(O18=0,Y18>0),100%,IF(AND(O18<0,Y18=0),(O18-Y18)/O18,IF(AND(O18>0,Y18>0),(Y18-O18)/O18,IF(AND(O18=0,Y18=0),"",(Y18-O18)/O18)))) | AC18: =SUM(AC19:AC20) -> 0 | AD18: =IF(AND(AC4=0,AC18>=0), "",AC18/AC4) -> 0 | AF18: =SUM(AF19:AF20) -> 0 | AG18: =IF(AND(AF4=0,AF18>=0), "",AF18/AF4) | AI18: =IF(AND(Y18=0,AF18>0),100%,IF(AND(Y18<0,AF18=0),(Y18-AF18)/Y18,IF(AND(Y18>0,AF18>0),(AF18-Y18)/Y18,IF(AND(Y18=0,AF18=0),"",(AF18-Y18)/Y18)))) | AJ18: =SUM(AJ19:AJ20) -> 0 | AK18: =IF(AND(AJ4=0,AJ18>=0), "",AJ18/AJ4) -> 0 | AM18: =SUM(AM19:AM20) -> 0 | AN18: =IF(AND(AM4=0,AM18>=0), "",AM18/AM4) | AP18: =IF(AND(AF18=0,AM18>0),100%,IF(AND(AF18<0,AM18=0),(AF18-AM18)/AF18,IF(AND(AF18>0,AM18>0),(AM18-AF18)/AF18,IF(AND(AF18=0,AM18=0),"",(AM18-AF18)/AF18)))) | AQ18: =SUM(AQ19:AQ20) -> 0 | AR18: =IF(AND(AQ4=0,AQ18>=0), "",AQ18/AQ4) -> 0 | AT18: =SUM(AT19:AT20) -> 0 | AU18: =IF(AND(AT4=0,AT18>=0), "",AT18/AT4) | AV18: =IF(AND(AT18=0,AQ18>0),100%,IF(AND(AT18<0,AQ18=0),(AT18-AQ18)/AT18,IF(AND(AT18>0,AQ18>0),(AQ18-AT18)/AT18,IF(AND(AT18=0,AQ18=0),"",(AQ18-AT18)/AT18)))) | AW18: =SUM(AW19:AW20) -> 0 | AX18: =IF(AND(AW4=0,AW18>=0), "",AW18/AW4) -> 0 | AZ18: =SUM(AZ19:AZ20) -> 0 | BA18: =IF(AND(AZ4=0,AZ18>=0), "",AZ18/AZ4) | BB18: =IF(AND(AZ18=0,AW18>0),100%,IF(AND(AZ18<0,AW18=0),(AZ18-AW18)/AZ18,IF(AND(AZ18>0,AW18>0),(AW18-AZ18)/AZ18,IF(AND(AZ18=0,AW18=0),"",(AW18-AZ18)/AZ18)))) | BC18: =SUM(BC19:BC20) -> 0 | BD18: =IF(AND(BC4=0,BC18>=0), "",BC18/BC4) | BF18: =IF(AND(AM18=0,BC18>0),100%,IF(AND(AM18<0,BC18=0),(AM18-BC18)/AM18,IF(AND(AM18>0,BC18>0),(BC18-AM18)/AM18,IF(AND(AM18=0,BC18=0),"",(BC18-AM18)/AM18)))) | BG18: =SUM(BG19:BG20) -> 0 | BH18: =IF(AND(BG4=0,BG18>=0), "",BG18/BG4) -> 0 | BJ18: =SUM(BJ19:BJ20) -> 0 | BK18: =IF(AND(BJ4=0,BJ18>=0), "",BJ18/BJ4) | BM18: =IF(AND(BC18=0,BJ18>0),100%,IF(AND(BC18<0,BJ18=0),(BC18-BJ18)/BC18,IF(AND(BC18>0,BJ18>0),(BJ18-BC18)/BC18,IF(AND(BC18=0,BJ18=0),"",(BJ18-BC18)/BC18)))) | BN18: =SUM(BN19:BN20) -> 0 | BO18: =IF(AND(BN4=0,BN18>=0), "",BN18/BN4) -> 0 | BQ18: =SUM(BQ19:BQ20) -> 0 | BR18: =IF(AND(BQ4=0,BQ18>=0), "",BQ18/BQ4) | BT18: =IF(AND(BJ18=0,BQ18>0),100%,IF(AND(BJ18<0,BQ18=0),(BJ18-BQ18)/BJ18,IF(AND(BJ18>0,BQ18>0),(BQ18-BJ18)/BJ18,IF(AND(BJ18=0,BQ18=0),"",(BQ18-BJ18)/BJ18)))) | BU18: =SUM(BU19:BU20) -> 0 | BV18: =IF(AND(BU4=0,BU18>=0), "",BU18/BU4) -> 0 | BX18: =SUM(BX19:BX20) -> 0 | BY18: =IF(AND(BX4=0,BX18>=0), "",BX18/BX4) | BZ18: =IF(AND(BX18=0,BU18>0),100%,IF(AND(BX18<0,BU18=0),(BX18-BU18)/BX18,IF(AND(BX18>0,BU18>0),(BU18-BX18)/BX18,IF(AND(BX18=0,BU18=0),"",(BU18-BX18)/BX18)))) | CA18: =SUM(CA19:CA20) -> 0 | CB18: =IF(AND(CA4=0,CA18>=0), "",CA18/CA4) | CD18: =IF(AND(BQ18=0,CA18>0),100%,IF(AND(BQ18<0,CA18=0),(BQ18-CA18)/BQ18,IF(AND(BQ18>0,CA18>0),(CA18-BQ18)/BQ18,IF(AND(BQ18=0,CA18=0),"",(CA18-BQ18)/BQ18)))) | CE18: =SUM(CE19:CE20) -> 0 | CF18: =IF(AND(CE4=0,CE18>=0), "",CE18/CE4) -> 0 | CH18: =SUM(CH19:CH20) -> 0 | CI18: =IF(AND(CH4=0,CH18>=0), "",CH18/CH4) | CK18: =IF(AND(CA18=0,CH18>0),100%,IF(AND(CA18<0,CH18=0),(CA18-CH18)/CA18,IF(AND(CA18>0,CH18>0),(CH18-CA18)/CA18,IF(AND(CA18=0,CH18=0),"",(CH18-CA18)/CA18)))) | CL18: =SUM(CL19:CL20) -> 0 | CM18: =IF(AND(CL4=0,CL18>=0), "",CL18/CL4) -> 0 | CO18: =SUM(CO19:CO20) -> 0 | CP18: =IF(AND(CO4=0,CO18>=0), "",CO18/CO4) | CR18: =IF(AND(CH18=0,CO18>0),100%,IF(AND(CH18<0,CO18=0),(CH18-CO18)/CH18,IF(AND(CH18>0,CO18>0),(CO18-CH18)/CH18,IF(AND(CH18=0,CO18=0),"",(CO18-CH18)/CH18)))) | CS18: =SUM(CS19:CS20) -> 0 | CT18: =IF(AND(CS4=0,CS18>=0), "",CS18/CS4) -> 0 | CV18: =SUM(CV19:CV20) -> 0 | CW18: =IF(AND(CV4=0,CV18>=0), "",CV18/CV4) | CX18: =IF(AND(CV18=0,CS18>0),100%,IF(AND(CV18<0,CS18=0),(CV18-CS18)/CV18,IF(AND(CV18>0,CS18>0),(CS18-CV18)/CV18,IF(AND(CV18=0,CS18=0),"",(CS18-CV18)/CV18))))
A19: Ingresos por taller | B19: =+'N EERR RODEO'!B15 -> 0 | C19: =IF(AND(B4=0,B19>=0), "",B19/B4) | E19: =+'N EERR RODEO'!C15 -> 0 | F19: =IF(AND(E4=0,E19>=0), "",E19/E4) -> 0 | H19: =+'N EERR RODEO'!D15 -> 0 | I19: =IF(AND(H4=0,H19>=0), "",H19/H4) -> 0 | K19: =IF(AND(E19=0,H19>0),100%,IF(AND(E19<0,H19=0),(E19-H19)/E19,IF(AND(E19>0,H19>0),(H19-E19)/E19,IF(AND(E19=0,H19=0),"",(H19-E19)/E19)))) | L19: =+E19+H19 -> 0 | M19: =IF(AND(L4=0,L19>=0), "",L19/L4) -> 0 | O19: =+'N EERR RODEO'!E15 -> 0 | P19: =IF(AND(O4=0,O19>=0), "",O19/O4) -> 0 | R19: =IF(AND(H19=0,O19>0),100%,IF(AND(H19<0,O19=0),(H19-O19)/H19,IF(AND(H19>0,O19>0),(O19-H19)/H19,IF(AND(H19=0,O19=0),"",(O19-H19)/H19)))) | S19: =+L19+O19 -> 0 | T19: =IF(AND(S4=0,S19>=0), "",S19/S4) -> 0 | W19: =IF(AND(V4=0,V19>=0), "",V19/V4) | X19: =IF(AND(V19=0,S19>0),100%,IF(AND(V19<0,S19=0),(V19-S19)/V19,IF(AND(V19>0,S19>0),(S19-V19)/V19,IF(AND(V19=0,S19=0),"",(S19-V19)/V19)))) | Y19: =+'N EERR RODEO'!F15 -> 0 | Z19: =IF(AND(Y4=0,Y19>=0), "",Y19/Y4) | AB19: =IF(AND(O19=0,Y19>0),100%,IF(AND(O19<0,Y19=0),(O19-Y19)/O19,IF(AND(O19>0,Y19>0),(Y19-O19)/O19,IF(AND(O19=0,Y19=0),"",(Y19-O19)/O19)))) | AC19: =+S19+Y19 -> 0 | AD19: =IF(AND(AC4=0,AC19>=0), "",AC19/AC4) -> 0 | AF19: =+'N EERR RODEO'!G15 -> 0 | AG19: =IF(AND(AF4=0,AF19>=0), "",AF19/AF4) | AI19: =IF(AND(Y19=0,AF19>0),100%,IF(AND(Y19<0,AF19=0),(Y19-AF19)/Y19,IF(AND(Y19>0,AF19>0),(AF19-Y19)/Y19,IF(AND(Y19=0,AF19=0),"",(AF19-Y19)/Y19)))) | AJ19: =+AC19+AF19 -> 0 | AK19: =IF(AND(AJ4=0,AJ19>=0), "",AJ19/AJ4) -> 0 | AM19: =+'N EERR RODEO'!H15 -> 0 | AN19: =IF(AND(AM4=0,AM19>=0), "",AM19/AM4) | AP19: =IF(AND(AF19=0,AM19>0),100%,IF(AND(AF19<0,AM19=0),(AF19-AM19)/AF19,IF(AND(AF19>0,AM19>0),(AM19-AF19)/AF19,IF(AND(AF19=0,AM19=0),"",(AM19-AF19)/AF19)))) | AQ19: =+AJ19+AM19 -> 0 | AR19: =IF(AND(AQ4=0,AQ19>=0), "",AQ19/AQ4) -> 0 | AT19: =+V19*2 -> 0 | AU19: =IF(AND(AT4=0,AT19>=0), "",AT19/AT4) | AV19: =IF(AND(AT19=0,AQ19>0),100%,IF(AND(AT19<0,AQ19=0),(AT19-AQ19)/AT19,IF(AND(AT19>0,AQ19>0),(AQ19-AT19)/AT19,IF(AND(AT19=0,AQ19=0),"",(AQ19-AT19)/AT19)))) | AW19: =+AQ19/6 -> 0 | AX19: =IF(AND(AW4=0,AW19>=0), "",AW19/AW4) -> 0 | AZ19: =+AT19/6 -> 0 | BA19: =IF(AND(AZ4=0,AZ19>=0), "",AZ19/AZ4) | BB19: =IF(AND(AZ19=0,AW19>0),100%,IF(AND(AZ19<0,AW19=0),(AZ19-AW19)/AZ19,IF(AND(AZ19>0,AW19>0),(AW19-AZ19)/AZ19,IF(AND(AZ19=0,AW19=0),"",(AW19-AZ19)/AZ19)))) | BC19: =+'N EERR RODEO'!I15 -> 0 | BD19: =IF(AND(BC4=0,BC19>=0), "",BC19/BC4) | BF19: =IF(AND(AM19=0,BC19>0),100%,IF(AND(AM19<0,BC19=0),(AM19-BC19)/AM19,IF(AND(AM19>0,BC19>0),(BC19-AM19)/AM19,IF(AND(AM19=0,BC19=0),"",(BC19-AM19)/AM19)))) | BG19: =+AQ19+BC19 -> 0 | BH19: =IF(AND(BG4=0,BG19>=0), "",BG19/BG4) -> 0 | BJ19: =+'N EERR RODEO'!J15 -> 0 | BK19: =IF(AND(BJ4=0,BJ19>=0), "",BJ19/BJ4) | BM19: =IF(AND(BC19=0,BJ19>0),100%,IF(AND(BC19<0,BJ19=0),(BC19-BJ19)/BC19,IF(AND(BC19>0,BJ19>0),(BJ19-BC19)/BC19,IF(AND(BC19=0,BJ19=0),"",(BJ19-BC19)/BC19)))) | BN19: =+BG19+BJ19 -> 0 | BO19: =IF(AND(BN4=0,BN19>=0), "",BN19/BN4) -> 0 | BQ19: =+'N EERR RODEO'!K15 -> 0 | BR19: =IF(AND(BQ4=0,BQ19>=0), "",BQ19/BQ4) | BT19: =IF(AND(BJ19=0,BQ19>0),100%,IF(AND(BJ19<0,BQ19=0),(BJ19-BQ19)/BJ19,IF(AND(BJ19>0,BQ19>0),(BQ19-BJ19)/BJ19,IF(AND(BJ19=0,BQ19=0),"",(BQ19-BJ19)/BJ19)))) | BU19: =+BN19+BQ19 -> 0 | BV19: =IF(AND(BU4=0,BU19>=0), "",BU19/BU4) -> 0 | BX19: =+AZ19*9 -> 0 | BY19: =IF(AND(BX4=0,BX19>=0), "",BX19/BX4) | BZ19: =IF(AND(BX19=0,BU19>0),100%,IF(AND(BX19<0,BU19=0),(BX19-BU19)/BX19,IF(AND(BX19>0,BU19>0),(BU19-BX19)/BX19,IF(AND(BX19=0,BU19=0),"",(BU19-BX19)/BX19)))) | CA19: =+'N EERR RODEO'!L15 -> 0 | CB19: =IF(AND(CA4=0,CA19>=0), "",CA19/CA4) | CD19: =IF(AND(BQ19=0,CA19>0),100%,IF(AND(BQ19<0,CA19=0),(BQ19-CA19)/BQ19,IF(AND(BQ19>0,CA19>0),(CA19-BQ19)/BQ19,IF(AND(BQ19=0,CA19=0),"",(CA19-BQ19)/BQ19)))) | CE19: =+BU19+CA19 -> 0 | CF19: =IF(AND(CE4=0,CE19>=0), "",CE19/CE4) -> 0 | CH19: =+'N EERR RODEO'!M15 -> 0 | CI19: =IF(AND(CH4=0,CH19>=0), "",CH19/CH4) | CK19: =IF(AND(CA19=0,CH19>0),100%,IF(AND(CA19<0,CH19=0),(CA19-CH19)/CA19,IF(AND(CA19>0,CH19>0),(CH19-CA19)/CA19,IF(AND(CA19=0,CH19=0),"",(CH19-CA19)/CA19)))) | CL19: =+CE19+CH19 -> 0 | CM19: =IF(AND(CL4=0,CL19>=0), "",CL19/CL4) -> 0 | CO19: =+'N EERR RODEO'!N15 -> 0 | CP19: =IF(AND(CO4=0,CO19>=0), "",CO19/CO4) | CR19: =IF(AND(CH19=0,CO19>0),100%,IF(AND(CH19<0,CO19=0),(CH19-CO19)/CH19,IF(AND(CH19>0,CO19>0),(CO19-CH19)/CH19,IF(AND(CH19=0,CO19=0),"",(CO19-CH19)/CH19)))) | CS19: =+CL19+CO19 -> 0 | CT19: =IF(AND(CS4=0,CS19>=0), "",CS19/CS4) -> 0 | CV19: =+AZ19*12 -> 0 | CW19: =IF(AND(CV4=0,CV19>=0), "",CV19/CV4) | CX19: =IF(AND(CV19=0,CS19>0),100%,IF(AND(CV19<0,CS19=0),(CV19-CS19)/CV19,IF(AND(CV19>0,CS19>0),(CS19-CV19)/CV19,IF(AND(CV19=0,CS19=0),"",(CS19-CV19)/CV19))))
K20: =IF(AND(E20=0,H20>0),100%,IF(AND(E20<0,H20=0),(E20-H20)/E20,IF(AND(E20>0,H20>0),(H20-E20)/E20,IF(AND(E20=0,H20=0),"",(H20-E20)/E20)))) | R20: =IF(AND(H20=0,O20>0),100%,IF(AND(H20<0,O20=0),(H20-O20)/H20,IF(AND(H20>0,O20>0),(O20-H20)/H20,IF(AND(H20=0,O20=0),"",(O20-H20)/H20)))) | X20: =IF(AND(V20=0,S20>0),100%,IF(AND(V20<0,S20=0),(V20-S20)/V20,IF(AND(V20>0,S20>0),(S20-V20)/V20,IF(AND(V20=0,S20=0),"",(S20-V20)/V20)))) | AB20: =IF(AND(O20=0,Y20>0),100%,IF(AND(O20<0,Y20=0),(O20-Y20)/O20,IF(AND(O20>0,Y20>0),(Y20-O20)/O20,IF(AND(O20=0,Y20=0),"",(Y20-O20)/O20)))) | AI20: =IF(AND(Y20=0,AF20>0),100%,IF(AND(Y20<0,AF20=0),(Y20-AF20)/Y20,IF(AND(Y20>0,AF20>0),(AF20-Y20)/Y20,IF(AND(Y20=0,AF20=0),"",(AF20-Y20)/Y20)))) | AJ20: =+AC20+AF20 -> 0 | AP20: =IF(AND(AF20=0,AM20>0),100%,IF(AND(AF20<0,AM20=0),(AF20-AM20)/AF20,IF(AND(AF20>0,AM20>0),(AM20-AF20)/AF20,IF(AND(AF20=0,AM20=0),"",(AM20-AF20)/AF20)))) | AQ20: =+AJ20+AM20 -> 0 | AT20: =+V20*2 -> 0 | AV20: =IF(AND(AT20=0,AQ20>0),100%,IF(AND(AT20<0,AQ20=0),(AT20-AQ20)/AT20,IF(AND(AT20>0,AQ20>0),(AQ20-AT20)/AT20,IF(AND(AT20=0,AQ20=0),"",(AQ20-AT20)/AT20)))) | AW20: =+AQ20/6 -> 0 | AZ20: =+AT20/6 -> 0 | BB20: =IF(AND(AZ20=0,AW20>0),100%,IF(AND(AZ20<0,AW20=0),(AZ20-AW20)/AZ20,IF(AND(AZ20>0,AW20>0),(AW20-AZ20)/AZ20,IF(AND(AZ20=0,AW20=0),"",(AW20-AZ20)/AZ20)))) | BF20: =IF(AND(AM20=0,BC20>0),100%,IF(AND(AM20<0,BC20=0),(AM20-BC20)/AM20,IF(AND(AM20>0,BC20>0),(BC20-AM20)/AM20,IF(AND(AM20=0,BC20=0),"",(BC20-AM20)/AM20)))) | BG20: =+AQ20+BC20 -> 0 | BM20: =IF(AND(BC20=0,BJ20>0),100%,IF(AND(BC20<0,BJ20=0),(BC20-BJ20)/BC20,IF(AND(BC20>0,BJ20>0),(BJ20-BC20)/BC20,IF(AND(BC20=0,BJ20=0),"",(BJ20-BC20)/BC20)))) | BN20: =+BG20+BJ20 -> 0 | BT20: =IF(AND(BJ20=0,BQ20>0),100%,IF(AND(BJ20<0,BQ20=0),(BJ20-BQ20)/BJ20,IF(AND(BJ20>0,BQ20>0),(BQ20-BJ20)/BJ20,IF(AND(BJ20=0,BQ20=0),"",(BQ20-BJ20)/BJ20)))) | BU20: =+BN20+BQ20 -> 0 | BX20: =+AZ20*9 -> 0 | BZ20: =IF(AND(BX20=0,BU20>0),100%,IF(AND(BX20<0,BU20=0),(BX20-BU20)/BX20,IF(AND(BX20>0,BU20>0),(BU20-BX20)/BX20,IF(AND(BX20=0,BU20=0),"",(BU20-BX20)/BX20)))) | CD20: =IF(AND(BQ20=0,CA20>0),100%,IF(AND(BQ20<0,CA20=0),(BQ20-CA20)/BQ20,IF(AND(BQ20>0,CA20>0),(CA20-BQ20)/BQ20,IF(AND(BQ20=0,CA20=0),"",(CA20-BQ20)/BQ20)))) | CK20: =IF(AND(CA20=0,CH20>0),100%,IF(AND(CA20<0,CH20=0),(CA20-CH20)/CA20,IF(AND(CA20>0,CH20>0),(CH20-CA20)/CA20,IF(AND(CA20=0,CH20=0),"",(CH20-CA20)/CA20)))) | CL20: =+CE20+CH20 -> 0 | CR20: =IF(AND(CH20=0,CO20>0),100%,IF(AND(CH20<0,CO20=0),(CH20-CO20)/CH20,IF(AND(CH20>0,CO20>0),(CO20-CH20)/CH20,IF(AND(CH20=0,CO20=0),"",(CO20-CH20)/CH20)))) | CS20: =+CL20+CO20 -> 0 | CV20: =+AZ20*12 -> 0 | CX20: =IF(AND(CV20=0,CS20>0),100%,IF(AND(CV20<0,CS20=0),(CV20-CS20)/CV20,IF(AND(CV20>0,CS20>0),(CS20-CV20)/CV20,IF(AND(CV20=0,CS20=0),"",(CS20-CV20)/CV20))))
K21: =IF(AND(E21=0,H21>0),100%,IF(AND(E21<0,H21=0),(E21-H21)/E21,IF(AND(E21>0,H21>0),(H21-E21)/E21,IF(AND(E21=0,H21=0),"",(H21-E21)/E21)))) | R21: =IF(AND(H21=0,O21>0),100%,IF(AND(H21<0,O21=0),(H21-O21)/H21,IF(AND(H21>0,O21>0),(O21-H21)/H21,IF(AND(H21=0,O21=0),"",(O21-H21)/H21)))) | X21: =IF(AND(V21=0,S21>0),100%,IF(AND(V21<0,S21=0),(V21-S21)/V21,IF(AND(V21>0,S21>0),(S21-V21)/V21,IF(AND(V21=0,S21=0),"",(S21-V21)/V21)))) | AB21: =IF(AND(O21=0,Y21>0),100%,IF(AND(O21<0,Y21=0),(O21-Y21)/O21,IF(AND(O21>0,Y21>0),(Y21-O21)/O21,IF(AND(O21=0,Y21=0),"",(Y21-O21)/O21)))) | AI21: =IF(AND(Y21=0,AF21>0),100%,IF(AND(Y21<0,AF21=0),(Y21-AF21)/Y21,IF(AND(Y21>0,AF21>0),(AF21-Y21)/Y21,IF(AND(Y21=0,AF21=0),"",(AF21-Y21)/Y21)))) | AJ21: =+AC21+AF21 -> 0 | AP21: =IF(AND(AF21=0,AM21>0),100%,IF(AND(AF21<0,AM21=0),(AF21-AM21)/AF21,IF(AND(AF21>0,AM21>0),(AM21-AF21)/AF21,IF(AND(AF21=0,AM21=0),"",(AM21-AF21)/AF21)))) | AQ21: =+AJ21+AM21 -> 0 | AT21: =+V21*2 -> 0 | AV21: =IF(AND(AT21=0,AQ21>0),100%,IF(AND(AT21<0,AQ21=0),(AT21-AQ21)/AT21,IF(AND(AT21>0,AQ21>0),(AQ21-AT21)/AT21,IF(AND(AT21=0,AQ21=0),"",(AQ21-AT21)/AT21)))) | AW21: =+AQ21/6 -> 0 | AZ21: =+AT21/6 -> 0 | BB21: =IF(AND(AZ21=0,AW21>0),100%,IF(AND(AZ21<0,AW21=0),(AZ21-AW21)/AZ21,IF(AND(AZ21>0,AW21>0),(AW21-AZ21)/AZ21,IF(AND(AZ21=0,AW21=0),"",(AW21-AZ21)/AZ21)))) | BF21: =IF(AND(AM21=0,BC21>0),100%,IF(AND(AM21<0,BC21=0),(AM21-BC21)/AM21,IF(AND(AM21>0,BC21>0),(BC21-AM21)/AM21,IF(AND(AM21=0,BC21=0),"",(BC21-AM21)/AM21)))) | BG21: =+AQ21+BC21 -> 0 | BM21: =IF(AND(BC21=0,BJ21>0),100%,IF(AND(BC21<0,BJ21=0),(BC21-BJ21)/BC21,IF(AND(BC21>0,BJ21>0),(BJ21-BC21)/BC21,IF(AND(BC21=0,BJ21=0),"",(BJ21-BC21)/BC21)))) | BN21: =+BG21+BJ21 -> 0 | BT21: =IF(AND(BJ21=0,BQ21>0),100%,IF(AND(BJ21<0,BQ21=0),(BJ21-BQ21)/BJ21,IF(AND(BJ21>0,BQ21>0),(BQ21-BJ21)/BJ21,IF(AND(BJ21=0,BQ21=0),"",(BQ21-BJ21)/BJ21)))) | BU21: =+BN21+BQ21 -> 0 | BX21: =+AZ21*9 -> 0 | BZ21: =IF(AND(BX21=0,BU21>0),100%,IF(AND(BX21<0,BU21=0),(BX21-BU21)/BX21,IF(AND(BX21>0,BU21>0),(BU21-BX21)/BX21,IF(AND(BX21=0,BU21=0),"",(BU21-BX21)/BX21)))) | CD21: =IF(AND(BQ21=0,CA21>0),100%,IF(AND(BQ21<0,CA21=0),(BQ21-CA21)/BQ21,IF(AND(BQ21>0,CA21>0),(CA21-BQ21)/BQ21,IF(AND(BQ21=0,CA21=0),"",(CA21-BQ21)/BQ21)))) | CK21: =IF(AND(CA21=0,CH21>0),100%,IF(AND(CA21<0,CH21=0),(CA21-CH21)/CA21,IF(AND(CA21>0,CH21>0),(CH21-CA21)/CA21,IF(AND(CA21=0,CH21=0),"",(CH21-CA21)/CA21)))) | CL21: =+CE21+CH21 -> 0 | CR21: =IF(AND(CH21=0,CO21>0),100%,IF(AND(CH21<0,CO21=0),(CH21-CO21)/CH21,IF(AND(CH21>0,CO21>0),(CO21-CH21)/CH21,IF(AND(CH21=0,CO21=0),"",(CO21-CH21)/CH21)))) | CS21: =+CL21+CO21 -> 0 | CV21: =+AZ21*12 -> 0 | CX21: =IF(AND(CV21=0,CS21>0),100%,IF(AND(CV21<0,CS21=0),(CV21-CS21)/CV21,IF(AND(CV21>0,CS21>0),(CS21-CV21)/CV21,IF(AND(CV21=0,CS21=0),"",(CS21-CV21)/CV21))))
A22: Total Costo de Ventas | B22: =+B23+B26+B29 -> 0 | C22: =IF(AND(B4=0,B22>=0), "",B22/B4) | E22: =+E23+E26+E29 -> 20670.85 | F22: =IF(AND(E4=0,E22>=0), "",E22/E4) -> 0.43124438 | H22: =+H23+H26+H29 -> 24313.03 | I22: =IF(AND(H4=0,H22>=0), "",H22/H4) -> 0.47225319 | K22: =IF(AND(E22=0,H22>0),100%,IF(AND(E22<0,H22=0),(E22-H22)/E22,IF(AND(E22>0,H22>0),(H22-E22)/E22,IF(AND(E22=0,H22=0),"",(H22-E22)/E22)))) -> 0.17619885 | L22: =+L23+L26+L29 -> 44983.88 | M22: =IF(AND(L4=0,L22>=0), "",L22/L4) -> 0.45248097 | O22: =+O23+O26+O29 -> 19883.02 | P22: =IF(AND(O4=0,O22>=0), "",O22/O4) -> 0.31015762 | R22: =IF(AND(H22=0,O22>0),100%,IF(AND(H22<0,O22=0),(H22-O22)/H22,IF(AND(H22>0,O22>0),(O22-H22)/H22,IF(AND(H22=0,O22=0),"",(O22-H22)/H22)))) -> -0.18220724 | S22: =+S23+S26+S29 -> 64866.9 | T22: =IF(AND(S4=0,S22>=0), "",S22/S4) -> 0.39668547 | V22: =+V23+V26+V29 -> 0 | W22: =IF(AND(V4=0,V22>=0), "",V22/V4) | X22: =IF(AND(V22=0,S22>0),100%,IF(AND(V22<0,S22=0),(V22-S22)/V22,IF(AND(V22>0,S22>0),(S22-V22)/V22,IF(AND(V22=0,S22=0),"",(S22-V22)/V22)))) -> 1 | Y22: =+Y23+Y26+Y29 -> 0 | Z22: =IF(AND(Y4=0,Y22>=0), "",Y22/Y4) | AB22: =IF(AND(O22=0,Y22>0),100%,IF(AND(O22<0,Y22=0),(O22-Y22)/O22,IF(AND(O22>0,Y22>0),(Y22-O22)/O22,IF(AND(O22=0,Y22=0),"",(Y22-O22)/O22)))) -> -1 | AC22: =+AC23+AC26+AC29 -> 64866.9 | AD22: =IF(AND(AC4=0,AC22>=0), "",AC22/AC4) -> 0.39668547 | AF22: =+AF23+AF26+AF29 -> 0 | AG22: =IF(AND(AF4=0,AF22>=0), "",AF22/AF4) | AI22: =IF(AND(Y22=0,AF22>0),100%,IF(AND(Y22<0,AF22=0),(Y22-AF22)/Y22,IF(AND(Y22>0,AF22>0),(AF22-Y22)/Y22,IF(AND(Y22=0,AF22=0),"",(AF22-Y22)/Y22)))) | AJ22: =+AJ23+AJ26+AJ29 -> 64866.9 | AK22: =IF(AND(AJ4=0,AJ22>=0), "",AJ22/AJ4) -> 0.39668547 | AM22: =+AM23+AM26+AM29 -> 0 | AN22: =IF(AND(AM4=0,AM22>=0), "",AM22/AM4) | AP22: =IF(AND(AF22=0,AM22>0),100%,IF(AND(AF22<0,AM22=0),(AF22-AM22)/AF22,IF(AND(AF22>0,AM22>0),(AM22-AF22)/AF22,IF(AND(AF22=0,AM22=0),"",(AM22-AF22)/AF22)))) | AQ22: =+AQ23+AQ26+AQ29 -> 64866.9 | AR22: =IF(AND(AQ4=0,AQ22>=0), "",AQ22/AQ4) -> 0.39668547 | AT22: =+AT23+AT26+AT29 -> 0 | AU22: =IF(AND(AT4=0,AT22>=0), "",AT22/AT4) | AV22: =IF(AND(AT22=0,AQ22>0),100%,IF(AND(AT22<0,AQ22=0),(AT22-AQ22)/AT22,IF(AND(AT22>0,AQ22>0),(AQ22-AT22)/AT22,IF(AND(AT22=0,AQ22=0),"",(AQ22-AT22)/AT22)))) -> 1 | AW22: =+AW23+AW26+AW29 -> 10811.15 | AX22: =IF(AND(AW4=0,AW22>=0), "",AW22/AW4) -> 0.39668547 | AZ22: =+AZ23+AZ26+AZ29 -> 0 | BA22: =IF(AND(AZ4=0,AZ22>=0), "",AZ22/AZ4) | BB22: =IF(AND(AZ22=0,AW22>0),100%,IF(AND(AZ22<0,AW22=0),(AZ22-AW22)/AZ22,IF(AND(AZ22>0,AW22>0),(AW22-AZ22)/AZ22,IF(AND(AZ22=0,AW22=0),"",(AW22-AZ22)/AZ22)))) -> 1 | BC22: =+BC23+BC26+BC29 -> 0 | BD22: =IF(AND(BC4=0,BC22>=0), "",BC22/BC4) | BF22: =IF(AND(AM22=0,BC22>0),100%,IF(AND(AM22<0,BC22=0),(AM22-BC22)/AM22,IF(AND(AM22>0,BC22>0),(BC22-AM22)/AM22,IF(AND(AM22=0,BC22=0),"",(BC22-AM22)/AM22)))) | BG22: =+BG23+BG26+BG29 -> 64866.9 | BH22: =IF(AND(BG4=0,BG22>=0), "",BG22/BG4) -> 0.39668547 | BJ22: =+BJ23+BJ26+BJ29 -> 0 | BK22: =IF(AND(BJ4=0,BJ22>=0), "",BJ22/BJ4) | BM22: =IF(AND(BC22=0,BJ22>0),100%,IF(AND(BC22<0,BJ22=0),(BC22-BJ22)/BC22,IF(AND(BC22>0,BJ22>0),(BJ22-BC22)/BC22,IF(AND(BC22=0,BJ22=0),"",(BJ22-BC22)/BC22)))) | BN22: =+BN23+BN26+BN29 -> 64866.9 | BO22: =IF(AND(BN4=0,BN22>=0), "",BN22/BN4) -> 0.39668547 | BQ22: =+BQ23+BQ26+BQ29 -> 0 | BR22: =IF(AND(BQ4=0,BQ22>=0), "",BQ22/BQ4) | BT22: =IF(AND(BJ22=0,BQ22>0),100%,IF(AND(BJ22<0,BQ22=0),(BJ22-BQ22)/BJ22,IF(AND(BJ22>0,BQ22>0),(BQ22-BJ22)/BJ22,IF(AND(BJ22=0,BQ22=0),"",(BQ22-BJ22)/BJ22)))) | BU22: =+BU23+BU26+BU29 -> 64866.9 | BV22: =IF(AND(BU4=0,BU22>=0), "",BU22/BU4) -> 0.39668547 | BX22: =+BX23+BX26+BX29 -> 0 | BY22: =IF(AND(BX4=0,BX22>=0), "",BX22/BX4) | BZ22: =IF(AND(BX22=0,BU22>0),100%,IF(AND(BX22<0,BU22=0),(BX22-BU22)/BX22,IF(AND(BX22>0,BU22>0),(BU22-BX22)/BX22,IF(AND(BX22=0,BU22=0),"",(BU22-BX22)/BX22)))) -> 1 | CA22: =+CA23+CA26+CA29 -> 0 | CB22: =IF(AND(CA4=0,CA22>=0), "",CA22/CA4) | CD22: =IF(AND(BQ22=0,CA22>0),100%,IF(AND(BQ22<0,CA22=0),(BQ22-CA22)/BQ22,IF(AND(BQ22>0,CA22>0),(CA22-BQ22)/BQ22,IF(AND(BQ22=0,CA22=0),"",(CA22-BQ22)/BQ22)))) | CE22: =+CE23+CE26+CE29 -> 64866.9 | CF22: =IF(AND(CE4=0,CE22>=0), "",CE22/CE4) -> 0.39668547 | CH22: =+CH23+CH26+CH29 -> 0 | CI22: =IF(AND(CH4=0,CH22>=0), "",CH22/CH4) | CK22: =IF(AND(CA22=0,CH22>0),100%,IF(AND(CA22<0,CH22=0),(CA22-CH22)/CA22,IF(AND(CA22>0,CH22>0),(CH22-CA22)/CA22,IF(AND(CA22=0,CH22=0),"",(CH22-CA22)/CA22)))) | CL22: =+CL23+CL26+CL29 -> 64866.9 | CM22: =IF(AND(CL4=0,CL22>=0), "",CL22/CL4) -> 0.39668547 | CO22: =+CO23+CO26+CO29 -> 0 | CP22: =IF(AND(CO4=0,CO22>=0), "",CO22/CO4) | CR22: =IF(AND(CH22=0,CO22>0),100%,IF(AND(CH22<0,CO22=0),(CH22-CO22)/CH22,IF(AND(CH22>0,CO22>0),(CO22-CH22)/CH22,IF(AND(CH22=0,CO22=0),"",(CO22-CH22)/CH22)))) | CS22: =+CS23+CS26+CS29 -> 64866.9 | CT22: =IF(AND(CS4=0,CS22>=0), "",CS22/CS4) -> 0.39668547 | CV22: =+CV23+CV26+CV29 -> 0 | CW22: =IF(AND(CV4=0,CV22>=0), "",CV22/CV4) | CX22: =IF(AND(CV22=0,CS22>0),100%,IF(AND(CV22<0,CS22=0),(CV22-CS22)/CV22,IF(AND(CV22>0,CS22>0),(CS22-CV22)/CV22,IF(AND(CV22=0,CS22=0),"",(CS22-CV22)/CV22)))) -> 1
A23: Subtotal Costo de Ventas por Mercancia | B23: =SUM(B24:B25) -> 0 | C23: =IF(AND(B5=0,B23>=0), "",B23/B5) | E23: =SUM(E24:E25) -> 20670.85 | F23: =IF(AND(E5=0,E23>=0), "",E23/E5) -> 0.43124438 | H23: =SUM(H24:H25) -> 24313.03 | I23: =IF(AND(H5=0,H23>=0), "",H23/H5) -> 0.47225319 | K23: =IF(AND(E23=0,H23>0),100%,IF(AND(E23<0,H23=0),(E23-H23)/E23,IF(AND(E23>0,H23>0),(H23-E23)/E23,IF(AND(E23=0,H23=0),"",(H23-E23)/E23)))) -> 0.17619885 | L23: =SUM(L24:L25) -> 44983.88 | M23: =IF(AND(L5=0,L23>=0), "",L23/L5) -> 0.45248097 | O23: =SUM(O24:O25) -> 19883.02 | P23: =IF(AND(O5=0,O23>=0), "",O23/O5) -> 0.31015762 | R23: =IF(AND(H23=0,O23>0),100%,IF(AND(H23<0,O23=0),(H23-O23)/H23,IF(AND(H23>0,O23>0),(O23-H23)/H23,IF(AND(H23=0,O23=0),"",(O23-H23)/H23)))) -> -0.18220724 | S23: =SUM(S24:S25) -> 64866.9 | T23: =IF(AND(S5=0,S23>=0), "",S23/S5) -> 0.39668547 | V23: =SUM(V24:V25) -> 0 | W23: =IF(AND(V5=0,V23>=0), "",V23/V5) | X23: =IF(AND(V23=0,S23>0),100%,IF(AND(V23<0,S23=0),(V23-S23)/V23,IF(AND(V23>0,S23>0),(S23-V23)/V23,IF(AND(V23=0,S23=0),"",(S23-V23)/V23)))) -> 1 | Y23: =SUM(Y24:Y25) -> 0 | Z23: =IF(AND(Y5=0,Y23>=0), "",Y23/Y5) | AB23: =IF(AND(O23=0,Y23>0),100%,IF(AND(O23<0,Y23=0),(O23-Y23)/O23,IF(AND(O23>0,Y23>0),(Y23-O23)/O23,IF(AND(O23=0,Y23=0),"",(Y23-O23)/O23)))) -> -1 | AC23: =SUM(AC24:AC25) -> 64866.9 | AD23: =IF(AND(AC5=0,AC23>=0), "",AC23/AC5) -> 0.39668547 | AF23: =SUM(AF24:AF25) -> 0 | AG23: =IF(AND(AF5=0,AF23>=0), "",AF23/AF5) | AI23: =IF(AND(Y23=0,AF23>0),100%,IF(AND(Y23<0,AF23=0),(Y23-AF23)/Y23,IF(AND(Y23>0,AF23>0),(AF23-Y23)/Y23,IF(AND(Y23=0,AF23=0),"",(AF23-Y23)/Y23)))) | AJ23: =SUM(AJ24:AJ25) -> 64866.9 | AK23: =IF(AND(AJ5=0,AJ23>=0), "",AJ23/AJ5) -> 0.39668547 | AM23: =SUM(AM24:AM25) -> 0 | AN23: =IF(AND(AM5=0,AM23>=0), "",AM23/AM5) | AP23: =IF(AND(AF23=0,AM23>0),100%,IF(AND(AF23<0,AM23=0),(AF23-AM23)/AF23,IF(AND(AF23>0,AM23>0),(AM23-AF23)/AF23,IF(AND(AF23=0,AM23=0),"",(AM23-AF23)/AF23)))) | AQ23: =SUM(AQ24:AQ25) -> 64866.9 | AR23: =IF(AND(AQ5=0,AQ23>=0), "",AQ23/AQ5) -> 0.39668547 | AT23: =SUM(AT24:AT25) -> 0 | AU23: =IF(AND(AT5=0,AT23>=0), "",AT23/AT5) | AV23: =IF(AND(AT23=0,AQ23>0),100%,IF(AND(AT23<0,AQ23=0),(AT23-AQ23)/AT23,IF(AND(AT23>0,AQ23>0),(AQ23-AT23)/AT23,IF(AND(AT23=0,AQ23=0),"",(AQ23-AT23)/AT23)))) -> 1 | AW23: =SUM(AW24:AW25) -> 10811.15 | AX23: =IF(AND(AW5=0,AW23>=0), "",AW23/AW5) -> 0.39668547 | AZ23: =SUM(AZ24:AZ25) -> 0 | BA23: =IF(AND(AZ5=0,AZ23>=0), "",AZ23/AZ5) | BB23: =IF(AND(AZ23=0,AW23>0),100%,IF(AND(AZ23<0,AW23=0),(AZ23-AW23)/AZ23,IF(AND(AZ23>0,AW23>0),(AW23-AZ23)/AZ23,IF(AND(AZ23=0,AW23=0),"",(AW23-AZ23)/AZ23)))) -> 1 | BC23: =SUM(BC24:BC25) -> 0 | BD23: =IF(AND(BC5=0,BC23>=0), "",BC23/BC5) | BF23: =IF(AND(AM23=0,BC23>0),100%,IF(AND(AM23<0,BC23=0),(AM23-BC23)/AM23,IF(AND(AM23>0,BC23>0),(BC23-AM23)/AM23,IF(AND(AM23=0,BC23=0),"",(BC23-AM23)/AM23)))) | BG23: =SUM(BG24:BG25) -> 64866.9 | BH23: =IF(AND(BG5=0,BG23>=0), "",BG23/BG5) -> 0.39668547 | BJ23: =SUM(BJ24:BJ25) -> 0 | BK23: =IF(AND(BJ5=0,BJ23>=0), "",BJ23/BJ5) | BM23: =IF(AND(BC23=0,BJ23>0),100%,IF(AND(BC23<0,BJ23=0),(BC23-BJ23)/BC23,IF(AND(BC23>0,BJ23>0),(BJ23-BC23)/BC23,IF(AND(BC23=0,BJ23=0),"",(BJ23-BC23)/BC23)))) | BN23: =SUM(BN24:BN25) -> 64866.9 | BO23: =IF(AND(BN5=0,BN23>=0), "",BN23/BN5) -> 0.39668547 | BQ23: =SUM(BQ24:BQ25) -> 0 | BR23: =IF(AND(BQ5=0,BQ23>=0), "",BQ23/BQ5) | BT23: =IF(AND(BJ23=0,BQ23>0),100%,IF(AND(BJ23<0,BQ23=0),(BJ23-BQ23)/BJ23,IF(AND(BJ23>0,BQ23>0),(BQ23-BJ23)/BJ23,IF(AND(BJ23=0,BQ23=0),"",(BQ23-BJ23)/BJ23)))) | BU23: =SUM(BU24:BU25) -> 64866.9 | BV23: =IF(AND(BU5=0,BU23>=0), "",BU23/BU5) -> 0.39668547 | BX23: =SUM(BX24:BX25) -> 0 | BY23: =IF(AND(BX5=0,BX23>=0), "",BX23/BX5) | BZ23: =IF(AND(BX23=0,BU23>0),100%,IF(AND(BX23<0,BU23=0),(BX23-BU23)/BX23,IF(AND(BX23>0,BU23>0),(BU23-BX23)/BX23,IF(AND(BX23=0,BU23=0),"",(BU23-BX23)/BX23)))) -> 1 | CA23: =SUM(CA24:CA25) -> 0 | CB23: =IF(AND(CA5=0,CA23>=0), "",CA23/CA5) | CD23: =IF(AND(BQ23=0,CA23>0),100%,IF(AND(BQ23<0,CA23=0),(BQ23-CA23)/BQ23,IF(AND(BQ23>0,CA23>0),(CA23-BQ23)/BQ23,IF(AND(BQ23=0,CA23=0),"",(CA23-BQ23)/BQ23)))) | CE23: =SUM(CE24:CE25) -> 64866.9 | CF23: =IF(AND(CE5=0,CE23>=0), "",CE23/CE5) -> 0.39668547 | CH23: =SUM(CH24:CH25) -> 0 | CI23: =IF(AND(CH5=0,CH23>=0), "",CH23/CH5) | CK23: =IF(AND(CA23=0,CH23>0),100%,IF(AND(CA23<0,CH23=0),(CA23-CH23)/CA23,IF(AND(CA23>0,CH23>0),(CH23-CA23)/CA23,IF(AND(CA23=0,CH23=0),"",(CH23-CA23)/CA23)))) | CL23: =SUM(CL24:CL25) -> 64866.9 | CM23: =IF(AND(CL5=0,CL23>=0), "",CL23/CL5) -> 0.39668547 | CO23: =SUM(CO24:CO25) -> 0 | CP23: =IF(AND(CO5=0,CO23>=0), "",CO23/CO5) | CR23: =IF(AND(CH23=0,CO23>0),100%,IF(AND(CH23<0,CO23=0),(CH23-CO23)/CH23,IF(AND(CH23>0,CO23>0),(CO23-CH23)/CH23,IF(AND(CH23=0,CO23=0),"",(CO23-CH23)/CH23)))) | CS23: =SUM(CS24:CS25) -> 64866.9 | CT23: =IF(AND(CS5=0,CS23>=0), "",CS23/CS5) -> 0.39668547 | CV23: =SUM(CV24:CV25) -> 0 | CW23: =IF(AND(CV5=0,CV23>=0), "",CV23/CV5) | CX23: =IF(AND(CV23=0,CS23>0),100%,IF(AND(CV23<0,CS23=0),(CV23-CS23)/CV23,IF(AND(CV23>0,CS23>0),(CS23-CV23)/CV23,IF(AND(CV23=0,CS23=0),"",(CS23-CV23)/CV23)))) -> 1
A24: Costo de venta por mercancía | B24: =+'N EERR RODEO'!B30 -> 0 | C24: =IF(AND(B5=0,B24>=0), "",B24/B5) | E24: =+'N EERR RODEO'!C30 -> 20670.85 | F24: =IF(AND(E5=0,E24>=0), "",E24/E5) -> 0.43124438 | H24: =+'N EERR RODEO'!D30 -> 24313.03 | I24: =IF(AND(H5=0,H24>=0), "",H24/H5) -> 0.47225319 | K24: =IF(AND(E24=0,H24>0),100%,IF(AND(E24<0,H24=0),(E24-H24)/E24,IF(AND(E24>0,H24>0),(H24-E24)/E24,IF(AND(E24=0,H24=0),"",(H24-E24)/E24)))) -> 0.17619885 | L24: =+E24+H24 -> 44983.88 | M24: =IF(AND(L5=0,L24>=0), "",L24/L5) -> 0.45248097 | O24: =+'N EERR RODEO'!E30 -> 19883.02 | P24: =IF(AND(O5=0,O24>=0), "",O24/O5) -> 0.31015762 | R24: =IF(AND(H24=0,O24>0),100%,IF(AND(H24<0,O24=0),(H24-O24)/H24,IF(AND(H24>0,O24>0),(O24-H24)/H24,IF(AND(H24=0,O24=0),"",(O24-H24)/H24)))) -> -0.18220724 | S24: =+L24+O24 -> 64866.9 | T24: =IF(AND(S5=0,S24>=0), "",S24/S5) -> 0.39668547 | V24: =+V6*66.71% -> 0 | W24: =IF(AND(V5=0,V24>=0), "",V24/V5) | X24: =IF(AND(V24=0,S24>0),100%,IF(AND(V24<0,S24=0),(V24-S24)/V24,IF(AND(V24>0,S24>0),(S24-V24)/V24,IF(AND(V24=0,S24=0),"",(S24-V24)/V24)))) -> 1 | Y24: =+'N EERR RODEO'!F30 -> 0 | Z24: =IF(AND(Y5=0,Y24>=0), "",Y24/Y5) | AB24: =IF(AND(O24=0,Y24>0),100%,IF(AND(O24<0,Y24=0),(O24-Y24)/O24,IF(AND(O24>0,Y24>0),(Y24-O24)/O24,IF(AND(O24=0,Y24=0),"",(Y24-O24)/O24)))) -> -1 | AC24: =+S24+Y24 -> 64866.9 | AD24: =IF(AND(AC5=0,AC24>=0), "",AC24/AC5) -> 0.39668547 | AF24: =+'N EERR RODEO'!G30 -> 0 | AG24: =IF(AND(AF5=0,AF24>=0), "",AF24/AF5) | AI24: =IF(AND(Y24=0,AF24>0),100%,IF(AND(Y24<0,AF24=0),(Y24-AF24)/Y24,IF(AND(Y24>0,AF24>0),(AF24-Y24)/Y24,IF(AND(Y24=0,AF24=0),"",(AF24-Y24)/Y24)))) | AJ24: =+AC24+AF24 -> 64866.9 | AK24: =IF(AND(AJ5=0,AJ24>=0), "",AJ24/AJ5) -> 0.39668547 | AM24: =+'N EERR RODEO'!H30 -> 0 | AN24: =IF(AND(AM5=0,AM24>=0), "",AM24/AM5) | AP24: =IF(AND(AF24=0,AM24>0),100%,IF(AND(AF24<0,AM24=0),(AF24-AM24)/AF24,IF(AND(AF24>0,AM24>0),(AM24-AF24)/AF24,IF(AND(AF24=0,AM24=0),"",(AM24-AF24)/AF24)))) | AQ24: =+AJ24+AM24 -> 64866.9 | AR24: =IF(AND(AQ5=0,AQ24>=0), "",AQ24/AQ5) -> 0.39668547 | AT24: =+V24*2 -> 0 | AU24: =IF(AND(AT5=0,AT24>=0), "",AT24/AT5) | AV24: =IF(AND(AT24=0,AQ24>0),100%,IF(AND(AT24<0,AQ24=0),(AT24-AQ24)/AT24,IF(AND(AT24>0,AQ24>0),(AQ24-AT24)/AT24,IF(AND(AT24=0,AQ24=0),"",(AQ24-AT24)/AT24)))) -> 1 | AW24: =+AQ24/6 -> 10811.15 | AX24: =IF(AND(AW5=0,AW24>=0), "",AW24/AW5) -> 0.39668547 | AZ24: =+AT24/6 -> 0 | BA24: =IF(AND(AZ5=0,AZ24>=0), "",AZ24/AZ5) | BB24: =IF(AND(AZ24=0,AW24>0),100%,IF(AND(AZ24<0,AW24=0),(AZ24-AW24)/AZ24,IF(AND(AZ24>0,AW24>0),(AW24-AZ24)/AZ24,IF(AND(AZ24=0,AW24=0),"",(AW24-AZ24)/AZ24)))) -> 1 | BC24: =+'N EERR RODEO'!I30 -> 0 | BD24: =IF(AND(BC5=0,BC24>=0), "",BC24/BC5) | BF24: =IF(AND(AM24=0,BC24>0),100%,IF(AND(AM24<0,BC24=0),(AM24-BC24)/AM24,IF(AND(AM24>0,BC24>0),(BC24-AM24)/AM24,IF(AND(AM24=0,BC24=0),"",(BC24-AM24)/AM24)))) | BG24: =+AQ24+BC24 -> 64866.9 | BH24: =IF(AND(BG5=0,BG24>=0), "",BG24/BG5) -> 0.39668547 | BJ24: =+'N EERR RODEO'!J30 -> 0 | BK24: =IF(AND(BJ5=0,BJ24>=0), "",BJ24/BJ5) | BM24: =IF(AND(BC24=0,BJ24>0),100%,IF(AND(BC24<0,BJ24=0),(BC24-BJ24)/BC24,IF(AND(BC24>0,BJ24>0),(BJ24-BC24)/BC24,IF(AND(BC24=0,BJ24=0),"",(BJ24-BC24)/BC24)))) | BN24: =+BG24+BJ24 -> 64866.9 | BO24: =IF(AND(BN5=0,BN24>=0), "",BN24/BN5) -> 0.39668547 | BQ24: =+'N EERR RODEO'!K30 -> 0 | BR24: =IF(AND(BQ5=0,BQ24>=0), "",BQ24/BQ5) | BT24: =IF(AND(BJ24=0,BQ24>0),100%,IF(AND(BJ24<0,BQ24=0),(BJ24-BQ24)/BJ24,IF(AND(BJ24>0,BQ24>0),(BQ24-BJ24)/BJ24,IF(AND(BJ24=0,BQ24=0),"",(BQ24-BJ24)/BJ24)))) | BU24: =+BN24+BQ24 -> 64866.9 | BV24: =IF(AND(BU5=0,BU24>=0), "",BU24/BU5) -> 0.39668547 | BX24: =+AZ24*9 -> 0 | BY24: =IF(AND(BX5=0,BX24>=0), "",BX24/BX5) | BZ24: =IF(AND(BX24=0,BU24>0),100%,IF(AND(BX24<0,BU24=0),(BX24-BU24)/BX24,IF(AND(BX24>0,BU24>0),(BU24-BX24)/BX24,IF(AND(BX24=0,BU24=0),"",(BU24-BX24)/BX24)))) -> 1 | CA24: =+'N EERR RODEO'!L30 -> 0 | CB24: =IF(AND(CA5=0,CA24>=0), "",CA24/CA5) | CD24: =IF(AND(BQ24=0,CA24>0),100%,IF(AND(BQ24<0,CA24=0),(BQ24-CA24)/BQ24,IF(AND(BQ24>0,CA24>0),(CA24-BQ24)/BQ24,IF(AND(BQ24=0,CA24=0),"",(CA24-BQ24)/BQ24)))) | CE24: =+BU24+CA24 -> 64866.9 | CF24: =IF(AND(CE5=0,CE24>=0), "",CE24/CE5) -> 0.39668547 | CH24: =+'N EERR RODEO'!M30 -> 0 | CI24: =IF(AND(CH5=0,CH24>=0), "",CH24/CH5) | CK24: =IF(AND(CA24=0,CH24>0),100%,IF(AND(CA24<0,CH24=0),(CA24-CH24)/CA24,IF(AND(CA24>0,CH24>0),(CH24-CA24)/CA24,IF(AND(CA24=0,CH24=0),"",(CH24-CA24)/CA24)))) | CL24: =+CE24+CH24 -> 64866.9 | CM24: =IF(AND(CL5=0,CL24>=0), "",CL24/CL5) -> 0.39668547 | CO24: =+'N EERR RODEO'!N30 -> 0 | CP24: =IF(AND(CO5=0,CO24>=0), "",CO24/CO5) | CR24: =IF(AND(CH24=0,CO24>0),100%,IF(AND(CH24<0,CO24=0),(CH24-CO24)/CH24,IF(AND(CH24>0,CO24>0),(CO24-CH24)/CH24,IF(AND(CH24=0,CO24=0),"",(CO24-CH24)/CH24)))) | CS24: =+CL24+CO24 -> 64866.9 | CT24: =IF(AND(CS5=0,CS24>=0), "",CS24/CS5) -> 0.39668547 | CV24: =+AZ24*12 -> 0 | CW24: =IF(AND(CV5=0,CV24>=0), "",CV24/CV5) | CX24: =IF(AND(CV24=0,CS24>0),100%,IF(AND(CV24<0,CS24=0),(CV24-CS24)/CV24,IF(AND(CV24>0,CS24>0),(CS24-CV24)/CV24,IF(AND(CV24=0,CS24=0),"",(CS24-CV24)/CV24)))) -> 1
K25: =IF(AND(E25=0,H25>0),100%,IF(AND(E25<0,H25=0),(E25-H25)/E25,IF(AND(E25>0,H25>0),(H25-E25)/E25,IF(AND(E25=0,H25=0),"",(H25-E25)/E25)))) | R25: =IF(AND(H25=0,O25>0),100%,IF(AND(H25<0,O25=0),(H25-O25)/H25,IF(AND(H25>0,O25>0),(O25-H25)/H25,IF(AND(H25=0,O25=0),"",(O25-H25)/H25)))) | X25: =IF(AND(V25=0,S25>0),100%,IF(AND(V25<0,S25=0),(V25-S25)/V25,IF(AND(V25>0,S25>0),(S25-V25)/V25,IF(AND(V25=0,S25=0),"",(S25-V25)/V25)))) | AB25: =IF(AND(O25=0,Y25>0),100%,IF(AND(O25<0,Y25=0),(O25-Y25)/O25,IF(AND(O25>0,Y25>0),(Y25-O25)/O25,IF(AND(O25=0,Y25=0),"",(Y25-O25)/O25)))) | AI25: =IF(AND(Y25=0,AF25>0),100%,IF(AND(Y25<0,AF25=0),(Y25-AF25)/Y25,IF(AND(Y25>0,AF25>0),(AF25-Y25)/Y25,IF(AND(Y25=0,AF25=0),"",(AF25-Y25)/Y25)))) | AJ25: =+AC25+AF25 -> 0 | AP25: =IF(AND(AF25=0,AM25>0),100%,IF(AND(AF25<0,AM25=0),(AF25-AM25)/AF25,IF(AND(AF25>0,AM25>0),(AM25-AF25)/AF25,IF(AND(AF25=0,AM25=0),"",(AM25-AF25)/AF25)))) | AQ25: =+AJ25+AM25 -> 0 | AT25: =+V25*2 -> 0 | AV25: =IF(AND(AT25=0,AQ25>0),100%,IF(AND(AT25<0,AQ25=0),(AT25-AQ25)/AT25,IF(AND(AT25>0,AQ25>0),(AQ25-AT25)/AT25,IF(AND(AT25=0,AQ25=0),"",(AQ25-AT25)/AT25)))) | AW25: =+AQ25/6 -> 0 | AZ25: =+AT25/6 -> 0 | BB25: =IF(AND(AZ25=0,AW25>0),100%,IF(AND(AZ25<0,AW25=0),(AZ25-AW25)/AZ25,IF(AND(AZ25>0,AW25>0),(AW25-AZ25)/AZ25,IF(AND(AZ25=0,AW25=0),"",(AW25-AZ25)/AZ25)))) | BF25: =IF(AND(AM25=0,BC25>0),100%,IF(AND(AM25<0,BC25=0),(AM25-BC25)/AM25,IF(AND(AM25>0,BC25>0),(BC25-AM25)/AM25,IF(AND(AM25=0,BC25=0),"",(BC25-AM25)/AM25)))) | BG25: =+AQ25+BC25 -> 0 | BM25: =IF(AND(BC25=0,BJ25>0),100%,IF(AND(BC25<0,BJ25=0),(BC25-BJ25)/BC25,IF(AND(BC25>0,BJ25>0),(BJ25-BC25)/BC25,IF(AND(BC25=0,BJ25=0),"",(BJ25-BC25)/BC25)))) | BN25: =+BG25+BJ25 -> 0 | BT25: =IF(AND(BJ25=0,BQ25>0),100%,IF(AND(BJ25<0,BQ25=0),(BJ25-BQ25)/BJ25,IF(AND(BJ25>0,BQ25>0),(BQ25-BJ25)/BJ25,IF(AND(BJ25=0,BQ25=0),"",(BQ25-BJ25)/BJ25)))) | BU25: =+BN25+BQ25 -> 0 | BX25: =+AZ25*9 -> 0 | BZ25: =IF(AND(BX25=0,BU25>0),100%,IF(AND(BX25<0,BU25=0),(BX25-BU25)/BX25,IF(AND(BX25>0,BU25>0),(BU25-BX25)/BX25,IF(AND(BX25=0,BU25=0),"",(BU25-BX25)/BX25)))) | CD25: =IF(AND(BQ25=0,CA25>0),100%,IF(AND(BQ25<0,CA25=0),(BQ25-CA25)/BQ25,IF(AND(BQ25>0,CA25>0),(CA25-BQ25)/BQ25,IF(AND(BQ25=0,CA25=0),"",(CA25-BQ25)/BQ25)))) | CK25: =IF(AND(CA25=0,CH25>0),100%,IF(AND(CA25<0,CH25=0),(CA25-CH25)/CA25,IF(AND(CA25>0,CH25>0),(CH25-CA25)/CA25,IF(AND(CA25=0,CH25=0),"",(CH25-CA25)/CA25)))) | CL25: =+CE25+CH25 -> 0 | CR25: =IF(AND(CH25=0,CO25>0),100%,IF(AND(CH25<0,CO25=0),(CH25-CO25)/CH25,IF(AND(CH25>0,CO25>0),(CO25-CH25)/CH25,IF(AND(CH25=0,CO25=0),"",(CO25-CH25)/CH25)))) | CS25: =+CL25+CO25 -> 0 | CV25: =+AZ25*12 -> 0 | CX25: =IF(AND(CV25=0,CS25>0),100%,IF(AND(CV25<0,CS25=0),(CV25-CS25)/CV25,IF(AND(CV25>0,CS25>0),(CS25-CV25)/CV25,IF(AND(CV25=0,CS25=0),"",(CS25-CV25)/CV25))))
A26: Subtotal Costo de Ventas por Servicios | B26: =SUM(B27:B28) -> 0 | C26: =IF(AND(B10=0,B26>=0), "",B26/B10) | E26: =SUM(E27:E28) -> 0 | F26: =IF(AND(E10=0,E26>=0), "",E26/E10) | H26: =SUM(H27:H28) -> 0 | I26: =IF(AND(H10=0,H26>=0), "",H26/H10) | K26: =IF(AND(E26=0,H26>0),100%,IF(AND(E26<0,H26=0),(E26-H26)/E26,IF(AND(E26>0,H26>0),(H26-E26)/E26,IF(AND(E26=0,H26=0),"",(H26-E26)/E26)))) | L26: =SUM(L27:L28) -> 0 | M26: =IF(AND(L10=0,L26>=0), "",L26/L10) | O26: =SUM(O27:O28) -> 0 | P26: =IF(AND(O10=0,O26>=0), "",O26/O10) | R26: =IF(AND(H26=0,O26>0),100%,IF(AND(H26<0,O26=0),(H26-O26)/H26,IF(AND(H26>0,O26>0),(O26-H26)/H26,IF(AND(H26=0,O26=0),"",(O26-H26)/H26)))) | S26: =SUM(S27:S28) -> 0 | T26: =IF(AND(S10=0,S26>=0), "",S26/S10) | V26: =SUM(V27:V28) -> 0 | W26: =IF(AND(V10=0,V26>=0), "",V26/V10) | X26: =IF(AND(V26=0,S26>0),100%,IF(AND(V26<0,S26=0),(V26-S26)/V26,IF(AND(V26>0,S26>0),(S26-V26)/V26,IF(AND(V26=0,S26=0),"",(S26-V26)/V26)))) | Y26: =SUM(Y27:Y28) -> 0 | Z26: =IF(AND(Y10=0,Y26>=0), "",Y26/Y10) | AB26: =IF(AND(O26=0,Y26>0),100%,IF(AND(O26<0,Y26=0),(O26-Y26)/O26,IF(AND(O26>0,Y26>0),(Y26-O26)/O26,IF(AND(O26=0,Y26=0),"",(Y26-O26)/O26)))) | AC26: =SUM(AC27:AC28) -> 0 | AD26: =IF(AND(AC10=0,AC26>=0), "",AC26/AC10) | AF26: =SUM(AF27:AF28) -> 0 | AG26: =IF(AND(AF10=0,AF26>=0), "",AF26/AF10) | AI26: =IF(AND(Y26=0,AF26>0),100%,IF(AND(Y26<0,AF26=0),(Y26-AF26)/Y26,IF(AND(Y26>0,AF26>0),(AF26-Y26)/Y26,IF(AND(Y26=0,AF26=0),"",(AF26-Y26)/Y26)))) | AJ26: =SUM(AJ27:AJ28) -> 0 | AK26: =IF(AND(AJ10=0,AJ26>=0), "",AJ26/AJ10) | AM26: =SUM(AM27:AM28) -> 0 | AN26: =IF(AND(AM10=0,AM26>=0), "",AM26/AM10) | AP26: =IF(AND(AF26=0,AM26>0),100%,IF(AND(AF26<0,AM26=0),(AF26-AM26)/AF26,IF(AND(AF26>0,AM26>0),(AM26-AF26)/AF26,IF(AND(AF26=0,AM26=0),"",(AM26-AF26)/AF26)))) | AQ26: =SUM(AQ27:AQ28) -> 0 | AR26: =IF(AND(AQ10=0,AQ26>=0), "",AQ26/AQ10) | AT26: =SUM(AT27:AT28) -> 0 | AU26: =IF(AND(AT10=0,AT26>=0), "",AT26/AT10) | AV26: =IF(AND(AT26=0,AQ26>0),100%,IF(AND(AT26<0,AQ26=0),(AT26-AQ26)/AT26,IF(AND(AT26>0,AQ26>0),(AQ26-AT26)/AT26,IF(AND(AT26=0,AQ26=0),"",(AQ26-AT26)/AT26)))) | AW26: =SUM(AW27:AW28) -> 0 | AX26: =IF(AND(AW10=0,AW26>=0), "",AW26/AW10) | AZ26: =SUM(AZ27:AZ28) -> 0 | BA26: =IF(AND(AZ10=0,AZ26>=0), "",AZ26/AZ10) | BB26: =IF(AND(AZ26=0,AW26>0),100%,IF(AND(AZ26<0,AW26=0),(AZ26-AW26)/AZ26,IF(AND(AZ26>0,AW26>0),(AW26-AZ26)/AZ26,IF(AND(AZ26=0,AW26=0),"",(AW26-AZ26)/AZ26)))) | BC26: =SUM(BC27:BC28) -> 0 | BD26: =IF(AND(BC10=0,BC26>=0), "",BC26/BC10) | BF26: =IF(AND(AM26=0,BC26>0),100%,IF(AND(AM26<0,BC26=0),(AM26-BC26)/AM26,IF(AND(AM26>0,BC26>0),(BC26-AM26)/AM26,IF(AND(AM26=0,BC26=0),"",(BC26-AM26)/AM26)))) | BG26: =SUM(BG27:BG28) -> 0 | BH26: =IF(AND(BG10=0,BG26>=0), "",BG26/BG10) | BJ26: =SUM(BJ27:BJ28) -> 0 | BK26: =IF(AND(BJ10=0,BJ26>=0), "",BJ26/BJ10) | BM26: =IF(AND(BC26=0,BJ26>0),100%,IF(AND(BC26<0,BJ26=0),(BC26-BJ26)/BC26,IF(AND(BC26>0,BJ26>0),(BJ26-BC26)/BC26,IF(AND(BC26=0,BJ26=0),"",(BJ26-BC26)/BC26)))) | BN26: =SUM(BN27:BN28) -> 0 | BO26: =IF(AND(BN10=0,BN26>=0), "",BN26/BN10) | BQ26: =SUM(BQ27:BQ28) -> 0 | BR26: =IF(AND(BQ10=0,BQ26>=0), "",BQ26/BQ10) | BT26: =IF(AND(BJ26=0,BQ26>0),100%,IF(AND(BJ26<0,BQ26=0),(BJ26-BQ26)/BJ26,IF(AND(BJ26>0,BQ26>0),(BQ26-BJ26)/BJ26,IF(AND(BJ26=0,BQ26=0),"",(BQ26-BJ26)/BJ26)))) | BU26: =SUM(BU27:BU28) -> 0 | BV26: =IF(AND(BU10=0,BU26>=0), "",BU26/BU10) | BX26: =SUM(BX27:BX28) -> 0 | BY26: =IF(AND(BX10=0,BX26>=0), "",BX26/BX10) | BZ26: =IF(AND(BX26=0,BU26>0),100%,IF(AND(BX26<0,BU26=0),(BX26-BU26)/BX26,IF(AND(BX26>0,BU26>0),(BU26-BX26)/BX26,IF(AND(BX26=0,BU26=0),"",(BU26-BX26)/BX26)))) | CA26: =SUM(CA27:CA28) -> 0 | CB26: =IF(AND(CA10=0,CA26>=0), "",CA26/CA10) | CD26: =IF(AND(BQ26=0,CA26>0),100%,IF(AND(BQ26<0,CA26=0),(BQ26-CA26)/BQ26,IF(AND(BQ26>0,CA26>0),(CA26-BQ26)/BQ26,IF(AND(BQ26=0,CA26=0),"",(CA26-BQ26)/BQ26)))) | CE26: =SUM(CE27:CE28) -> 0 | CF26: =IF(AND(CE10=0,CE26>=0), "",CE26/CE10) | CH26: =SUM(CH27:CH28) -> 0 | CI26: =IF(AND(CH10=0,CH26>=0), "",CH26/CH10) | CK26: =IF(AND(CA26=0,CH26>0),100%,IF(AND(CA26<0,CH26=0),(CA26-CH26)/CA26,IF(AND(CA26>0,CH26>0),(CH26-CA26)/CA26,IF(AND(CA26=0,CH26=0),"",(CH26-CA26)/CA26)))) | CL26: =SUM(CL27:CL28) -> 0 | CM26: =IF(AND(CL10=0,CL26>=0), "",CL26/CL10) | CO26: =SUM(CO27:CO28) -> 0 | CP26: =IF(AND(CO10=0,CO26>=0), "",CO26/CO10) | CR26: =IF(AND(CH26=0,CO26>0),100%,IF(AND(CH26<0,CO26=0),(CH26-CO26)/CH26,IF(AND(CH26>0,CO26>0),(CO26-CH26)/CH26,IF(AND(CH26=0,CO26=0),"",(CO26-CH26)/CH26)))) | CS26: =SUM(CS27:CS28) -> 0 | CT26: =IF(AND(CS10=0,CS26>=0), "",CS26/CS10) | CV26: =SUM(CV27:CV28) -> 0 | CW26: =IF(AND(CV10=0,CV26>=0), "",CV26/CV10) | CX26: =IF(AND(CV26=0,CS26>0),100%,IF(AND(CV26<0,CS26=0),(CV26-CS26)/CV26,IF(AND(CV26>0,CS26>0),(CS26-CV26)/CV26,IF(AND(CV26=0,CS26=0),"",(CS26-CV26)/CV26))))
A27: Costo de venta por servicio del café | B27: =+'N EERR RODEO'!B31 -> 0 | C27: =IF(AND(B10=0,B27>=0), "",B27/B10) | E27: =+'N EERR RODEO'!C31 -> 0 | F27: =IF(AND(E10=0,E27>=0), "",E27/E10) | H27: =+'N EERR RODEO'!D31 -> 0 | I27: =IF(AND(H10=0,H27>=0), "",H27/H10) | K27: =IF(AND(E27=0,H27>0),100%,IF(AND(E27<0,H27=0),(E27-H27)/E27,IF(AND(E27>0,H27>0),(H27-E27)/E27,IF(AND(E27=0,H27=0),"",(H27-E27)/E27)))) | L27: =+E27+H27 -> 0 | M27: =IF(AND(L10=0,L27>=0), "",L27/L10) | O27: =+'N EERR RODEO'!E31 -> 0 | P27: =IF(AND(O10=0,O27>=0), "",O27/O10) | R27: =IF(AND(H27=0,O27>0),100%,IF(AND(H27<0,O27=0),(H27-O27)/H27,IF(AND(H27>0,O27>0),(O27-H27)/H27,IF(AND(H27=0,O27=0),"",(O27-H27)/H27)))) | S27: =+L27+O27 -> 0 | T27: =IF(AND(S10=0,S27>=0), "",S27/S10) | W27: =IF(AND(V10=0,V27>=0), "",V27/V10) | X27: =IF(AND(V27=0,S27>0),100%,IF(AND(V27<0,S27=0),(V27-S27)/V27,IF(AND(V27>0,S27>0),(S27-V27)/V27,IF(AND(V27=0,S27=0),"",(S27-V27)/V27)))) | Y27: =+'N EERR RODEO'!F31 -> 0 | Z27: =IF(AND(Y10=0,Y27>=0), "",Y27/Y10) | AB27: =IF(AND(O27=0,Y27>0),100%,IF(AND(O27<0,Y27=0),(O27-Y27)/O27,IF(AND(O27>0,Y27>0),(Y27-O27)/O27,IF(AND(O27=0,Y27=0),"",(Y27-O27)/O27)))) | AC27: =+S27+Y27 -> 0 | AD27: =IF(AND(AC10=0,AC27>=0), "",AC27/AC10) | AF27: =+'N EERR RODEO'!G31 -> 0 | AG27: =IF(AND(AF10=0,AF27>=0), "",AF27/AF10) | AI27: =IF(AND(Y27=0,AF27>0),100%,IF(AND(Y27<0,AF27=0),(Y27-AF27)/Y27,IF(AND(Y27>0,AF27>0),(AF27-Y27)/Y27,IF(AND(Y27=0,AF27=0),"",(AF27-Y27)/Y27)))) | AJ27: =+AC27+AF27 -> 0 | AK27: =IF(AND(AJ10=0,AJ27>=0), "",AJ27/AJ10) | AM27: =+'N EERR RODEO'!H31 -> 0 | AN27: =IF(AND(AM10=0,AM27>=0), "",AM27/AM10) | AP27: =IF(AND(AF27=0,AM27>0),100%,IF(AND(AF27<0,AM27=0),(AF27-AM27)/AF27,IF(AND(AF27>0,AM27>0),(AM27-AF27)/AF27,IF(AND(AF27=0,AM27=0),"",(AM27-AF27)/AF27)))) | AQ27: =+AJ27+AM27 -> 0 | AR27: =IF(AND(AQ10=0,AQ27>=0), "",AQ27/AQ10) | AT27: =+V27*2 -> 0 | AU27: =IF(AND(AT10=0,AT27>=0), "",AT27/AT10) | AV27: =IF(AND(AT27=0,AQ27>0),100%,IF(AND(AT27<0,AQ27=0),(AT27-AQ27)/AT27,IF(AND(AT27>0,AQ27>0),(AQ27-AT27)/AT27,IF(AND(AT27=0,AQ27=0),"",(AQ27-AT27)/AT27)))) | AW27: =+AQ27/6 -> 0 | AX27: =IF(AND(AW10=0,AW27>=0), "",AW27/AW10) | AZ27: =+AT27/6 -> 0 | BA27: =IF(AND(AZ10=0,AZ27>=0), "",AZ27/AZ10) | BB27: =IF(AND(AZ27=0,AW27>0),100%,IF(AND(AZ27<0,AW27=0),(AZ27-AW27)/AZ27,IF(AND(AZ27>0,AW27>0),(AW27-AZ27)/AZ27,IF(AND(AZ27=0,AW27=0),"",(AW27-AZ27)/AZ27)))) | BC27: =+'N EERR RODEO'!I31 -> 0 | BD27: =IF(AND(BC10=0,BC27>=0), "",BC27/BC10) | BF27: =IF(AND(AM27=0,BC27>0),100%,IF(AND(AM27<0,BC27=0),(AM27-BC27)/AM27,IF(AND(AM27>0,BC27>0),(BC27-AM27)/AM27,IF(AND(AM27=0,BC27=0),"",(BC27-AM27)/AM27)))) | BG27: =+AQ27+BC27 -> 0 | BH27: =IF(AND(BG10=0,BG27>=0), "",BG27/BG10) | BJ27: =+'N EERR RODEO'!J31 -> 0 | BK27: =IF(AND(BJ10=0,BJ27>=0), "",BJ27/BJ10) | BM27: =IF(AND(BC27=0,BJ27>0),100%,IF(AND(BC27<0,BJ27=0),(BC27-BJ27)/BC27,IF(AND(BC27>0,BJ27>0),(BJ27-BC27)/BC27,IF(AND(BC27=0,BJ27=0),"",(BJ27-BC27)/BC27)))) | BN27: =+BG27+BJ27 -> 0 | BO27: =IF(AND(BN10=0,BN27>=0), "",BN27/BN10) | BQ27: =+'N EERR RODEO'!K31 -> 0 | BR27: =IF(AND(BQ10=0,BQ27>=0), "",BQ27/BQ10) | BT27: =IF(AND(BJ27=0,BQ27>0),100%,IF(AND(BJ27<0,BQ27=0),(BJ27-BQ27)/BJ27,IF(AND(BJ27>0,BQ27>0),(BQ27-BJ27)/BJ27,IF(AND(BJ27=0,BQ27=0),"",(BQ27-BJ27)/BJ27)))) | BU27: =+BN27+BQ27 -> 0 | BV27: =IF(AND(BU10=0,BU27>=0), "",BU27/BU10) | BX27: =+AZ27*9 -> 0 | BY27: =IF(AND(BX10=0,BX27>=0), "",BX27/BX10) | BZ27: =IF(AND(BX27=0,BU27>0),100%,IF(AND(BX27<0,BU27=0),(BX27-BU27)/BX27,IF(AND(BX27>0,BU27>0),(BU27-BX27)/BX27,IF(AND(BX27=0,BU27=0),"",(BU27-BX27)/BX27)))) | CA27: =+'N EERR RODEO'!L31 -> 0 | CB27: =IF(AND(CA10=0,CA27>=0), "",CA27/CA10) | CD27: =IF(AND(BQ27=0,CA27>0),100%,IF(AND(BQ27<0,CA27=0),(BQ27-CA27)/BQ27,IF(AND(BQ27>0,CA27>0),(CA27-BQ27)/BQ27,IF(AND(BQ27=0,CA27=0),"",(CA27-BQ27)/BQ27)))) | CE27: =+BU27+CA27 -> 0 | CF27: =IF(AND(CE10=0,CE27>=0), "",CE27/CE10) | CH27: =+'N EERR RODEO'!M31 -> 0 | CI27: =IF(AND(CH10=0,CH27>=0), "",CH27/CH10) | CK27: =IF(AND(CA27=0,CH27>0),100%,IF(AND(CA27<0,CH27=0),(CA27-CH27)/CA27,IF(AND(CA27>0,CH27>0),(CH27-CA27)/CA27,IF(AND(CA27=0,CH27=0),"",(CH27-CA27)/CA27)))) | CL27: =+CE27+CH27 -> 0 | CM27: =IF(AND(CL10=0,CL27>=0), "",CL27/CL10) | CO27: =+'N EERR RODEO'!N31 -> 0 | CP27: =IF(AND(CO10=0,CO27>=0), "",CO27/CO10) | CR27: =IF(AND(CH27=0,CO27>0),100%,IF(AND(CH27<0,CO27=0),(CH27-CO27)/CH27,IF(AND(CH27>0,CO27>0),(CO27-CH27)/CH27,IF(AND(CH27=0,CO27=0),"",(CO27-CH27)/CH27)))) | CS27: =+CL27+CO27 -> 0 | CT27: =IF(AND(CS10=0,CS27>=0), "",CS27/CS10) | CV27: =+AZ27*12 -> 0 | CW27: =IF(AND(CV10=0,CV27>=0), "",CV27/CV10) | CX27: =IF(AND(CV27=0,CS27>0),100%,IF(AND(CV27<0,CS27=0),(CV27-CS27)/CV27,IF(AND(CV27>0,CS27>0),(CS27-CV27)/CV27,IF(AND(CV27=0,CS27=0),"",(CS27-CV27)/CV27))))
K28: =IF(AND(E28=0,H28>0),100%,IF(AND(E28<0,H28=0),(E28-H28)/E28,IF(AND(E28>0,H28>0),(H28-E28)/E28,IF(AND(E28=0,H28=0),"",(H28-E28)/E28)))) | R28: =IF(AND(H28=0,O28>0),100%,IF(AND(H28<0,O28=0),(H28-O28)/H28,IF(AND(H28>0,O28>0),(O28-H28)/H28,IF(AND(H28=0,O28=0),"",(O28-H28)/H28)))) | X28: =IF(AND(V28=0,S28>0),100%,IF(AND(V28<0,S28=0),(V28-S28)/V28,IF(AND(V28>0,S28>0),(S28-V28)/V28,IF(AND(V28=0,S28=0),"",(S28-V28)/V28)))) | AB28: =IF(AND(O28=0,Y28>0),100%,IF(AND(O28<0,Y28=0),(O28-Y28)/O28,IF(AND(O28>0,Y28>0),(Y28-O28)/O28,IF(AND(O28=0,Y28=0),"",(Y28-O28)/O28)))) | AI28: =IF(AND(Y28=0,AF28>0),100%,IF(AND(Y28<0,AF28=0),(Y28-AF28)/Y28,IF(AND(Y28>0,AF28>0),(AF28-Y28)/Y28,IF(AND(Y28=0,AF28=0),"",(AF28-Y28)/Y28)))) | AJ28: =+AC28+AF28 -> 0 | AP28: =IF(AND(AF28=0,AM28>0),100%,IF(AND(AF28<0,AM28=0),(AF28-AM28)/AF28,IF(AND(AF28>0,AM28>0),(AM28-AF28)/AF28,IF(AND(AF28=0,AM28=0),"",(AM28-AF28)/AF28)))) | AQ28: =+AJ28+AM28 -> 0 | AT28: =+V28*2 -> 0 | AV28: =IF(AND(AT28=0,AQ28>0),100%,IF(AND(AT28<0,AQ28=0),(AT28-AQ28)/AT28,IF(AND(AT28>0,AQ28>0),(AQ28-AT28)/AT28,IF(AND(AT28=0,AQ28=0),"",(AQ28-AT28)/AT28)))) | AW28: =+AQ28/6 -> 0 | AZ28: =+AT28/6 -> 0 | BB28: =IF(AND(AZ28=0,AW28>0),100%,IF(AND(AZ28<0,AW28=0),(AZ28-AW28)/AZ28,IF(AND(AZ28>0,AW28>0),(AW28-AZ28)/AZ28,IF(AND(AZ28=0,AW28=0),"",(AW28-AZ28)/AZ28)))) | BF28: =IF(AND(AM28=0,BC28>0),100%,IF(AND(AM28<0,BC28=0),(AM28-BC28)/AM28,IF(AND(AM28>0,BC28>0),(BC28-AM28)/AM28,IF(AND(AM28=0,BC28=0),"",(BC28-AM28)/AM28)))) | BG28: =+AQ28+BC28 -> 0 | BM28: =IF(AND(BC28=0,BJ28>0),100%,IF(AND(BC28<0,BJ28=0),(BC28-BJ28)/BC28,IF(AND(BC28>0,BJ28>0),(BJ28-BC28)/BC28,IF(AND(BC28=0,BJ28=0),"",(BJ28-BC28)/BC28)))) | BN28: =+BG28+BJ28 -> 0 | BT28: =IF(AND(BJ28=0,BQ28>0),100%,IF(AND(BJ28<0,BQ28=0),(BJ28-BQ28)/BJ28,IF(AND(BJ28>0,BQ28>0),(BQ28-BJ28)/BJ28,IF(AND(BJ28=0,BQ28=0),"",(BQ28-BJ28)/BJ28)))) | BU28: =+BN28+BQ28 -> 0 | BX28: =+AZ28*9 -> 0 | BZ28: =IF(AND(BX28=0,BU28>0),100%,IF(AND(BX28<0,BU28=0),(BX28-BU28)/BX28,IF(AND(BX28>0,BU28>0),(BU28-BX28)/BX28,IF(AND(BX28=0,BU28=0),"",(BU28-BX28)/BX28)))) | CD28: =IF(AND(BQ28=0,CA28>0),100%,IF(AND(BQ28<0,CA28=0),(BQ28-CA28)/BQ28,IF(AND(BQ28>0,CA28>0),(CA28-BQ28)/BQ28,IF(AND(BQ28=0,CA28=0),"",(CA28-BQ28)/BQ28)))) | CK28: =IF(AND(CA28=0,CH28>0),100%,IF(AND(CA28<0,CH28=0),(CA28-CH28)/CA28,IF(AND(CA28>0,CH28>0),(CH28-CA28)/CA28,IF(AND(CA28=0,CH28=0),"",(CH28-CA28)/CA28)))) | CL28: =+CE28+CH28 -> 0 | CR28: =IF(AND(CH28=0,CO28>0),100%,IF(AND(CH28<0,CO28=0),(CH28-CO28)/CH28,IF(AND(CH28>0,CO28>0),(CO28-CH28)/CH28,IF(AND(CH28=0,CO28=0),"",(CO28-CH28)/CH28)))) | CS28: =+CL28+CO28 -> 0 | CV28: =+AZ28*12 -> 0 | CX28: =IF(AND(CV28=0,CS28>0),100%,IF(AND(CV28<0,CS28=0),(CV28-CS28)/CV28,IF(AND(CV28>0,CS28>0),(CS28-CV28)/CV28,IF(AND(CV28=0,CS28=0),"",(CS28-CV28)/CV28))))
A29: Subtotal Costo de Ventas por Eventos | B29: =SUM(B30:B31) -> 0 | C29: =IF(AND(B15=0,B29>=0), "",B29/B15) | E29: =SUM(E30:E31) -> 0 | F29: =IF(AND(E15=0,E29>=0), "",E29/E15) | H29: =SUM(H30:H31) -> 0 | I29: =IF(AND(H15=0,H29>=0), "",H29/H15) | K29: =IF(AND(E29=0,H29>0),100%,IF(AND(E29<0,H29=0),(E29-H29)/E29,IF(AND(E29>0,H29>0),(H29-E29)/E29,IF(AND(E29=0,H29=0),"",(H29-E29)/E29)))) | L29: =SUM(L30:L31) -> 0 | M29: =IF(AND(L15=0,L29>=0), "",L29/L15) | O29: =SUM(O30:O31) -> 0 | P29: =IF(AND(O15=0,O29>=0), "",O29/O15) | R29: =IF(AND(H29=0,O29>0),100%,IF(AND(H29<0,O29=0),(H29-O29)/H29,IF(AND(H29>0,O29>0),(O29-H29)/H29,IF(AND(H29=0,O29=0),"",(O29-H29)/H29)))) | S29: =SUM(S30:S31) -> 0 | T29: =IF(AND(S15=0,S29>=0), "",S29/S15) | V29: =SUM(V30:V31) -> 0 | W29: =IF(AND(V15=0,V29>=0), "",V29/V15) | X29: =IF(AND(V29=0,S29>0),100%,IF(AND(V29<0,S29=0),(V29-S29)/V29,IF(AND(V29>0,S29>0),(S29-V29)/V29,IF(AND(V29=0,S29=0),"",(S29-V29)/V29)))) | Y29: =SUM(Y30:Y31) -> 0 | Z29: =IF(AND(Y15=0,Y29>=0), "",Y29/Y15) | AB29: =IF(AND(O29=0,Y29>0),100%,IF(AND(O29<0,Y29=0),(O29-Y29)/O29,IF(AND(O29>0,Y29>0),(Y29-O29)/O29,IF(AND(O29=0,Y29=0),"",(Y29-O29)/O29)))) | AC29: =SUM(AC30:AC31) -> 0 | AD29: =IF(AND(AC15=0,AC29>=0), "",AC29/AC15) | AF29: =SUM(AF30:AF31) -> 0 | AG29: =IF(AND(AF15=0,AF29>=0), "",AF29/AF15) | AI29: =IF(AND(Y29=0,AF29>0),100%,IF(AND(Y29<0,AF29=0),(Y29-AF29)/Y29,IF(AND(Y29>0,AF29>0),(AF29-Y29)/Y29,IF(AND(Y29=0,AF29=0),"",(AF29-Y29)/Y29)))) | AJ29: =SUM(AJ30:AJ31) -> 0 | AK29: =IF(AND(AJ15=0,AJ29>=0), "",AJ29/AJ15) | AM29: =SUM(AM30:AM31) -> 0 | AN29: =IF(AND(AM15=0,AM29>=0), "",AM29/AM15) | AP29: =IF(AND(AF29=0,AM29>0),100%,IF(AND(AF29<0,AM29=0),(AF29-AM29)/AF29,IF(AND(AF29>0,AM29>0),(AM29-AF29)/AF29,IF(AND(AF29=0,AM29=0),"",(AM29-AF29)/AF29)))) | AQ29: =SUM(AQ30:AQ31) -> 0 | AR29: =IF(AND(AQ15=0,AQ29>=0), "",AQ29/AQ15) | AT29: =SUM(AT30:AT31) -> 0 | AU29: =IF(AND(AT15=0,AT29>=0), "",AT29/AT15) | AV29: =IF(AND(AT29=0,AQ29>0),100%,IF(AND(AT29<0,AQ29=0),(AT29-AQ29)/AT29,IF(AND(AT29>0,AQ29>0),(AQ29-AT29)/AT29,IF(AND(AT29=0,AQ29=0),"",(AQ29-AT29)/AT29)))) | AW29: =SUM(AW30:AW31) -> 0 | AX29: =IF(AND(AW15=0,AW29>=0), "",AW29/AW15) | AZ29: =SUM(AZ30:AZ31) -> 0 | BA29: =IF(AND(AZ15=0,AZ29>=0), "",AZ29/AZ15) | BB29: =IF(AND(AZ29=0,AW29>0),100%,IF(AND(AZ29<0,AW29=0),(AZ29-AW29)/AZ29,IF(AND(AZ29>0,AW29>0),(AW29-AZ29)/AZ29,IF(AND(AZ29=0,AW29=0),"",(AW29-AZ29)/AZ29)))) | BC29: =SUM(BC30:BC31) -> 0 | BD29: =IF(AND(BC15=0,BC29>=0), "",BC29/BC15) | BF29: =IF(AND(AM29=0,BC29>0),100%,IF(AND(AM29<0,BC29=0),(AM29-BC29)/AM29,IF(AND(AM29>0,BC29>0),(BC29-AM29)/AM29,IF(AND(AM29=0,BC29=0),"",(BC29-AM29)/AM29)))) | BG29: =SUM(BG30:BG31) -> 0 | BH29: =IF(AND(BG15=0,BG29>=0), "",BG29/BG15) | BJ29: =SUM(BJ30:BJ31) -> 0 | BK29: =IF(AND(BJ15=0,BJ29>=0), "",BJ29/BJ15) | BM29: =IF(AND(BC29=0,BJ29>0),100%,IF(AND(BC29<0,BJ29=0),(BC29-BJ29)/BC29,IF(AND(BC29>0,BJ29>0),(BJ29-BC29)/BC29,IF(AND(BC29=0,BJ29=0),"",(BJ29-BC29)/BC29)))) | BN29: =SUM(BN30:BN31) -> 0 | BO29: =IF(AND(BN15=0,BN29>=0), "",BN29/BN15) | BQ29: =SUM(BQ30:BQ31) -> 0 | BR29: =IF(AND(BQ15=0,BQ29>=0), "",BQ29/BQ15) | BT29: =IF(AND(BJ29=0,BQ29>0),100%,IF(AND(BJ29<0,BQ29=0),(BJ29-BQ29)/BJ29,IF(AND(BJ29>0,BQ29>0),(BQ29-BJ29)/BJ29,IF(AND(BJ29=0,BQ29=0),"",(BQ29-BJ29)/BJ29)))) | BU29: =SUM(BU30:BU31) -> 0 | BV29: =IF(AND(BU15=0,BU29>=0), "",BU29/BU15) | BX29: =SUM(BX30:BX31) -> 0 | BY29: =IF(AND(BX15=0,BX29>=0), "",BX29/BX15) | BZ29: =IF(AND(BX29=0,BU29>0),100%,IF(AND(BX29<0,BU29=0),(BX29-BU29)/BX29,IF(AND(BX29>0,BU29>0),(BU29-BX29)/BX29,IF(AND(BX29=0,BU29=0),"",(BU29-BX29)/BX29)))) | CA29: =SUM(CA30:CA31) -> 0 | CB29: =IF(AND(CA15=0,CA29>=0), "",CA29/CA15) | CD29: =IF(AND(BQ29=0,CA29>0),100%,IF(AND(BQ29<0,CA29=0),(BQ29-CA29)/BQ29,IF(AND(BQ29>0,CA29>0),(CA29-BQ29)/BQ29,IF(AND(BQ29=0,CA29=0),"",(CA29-BQ29)/BQ29)))) | CE29: =SUM(CE30:CE31) -> 0 | CF29: =IF(AND(CE15=0,CE29>=0), "",CE29/CE15) | CH29: =SUM(CH30:CH31) -> 0 | CI29: =IF(AND(CH15=0,CH29>=0), "",CH29/CH15) | CK29: =IF(AND(CA29=0,CH29>0),100%,IF(AND(CA29<0,CH29=0),(CA29-CH29)/CA29,IF(AND(CA29>0,CH29>0),(CH29-CA29)/CA29,IF(AND(CA29=0,CH29=0),"",(CH29-CA29)/CA29)))) | CL29: =SUM(CL30:CL31) -> 0 | CM29: =IF(AND(CL15=0,CL29>=0), "",CL29/CL15) | CO29: =SUM(CO30:CO31) -> 0 | CP29: =IF(AND(CO15=0,CO29>=0), "",CO29/CO15) | CR29: =IF(AND(CH29=0,CO29>0),100%,IF(AND(CH29<0,CO29=0),(CH29-CO29)/CH29,IF(AND(CH29>0,CO29>0),(CO29-CH29)/CH29,IF(AND(CH29=0,CO29=0),"",(CO29-CH29)/CH29)))) | CS29: =SUM(CS30:CS31) -> 0 | CT29: =IF(AND(CS15=0,CS29>=0), "",CS29/CS15) | CV29: =SUM(CV30:CV31) -> 0 | CW29: =IF(AND(CV15=0,CV29>=0), "",CV29/CV15) | CX29: =IF(AND(CV29=0,CS29>0),100%,IF(AND(CV29<0,CS29=0),(CV29-CS29)/CV29,IF(AND(CV29>0,CS29>0),(CS29-CV29)/CV29,IF(AND(CV29=0,CS29=0),"",(CS29-CV29)/CV29))))
A30: Costo de ventas por eventos | B30: =+'N EERR RODEO'!B32 -> 0 | C30: =IF(AND(B15=0,B30>=0), "",B30/B15) | E30: =+'N EERR RODEO'!C32 -> 0 | F30: =IF(AND(E15=0,E30>=0), "",E30/E15) | H30: =+'N EERR RODEO'!D32 -> 0 | I30: =IF(AND(H15=0,H30>=0), "",H30/H15) | K30: =IF(AND(E30=0,H30>0),100%,IF(AND(E30<0,H30=0),(E30-H30)/E30,IF(AND(E30>0,H30>0),(H30-E30)/E30,IF(AND(E30=0,H30=0),"",(H30-E30)/E30)))) | L30: =+E30+H30 -> 0 | M30: =IF(AND(L15=0,L30>=0), "",L30/L15) | O30: =+'N EERR RODEO'!E32 -> 0 | P30: =IF(AND(O15=0,O30>=0), "",O30/O15) | R30: =IF(AND(H30=0,O30>0),100%,IF(AND(H30<0,O30=0),(H30-O30)/H30,IF(AND(H30>0,O30>0),(O30-H30)/H30,IF(AND(H30=0,O30=0),"",(O30-H30)/H30)))) | S30: =+L30+O30 -> 0 | T30: =IF(AND(S15=0,S30>=0), "",S30/S15) | W30: =IF(AND(V15=0,V30>=0), "",V30/V15) | X30: =IF(AND(V30=0,S30>0),100%,IF(AND(V30<0,S30=0),(V30-S30)/V30,IF(AND(V30>0,S30>0),(S30-V30)/V30,IF(AND(V30=0,S30=0),"",(S30-V30)/V30)))) | Y30: =+'N EERR RODEO'!F32 -> 0 | Z30: =IF(AND(Y15=0,Y30>=0), "",Y30/Y15) | AB30: =IF(AND(O30=0,Y30>0),100%,IF(AND(O30<0,Y30=0),(O30-Y30)/O30,IF(AND(O30>0,Y30>0),(Y30-O30)/O30,IF(AND(O30=0,Y30=0),"",(Y30-O30)/O30)))) | AC30: =+S30+Y30 -> 0 | AD30: =IF(AND(AC15=0,AC30>=0), "",AC30/AC15) | AF30: =+'N EERR RODEO'!G32 -> 0 | AG30: =IF(AND(AF15=0,AF30>=0), "",AF30/AF15) | AI30: =IF(AND(Y30=0,AF30>0),100%,IF(AND(Y30<0,AF30=0),(Y30-AF30)/Y30,IF(AND(Y30>0,AF30>0),(AF30-Y30)/Y30,IF(AND(Y30=0,AF30=0),"",(AF30-Y30)/Y30)))) | AJ30: =+AC30+AF30 -> 0 | AK30: =IF(AND(AJ15=0,AJ30>=0), "",AJ30/AJ15) | AM30: =+'N EERR RODEO'!H32 -> 0 | AN30: =IF(AND(AM15=0,AM30>=0), "",AM30/AM15) | AP30: =IF(AND(AF30=0,AM30>0),100%,IF(AND(AF30<0,AM30=0),(AF30-AM30)/AF30,IF(AND(AF30>0,AM30>0),(AM30-AF30)/AF30,IF(AND(AF30=0,AM30=0),"",(AM30-AF30)/AF30)))) | AQ30: =+AJ30+AM30 -> 0 | AR30: =IF(AND(AQ15=0,AQ30>=0), "",AQ30/AQ15) | AT30: =+V30*2 -> 0 | AU30: =IF(AND(AT15=0,AT30>=0), "",AT30/AT15) | AV30: =IF(AND(AT30=0,AQ30>0),100%,IF(AND(AT30<0,AQ30=0),(AT30-AQ30)/AT30,IF(AND(AT30>0,AQ30>0),(AQ30-AT30)/AT30,IF(AND(AT30=0,AQ30=0),"",(AQ30-AT30)/AT30)))) | AW30: =+AQ30/6 -> 0 | AX30: =IF(AND(AW15=0,AW30>=0), "",AW30/AW15) | AZ30: =+AT30/6 -> 0 | BA30: =IF(AND(AZ15=0,AZ30>=0), "",AZ30/AZ15) | BB30: =IF(AND(AZ30=0,AW30>0),100%,IF(AND(AZ30<0,AW30=0),(AZ30-AW30)/AZ30,IF(AND(AZ30>0,AW30>0),(AW30-AZ30)/AZ30,IF(AND(AZ30=0,AW30=0),"",(AW30-AZ30)/AZ30)))) | BC30: =+'N EERR RODEO'!I32 -> 0 | BD30: =IF(AND(BC15=0,BC30>=0), "",BC30/BC15) | BF30: =IF(AND(AM30=0,BC30>0),100%,IF(AND(AM30<0,BC30=0),(AM30-BC30)/AM30,IF(AND(AM30>0,BC30>0),(BC30-AM30)/AM30,IF(AND(AM30=0,BC30=0),"",(BC30-AM30)/AM30)))) | BG30: =+AQ30+BC30 -> 0 | BH30: =IF(AND(BG15=0,BG30>=0), "",BG30/BG15) | BJ30: =+'N EERR RODEO'!J32 -> 0 | BK30: =IF(AND(BJ15=0,BJ30>=0), "",BJ30/BJ15) | BM30: =IF(AND(BC30=0,BJ30>0),100%,IF(AND(BC30<0,BJ30=0),(BC30-BJ30)/BC30,IF(AND(BC30>0,BJ30>0),(BJ30-BC30)/BC30,IF(AND(BC30=0,BJ30=0),"",(BJ30-BC30)/BC30)))) | BN30: =+BG30+BJ30 -> 0 | BO30: =IF(AND(BN15=0,BN30>=0), "",BN30/BN15) | BQ30: =+'N EERR RODEO'!K32 -> 0 | BR30: =IF(AND(BQ15=0,BQ30>=0), "",BQ30/BQ15) | BT30: =IF(AND(BJ30=0,BQ30>0),100%,IF(AND(BJ30<0,BQ30=0),(BJ30-BQ30)/BJ30,IF(AND(BJ30>0,BQ30>0),(BQ30-BJ30)/BJ30,IF(AND(BJ30=0,BQ30=0),"",(BQ30-BJ30)/BJ30)))) | BU30: =+BN30+BQ30 -> 0 | BV30: =IF(AND(BU15=0,BU30>=0), "",BU30/BU15) | BX30: =+AZ30*9 -> 0 | BY30: =IF(AND(BX15=0,BX30>=0), "",BX30/BX15) | BZ30: =IF(AND(BX30=0,BU30>0),100%,IF(AND(BX30<0,BU30=0),(BX30-BU30)/BX30,IF(AND(BX30>0,BU30>0),(BU30-BX30)/BX30,IF(AND(BX30=0,BU30=0),"",(BU30-BX30)/BX30)))) | CA30: =+'N EERR RODEO'!L32 -> 0 | CB30: =IF(AND(CA15=0,CA30>=0), "",CA30/CA15) | CD30: =IF(AND(BQ30=0,CA30>0),100%,IF(AND(BQ30<0,CA30=0),(BQ30-CA30)/BQ30,IF(AND(BQ30>0,CA30>0),(CA30-BQ30)/BQ30,IF(AND(BQ30=0,CA30=0),"",(CA30-BQ30)/BQ30)))) | CE30: =+BU30+CA30 -> 0 | CF30: =IF(AND(CE15=0,CE30>=0), "",CE30/CE15) | CH30: =+'N EERR RODEO'!M32 -> 0 | CI30: =IF(AND(CH15=0,CH30>=0), "",CH30/CH15) | CK30: =IF(AND(CA30=0,CH30>0),100%,IF(AND(CA30<0,CH30=0),(CA30-CH30)/CA30,IF(AND(CA30>0,CH30>0),(CH30-CA30)/CA30,IF(AND(CA30=0,CH30=0),"",(CH30-CA30)/CA30)))) | CL30: =+CE30+CH30 -> 0 | CM30: =IF(AND(CL15=0,CL30>=0), "",CL30/CL15) | CO30: =+'N EERR RODEO'!N32 -> 0 | CP30: =IF(AND(CO15=0,CO30>=0), "",CO30/CO15) | CR30: =IF(AND(CH30=0,CO30>0),100%,IF(AND(CH30<0,CO30=0),(CH30-CO30)/CH30,IF(AND(CH30>0,CO30>0),(CO30-CH30)/CH30,IF(AND(CH30=0,CO30=0),"",(CO30-CH30)/CH30)))) | CS30: =+CL30+CO30 -> 0 | CT30: =IF(AND(CS15=0,CS30>=0), "",CS30/CS15) | CV30: =+AZ30*12 -> 0 | CW30: =IF(AND(CV15=0,CV30>=0), "",CV30/CV15) | CX30: =IF(AND(CV30=0,CS30>0),100%,IF(AND(CV30<0,CS30=0),(CV30-CS30)/CV30,IF(AND(CV30>0,CS30>0),(CS30-CV30)/CV30,IF(AND(CV30=0,CS30=0),"",(CS30-CV30)/CV30))))
K31: =IF(AND(E31=0,H31>0),100%,IF(AND(E31<0,H31=0),(E31-H31)/E31,IF(AND(E31>0,H31>0),(H31-E31)/E31,IF(AND(E31=0,H31=0),"",(H31-E31)/E31)))) | R31: =IF(AND(H31=0,O31>0),100%,IF(AND(H31<0,O31=0),(H31-O31)/H31,IF(AND(H31>0,O31>0),(O31-H31)/H31,IF(AND(H31=0,O31=0),"",(O31-H31)/H31)))) | X31: =IF(AND(V31=0,S31>0),100%,IF(AND(V31<0,S31=0),(V31-S31)/V31,IF(AND(V31>0,S31>0),(S31-V31)/V31,IF(AND(V31=0,S31=0),"",(S31-V31)/V31)))) | AB31: =IF(AND(O31=0,Y31>0),100%,IF(AND(O31<0,Y31=0),(O31-Y31)/O31,IF(AND(O31>0,Y31>0),(Y31-O31)/O31,IF(AND(O31=0,Y31=0),"",(Y31-O31)/O31)))) | AI31: =IF(AND(Y31=0,AF31>0),100%,IF(AND(Y31<0,AF31=0),(Y31-AF31)/Y31,IF(AND(Y31>0,AF31>0),(AF31-Y31)/Y31,IF(AND(Y31=0,AF31=0),"",(AF31-Y31)/Y31)))) | AJ31: =+AC31+AF31 -> 0 | AP31: =IF(AND(AF31=0,AM31>0),100%,IF(AND(AF31<0,AM31=0),(AF31-AM31)/AF31,IF(AND(AF31>0,AM31>0),(AM31-AF31)/AF31,IF(AND(AF31=0,AM31=0),"",(AM31-AF31)/AF31)))) | AQ31: =+AJ31+AM31 -> 0 | AT31: =+V31*2 -> 0 | AV31: =IF(AND(AT31=0,AQ31>0),100%,IF(AND(AT31<0,AQ31=0),(AT31-AQ31)/AT31,IF(AND(AT31>0,AQ31>0),(AQ31-AT31)/AT31,IF(AND(AT31=0,AQ31=0),"",(AQ31-AT31)/AT31)))) | AW31: =+AQ31/6 -> 0 | AZ31: =+AT31/6 -> 0 | BB31: =IF(AND(AZ31=0,AW31>0),100%,IF(AND(AZ31<0,AW31=0),(AZ31-AW31)/AZ31,IF(AND(AZ31>0,AW31>0),(AW31-AZ31)/AZ31,IF(AND(AZ31=0,AW31=0),"",(AW31-AZ31)/AZ31)))) | BF31: =IF(AND(AM31=0,BC31>0),100%,IF(AND(AM31<0,BC31=0),(AM31-BC31)/AM31,IF(AND(AM31>0,BC31>0),(BC31-AM31)/AM31,IF(AND(AM31=0,BC31=0),"",(BC31-AM31)/AM31)))) | BG31: =+AQ31+BC31 -> 0 | BM31: =IF(AND(BC31=0,BJ31>0),100%,IF(AND(BC31<0,BJ31=0),(BC31-BJ31)/BC31,IF(AND(BC31>0,BJ31>0),(BJ31-BC31)/BC31,IF(AND(BC31=0,BJ31=0),"",(BJ31-BC31)/BC31)))) | BN31: =+BG31+BJ31 -> 0 | BT31: =IF(AND(BJ31=0,BQ31>0),100%,IF(AND(BJ31<0,BQ31=0),(BJ31-BQ31)/BJ31,IF(AND(BJ31>0,BQ31>0),(BQ31-BJ31)/BJ31,IF(AND(BJ31=0,BQ31=0),"",(BQ31-BJ31)/BJ31)))) | BU31: =+BN31+BQ31 -> 0 | BX31: =+AZ31*9 -> 0 | BZ31: =IF(AND(BX31=0,BU31>0),100%,IF(AND(BX31<0,BU31=0),(BX31-BU31)/BX31,IF(AND(BX31>0,BU31>0),(BU31-BX31)/BX31,IF(AND(BX31=0,BU31=0),"",(BU31-BX31)/BX31)))) | CD31: =IF(AND(BQ31=0,CA31>0),100%,IF(AND(BQ31<0,CA31=0),(BQ31-CA31)/BQ31,IF(AND(BQ31>0,CA31>0),(CA31-BQ31)/BQ31,IF(AND(BQ31=0,CA31=0),"",(CA31-BQ31)/BQ31)))) | CK31: =IF(AND(CA31=0,CH31>0),100%,IF(AND(CA31<0,CH31=0),(CA31-CH31)/CA31,IF(AND(CA31>0,CH31>0),(CH31-CA31)/CA31,IF(AND(CA31=0,CH31=0),"",(CH31-CA31)/CA31)))) | CL31: =+CE31+CH31 -> 0 | CR31: =IF(AND(CH31=0,CO31>0),100%,IF(AND(CH31<0,CO31=0),(CH31-CO31)/CH31,IF(AND(CH31>0,CO31>0),(CO31-CH31)/CH31,IF(AND(CH31=0,CO31=0),"",(CO31-CH31)/CH31)))) | CS31: =+CL31+CO31 -> 0 | CV31: =+AZ31*12 -> 0 | CX31: =IF(AND(CV31=0,CS31>0),100%,IF(AND(CV31<0,CS31=0),(CV31-CS31)/CV31,IF(AND(CV31>0,CS31>0),(CS31-CV31)/CV31,IF(AND(CV31=0,CS31=0),"",(CS31-CV31)/CV31))))
K32: =IF(AND(E32=0,H32>0),100%,IF(AND(E32<0,H32=0),(E32-H32)/E32,IF(AND(E32>0,H32>0),(H32-E32)/E32,IF(AND(E32=0,H32=0),"",(H32-E32)/E32)))) | X32: =IF(AND(V32=0,S32>0),100%,IF(AND(V32<0,S32=0),(V32-S32)/V32,IF(AND(V32>0,S32>0),(S32-V32)/V32,IF(AND(V32=0,S32=0),"",(S32-V32)/V32)))) | AB32: =IF(AND(O32=0,Y32>0),100%,IF(AND(O32<0,Y32=0),(O32-Y32)/O32,IF(AND(O32>0,Y32>0),(Y32-O32)/O32,IF(AND(O32=0,Y32=0),"",(Y32-O32)/O32)))) | AI32: =IF(AND(Y32=0,AF32>0),100%,IF(AND(Y32<0,AF32=0),(Y32-AF32)/Y32,IF(AND(Y32>0,AF32>0),(AF32-Y32)/Y32,IF(AND(Y32=0,AF32=0),"",(AF32-Y32)/Y32)))) | AJ32: =+AC32+AF32 -> 0 | AP32: =IF(AND(AF32=0,AM32>0),100%,IF(AND(AF32<0,AM32=0),(AF32-AM32)/AF32,IF(AND(AF32>0,AM32>0),(AM32-AF32)/AF32,IF(AND(AF32=0,AM32=0),"",(AM32-AF32)/AF32)))) | AQ32: =+AJ32+AM32 -> 0 | AV32: =IF(AND(AT32=0,AQ32>0),100%,IF(AND(AT32<0,AQ32=0),(AT32-AQ32)/AT32,IF(AND(AT32>0,AQ32>0),(AQ32-AT32)/AT32,IF(AND(AT32=0,AQ32=0),"",(AQ32-AT32)/AT32)))) | BB32: =IF(AND(AZ32=0,AW32>0),100%,IF(AND(AZ32<0,AW32=0),(AZ32-AW32)/AZ32,IF(AND(AZ32>0,AW32>0),(AW32-AZ32)/AZ32,IF(AND(AZ32=0,AW32=0),"",(AW32-AZ32)/AZ32)))) | BF32: =IF(AND(AM32=0,BC32>0),100%,IF(AND(AM32<0,BC32=0),(AM32-BC32)/AM32,IF(AND(AM32>0,BC32>0),(BC32-AM32)/AM32,IF(AND(AM32=0,BC32=0),"",(BC32-AM32)/AM32)))) | BG32: =+AZ32+BC32 -> 0 | BM32: =IF(AND(BC32=0,BJ32>0),100%,IF(AND(BC32<0,BJ32=0),(BC32-BJ32)/BC32,IF(AND(BC32>0,BJ32>0),(BJ32-BC32)/BC32,IF(AND(BC32=0,BJ32=0),"",(BJ32-BC32)/BC32)))) | BN32: =+BG32+BJ32 -> 0 | BT32: =IF(AND(BJ32=0,BQ32>0),100%,IF(AND(BJ32<0,BQ32=0),(BJ32-BQ32)/BJ32,IF(AND(BJ32>0,BQ32>0),(BQ32-BJ32)/BJ32,IF(AND(BJ32=0,BQ32=0),"",(BQ32-BJ32)/BJ32)))) | BU32: =+BN32+BQ32 -> 0 | BZ32: =IF(AND(BX32=0,BU32>0),100%,IF(AND(BX32<0,BU32=0),(BX32-BU32)/BX32,IF(AND(BX32>0,BU32>0),(BU32-BX32)/BX32,IF(AND(BX32=0,BU32=0),"",(BU32-BX32)/BX32)))) | CD32: =IF(AND(BQ32=0,CA32>0),100%,IF(AND(BQ32<0,CA32=0),(BQ32-CA32)/BQ32,IF(AND(BQ32>0,CA32>0),(CA32-BQ32)/BQ32,IF(AND(BQ32=0,CA32=0),"",(CA32-BQ32)/BQ32)))) | CK32: =IF(AND(CA32=0,CH32>0),100%,IF(AND(CA32<0,CH32=0),(CA32-CH32)/CA32,IF(AND(CA32>0,CH32>0),(CH32-CA32)/CA32,IF(AND(CA32=0,CH32=0),"",(CH32-CA32)/CA32)))) | CL32: =+CE32+CH32 -> 0 | CR32: =IF(AND(CH32=0,CO32>0),100%,IF(AND(CH32<0,CO32=0),(CH32-CO32)/CH32,IF(AND(CH32>0,CO32>0),(CO32-CH32)/CH32,IF(AND(CH32=0,CO32=0),"",(CO32-CH32)/CH32)))) | CS32: =+CL32+CO32 -> 0 | CX32: =IF(AND(CV32=0,CS32>0),100%,IF(AND(CV32<0,CS32=0),(CV32-CS32)/CV32,IF(AND(CV32>0,CS32>0),(CS32-CV32)/CV32,IF(AND(CV32=0,CS32=0),"",(CS32-CV32)/CV32))))
A33: Utilidad Bruta por Venta de Mercancia y Taller | B33: =+B5+B18-B23 -> 0 | C33: =IF(AND((B5+B18)=0,B33<=0), "",B33/(B5+B18)) | E33: =+E5+E18-E23 -> 27262.18 | F33: =IF(AND((E5+E18)=0,E33<=0), "",E33/(E5+E18)) -> 0.56875562 | H33: =+H5+H18-H23 -> 27170.01 | I33: =IF(AND((H5+H18)=0,H33<=0), "",H33/(H5+H18)) -> 0.52774681 | K33: =IF(AND(E33=0,H33>0),100%,IF(AND(E33<0,H33=0),(E33-H33)/E33,IF(AND(E33>0,H33>0),(H33-E33)/E33,IF(AND(E33=0,H33=0),"",(H33-E33)/E33)))) -> -0.0033808742 | L33: =+L5+L18-L23 -> 54432.19 | M33: =IF(AND((L5+L18)=0,L33<=0), "",L33/(L5+L18)) -> 0.54751903 | O33: =+O5+O18-O23 -> 44223.16 | P33: =IF(AND((O5+O18)=0,O33<=0), "",O33/(O5+O18)) -> 0.68984238 | R33: =IF(AND(H33=0,O33>0),100%,IF(AND(H33<0,O33=0),(H33-O33)/H33,IF(AND(H33>0,O33>0),(O33-H33)/H33,IF(AND(H33=0,O33=0),"",(O33-H33)/H33)))) -> 0.62764607 | S33: =+S5+S18-S23 -> 98655.35 | T33: =IF(AND((S5+S18)=0,S33<=0), "",S33/(S5+S18)) -> 0.60331453 | V33: =+V5+V18-V23 -> 0 | W33: =IF(AND((V5+V18)=0,V33<=0), "",V33/(V5+V18)) | X33: =IF(AND(V33=0,S33>0),100%,IF(AND(V33<0,S33=0),(V33-S33)/V33,IF(AND(V33>0,S33>0),(S33-V33)/V33,IF(AND(V33=0,S33=0),"",(S33-V33)/V33)))) -> 1 | Y33: =+Y5+Y18-Y23 -> 0 | Z33: =IF(AND((Y5+Y18)=0,Y33<=0), "",Y33/(Y5+Y18)) | AB33: =IF(AND(O33=0,Y33>0),100%,IF(AND(O33<0,Y33=0),(O33-Y33)/O33,IF(AND(O33>0,Y33>0),(Y33-O33)/O33,IF(AND(O33=0,Y33=0),"",(Y33-O33)/O33)))) -> -1 | AC33: =+AC5+AC18-AC23 -> 98655.35 | AD33: =IF(AND((AC5+AC18)=0,AC33<=0), "",AC33/(AC5+AC18)) -> 0.60331453 | AF33: =+AF5+AF18-AF23 -> 0 | AG33: =IF(AND((AF5+AF18)=0,AF33<=0), "",AF33/(AF5+AF18)) | AI33: =IF(AND(Y33=0,AF33>0),100%,IF(AND(Y33<0,AF33=0),(Y33-AF33)/Y33,IF(AND(Y33>0,AF33>0),(AF33-Y33)/Y33,IF(AND(Y33=0,AF33=0),"",(AF33-Y33)/Y33)))) | AJ33: =+AJ5+AJ18-AJ23 -> 98655.35 | AK33: =IF(AND((AJ5+AJ18)=0,AJ33<=0), "",AJ33/(AJ5+AJ18)) -> 0.60331453 | AM33: =+AM5+AM18-AM23 -> 0 | AN33: =IF(AND((AM5+AM18)=0,AM33<=0), "",AM33/(AM5+AM18)) | AP33: =IF(AND(AF33=0,AM33>0),100%,IF(AND(AF33<0,AM33=0),(AF33-AM33)/AF33,IF(AND(AF33>0,AM33>0),(AM33-AF33)/AF33,IF(AND(AF33=0,AM33=0),"",(AM33-AF33)/AF33)))) | AQ33: =+AQ5+AQ18-AQ23 -> 98655.35 | AR33: =IF(AND((AQ5+AQ18)=0,AQ33<=0), "",AQ33/(AQ5+AQ18)) -> 0.60331453 | AT33: =+AT5+AT18-AT23 -> 0 | AU33: =IF(AND((AT5+AT18)=0,AT33<=0), "",AT33/(AT5+AT18)) | AV33: =IF(AND(AT33=0,AQ33>0),100%,IF(AND(AT33<0,AQ33=0),(AT33-AQ33)/AT33,IF(AND(AT33>0,AQ33>0),(AQ33-AT33)/AT33,IF(AND(AT33=0,AQ33=0),"",(AQ33-AT33)/AT33)))) -> 1 | AW33: =+AW5+AW18-AW23 -> 16442.558 | AX33: =IF(AND((AW5+AW18)=0,AW33<=0), "",AW33/(AW5+AW18)) -> 0.60331453 | AZ33: =+AZ5+AZ18-AZ23 -> 0 | BA33: =IF(AND((AZ5+AZ18)=0,AZ33<=0), "",AZ33/(AZ5+AZ18)) | BB33: =IF(AND(AZ33=0,AW33>0),100%,IF(AND(AZ33<0,AW33=0),(AZ33-AW33)/AZ33,IF(AND(AZ33>0,AW33>0),(AW33-AZ33)/AZ33,IF(AND(AZ33=0,AW33=0),"",(AW33-AZ33)/AZ33)))) -> 1 | BC33: =+BC5+BC18-BC23 -> 0 | BD33: =IF(AND((BC5+BC18)=0,BC33<=0), "",BC33/(BC5+BC18)) | BF33: =IF(AND(AM33=0,BC33>0),100%,IF(AND(AM33<0,BC33=0),(AM33-BC33)/AM33,IF(AND(AM33>0,BC33>0),(BC33-AM33)/AM33,IF(AND(AM33=0,BC33=0),"",(BC33-AM33)/AM33)))) | BG33: =+BG5+BG18-BG23 -> 98655.35 | BH33: =IF(AND((BG5+BG18)=0,BG33<=0), "",BG33/(BG5+BG18)) -> 0.60331453 | BJ33: =+BJ5+BJ18-BJ23 -> 0 | BK33: =IF(AND((BJ5+BJ18)=0,BJ33<=0), "",BJ33/(BJ5+BJ18)) | BM33: =IF(AND(BC33=0,BJ33>0),100%,IF(AND(BC33<0,BJ33=0),(BC33-BJ33)/BC33,IF(AND(BC33>0,BJ33>0),(BJ33-BC33)/BC33,IF(AND(BC33=0,BJ33=0),"",(BJ33-BC33)/BC33)))) | BN33: =+BN5+BN18-BN23 -> 98655.35 | BO33: =IF(AND((BN5+BN18)=0,BN33<=0), "",BN33/(BN5+BN18)) -> 0.60331453 | BQ33: =+BQ5+BQ18-BQ23 -> 0 | BR33: =IF(AND((BQ5+BQ18)=0,BQ33<=0), "",BQ33/(BQ5+BQ18)) | BT33: =IF(AND(BJ33=0,BQ33>0),100%,IF(AND(BJ33<0,BQ33=0),(BJ33-BQ33)/BJ33,IF(AND(BJ33>0,BQ33>0),(BQ33-BJ33)/BJ33,IF(AND(BJ33=0,BQ33=0),"",(BQ33-BJ33)/BJ33)))) | BU33: =+BU5+BU18-BU23 -> 98655.35 | BV33: =IF(AND((BU5+BU18)=0,BU33<=0), "",BU33/(BU5+BU18)) -> 0.60331453 | BX33: =+BX5+BX18-BX23 -> 0 | BY33: =IF(AND((BX5+BX18)=0,BX33<=0), "",BX33/(BX5+BX18)) | BZ33: =IF(AND(BX33=0,BU33>0),100%,IF(AND(BX33<0,BU33=0),(BX33-BU33)/BX33,IF(AND(BX33>0,BU33>0),(BU33-BX33)/BX33,IF(AND(BX33=0,BU33=0),"",(BU33-BX33)/BX33)))) -> 1 | CA33: =+CA5+CA18-CA23 -> 0 | CB33: =IF(AND((CA5+CA18)=0,CA33<=0), "",CA33/(CA5+CA18)) | CD33: =IF(AND(BQ33=0,CA33>0),100%,IF(AND(BQ33<0,CA33=0),(BQ33-CA33)/BQ33,IF(AND(BQ33>0,CA33>0),(CA33-BQ33)/BQ33,IF(AND(BQ33=0,CA33=0),"",(CA33-BQ33)/BQ33)))) | CE33: =+CE5+CE18-CE23 -> 98655.35 | CF33: =IF(AND((CE5+CE18)=0,CE33<=0), "",CE33/(CE5+CE18)) -> 0.60331453 | CH33: =+CH5+CH18-CH23 -> 0 | CI33: =IF(AND((CH5+CH18)=0,CH33<=0), "",CH33/(CH5+CH18)) | CK33: =IF(AND(CA33=0,CH33>0),100%,IF(AND(CA33<0,CH33=0),(CA33-CH33)/CA33,IF(AND(CA33>0,CH33>0),(CH33-CA33)/CA33,IF(AND(CA33=0,CH33=0),"",(CH33-CA33)/CA33)))) | CL33: =+CL5+CL18-CL23 -> 98655.35 | CM33: =IF(AND((CL5+CL18)=0,CL33<=0), "",CL33/(CL5+CL18)) -> 0.60331453 | CO33: =+CO5+CO18-CO23 -> 0 | CP33: =IF(AND((CO5+CO18)=0,CO33<=0), "",CO33/(CO5+CO18)) | CR33: =IF(AND(CH33=0,CO33>0),100%,IF(AND(CH33<0,CO33=0),(CH33-CO33)/CH33,IF(AND(CH33>0,CO33>0),(CO33-CH33)/CH33,IF(AND(CH33=0,CO33=0),"",(CO33-CH33)/CH33)))) | CS33: =+CS5+CS18-CS23 -> 98655.35 | CT33: =IF(AND((CS5+CS18)=0,CS33<=0), "",CS33/(CS5+CS18)) -> 0.60331453 | CV33: =+CV5+CV18-CV23 -> 0 | CW33: =IF(AND((CV5+CV18)=0,CV33<=0), "",CV33/(CV5+CV18)) | CX33: =IF(AND(CV33=0,CS33>0),100%,IF(AND(CV33<0,CS33=0),(CV33-CS33)/CV33,IF(AND(CV33>0,CS33>0),(CS33-CV33)/CV33,IF(AND(CV33=0,CS33=0),"",(CS33-CV33)/CV33)))) -> 1
A34: Utilidad Bruta por Servicios | B34: =+B10-B26 -> 0 | C34: =IF(AND(B10=0,B34<=0), "",B34/B10) | E34: =+E10-E26 -> 0 | F34: =IF(AND(E10=0,E34<=0), "",E34/E10) | H34: =+H10-H26 -> 0 | I34: =IF(AND(H10=0,H34<=0), "",H34/H10) | K34: =IF(AND(E34=0,H34>0),100%,IF(AND(E34<0,H34=0),(E34-H34)/E34,IF(AND(E34>0,H34>0),(H34-E34)/E34,IF(AND(E34=0,H34=0),"",(H34-E34)/E34)))) | L34: =+L10-L26 -> 0 | M34: =IF(AND(L10=0,L34<=0), "",L34/L10) | O34: =+O10-O26 -> 0 | P34: =IF(AND(O10=0,O34<=0), "",O34/O10) | R34: =IF(AND(H34=0,O34>0),100%,IF(AND(H34<0,O34=0),(H34-O34)/H34,IF(AND(H34>0,O34>0),(O34-H34)/H34,IF(AND(H34=0,O34=0),"",(O34-H34)/H34)))) | S34: =+S10-S26 -> 0 | T34: =IF(AND(S10=0,S34<=0), "",S34/S10) | V34: =+V10-V26 -> 0 | W34: =IF(AND(V10=0,V34<=0), "",V34/V10) | X34: =IF(AND(V34=0,S34>0),100%,IF(AND(V34<0,S34=0),(V34-S34)/V34,IF(AND(V34>0,S34>0),(S34-V34)/V34,IF(AND(V34=0,S34=0),"",(S34-V34)/V34)))) | Y34: =+Y10-Y26 -> 0 | Z34: =IF(AND(Y10=0,Y34<=0), "",Y34/Y10) | AB34: =IF(AND(O34=0,Y34>0),100%,IF(AND(O34<0,Y34=0),(O34-Y34)/O34,IF(AND(O34>0,Y34>0),(Y34-O34)/O34,IF(AND(O34=0,Y34=0),"",(Y34-O34)/O34)))) | AC34: =+AC10-AC26 -> 0 | AD34: =IF(AND(AC10=0,AC34<=0), "",AC34/AC10) | AF34: =+AF10-AF26 -> 0 | AG34: =IF(AND(AF10=0,AF34<=0), "",AF34/AF10) | AI34: =IF(AND(Y34=0,AF34>0),100%,IF(AND(Y34<0,AF34=0),(Y34-AF34)/Y34,IF(AND(Y34>0,AF34>0),(AF34-Y34)/Y34,IF(AND(Y34=0,AF34=0),"",(AF34-Y34)/Y34)))) | AJ34: =+AJ10-AJ26 -> 0 | AK34: =IF(AND(AJ10=0,AJ34<=0), "",AJ34/AJ10) | AM34: =+AM10-AM26 -> 0 | AN34: =IF(AND(AM10=0,AM34<=0), "",AM34/AM10) | AP34: =IF(AND(AF34=0,AM34>0),100%,IF(AND(AF34<0,AM34=0),(AF34-AM34)/AF34,IF(AND(AF34>0,AM34>0),(AM34-AF34)/AF34,IF(AND(AF34=0,AM34=0),"",(AM34-AF34)/AF34)))) | AQ34: =+AQ10-AQ26 -> 0 | AR34: =IF(AND(AQ10=0,AQ34<=0), "",AQ34/AQ10) | AT34: =+AT10-AT26 -> 0 | AU34: =IF(AND(AT10=0,AT34<=0), "",AT34/AT10) | AV34: =IF(AND(AT34=0,AQ34>0),100%,IF(AND(AT34<0,AQ34=0),(AT34-AQ34)/AT34,IF(AND(AT34>0,AQ34>0),(AQ34-AT34)/AT34,IF(AND(AT34=0,AQ34=0),"",(AQ34-AT34)/AT34)))) | AW34: =+AW10-AW26 -> 0 | AX34: =IF(AND(AW10=0,AW34<=0), "",AW34/AW10) | AZ34: =+AZ10-AZ26 -> 0 | BA34: =IF(AND(AZ10=0,AZ34<=0), "",AZ34/AZ10) | BB34: =IF(AND(AZ34=0,AW34>0),100%,IF(AND(AZ34<0,AW34=0),(AZ34-AW34)/AZ34,IF(AND(AZ34>0,AW34>0),(AW34-AZ34)/AZ34,IF(AND(AZ34=0,AW34=0),"",(AW34-AZ34)/AZ34)))) | BC34: =+BC10-BC26 -> 0 | BD34: =IF(AND(BC10=0,BC34<=0), "",BC34/BC10) | BF34: =IF(AND(AM34=0,BC34>0),100%,IF(AND(AM34<0,BC34=0),(AM34-BC34)/AM34,IF(AND(AM34>0,BC34>0),(BC34-AM34)/AM34,IF(AND(AM34=0,BC34=0),"",(BC34-AM34)/AM34)))) | BG34: =+BG10-BG26 -> 0 | BH34: =IF(AND(BG10=0,BG34<=0), "",BG34/BG10) | BJ34: =+BJ10-BJ26 -> 0 | BK34: =IF(AND(BJ10=0,BJ34<=0), "",BJ34/BJ10) | BM34: =IF(AND(BC34=0,BJ34>0),100%,IF(AND(BC34<0,BJ34=0),(BC34-BJ34)/BC34,IF(AND(BC34>0,BJ34>0),(BJ34-BC34)/BC34,IF(AND(BC34=0,BJ34=0),"",(BJ34-BC34)/BC34)))) | BN34: =+BN10-BN26 -> 0 | BO34: =IF(AND(BN10=0,BN34<=0), "",BN34/BN10) | BQ34: =+BQ10-BQ26 -> 0 | BR34: =IF(AND(BQ10=0,BQ34<=0), "",BQ34/BQ10) | BT34: =IF(AND(BJ34=0,BQ34>0),100%,IF(AND(BJ34<0,BQ34=0),(BJ34-BQ34)/BJ34,IF(AND(BJ34>0,BQ34>0),(BQ34-BJ34)/BJ34,IF(AND(BJ34=0,BQ34=0),"",(BQ34-BJ34)/BJ34)))) | BU34: =+BU10-BU26 -> 0 | BV34: =IF(AND(BU10=0,BU34<=0), "",BU34/BU10) | BX34: =+BX10-BX26 -> 0 | BY34: =IF(AND(BX10=0,BX34<=0), "",BX34/BX10) | BZ34: =IF(AND(BX34=0,BU34>0),100%,IF(AND(BX34<0,BU34=0),(BX34-BU34)/BX34,IF(AND(BX34>0,BU34>0),(BU34-BX34)/BX34,IF(AND(BX34=0,BU34=0),"",(BU34-BX34)/BX34)))) | CA34: =+CA10-CA26 -> 0 | CB34: =IF(AND(CA10=0,CA34<=0), "",CA34/CA10) | CD34: =IF(AND(BQ34=0,CA34>0),100%,IF(AND(BQ34<0,CA34=0),(BQ34-CA34)/BQ34,IF(AND(BQ34>0,CA34>0),(CA34-BQ34)/BQ34,IF(AND(BQ34=0,CA34=0),"",(CA34-BQ34)/BQ34)))) | CE34: =+CE10-CE26 -> 0 | CF34: =IF(AND(CE10=0,CE34<=0), "",CE34/CE10) | CH34: =+CH10-CH26 -> 0 | CI34: =IF(AND(CH10=0,CH34<=0), "",CH34/CH10) | CK34: =IF(AND(CA34=0,CH34>0),100%,IF(AND(CA34<0,CH34=0),(CA34-CH34)/CA34,IF(AND(CA34>0,CH34>0),(CH34-CA34)/CA34,IF(AND(CA34=0,CH34=0),"",(CH34-CA34)/CA34)))) | CL34: =+CL10-CL26 -> 0 | CM34: =IF(AND(CL10=0,CL34<=0), "",CL34/CL10) | CO34: =+CO10-CO26 -> 0 | CP34: =IF(AND(CO10=0,CO34<=0), "",CO34/CO10) | CR34: =IF(AND(CH34=0,CO34>0),100%,IF(AND(CH34<0,CO34=0),(CH34-CO34)/CH34,IF(AND(CH34>0,CO34>0),(CO34-CH34)/CH34,IF(AND(CH34=0,CO34=0),"",(CO34-CH34)/CH34)))) | CS34: =+CS10-CS26 -> 0 | CT34: =IF(AND(CS10=0,CS34<=0), "",CS34/CS10) | CV34: =+CV10-CV26 -> 0 | CW34: =IF(AND(CV10=0,CV34<=0), "",CV34/CV10) | CX34: =IF(AND(CV34=0,CS34>0),100%,IF(AND(CV34<0,CS34=0),(CV34-CS34)/CV34,IF(AND(CV34>0,CS34>0),(CS34-CV34)/CV34,IF(AND(CV34=0,CS34=0),"",(CS34-CV34)/CV34))))
A35: Utilidad Bruta por Eventos | B35: =+B15-B29 -> 0 | C35: =IF(AND(B15=0,B35<=0), "",B35/B15) | E35: =+E15-E29 -> 0 | F35: =IF(AND(E15=0,E35<=0), "",E35/E15) | H35: =+H15-H29 -> 0 | I35: =IF(AND(H15=0,H35<=0), "",H35/H15) | K35: =IF(AND(E35=0,H35>0),100%,IF(AND(E35<0,H35=0),(E35-H35)/E35,IF(AND(E35>0,H35>0),(H35-E35)/E35,IF(AND(E35=0,H35=0),"",(H35-E35)/E35)))) | L35: =+L15-L29 -> 0 | M35: =IF(AND(L15=0,L35<=0), "",L35/L15) | O35: =+O15-O29 -> 0 | P35: =IF(AND(O15=0,O35<=0), "",O35/O15) | R35: =IF(AND(H35=0,O35>0),100%,IF(AND(H35<0,O35=0),(H35-O35)/H35,IF(AND(H35>0,O35>0),(O35-H35)/H35,IF(AND(H35=0,O35=0),"",(O35-H35)/H35)))) | S35: =+S15-S29 -> 0 | T35: =IF(AND(S15=0,S35<=0), "",S35/S15) | V35: =+V15-V29 -> 0 | W35: =IF(AND(V15=0,V35<=0), "",V35/V15) | X35: =IF(AND(V35=0,S35>0),100%,IF(AND(V35<0,S35=0),(V35-S35)/V35,IF(AND(V35>0,S35>0),(S35-V35)/V35,IF(AND(V35=0,S35=0),"",(S35-V35)/V35)))) | Y35: =+Y15-Y29 -> 0 | Z35: =IF(AND(Y15=0,Y35<=0), "",Y35/Y15) | AB35: =IF(AND(O35=0,Y35>0),100%,IF(AND(O35<0,Y35=0),(O35-Y35)/O35,IF(AND(O35>0,Y35>0),(Y35-O35)/O35,IF(AND(O35=0,Y35=0),"",(Y35-O35)/O35)))) | AC35: =+AC15-AC29 -> 0 | AD35: =IF(AND(AC15=0,AC35<=0), "",AC35/AC15) | AF35: =+AF15-AF29 -> 0 | AG35: =IF(AND(AF15=0,AF35<=0), "",AF35/AF15) | AI35: =IF(AND(Y35=0,AF35>0),100%,IF(AND(Y35<0,AF35=0),(Y35-AF35)/Y35,IF(AND(Y35>0,AF35>0),(AF35-Y35)/Y35,IF(AND(Y35=0,AF35=0),"",(AF35-Y35)/Y35)))) | AJ35: =+AJ15-AJ29 -> 0 | AK35: =IF(AND(AJ15=0,AJ35<=0), "",AJ35/AJ15) | AM35: =+AM15-AM29 -> 0 | AN35: =IF(AND(AM15=0,AM35<=0), "",AM35/AM15) | AP35: =IF(AND(AF35=0,AM35>0),100%,IF(AND(AF35<0,AM35=0),(AF35-AM35)/AF35,IF(AND(AF35>0,AM35>0),(AM35-AF35)/AF35,IF(AND(AF35=0,AM35=0),"",(AM35-AF35)/AF35)))) | AQ35: =+AQ15-AQ29 -> 0 | AR35: =IF(AND(AQ15=0,AQ35<=0), "",AQ35/AQ15) | AT35: =+AT15-AT29 -> 0 | AU35: =IF(AND(AT15=0,AT35<=0), "",AT35/AT15) | AV35: =IF(AND(AT35=0,AQ35>0),100%,IF(AND(AT35<0,AQ35=0),(AT35-AQ35)/AT35,IF(AND(AT35>0,AQ35>0),(AQ35-AT35)/AT35,IF(AND(AT35=0,AQ35=0),"",(AQ35-AT35)/AT35)))) | AW35: =+AW15-AW29 -> 0 | AX35: =IF(AND(AW15=0,AW35<=0), "",AW35/AW15) | AZ35: =+AZ15-AZ29 -> 0 | BA35: =IF(AND(AZ15=0,AZ35<=0), "",AZ35/AZ15) | BB35: =IF(AND(AZ35=0,AW35>0),100%,IF(AND(AZ35<0,AW35=0),(AZ35-AW35)/AZ35,IF(AND(AZ35>0,AW35>0),(AW35-AZ35)/AZ35,IF(AND(AZ35=0,AW35=0),"",(AW35-AZ35)/AZ35)))) | BC35: =+BC15-BC29 -> 0 | BD35: =IF(AND(BC15=0,BC35<=0), "",BC35/BC15) | BF35: =IF(AND(AM35=0,BC35>0),100%,IF(AND(AM35<0,BC35=0),(AM35-BC35)/AM35,IF(AND(AM35>0,BC35>0),(BC35-AM35)/AM35,IF(AND(AM35=0,BC35=0),"",(BC35-AM35)/AM35)))) | BG35: =+BG15-BG29 -> 0 | BH35: =IF(AND(BG15=0,BG35<=0), "",BG35/BG15) | BJ35: =+BJ15-BJ29 -> 0 | BK35: =IF(AND(BJ15=0,BJ35<=0), "",BJ35/BJ15) | BM35: =IF(AND(BC35=0,BJ35>0),100%,IF(AND(BC35<0,BJ35=0),(BC35-BJ35)/BC35,IF(AND(BC35>0,BJ35>0),(BJ35-BC35)/BC35,IF(AND(BC35=0,BJ35=0),"",(BJ35-BC35)/BC35)))) | BN35: =+BN15-BN29 -> 0 | BO35: =IF(AND(BN15=0,BN35<=0), "",BN35/BN15) | BQ35: =+BQ15-BQ29 -> 0 | BR35: =IF(AND(BQ15=0,BQ35<=0), "",BQ35/BQ15) | BT35: =IF(AND(BJ35=0,BQ35>0),100%,IF(AND(BJ35<0,BQ35=0),(BJ35-BQ35)/BJ35,IF(AND(BJ35>0,BQ35>0),(BQ35-BJ35)/BJ35,IF(AND(BJ35=0,BQ35=0),"",(BQ35-BJ35)/BJ35)))) | BU35: =+BU15-BU29 -> 0 | BV35: =IF(AND(BU15=0,BU35<=0), "",BU35/BU15) | BX35: =+BX15-BX29 -> 0 | BY35: =IF(AND(BX15=0,BX35<=0), "",BX35/BX15) | BZ35: =IF(AND(BX35=0,BU35>0),100%,IF(AND(BX35<0,BU35=0),(BX35-BU35)/BX35,IF(AND(BX35>0,BU35>0),(BU35-BX35)/BX35,IF(AND(BX35=0,BU35=0),"",(BU35-BX35)/BX35)))) | CA35: =+CA15-CA29 -> 0 | CB35: =IF(AND(CA15=0,CA35<=0), "",CA35/CA15) | CD35: =IF(AND(BQ35=0,CA35>0),100%,IF(AND(BQ35<0,CA35=0),(BQ35-CA35)/BQ35,IF(AND(BQ35>0,CA35>0),(CA35-BQ35)/BQ35,IF(AND(BQ35=0,CA35=0),"",(CA35-BQ35)/BQ35)))) | CE35: =+CE15-CE29 -> 0 | CF35: =IF(AND(CE15=0,CE35<=0), "",CE35/CE15) | CH35: =+CH15-CH29 -> 0 | CI35: =IF(AND(CH15=0,CH35<=0), "",CH35/CH15) | CK35: =IF(AND(CA35=0,CH35>0),100%,IF(AND(CA35<0,CH35=0),(CA35-CH35)/CA35,IF(AND(CA35>0,CH35>0),(CH35-CA35)/CA35,IF(AND(CA35=0,CH35=0),"",(CH35-CA35)/CA35)))) | CL35: =+CL15-CL29 -> 0 | CM35: =IF(AND(CL15=0,CL35<=0), "",CL35/CL15) | CO35: =+CO15-CO29 -> 0 | CP35: =IF(AND(CO15=0,CO35<=0), "",CO35/CO15) | CR35: =IF(AND(CH35=0,CO35>0),100%,IF(AND(CH35<0,CO35=0),(CH35-CO35)/CH35,IF(AND(CH35>0,CO35>0),(CO35-CH35)/CH35,IF(AND(CH35=0,CO35=0),"",(CO35-CH35)/CH35)))) | CS35: =+CS15-CS29 -> 0 | CT35: =IF(AND(CS15=0,CS35<=0), "",CS35/CS15) | CV35: =+CV15-CV29 -> 0 | CW35: =IF(AND(CV15=0,CV35<=0), "",CV35/CV15) | CX35: =IF(AND(CV35=0,CS35>0),100%,IF(AND(CV35<0,CS35=0),(CV35-CS35)/CV35,IF(AND(CV35>0,CS35>0),(CS35-CV35)/CV35,IF(AND(CV35=0,CS35=0),"",(CS35-CV35)/CV35))))
A36: Utilidad Bruta | B36: =+B4-B22 -> 0 | C36: =IF(AND(B4=0,B36<=0), "",B36/B4) | E36: =+E4-E22 -> 27262.18 | F36: =IF(AND(E4=0,E36<=0), "",E36/E4) -> 0.56875562 | H36: =+H4-H22 -> 27170.01 | I36: =IF(AND(H4=0,H36<=0), "",H36/H4) -> 0.52774681 | K36: =IF(AND(E36=0,H36>0),100%,IF(AND(E36<0,H36=0),(E36-H36)/E36,IF(AND(E36>0,H36>0),(H36-E36)/E36,IF(AND(E36=0,H36=0),"",(H36-E36)/E36)))) -> -0.0033808742 | L36: =+L4-L22 -> 54432.19 | M36: =IF(AND(L4=0,L36<=0), "",L36/L4) -> 0.54751903 | O36: =+O4-O22 -> 44223.16 | P36: =IF(AND(O4=0,O36<=0), "",O36/O4) -> 0.68984238 | R36: =IF(AND(H36=0,O36>0),100%,IF(AND(H36<0,O36=0),(H36-O36)/H36,IF(AND(H36>0,O36>0),(O36-H36)/H36,IF(AND(H36=0,O36=0),"",(O36-H36)/H36)))) -> 0.62764607 | S36: =+S4-S22 -> 98655.35 | T36: =IF(AND(S4=0,S36<=0), "",S36/S4) -> 0.60331453 | V36: =+V4-V22 -> 0 | W36: =IF(AND(V4=0,V36<=0), "",V36/V4) | X36: =IF(AND(V36=0,S36>0),100%,IF(AND(V36<0,S36=0),(V36-S36)/V36,IF(AND(V36>0,S36>0),(S36-V36)/V36,IF(AND(V36=0,S36=0),"",(S36-V36)/V36)))) -> 1 | Y36: =+Y4-Y22 -> 0 | Z36: =IF(AND(Y4=0,Y36<=0), "",Y36/Y4) | AB36: =IF(AND(O36=0,Y36>0),100%,IF(AND(O36<0,Y36=0),(O36-Y36)/O36,IF(AND(O36>0,Y36>0),(Y36-O36)/O36,IF(AND(O36=0,Y36=0),"",(Y36-O36)/O36)))) -> -1 | AC36: =+AC4-AC22 -> 98655.35 | AD36: =IF(AND(AC4=0,AC36<=0), "",AC36/AC4) -> 0.60331453 | AF36: =+AF4-AF22 -> 0 | AG36: =IF(AND(AF4=0,AF36<=0), "",AF36/AF4) | AI36: =IF(AND(Y36=0,AF36>0),100%,IF(AND(Y36<0,AF36=0),(Y36-AF36)/Y36,IF(AND(Y36>0,AF36>0),(AF36-Y36)/Y36,IF(AND(Y36=0,AF36=0),"",(AF36-Y36)/Y36)))) | AJ36: =+AJ4-AJ22 -> 98655.35 | AK36: =IF(AND(AJ4=0,AJ36<=0), "",AJ36/AJ4) -> 0.60331453 | AM36: =+AM4-AM22 -> 0 | AN36: =IF(AND(AM4=0,AM36<=0), "",AM36/AM4) | AP36: =IF(AND(AF36=0,AM36>0),100%,IF(AND(AF36<0,AM36=0),(AF36-AM36)/AF36,IF(AND(AF36>0,AM36>0),(AM36-AF36)/AF36,IF(AND(AF36=0,AM36=0),"",(AM36-AF36)/AF36)))) | AQ36: =+AQ4-AQ22 -> 98655.35 | AR36: =IF(AND(AQ4=0,AQ36<=0), "",AQ36/AQ4) -> 0.60331453 | AT36: =+AT4-AT22 -> 0 | AU36: =IF(AND(AT4=0,AT36<=0), "",AT36/AT4) | AV36: =IF(AND(AT36=0,AQ36>0),100%,IF(AND(AT36<0,AQ36=0),(AT36-AQ36)/AT36,IF(AND(AT36>0,AQ36>0),(AQ36-AT36)/AT36,IF(AND(AT36=0,AQ36=0),"",(AQ36-AT36)/AT36)))) -> 1 | AW36: =+AW4-AW22 -> 16442.558 | AX36: =IF(AND(AW4=0,AW36<=0), "",AW36/AW4) -> 0.60331453 | AZ36: =+AZ4-AZ22 -> 0 | BA36: =IF(AND(AZ4=0,AZ36<=0), "",AZ36/AZ4) | BB36: =IF(AND(AZ36=0,AW36>0),100%,IF(AND(AZ36<0,AW36=0),(AZ36-AW36)/AZ36,IF(AND(AZ36>0,AW36>0),(AW36-AZ36)/AZ36,IF(AND(AZ36=0,AW36=0),"",(AW36-AZ36)/AZ36)))) -> 1 | BC36: =+BC4-BC22 -> 0 | BD36: =IF(AND(BC4=0,BC36<=0), "",BC36/BC4) | BF36: =IF(AND(AM36=0,BC36>0),100%,IF(AND(AM36<0,BC36=0),(AM36-BC36)/AM36,IF(AND(AM36>0,BC36>0),(BC36-AM36)/AM36,IF(AND(AM36=0,BC36=0),"",(BC36-AM36)/AM36)))) | BG36: =+BG4-BG22 -> 98655.35 | BH36: =IF(AND(BG4=0,BG36<=0), "",BG36/BG4) -> 0.60331453 | BJ36: =+BJ4-BJ22 -> 0 | BK36: =IF(AND(BJ4=0,BJ36<=0), "",BJ36/BJ4) | BM36: =IF(AND(BC36=0,BJ36>0),100%,IF(AND(BC36<0,BJ36=0),(BC36-BJ36)/BC36,IF(AND(BC36>0,BJ36>0),(BJ36-BC36)/BC36,IF(AND(BC36=0,BJ36=0),"",(BJ36-BC36)/BC36)))) | BN36: =+BN4-BN22 -> 98655.35 | BO36: =IF(AND(BN4=0,BN36<=0), "",BN36/BN4) -> 0.60331453 | BQ36: =+BQ4-BQ22 -> 0 | BR36: =IF(AND(BQ4=0,BQ36<=0), "",BQ36/BQ4) | BT36: =IF(AND(BJ36=0,BQ36>0),100%,IF(AND(BJ36<0,BQ36=0),(BJ36-BQ36)/BJ36,IF(AND(BJ36>0,BQ36>0),(BQ36-BJ36)/BJ36,IF(AND(BJ36=0,BQ36=0),"",(BQ36-BJ36)/BJ36)))) | BU36: =+BU4-BU22 -> 98655.35 | BV36: =IF(AND(BU4=0,BU36<=0), "",BU36/BU4) -> 0.60331453 | BX36: =+BX4-BX22 -> 0 | BY36: =IF(AND(BX4=0,BX36<=0), "",BX36/BX4) | BZ36: =IF(AND(BX36=0,BU36>0),100%,IF(AND(BX36<0,BU36=0),(BX36-BU36)/BX36,IF(AND(BX36>0,BU36>0),(BU36-BX36)/BX36,IF(AND(BX36=0,BU36=0),"",(BU36-BX36)/BX36)))) -> 1 | CA36: =+CA4-CA22 -> 0 | CB36: =IF(AND(CA4=0,CA36<=0), "",CA36/CA4) | CD36: =IF(AND(BQ36=0,CA36>0),100%,IF(AND(BQ36<0,CA36=0),(BQ36-CA36)/BQ36,IF(AND(BQ36>0,CA36>0),(CA36-BQ36)/BQ36,IF(AND(BQ36=0,CA36=0),"",(CA36-BQ36)/BQ36)))) | CE36: =+CE4-CE22 -> 98655.35 | CF36: =IF(AND(CE4=0,CE36<=0), "",CE36/CE4) -> 0.60331453 | CH36: =+CH4-CH22 -> 0 | CI36: =IF(AND(CH4=0,CH36<=0), "",CH36/CH4) | CK36: =IF(AND(CA36=0,CH36>0),100%,IF(AND(CA36<0,CH36=0),(CA36-CH36)/CA36,IF(AND(CA36>0,CH36>0),(CH36-CA36)/CA36,IF(AND(CA36=0,CH36=0),"",(CH36-CA36)/CA36)))) | CL36: =+CL4-CL22 -> 98655.35 | CM36: =IF(AND(CL4=0,CL36<=0), "",CL36/CL4) -> 0.60331453 | CO36: =+CO4-CO22 -> 0 | CP36: =IF(AND(CO4=0,CO36<=0), "",CO36/CO4) | CR36: =IF(AND(CH36=0,CO36>0),100%,IF(AND(CH36<0,CO36=0),(CH36-CO36)/CH36,IF(AND(CH36>0,CO36>0),(CO36-CH36)/CH36,IF(AND(CH36=0,CO36=0),"",(CO36-CH36)/CH36)))) | CS36: =+CS4-CS22 -> 98655.35 | CT36: =IF(AND(CS4=0,CS36<=0), "",CS36/CS4) -> 0.60331453 | CV36: =+CV4-CV22 -> 0 | CW36: =IF(AND(CV4=0,CV36<=0), "",CV36/CV4) | CX36: =IF(AND(CV36=0,CS36>0),100%,IF(AND(CV36<0,CS36=0),(CV36-CS36)/CV36,IF(AND(CV36>0,CS36>0),(CS36-CV36)/CV36,IF(AND(CV36=0,CS36=0),"",(CS36-CV36)/CV36)))) -> 1
AI37: =IF(AND(Y37=0,AF37>0),100%,IF(AND(Y37<0,AF37=0),(Y37-AF37)/Y37,IF(AND(Y37>0,AF37>0),(AF37-Y37)/Y37,IF(AND(Y37=0,AF37=0),"",(AF37-Y37)/Y37)))) | AP37: =IF(AND(AF37=0,AM37>0),100%,IF(AND(AF37<0,AM37=0),(AF37-AM37)/AF37,IF(AND(AF37>0,AM37>0),(AM37-AF37)/AF37,IF(AND(AF37=0,AM37=0),"",(AM37-AF37)/AF37)))) | BM37: =IF(AND(BC37=0,BJ37>0),100%,IF(AND(BC37<0,BJ37=0),(BC37-BJ37)/BC37,IF(AND(BC37>0,BJ37>0),(BJ37-BC37)/BC37,IF(AND(BC37=0,BJ37=0),"",(BJ37-BC37)/BC37)))) | BT37: =IF(AND(BJ37=0,BQ37>0),100%,IF(AND(BJ37<0,BQ37=0),(BJ37-BQ37)/BJ37,IF(AND(BJ37>0,BQ37>0),(BQ37-BJ37)/BJ37,IF(AND(BJ37=0,BQ37=0),"",(BQ37-BJ37)/BJ37)))) | BZ37: =IF(AND(BX37=0,BU37>0),100%,IF(AND(BX37<0,BU37=0),(BX37-BU37)/BX37,IF(AND(BX37>0,BU37>0),(BU37-BX37)/BX37,IF(AND(BX37=0,BU37=0),"",(BU37-BX37)/BX37)))) | CK37: =IF(AND(CA37=0,CH37>0),100%,IF(AND(CA37<0,CH37=0),(CA37-CH37)/CA37,IF(AND(CA37>0,CH37>0),(CH37-CA37)/CA37,IF(AND(CA37=0,CH37=0),"",(CH37-CA37)/CA37)))) | CR37: =IF(AND(CH37=0,CO37>0),100%,IF(AND(CH37<0,CO37=0),(CH37-CO37)/CH37,IF(AND(CH37>0,CO37>0),(CO37-CH37)/CH37,IF(AND(CH37=0,CO37=0),"",(CO37-CH37)/CH37)))) | CX37: =IF(AND(CV37=0,CS37>0),100%,IF(AND(CV37<0,CS37=0),(CV37-CS37)/CV37,IF(AND(CV37>0,CS37>0),(CS37-CV37)/CV37,IF(AND(CV37=0,CS37=0),"",(CS37-CV37)/CV37))))
A38: Total Gastos Operacionales | B38: =+B39+B68+B83+B93+B104 -> 0 | C38: =IF(AND(B4=0,B38>=0), "",B38/B4) | D38: =IF(AND(B124=0,B38>=0),"",B38/B124) | E38: =+E39+E68+E83+E93+E104 -> 12855.64 | F38: =IF(AND(E4=0,E38>=0), "",E38/E4) -> 0.26820003 | G38: =IF(AND(E124=0,E38>=0),"",E38/E124) -> 0.41516935 | H38: =+H39+H68+H83+H93+H104 -> 9848.88 | I38: =IF(AND(H4=0,H38>=0), "",H38/H4) -> 0.19130339 | J38: =IF(AND(H124=0,H38>=0),"",H38/H124) -> 0.50938908 | K38: =IF(AND(E38=0,H38>0),100%,IF(AND(E38<0,H38=0),(E38-H38)/E38,IF(AND(E38>0,H38>0),(H38-E38)/E38,IF(AND(E38=0,H38=0),"",(H38-E38)/E38)))) -> -0.23388645 | L38: =+L39+L68+L83+L93+L104 -> 22704.52 | M38: =IF(AND(L4=0,L38>=0), "",L38/L4) -> 0.22837877 | N38: =IF(AND(L124=0,L38>=0),"",L38/L124) -> 0.45138659 | O38: =+O39+O68+O83+O93+O104 -> 13947.96 | P38: =IF(AND(O4=0,O38>=0), "",O38/O4) -> 0.2175759 | Q38: =IF(AND(O124=0,O38>=0),"",O38/O124) -> 0.53776594 | R38: =IF(AND(H38=0,O38>0),100%,IF(AND(H38<0,O38=0),(H38-O38)/H38,IF(AND(H38>0,O38>0),(O38-H38)/H38,IF(AND(H38=0,O38=0),"",(O38-H38)/H38)))) -> 0.41619758 | S38: =+S39+S68+S83+S93+S104 -> 36652.48 | T38: =IF(AND(S4=0,S38>=0), "",S38/S4) -> 0.22414369 | U38: =IF(AND(S124=0,S38>=0),"",S38/S124) -> 0.48077427 | V38: =+V39+V68+V83+V93+V104 -> 0 | W38: =IF(AND(V4=0,V38>=0), "",V38/V4) | X38: =IF(AND(V38=0,S38>0),100%,IF(AND(V38<0,S38=0),(V38-S38)/V38,IF(AND(V38>0,S38>0),(S38-V38)/V38,IF(AND(V38=0,S38=0),"",(S38-V38)/V38)))) -> 1 | Y38: =+Y39+Y68+Y83+Y93+Y104 -> 0 | Z38: =IF(AND(Y4=0,Y38>=0), "",Y38/Y4) | AA38: =IF(AND(Y124=0,Y38>=0),"",Y38/Y124) | AB38: =IF(AND(O38=0,Y38>0),100%,IF(AND(O38<0,Y38=0),(O38-Y38)/O38,IF(AND(O38>0,Y38>0),(Y38-O38)/O38,IF(AND(O38=0,Y38=0),"",(Y38-O38)/O38)))) -> -1 | AC38: =+AC39+AC68+AC83+AC93+AC104 -> 36652.48 | AD38: =IF(AND(AC4=0,AC38>=0), "",AC38/AC4) -> 0.22414369 | AE38: =IF(AND(AC124=0,AC38>=0),"",AC38/AC124) -> 0.48077427 | AF38: =+AF39+AF68+AF83+AF93+AF104 -> 0 | AG38: =IF(AND(AF4=0,AF38>=0), "",AF38/AF4) | AH38: =IF(AND(AF124=0,AF38>=0),"",AF38/AF124) | AI38: =IF(AND(Y38=0,AF38>0),100%,IF(AND(Y38<0,AF38=0),(Y38-AF38)/Y38,IF(AND(Y38>0,AF38>0),(AF38-Y38)/Y38,IF(AND(Y38=0,AF38=0),"",(AF38-Y38)/Y38)))) | AJ38: =+AJ39+AJ68+AJ83+AJ93+AJ104 -> 36652.48 | AK38: =IF(AND(AJ4=0,AJ38>=0), "",AJ38/AJ4) -> 0.22414369 | AL38: =IF(AND(AJ124=0,AJ38>=0),"",AJ38/AJ124) -> 0.48077427 | AM38: =+AM39+AM68+AM83+AM93+AM104 -> 0 | AN38: =IF(AND(AM4=0,AM38>=0), "",AM38/AM4) | AO38: =IF(AND(AM124=0,AM38>=0),"",AM38/AM124) | AP38: =IF(AND(AF38=0,AM38>0),100%,IF(AND(AF38<0,AM38=0),(AF38-AM38)/AF38,IF(AND(AF38>0,AM38>0),(AM38-AF38)/AF38,IF(AND(AF38=0,AM38=0),"",(AM38-AF38)/AF38)))) | AQ38: =+AQ39+AQ68+AQ83+AQ93+AQ104 -> 36652.48 | AR38: =IF(AND(AQ4=0,AQ38>=0), "",AQ38/AQ4) -> 0.22414369 | AS38: =IF(AND(AQ124=0,AQ38>=0),"",AQ38/AQ124) -> 0.48077427 | AT38: =+AT39+AT68+AT83+AT93+AT104 -> 0 | AU38: =IF(AND(AT4=0,AT38>=0), "",AT38/AT4) | AV38: =IF(AND(AT38=0,AQ38>0),100%,IF(AND(AT38<0,AQ38=0),(AT38-AQ38)/AT38,IF(AND(AT38>0,AQ38>0),(AQ38-AT38)/AT38,IF(AND(AT38=0,AQ38=0),"",(AQ38-AT38)/AT38)))) -> 1 | AW38: =+AW39+AW68+AW83+AW93+AW104 -> 6108.7467 | AX38: =IF(AND(AW4=0,AW38>=0), "",AW38/AW4) -> 0.22414369 | AY38: =IF(AND(AW124=0,AW38>=0),"",AW38/AW124) -> 0.48077427 | AZ38: =+AZ39+AZ68+AZ83+AZ93+AZ104 -> 0 | BA38: =IF(AND(AZ4=0,AZ38>=0), "",AZ38/AZ4) | BB38: =IF(AND(AZ38=0,AW38>0),100%,IF(AND(AZ38<0,AW38=0),(AZ38-AW38)/AZ38,IF(AND(AZ38>0,AW38>0),(AW38-AZ38)/AZ38,IF(AND(AZ38=0,AW38=0),"",(AW38-AZ38)/AZ38)))) -> 1 | BC38: =+BC39+BC68+BC83+BC93+BC104 -> 0 | BD38: =IF(AND(BC4=0,BC38>=0), "",BC38/BC4) | BE38: =IF(AND(BC124=0,BC38>=0),"",BC38/BC124) | BF38: =IF(AND(AM38=0,BC38>0),100%,IF(AND(AM38<0,BC38=0),(AM38-BC38)/AM38,IF(AND(AM38>0,BC38>0),(BC38-AM38)/AM38,IF(AND(AM38=0,BC38=0),"",(BC38-AM38)/AM38)))) | BG38: =+BG39+BG68+BG83+BG93+BG104 -> 36652.48 | BH38: =IF(AND(BG4=0,BG38>=0), "",BG38/BG4) -> 0.22414369 | BI38: =IF(AND(BG124=0,BG38>=0),"",BG38/BG124) -> 0.48077427 | BJ38: =+BJ39+BJ68+BJ83+BJ93+BJ104 -> 0 | BK38: =IF(AND(BJ4=0,BJ38>=0), "",BJ38/BJ4) | BL38: =IF(AND(BJ124=0,BJ38>=0),"",BJ38/BJ124) | BM38: =IF(AND(BC38=0,BJ38>0),100%,IF(AND(BC38<0,BJ38=0),(BC38-BJ38)/BC38,IF(AND(BC38>0,BJ38>0),(BJ38-BC38)/BC38,IF(AND(BC38=0,BJ38=0),"",(BJ38-BC38)/BC38)))) | BN38: =+BN39+BN68+BN83+BN93+BN104 -> 36652.48 | BO38: =IF(AND(BN4=0,BN38>=0), "",BN38/BN4) -> 0.22414369 | BP38: =IF(AND(BN124=0,BN38>=0),"",BN38/BN124) -> 0.48077427 | BQ38: =+BQ39+BQ68+BQ83+BQ93+BQ104 -> 0 | BR38: =IF(AND(BQ4=0,BQ38>=0), "",BQ38/BQ4) | BS38: =IF(AND(BQ124=0,BQ38>=0),"",BQ38/BQ124) | BT38: =IF(AND(BJ38=0,BQ38>0),100%,IF(AND(BJ38<0,BQ38=0),(BJ38-BQ38)/BJ38,IF(AND(BJ38>0,BQ38>0),(BQ38-BJ38)/BJ38,IF(AND(BJ38=0,BQ38=0),"",(BQ38-BJ38)/BJ38)))) | BU38: =+BU39+BU68+BU83+BU93+BU104 -> 36652.48 | BV38: =IF(AND(BU4=0,BU38>=0), "",BU38/BU4) -> 0.22414369 | BW38: =IF(AND(BU124=0,BU38>=0),"",BU38/BU124) -> 0.48077427 | BX38: =+BX39+BX68+BX83+BX93+BX104 -> 0 | BY38: =IF(AND(BX4=0,BX38>=0), "",BX38/BX4) | BZ38: =IF(AND(BX38=0,BU38>0),100%,IF(AND(BX38<0,BU38=0),(BX38-BU38)/BX38,IF(AND(BX38>0,BU38>0),(BU38-BX38)/BX38,IF(AND(BX38=0,BU38=0),"",(BU38-BX38)/BX38)))) -> 1 | CA38: =+CA39+CA68+CA83+CA93+CA104 -> 0 | CB38: =IF(AND(CA4=0,CA38>=0), "",CA38/CA4) | CC38: =IF(AND(CA124=0,CA38>=0),"",CA38/CA124) | CD38: =IF(AND(BQ38=0,CA38>0),100%,IF(AND(BQ38<0,CA38=0),(BQ38-CA38)/BQ38,IF(AND(BQ38>0,CA38>0),(CA38-BQ38)/BQ38,IF(AND(BQ38=0,CA38=0),"",(CA38-BQ38)/BQ38)))) | CE38: =+CE39+CE68+CE83+CE93+CE104 -> 36652.48 | CF38: =IF(AND(CE4=0,CE38>=0), "",CE38/CE4) -> 0.22414369 | CG38: =IF(AND(CE124=0,CE38>=0),"",CE38/CE124) -> 0.48077427 | CH38: =+CH39+CH68+CH83+CH93+CH104 -> 0 | CI38: =IF(AND(CH4=0,CH38>=0), "",CH38/CH4) | CJ38: =IF(AND(CH124=0,CH38>=0),"",CH38/CH124) | CK38: =IF(AND(CA38=0,CH38>0),100%,IF(AND(CA38<0,CH38=0),(CA38-CH38)/CA38,IF(AND(CA38>0,CH38>0),(CH38-CA38)/CA38,IF(AND(CA38=0,CH38=0),"",(CH38-CA38)/CA38)))) | CL38: =+CL39+CL68+CL83+CL93+CL104 -> 36652.48 | CM38: =IF(AND(CL4=0,CL38>=0), "",CL38/CL4) -> 0.22414369 | CN38: =IF(AND(CL124=0,CL38>=0),"",CL38/CL124) -> 0.48077427 | CO38: =+CO39+CO68+CO83+CO93+CO104 -> 0 | CP38: =IF(AND(CO4=0,CO38>=0), "",CO38/CO4) | CQ38: =IF(AND(CO124=0,CO38>=0),"",CO38/CO124) | CR38: =IF(AND(CH38=0,CO38>0),100%,IF(AND(CH38<0,CO38=0),(CH38-CO38)/CH38,IF(AND(CH38>0,CO38>0),(CO38-CH38)/CH38,IF(AND(CH38=0,CO38=0),"",(CO38-CH38)/CH38)))) | CS38: =+CS39+CS68+CS83+CS93+CS104 -> 36652.48 | CT38: =IF(AND(CS4=0,CS38>=0), "",CS38/CS4) -> 0.22414369 | CU38: =IF(AND(CS124=0,CS38>=0),"",CS38/CS124) -> 0.48077427 | CV38: =+CV39+CV68+CV83+CV93+CV104 -> 0 | CW38: =IF(AND(CV4=0,CV38>=0), "",CV38/CV4) | CX38: =IF(AND(CV38=0,CS38>0),100%,IF(AND(CV38<0,CS38=0),(CV38-CS38)/CV38,IF(AND(CV38>0,CS38>0),(CS38-CV38)/CV38,IF(AND(CV38=0,CS38=0),"",(CS38-CV38)/CV38)))) -> 1
A39: Subtotal Gastos de Administración | B39: =SUM(B40:B67) -> 0 | C39: =IF(AND(B4=0,B39>=0), "",B39/B4) | D39: =IF(AND(B124=0,B39>=0),"",B39/B124) | E39: =SUM(E40:E67) -> 7181.2 | F39: =IF(AND(E4=0,E39>=0), "",E39/E4) -> 0.14981736 | G39: =IF(AND(E124=0,E39>=0),"",E39/E124) -> 0.23191487 | H39: =SUM(H40:H67) -> 6517.11 | I39: =IF(AND(H4=0,H39>=0), "",H39/H4) -> 0.12658751 | J39: =IF(AND(H124=0,H39>=0),"",H39/H124) -> 0.33706824 | K39: =IF(AND(E39=0,H39>0),100%,IF(AND(E39<0,H39=0),(E39-H39)/E39,IF(AND(E39>0,H39>0),(H39-E39)/E39,IF(AND(E39=0,H39=0),"",(H39-E39)/E39)))) -> -0.092476188 | L39: =SUM(L40:L67) -> 13698.31 | M39: =IF(AND(L4=0,L39>=0), "",L39/L4) -> 0.13778768 | N39: =IF(AND(L124=0,L39>=0),"",L39/L124) -> 0.27233491 | O39: =SUM(O40:O67) -> 6988.84 | P39: =IF(AND(O4=0,O39>=0), "",O39/O4) -> 0.10901975 | Q39: =IF(AND(O124=0,O39>=0),"",O39/O124) -> 0.2694559 | R39: =IF(AND(H39=0,O39>0),100%,IF(AND(H39<0,O39=0),(H39-O39)/H39,IF(AND(H39>0,O39>0),(O39-H39)/H39,IF(AND(H39=0,O39=0),"",(O39-H39)/H39)))) -> 0.072383311 | S39: =SUM(S40:S67) -> 20687.15 | T39: =IF(AND(S4=0,S39>=0), "",S39/S4) -> 0.1265097 | U39: =IF(AND(S124=0,S39>=0),"",S39/S124) -> 0.27135543 | V39: =SUM(V40:V67) -> 0 | W39: =IF(AND(V4=0,V39>=0), "",V39/V4) | X39: =IF(AND(V39=0,S39>0),100%,IF(AND(V39<0,S39=0),(V39-S39)/V39,IF(AND(V39>0,S39>0),(S39-V39)/V39,IF(AND(V39=0,S39=0),"",(S39-V39)/V39)))) -> 1 | Y39: =SUM(Y40:Y67) -> 0 | Z39: =IF(AND(Y4=0,Y39>=0), "",Y39/Y4) | AA39: =IF(AND(Y124=0,Y39>=0),"",Y39/Y124) | AB39: =IF(AND(O39=0,Y39>0),100%,IF(AND(O39<0,Y39=0),(O39-Y39)/O39,IF(AND(O39>0,Y39>0),(Y39-O39)/O39,IF(AND(O39=0,Y39=0),"",(Y39-O39)/O39)))) -> -1 | AC39: =SUM(AC40:AC67) -> 20687.15 | AD39: =IF(AND(AC4=0,AC39>=0), "",AC39/AC4) -> 0.1265097 | AE39: =IF(AND(AC124=0,AC39>=0),"",AC39/AC124) -> 0.27135543 | AF39: =SUM(AF40:AF67) -> 0 | AG39: =IF(AND(AF4=0,AF39>=0), "",AF39/AF4) | AH39: =IF(AND(AF124=0,AF39>=0),"",AF39/AF124) | AI39: =IF(AND(Y39=0,AF39>0),100%,IF(AND(Y39<0,AF39=0),(Y39-AF39)/Y39,IF(AND(Y39>0,AF39>0),(AF39-Y39)/Y39,IF(AND(Y39=0,AF39=0),"",(AF39-Y39)/Y39)))) | AJ39: =SUM(AJ40:AJ67) -> 20687.15 | AK39: =IF(AND(AJ4=0,AJ39>=0), "",AJ39/AJ4) -> 0.1265097 | AL39: =IF(AND(AJ124=0,AJ39>=0),"",AJ39/AJ124) -> 0.27135543 | AM39: =SUM(AM40:AM67) -> 0 | AN39: =IF(AND(AM4=0,AM39>=0), "",AM39/AM4) | AO39: =IF(AND(AM124=0,AM39>=0),"",AM39/AM124) | AP39: =IF(AND(AF39=0,AM39>0),100%,IF(AND(AF39<0,AM39=0),(AF39-AM39)/AF39,IF(AND(AF39>0,AM39>0),(AM39-AF39)/AF39,IF(AND(AF39=0,AM39=0),"",(AM39-AF39)/AF39)))) | AQ39: =SUM(AQ40:AQ67) -> 20687.15 | AR39: =IF(AND(AQ4=0,AQ39>=0), "",AQ39/AQ4) -> 0.1265097 | AS39: =IF(AND(AQ124=0,AQ39>=0),"",AQ39/AQ124) -> 0.27135543 | AT39: =SUM(AT40:AT67) -> 0 | AU39: =IF(AND(AT4=0,AT39>=0), "",AT39/AT4) | AV39: =IF(AND(AT39=0,AQ39>0),100%,IF(AND(AT39<0,AQ39=0),(AT39-AQ39)/AT39,IF(AND(AT39>0,AQ39>0),(AQ39-AT39)/AT39,IF(AND(AT39=0,AQ39=0),"",(AQ39-AT39)/AT39)))) -> 1 | AW39: =SUM(AW40:AW67) -> 3447.8583 | AX39: =IF(AND(AW4=0,AW39>=0), "",AW39/AW4) -> 0.1265097 | AY39: =IF(AND(AW124=0,AW39>=0),"",AW39/AW124) -> 0.27135543 | AZ39: =SUM(AZ40:AZ67) -> 0 | BA39: =IF(AND(AZ4=0,AZ39>=0), "",AZ39/AZ4) | BB39: =IF(AND(AZ39=0,AW39>0),100%,IF(AND(AZ39<0,AW39=0),(AZ39-AW39)/AZ39,IF(AND(AZ39>0,AW39>0),(AW39-AZ39)/AZ39,IF(AND(AZ39=0,AW39=0),"",(AW39-AZ39)/AZ39)))) -> 1 | BC39: =SUM(BC40:BC67) -> 0 | BD39: =IF(AND(BC4=0,BC39>=0), "",BC39/BC4) | BE39: =IF(AND(BC124=0,BC39>=0),"",BC39/BC124) | BF39: =IF(AND(AM39=0,BC39>0),100%,IF(AND(AM39<0,BC39=0),(AM39-BC39)/AM39,IF(AND(AM39>0,BC39>0),(BC39-AM39)/AM39,IF(AND(AM39=0,BC39=0),"",(BC39-AM39)/AM39)))) | BG39: =SUM(BG40:BG67) -> 20687.15 | BH39: =IF(AND(BG4=0,BG39>=0), "",BG39/BG4) -> 0.1265097 | BI39: =IF(AND(BG124=0,BG39>=0),"",BG39/BG124) -> 0.27135543 | BJ39: =SUM(BJ40:BJ67) -> 0 | BK39: =IF(AND(BJ4=0,BJ39>=0), "",BJ39/BJ4) | BL39: =IF(AND(BJ124=0,BJ39>=0),"",BJ39/BJ124) | BM39: =IF(AND(BC39=0,BJ39>0),100%,IF(AND(BC39<0,BJ39=0),(BC39-BJ39)/BC39,IF(AND(BC39>0,BJ39>0),(BJ39-BC39)/BC39,IF(AND(BC39=0,BJ39=0),"",(BJ39-BC39)/BC39)))) | BN39: =SUM(BN40:BN67) -> 20687.15 | BO39: =IF(AND(BN4=0,BN39>=0), "",BN39/BN4) -> 0.1265097 | BP39: =IF(AND(BN124=0,BN39>=0),"",BN39/BN124) -> 0.27135543 | BQ39: =SUM(BQ40:BQ67) -> 0 | BR39: =IF(AND(BQ4=0,BQ39>=0), "",BQ39/BQ4) | BS39: =IF(AND(BQ124=0,BQ39>=0),"",BQ39/BQ124) | BT39: =IF(AND(BJ39=0,BQ39>0),100%,IF(AND(BJ39<0,BQ39=0),(BJ39-BQ39)/BJ39,IF(AND(BJ39>0,BQ39>0),(BQ39-BJ39)/BJ39,IF(AND(BJ39=0,BQ39=0),"",(BQ39-BJ39)/BJ39)))) | BU39: =SUM(BU40:BU67) -> 20687.15 | BV39: =IF(AND(BU4=0,BU39>=0), "",BU39/BU4) -> 0.1265097 | BW39: =IF(AND(BU124=0,BU39>=0),"",BU39/BU124) -> 0.27135543 | BX39: =SUM(BX40:BX67) -> 0 | BY39: =IF(AND(BX4=0,BX39>=0), "",BX39/BX4) | BZ39: =IF(AND(BX39=0,BU39>0),100%,IF(AND(BX39<0,BU39=0),(BX39-BU39)/BX39,IF(AND(BX39>0,BU39>0),(BU39-BX39)/BX39,IF(AND(BX39=0,BU39=0),"",(BU39-BX39)/BX39)))) -> 1 | CA39: =SUM(CA40:CA67) -> 0 | CB39: =IF(AND(CA4=0,CA39>=0), "",CA39/CA4) | CC39: =IF(AND(CA124=0,CA39>=0),"",CA39/CA124) | CD39: =IF(AND(BQ39=0,CA39>0),100%,IF(AND(BQ39<0,CA39=0),(BQ39-CA39)/BQ39,IF(AND(BQ39>0,CA39>0),(CA39-BQ39)/BQ39,IF(AND(BQ39=0,CA39=0),"",(CA39-BQ39)/BQ39)))) | CE39: =SUM(CE40:CE67) -> 20687.15 | CF39: =IF(AND(CE4=0,CE39>=0), "",CE39/CE4) -> 0.1265097 | CG39: =IF(AND(CE124=0,CE39>=0),"",CE39/CE124) -> 0.27135543 | CH39: =SUM(CH40:CH67) -> 0 | CI39: =IF(AND(CH4=0,CH39>=0), "",CH39/CH4) | CJ39: =IF(AND(CH124=0,CH39>=0),"",CH39/CH124) | CK39: =IF(AND(CA39=0,CH39>0),100%,IF(AND(CA39<0,CH39=0),(CA39-CH39)/CA39,IF(AND(CA39>0,CH39>0),(CH39-CA39)/CA39,IF(AND(CA39=0,CH39=0),"",(CH39-CA39)/CA39)))) | CL39: =SUM(CL40:CL67) -> 20687.15 | CM39: =IF(AND(CL4=0,CL39>=0), "",CL39/CL4) -> 0.1265097 | CN39: =IF(AND(CL124=0,CL39>=0),"",CL39/CL124) -> 0.27135543 | CO39: =SUM(CO40:CO67) -> 0 | CP39: =IF(AND(CO4=0,CO39>=0), "",CO39/CO4) | CQ39: =IF(AND(CO124=0,CO39>=0),"",CO39/CO124) | CR39: =IF(AND(CH39=0,CO39>0),100%,IF(AND(CH39<0,CO39=0),(CH39-CO39)/CH39,IF(AND(CH39>0,CO39>0),(CO39-CH39)/CH39,IF(AND(CH39=0,CO39=0),"",(CO39-CH39)/CH39)))) | CS39: =SUM(CS40:CS67) -> 20687.15 | CT39: =IF(AND(CS4=0,CS39>=0), "",CS39/CS4) -> 0.1265097 | CU39: =IF(AND(CS124=0,CS39>=0),"",CS39/CS124) -> 0.27135543 | CV39: =SUM(CV40:CV67) -> 0 | CW39: =IF(AND(CV4=0,CV39>=0), "",CV39/CV4) | CX39: =IF(AND(CV39=0,CS39>0),100%,IF(AND(CV39<0,CS39=0),(CV39-CS39)/CV39,IF(AND(CV39>0,CS39>0),(CS39-CV39)/CV39,IF(AND(CV39=0,CS39=0),"",(CS39-CV39)/CV39)))) -> 1
A40: Gastos de servicios públicos (Agua, luz, Aseo Urbano) | B40: =+'N EERR RODEO'!B39 -> 0 | C40: =IF(AND(B4=0,B40>=0), "",B40/B4) | D40: =IF(AND(B124=0,B40>=0),"",B40/B124) | E40: =+'N EERR RODEO'!C39 -> 91.41 | F40: =IF(AND(E4=0,E40>=0), "",E40/E4) -> 0.0019070357 | G40: =IF(AND(E124=0,E40>=0),"",E40/E124) -> 0.0029520607 | H40: =+'N EERR RODEO'!D39 -> 94.56 | I40: =IF(AND(H4=0,H40>=0), "",H40/H4) -> 0.0018367214 | J40: =IF(AND(H124=0,H40>=0),"",H40/H124) -> 0.0048906913 | K40: =IF(AND(E40=0,H40>0),100%,IF(AND(E40<0,H40=0),(E40-H40)/E40,IF(AND(E40>0,H40>0),(H40-E40)/E40,IF(AND(E40=0,H40=0),"",(H40-E40)/E40)))) -> 0.034460125 | L40: =+E40+H40 -> 185.97 | M40: =IF(AND(L4=0,L40>=0), "",L40/L4) -> 0.0018706231 | N40: =IF(AND(L124=0,L40>=0),"",L40/L124) -> 0.0036972535 | O40: =+'N EERR RODEO'!E39 -> 89.04 | P40: =IF(AND(O4=0,O40>=0), "",O40/O4) -> 0.0013889457 | Q40: =IF(AND(O124=0,O40>=0),"",O40/O124) -> 0.0034329522 | R40: =IF(AND(H40=0,O40>0),100%,IF(AND(H40<0,O40=0),(H40-O40)/H40,IF(AND(H40>0,O40>0),(O40-H40)/H40,IF(AND(H40=0,O40=0),"",(O40-H40)/H40)))) -> -0.058375635 | S40: =+L40+O40 -> 275.01 | T40: =IF(AND(S4=0,S40>=0), "",S40/S4) -> 0.0016817895 | U40: =IF(AND(S124=0,S40>=0),"",S40/S124) -> 0.0036073338 | W40: =IF(AND(V4=0,V40>=0), "",V40/V4) | X40: =IF(AND(V40=0,S40>0),100%,IF(AND(V40<0,S40=0),(V40-S40)/V40,IF(AND(V40>0,S40>0),(S40-V40)/V40,IF(AND(V40=0,S40=0),"",(S40-V40)/V40)))) -> 1 | Y40: =+'N EERR RODEO'!F39 -> 0 | Z40: =IF(AND(Y4=0,Y40>=0), "",Y40/Y4) | AA40: =IF(AND(Y124=0,Y40>=0),"",Y40/Y124) | AB40: =IF(AND(O40=0,Y40>0),100%,IF(AND(O40<0,Y40=0),(O40-Y40)/O40,IF(AND(O40>0,Y40>0),(Y40-O40)/O40,IF(AND(O40=0,Y40=0),"",(Y40-O40)/O40)))) -> -1 | AC40: =+S40+Y40 -> 275.01 | AD40: =IF(AND(AC4=0,AC40>=0), "",AC40/AC4) -> 0.0016817895 | AE40: =IF(AND(AC124=0,AC40>=0),"",AC40/AC124) -> 0.0036073338 | AF40: =+'N EERR RODEO'!G39 -> 0 | AG40: =IF(AND(AF4=0,AF40>=0), "",AF40/AF4) | AH40: =IF(AND(AF124=0,AF40>=0),"",AF40/AF124) | AI40: =IF(AND(Y40=0,AF40>0),100%,IF(AND(Y40<0,AF40=0),(Y40-AF40)/Y40,IF(AND(Y40>0,AF40>0),(AF40-Y40)/Y40,IF(AND(Y40=0,AF40=0),"",(AF40-Y40)/Y40)))) | AJ40: =+AC40+AF40 -> 275.01 | AK40: =IF(AND(AJ4=0,AJ40>=0), "",AJ40/AJ4) -> 0.0016817895 | AL40: =IF(AND(AJ124=0,AJ40>=0),"",AJ40/AJ124) -> 0.0036073338 | AM40: =+'N EERR RODEO'!H39 -> 0 | AN40: =IF(AND(AM4=0,AM40>=0), "",AM40/AM4) | AO40: =IF(AND(AM124=0,AM40>=0),"",AM40/AM124) | AP40: =IF(AND(AF40=0,AM40>0),100%,IF(AND(AF40<0,AM40=0),(AF40-AM40)/AF40,IF(AND(AF40>0,AM40>0),(AM40-AF40)/AF40,IF(AND(AF40=0,AM40=0),"",(AM40-AF40)/AF40)))) | AQ40: =+AJ40+AM40 -> 275.01 | AR40: =IF(AND(AQ4=0,AQ40>=0), "",AQ40/AQ4) -> 0.0016817895 | AS40: =IF(AND(AQ124=0,AQ40>=0),"",AQ40/AQ124) -> 0.0036073338 | AT40: =+V40*2 -> 0 | AU40: =IF(AND(AT4=0,AT40>=0), "",AT40/AT4) | AV40: =IF(AND(AT40=0,AQ40>0),100%,IF(AND(AT40<0,AQ40=0),(AT40-AQ40)/AT40,IF(AND(AT40>0,AQ40>0),(AQ40-AT40)/AT40,IF(AND(AT40=0,AQ40=0),"",(AQ40-AT40)/AT40)))) -> 1 | AW40: =+AQ40/6 -> 45.835 | AX40: =IF(AND(AW4=0,AW40>=0), "",AW40/AW4) -> 0.0016817895 | AY40: =IF(AND(AW124=0,AW40>=0),"",AW40/AW124) -> 0.0036073338 | AZ40: =+AT40/6 -> 0 | BA40: =IF(AND(AZ4=0,AZ40>=0), "",AZ40/AZ4) | BB40: =IF(AND(AZ40=0,AW40>0),100%,IF(AND(AZ40<0,AW40=0),(AZ40-AW40)/AZ40,IF(AND(AZ40>0,AW40>0),(AW40-AZ40)/AZ40,IF(AND(AZ40=0,AW40=0),"",(AW40-AZ40)/AZ40)))) -> 1 | BC40: =+'N EERR RODEO'!I39 -> 0 | BD40: =IF(AND(BC4=0,BC40>=0), "",BC40/BC4) | BE40: =IF(AND(BC124=0,BC40>=0),"",BC40/BC124) | BF40: =IF(AND(AM40=0,BC40>0),100%,IF(AND(AM40<0,BC40=0),(AM40-BC40)/AM40,IF(AND(AM40>0,BC40>0),(BC40-AM40)/AM40,IF(AND(AM40=0,BC40=0),"",(BC40-AM40)/AM40)))) | BG40: =+AQ40+BC40 -> 275.01 | BH40: =IF(AND(BG4=0,BG40>=0), "",BG40/BG4) -> 0.0016817895 | BI40: =IF(AND(BG124=0,BG40>=0),"",BG40/BG124) -> 0.0036073338 | BJ40: =+'N EERR RODEO'!J39 -> 0 | BK40: =IF(AND(BJ4=0,BJ40>=0), "",BJ40/BJ4) | BL40: =IF(AND(BJ124=0,BJ40>=0),"",BJ40/BJ124) | BM40: =IF(AND(BC40=0,BJ40>0),100%,IF(AND(BC40<0,BJ40=0),(BC40-BJ40)/BC40,IF(AND(BC40>0,BJ40>0),(BJ40-BC40)/BC40,IF(AND(BC40=0,BJ40=0),"",(BJ40-BC40)/BC40)))) | BN40: =+BG40+BJ40 -> 275.01 | BO40: =IF(AND(BN4=0,BN40>=0), "",BN40/BN4) -> 0.0016817895 | BP40: =IF(AND(BN124=0,BN40>=0),"",BN40/BN124) -> 0.0036073338 | BQ40: =+'N EERR RODEO'!K39 -> 0 | BR40: =IF(AND(BQ4=0,BQ40>=0), "",BQ40/BQ4) | BS40: =IF(AND(BQ124=0,BQ40>=0),"",BQ40/BQ124) | BT40: =IF(AND(BJ40=0,BQ40>0),100%,IF(AND(BJ40<0,BQ40=0),(BJ40-BQ40)/BJ40,IF(AND(BJ40>0,BQ40>0),(BQ40-BJ40)/BJ40,IF(AND(BJ40=0,BQ40=0),"",(BQ40-BJ40)/BJ40)))) | BU40: =+BN40+BQ40 -> 275.01 | BV40: =IF(AND(BU4=0,BU40>=0), "",BU40/BU4) -> 0.0016817895 | BW40: =IF(AND(BU124=0,BU40>=0),"",BU40/BU124) -> 0.0036073338 | BX40: =+AZ40*9 -> 0 | BY40: =IF(AND(BX4=0,BX40>=0), "",BX40/BX4) | BZ40: =IF(AND(BX40=0,BU40>0),100%,IF(AND(BX40<0,BU40=0),(BX40-BU40)/BX40,IF(AND(BX40>0,BU40>0),(BU40-BX40)/BX40,IF(AND(BX40=0,BU40=0),"",(BU40-BX40)/BX40)))) -> 1 | CA40: =+'N EERR RODEO'!L39 -> 0 | CB40: =IF(AND(CA4=0,CA40>=0), "",CA40/CA4) | CC40: =IF(AND(CA124=0,CA40>=0),"",CA40/CA124) | CD40: =IF(AND(BQ40=0,CA40>0),100%,IF(AND(BQ40<0,CA40=0),(BQ40-CA40)/BQ40,IF(AND(BQ40>0,CA40>0),(CA40-BQ40)/BQ40,IF(AND(BQ40=0,CA40=0),"",(CA40-BQ40)/BQ40)))) | CE40: =+BU40+CA40 -> 275.01 | CF40: =IF(AND(CE4=0,CE40>=0), "",CE40/CE4) -> 0.0016817895 | CG40: =IF(AND(CE124=0,CE40>=0),"",CE40/CE124) -> 0.0036073338 | CH40: =+'N EERR RODEO'!M39 -> 0 | CI40: =IF(AND(CH4=0,CH40>=0), "",CH40/CH4) | CJ40: =IF(AND(CH124=0,CH40>=0),"",CH40/CH124) | CK40: =IF(AND(CA40=0,CH40>0),100%,IF(AND(CA40<0,CH40=0),(CA40-CH40)/CA40,IF(AND(CA40>0,CH40>0),(CH40-CA40)/CA40,IF(AND(CA40=0,CH40=0),"",(CH40-CA40)/CA40)))) | CL40: =+CE40+CH40 -> 275.01 | CM40: =IF(AND(CL4=0,CL40>=0), "",CL40/CL4) -> 0.0016817895 | CN40: =IF(AND(CL124=0,CL40>=0),"",CL40/CL124) -> 0.0036073338 | CO40: =+'N EERR RODEO'!N39 -> 0 | CP40: =IF(AND(CO4=0,CO40>=0), "",CO40/CO4) | CQ40: =IF(AND(CO124=0,CO40>=0),"",CO40/CO124) | CR40: =IF(AND(CH40=0,CO40>0),100%,IF(AND(CH40<0,CO40=0),(CH40-CO40)/CH40,IF(AND(CH40>0,CO40>0),(CO40-CH40)/CH40,IF(AND(CH40=0,CO40=0),"",(CO40-CH40)/CH40)))) | CS40: =+CL40+CO40 -> 275.01 | CT40: =IF(AND(CS4=0,CS40>=0), "",CS40/CS4) -> 0.0016817895 | CU40: =IF(AND(CS124=0,CS40>=0),"",CS40/CS124) -> 0.0036073338 | CV40: =+AZ40*12 -> 0 | CW40: =IF(AND(CV4=0,CV40>=0), "",CV40/CV4) | CX40: =IF(AND(CV40=0,CS40>0),100%,IF(AND(CV40<0,CS40=0),(CV40-CS40)/CV40,IF(AND(CV40>0,CS40>0),(CS40-CV40)/CV40,IF(AND(CV40=0,CS40=0),"",(CS40-CV40)/CV40)))) -> 1
A41: Gastos de servicios de telefonía e internet | B41: =+'N EERR RODEO'!B40 -> 0 | C41: =IF(AND(B4=0,B41>=0), "",B41/B4) | D41: =IF(AND(B124=0,B41>=0),"",B41/B124) | E41: =+'N EERR RODEO'!C40 -> 21.6 | F41: =IF(AND(E4=0,E41>=0), "",E41/E4) -> 0.00045062872 | G41: =IF(AND(E124=0,E41>=0),"",E41/E124) -> 0.00069756604 | H41: =+'N EERR RODEO'!D40 -> 0 | I41: =IF(AND(H4=0,H41>=0), "",H41/H4) -> 0 | J41: =IF(AND(H124=0,H41>=0),"",H41/H124) -> 0 | K41: =IF(AND(E41=0,H41>0),100%,IF(AND(E41<0,H41=0),(E41-H41)/E41,IF(AND(E41>0,H41>0),(H41-E41)/E41,IF(AND(E41=0,H41=0),"",(H41-E41)/E41)))) -> -1 | L41: =+E41+H41 -> 21.6 | M41: =IF(AND(L4=0,L41>=0), "",L41/L4) -> 0.0002172687 | N41: =IF(AND(L124=0,L41>=0),"",L41/L124) -> 0.00042942773 | O41: =+'N EERR RODEO'!E40 -> 0 | P41: =IF(AND(O4=0,O41>=0), "",O41/O4) -> 0 | Q41: =IF(AND(O124=0,O41>=0),"",O41/O124) -> 0 | R41: =IF(AND(H41=0,O41>0),100%,IF(AND(H41<0,O41=0),(H41-O41)/H41,IF(AND(H41>0,O41>0),(O41-H41)/H41,IF(AND(H41=0,O41=0),"",(O41-H41)/H41)))) | S41: =+L41+O41 -> 21.6 | T41: =IF(AND(S4=0,S41>=0), "",S41/S4) -> 0.00013209212 | U41: =IF(AND(S124=0,S41>=0),"",S41/S124) -> 0.00028332937 | W41: =IF(AND(V4=0,V41>=0), "",V41/V4) | X41: =IF(AND(V41=0,S41>0),100%,IF(AND(V41<0,S41=0),(V41-S41)/V41,IF(AND(V41>0,S41>0),(S41-V41)/V41,IF(AND(V41=0,S41=0),"",(S41-V41)/V41)))) -> 1 | Y41: =+'N EERR RODEO'!F40 -> 0 | Z41: =IF(AND(Y4=0,Y41>=0), "",Y41/Y4) | AA41: =IF(AND(Y124=0,Y41>=0),"",Y41/Y124) | AB41: =IF(AND(O41=0,Y41>0),100%,IF(AND(O41<0,Y41=0),(O41-Y41)/O41,IF(AND(O41>0,Y41>0),(Y41-O41)/O41,IF(AND(O41=0,Y41=0),"",(Y41-O41)/O41)))) | AC41: =+S41+Y41 -> 21.6 | AD41: =IF(AND(AC4=0,AC41>=0), "",AC41/AC4) -> 0.00013209212 | AE41: =IF(AND(AC124=0,AC41>=0),"",AC41/AC124) -> 0.00028332937 | AF41: =+'N EERR RODEO'!G40 -> 0 | AG41: =IF(AND(AF4=0,AF41>=0), "",AF41/AF4) | AH41: =IF(AND(AF124=0,AF41>=0),"",AF41/AF124) | AI41: =IF(AND(Y41=0,AF41>0),100%,IF(AND(Y41<0,AF41=0),(Y41-AF41)/Y41,IF(AND(Y41>0,AF41>0),(AF41-Y41)/Y41,IF(AND(Y41=0,AF41=0),"",(AF41-Y41)/Y41)))) | AJ41: =+AC41+AF41 -> 21.6 | AK41: =IF(AND(AJ4=0,AJ41>=0), "",AJ41/AJ4) -> 0.00013209212 | AL41: =IF(AND(AJ124=0,AJ41>=0),"",AJ41/AJ124) -> 0.00028332937 | AM41: =+'N EERR RODEO'!H40 -> 0 | AN41: =IF(AND(AM4=0,AM41>=0), "",AM41/AM4) | AO41: =IF(AND(AM124=0,AM41>=0),"",AM41/AM124) | AP41: =IF(AND(AF41=0,AM41>0),100%,IF(AND(AF41<0,AM41=0),(AF41-AM41)/AF41,IF(AND(AF41>0,AM41>0),(AM41-AF41)/AF41,IF(AND(AF41=0,AM41=0),"",(AM41-AF41)/AF41)))) | AQ41: =+AJ41+AM41 -> 21.6 | AR41: =IF(AND(AQ4=0,AQ41>=0), "",AQ41/AQ4) -> 0.00013209212 | AS41: =IF(AND(AQ124=0,AQ41>=0),"",AQ41/AQ124) -> 0.00028332937 | AT41: =+V41*2 -> 0 | AU41: =IF(AND(AT4=0,AT41>=0), "",AT41/AT4) | AV41: =IF(AND(AT41=0,AQ41>0),100%,IF(AND(AT41<0,AQ41=0),(AT41-AQ41)/AT41,IF(AND(AT41>0,AQ41>0),(AQ41-AT41)/AT41,IF(AND(AT41=0,AQ41=0),"",(AQ41-AT41)/AT41)))) -> 1 | AW41: =+AQ41/6 -> 3.6 | AX41: =IF(AND(AW4=0,AW41>=0), "",AW41/AW4) -> 0.00013209212 | AY41: =IF(AND(AW124=0,AW41>=0),"",AW41/AW124) -> 0.00028332937 | AZ41: =+AT41/6 -> 0 | BA41: =IF(AND(AZ4=0,AZ41>=0), "",AZ41/AZ4) | BB41: =IF(AND(AZ41=0,AW41>0),100%,IF(AND(AZ41<0,AW41=0),(AZ41-AW41)/AZ41,IF(AND(AZ41>0,AW41>0),(AW41-AZ41)/AZ41,IF(AND(AZ41=0,AW41=0),"",(AW41-AZ41)/AZ41)))) -> 1 | BC41: =+'N EERR RODEO'!I40 -> 0 | BD41: =IF(AND(BC4=0,BC41>=0), "",BC41/BC4) | BE41: =IF(AND(BC124=0,BC41>=0),"",BC41/BC124) | BF41: =IF(AND(AM41=0,BC41>0),100%,IF(AND(AM41<0,BC41=0),(AM41-BC41)/AM41,IF(AND(AM41>0,BC41>0),(BC41-AM41)/AM41,IF(AND(AM41=0,BC41=0),"",(BC41-AM41)/AM41)))) | BG41: =+AQ41+BC41 -> 21.6 | BH41: =IF(AND(BG4=0,BG41>=0), "",BG41/BG4) -> 0.00013209212 | BI41: =IF(AND(BG124=0,BG41>=0),"",BG41/BG124) -> 0.00028332937 | BJ41: =+'N EERR RODEO'!J40 -> 0 | BK41: =IF(AND(BJ4=0,BJ41>=0), "",BJ41/BJ4) | BL41: =IF(AND(BJ124=0,BJ41>=0),"",BJ41/BJ124) | BM41: =IF(AND(BC41=0,BJ41>0),100%,IF(AND(BC41<0,BJ41=0),(BC41-BJ41)/BC41,IF(AND(BC41>0,BJ41>0),(BJ41-BC41)/BC41,IF(AND(BC41=0,BJ41=0),"",(BJ41-BC41)/BC41)))) | BN41: =+BG41+BJ41 -> 21.6 | BO41: =IF(AND(BN4=0,BN41>=0), "",BN41/BN4) -> 0.00013209212 | BP41: =IF(AND(BN124=0,BN41>=0),"",BN41/BN124) -> 0.00028332937 | BQ41: =+'N EERR RODEO'!K40 -> 0 | BR41: =IF(AND(BQ4=0,BQ41>=0), "",BQ41/BQ4) | BS41: =IF(AND(BQ124=0,BQ41>=0),"",BQ41/BQ124) | BT41: =IF(AND(BJ41=0,BQ41>0),100%,IF(AND(BJ41<0,BQ41=0),(BJ41-BQ41)/BJ41,IF(AND(BJ41>0,BQ41>0),(BQ41-BJ41)/BJ41,IF(AND(BJ41=0,BQ41=0),"",(BQ41-BJ41)/BJ41)))) | BU41: =+BN41+BQ41 -> 21.6 | BV41: =IF(AND(BU4=0,BU41>=0), "",BU41/BU4) -> 0.00013209212 | BW41: =IF(AND(BU124=0,BU41>=0),"",BU41/BU124) -> 0.00028332937 | BX41: =+AZ41*9 -> 0 | BY41: =IF(AND(BX4=0,BX41>=0), "",BX41/BX4) | BZ41: =IF(AND(BX41=0,BU41>0),100%,IF(AND(BX41<0,BU41=0),(BX41-BU41)/BX41,IF(AND(BX41>0,BU41>0),(BU41-BX41)/BX41,IF(AND(BX41=0,BU41=0),"",(BU41-BX41)/BX41)))) -> 1 | CA41: =+'N EERR RODEO'!L40 -> 0 | CB41: =IF(AND(CA4=0,CA41>=0), "",CA41/CA4) | CC41: =IF(AND(CA124=0,CA41>=0),"",CA41/CA124) | CD41: =IF(AND(BQ41=0,CA41>0),100%,IF(AND(BQ41<0,CA41=0),(BQ41-CA41)/BQ41,IF(AND(BQ41>0,CA41>0),(CA41-BQ41)/BQ41,IF(AND(BQ41=0,CA41=0),"",(CA41-BQ41)/BQ41)))) | CE41: =+BU41+CA41 -> 21.6 | CF41: =IF(AND(CE4=0,CE41>=0), "",CE41/CE4) -> 0.00013209212 | CG41: =IF(AND(CE124=0,CE41>=0),"",CE41/CE124) -> 0.00028332937 | CH41: =+'N EERR RODEO'!M40 -> 0 | CI41: =IF(AND(CH4=0,CH41>=0), "",CH41/CH4) | CJ41: =IF(AND(CH124=0,CH41>=0),"",CH41/CH124) | CK41: =IF(AND(CA41=0,CH41>0),100%,IF(AND(CA41<0,CH41=0),(CA41-CH41)/CA41,IF(AND(CA41>0,CH41>0),(CH41-CA41)/CA41,IF(AND(CA41=0,CH41=0),"",(CH41-CA41)/CA41)))) | CL41: =+CE41+CH41 -> 21.6 | CM41: =IF(AND(CL4=0,CL41>=0), "",CL41/CL4) -> 0.00013209212 | CN41: =IF(AND(CL124=0,CL41>=0),"",CL41/CL124) -> 0.00028332937 | CO41: =+'N EERR RODEO'!N40 -> 0 | CP41: =IF(AND(CO4=0,CO41>=0), "",CO41/CO4) | CQ41: =IF(AND(CO124=0,CO41>=0),"",CO41/CO124) | CR41: =IF(AND(CH41=0,CO41>0),100%,IF(AND(CH41<0,CO41=0),(CH41-CO41)/CH41,IF(AND(CH41>0,CO41>0),(CO41-CH41)/CH41,IF(AND(CH41=0,CO41=0),"",(CO41-CH41)/CH41)))) | CS41: =+CL41+CO41 -> 21.6 | CT41: =IF(AND(CS4=0,CS41>=0), "",CS41/CS4) -> 0.00013209212 | CU41: =IF(AND(CS124=0,CS41>=0),"",CS41/CS124) -> 0.00028332937 | CV41: =+AZ41*12 -> 0 | CW41: =IF(AND(CV4=0,CV41>=0), "",CV41/CV4) | CX41: =IF(AND(CV41=0,CS41>0),100%,IF(AND(CV41<0,CS41=0),(CV41-CS41)/CV41,IF(AND(CV41>0,CS41>0),(CS41-CV41)/CV41,IF(AND(CV41=0,CS41=0),"",(CS41-CV41)/CV41)))) -> 1
A42: Gastos de alquiler del local | B42: =+'N EERR RODEO'!B41 -> 0 | C42: =IF(AND(B4=0,B42>=0), "",B42/B4) | D42: =IF(AND(B124=0,B42>=0),"",B42/B124) | E42: =+'N EERR RODEO'!C41 -> 1460.74 | F42: =IF(AND(E4=0,E42>=0), "",E42/E4) -> 0.030474602 | G42: =IF(AND(E124=0,E42>=0),"",E42/E124) -> 0.047174195 | H42: =+'N EERR RODEO'!D41 -> 1474.99 | I42: =IF(AND(H4=0,H42>=0), "",H42/H4) -> 0.028650018 | J42: =IF(AND(H124=0,H42>=0),"",H42/H124) -> 0.076287233 | K42: =IF(AND(E42=0,H42>0),100%,IF(AND(E42<0,H42=0),(E42-H42)/E42,IF(AND(E42>0,H42>0),(H42-E42)/E42,IF(AND(E42=0,H42=0),"",(H42-E42)/E42)))) -> 0.0097553295 | L42: =+E42+H42 -> 2935.73 | M42: =IF(AND(L4=0,L42>=0), "",L42/L4) -> 0.029529733 | N42: =IF(AND(L124=0,L42>=0),"",L42/L124) -> 0.058364994 | O42: =+'N EERR RODEO'!E41 -> 1462.32 | P42: =IF(AND(O4=0,O42>=0), "",O42/O4) -> 0.022810905 | Q42: =IF(AND(O124=0,O42>=0),"",O42/O124) -> 0.056379994 | R42: =IF(AND(H42=0,O42>0),100%,IF(AND(H42<0,O42=0),(H42-O42)/H42,IF(AND(H42>0,O42>0),(O42-H42)/H42,IF(AND(H42=0,O42=0),"",(O42-H42)/H42)))) -> -0.0085898887 | S42: =+L42+O42 -> 4398.05 | T42: =IF(AND(S4=0,S42>=0), "",S42/S4) -> 0.026895728 | U42: =IF(AND(S124=0,S42>=0),"",S42/S124) -> 0.057689664 | W42: =IF(AND(V4=0,V42>=0), "",V42/V4) | X42: =IF(AND(V42=0,S42>0),100%,IF(AND(V42<0,S42=0),(V42-S42)/V42,IF(AND(V42>0,S42>0),(S42-V42)/V42,IF(AND(V42=0,S42=0),"",(S42-V42)/V42)))) -> 1 | Y42: =+'N EERR RODEO'!F41 -> 0 | Z42: =IF(AND(Y4=0,Y42>=0), "",Y42/Y4) | AA42: =IF(AND(Y124=0,Y42>=0),"",Y42/Y124) | AB42: =IF(AND(O42=0,Y42>0),100%,IF(AND(O42<0,Y42=0),(O42-Y42)/O42,IF(AND(O42>0,Y42>0),(Y42-O42)/O42,IF(AND(O42=0,Y42=0),"",(Y42-O42)/O42)))) -> -1 | AC42: =+S42+Y42 -> 4398.05 | AD42: =IF(AND(AC4=0,AC42>=0), "",AC42/AC4) -> 0.026895728 | AE42: =IF(AND(AC124=0,AC42>=0),"",AC42/AC124) -> 0.057689664 | AF42: =+'N EERR RODEO'!G41 -> 0 | AG42: =IF(AND(AF4=0,AF42>=0), "",AF42/AF4) | AH42: =IF(AND(AF124=0,AF42>=0),"",AF42/AF124) | AI42: =IF(AND(Y42=0,AF42>0),100%,IF(AND(Y42<0,AF42=0),(Y42-AF42)/Y42,IF(AND(Y42>0,AF42>0),(AF42-Y42)/Y42,IF(AND(Y42=0,AF42=0),"",(AF42-Y42)/Y42)))) | AJ42: =+AC42+AF42 -> 4398.05 | AK42: =IF(AND(AJ4=0,AJ42>=0), "",AJ42/AJ4) -> 0.026895728 | AL42: =IF(AND(AJ124=0,AJ42>=0),"",AJ42/AJ124) -> 0.057689664 | AM42: =+'N EERR RODEO'!H41 -> 0 | AN42: =IF(AND(AM4=0,AM42>=0), "",AM42/AM4) | AO42: =IF(AND(AM124=0,AM42>=0),"",AM42/AM124) | AP42: =IF(AND(AF42=0,AM42>0),100%,IF(AND(AF42<0,AM42=0),(AF42-AM42)/AF42,IF(AND(AF42>0,AM42>0),(AM42-AF42)/AF42,IF(AND(AF42=0,AM42=0),"",(AM42-AF42)/AF42)))) | AQ42: =+AJ42+AM42 -> 4398.05 | AR42: =IF(AND(AQ4=0,AQ42>=0), "",AQ42/AQ4) -> 0.026895728 | AS42: =IF(AND(AQ124=0,AQ42>=0),"",AQ42/AQ124) -> 0.057689664 | AT42: =+V42*2 -> 0 | AU42: =IF(AND(AT4=0,AT42>=0), "",AT42/AT4) | AV42: =IF(AND(AT42=0,AQ42>0),100%,IF(AND(AT42<0,AQ42=0),(AT42-AQ42)/AT42,IF(AND(AT42>0,AQ42>0),(AQ42-AT42)/AT42,IF(AND(AT42=0,AQ42=0),"",(AQ42-AT42)/AT42)))) -> 1 | AW42: =+AQ42/6 -> 733.00833 | AX42: =IF(AND(AW4=0,AW42>=0), "",AW42/AW4) -> 0.026895728 | AY42: =IF(AND(AW124=0,AW42>=0),"",AW42/AW124) -> 0.057689664 | AZ42: =+AT42/6 -> 0 | BA42: =IF(AND(AZ4=0,AZ42>=0), "",AZ42/AZ4) | BB42: =IF(AND(AZ42=0,AW42>0),100%,IF(AND(AZ42<0,AW42=0),(AZ42-AW42)/AZ42,IF(AND(AZ42>0,AW42>0),(AW42-AZ42)/AZ42,IF(AND(AZ42=0,AW42=0),"",(AW42-AZ42)/AZ42)))) -> 1 | BC42: =+'N EERR RODEO'!I41 -> 0 | BD42: =IF(AND(BC4=0,BC42>=0), "",BC42/BC4) | BE42: =IF(AND(BC124=0,BC42>=0),"",BC42/BC124) | BF42: =IF(AND(AM42=0,BC42>0),100%,IF(AND(AM42<0,BC42=0),(AM42-BC42)/AM42,IF(AND(AM42>0,BC42>0),(BC42-AM42)/AM42,IF(AND(AM42=0,BC42=0),"",(BC42-AM42)/AM42)))) | BG42: =+AQ42+BC42 -> 4398.05 | BH42: =IF(AND(BG4=0,BG42>=0), "",BG42/BG4) -> 0.026895728 | BI42: =IF(AND(BG124=0,BG42>=0),"",BG42/BG124) -> 0.057689664 | BJ42: =+'N EERR RODEO'!J41 -> 0 | BK42: =IF(AND(BJ4=0,BJ42>=0), "",BJ42/BJ4) | BL42: =IF(AND(BJ124=0,BJ42>=0),"",BJ42/BJ124) | BM42: =IF(AND(BC42=0,BJ42>0),100%,IF(AND(BC42<0,BJ42=0),(BC42-BJ42)/BC42,IF(AND(BC42>0,BJ42>0),(BJ42-BC42)/BC42,IF(AND(BC42=0,BJ42=0),"",(BJ42-BC42)/BC42)))) | BN42: =+BG42+BJ42 -> 4398.05 | BO42: =IF(AND(BN4=0,BN42>=0), "",BN42/BN4) -> 0.026895728 | BP42: =IF(AND(BN124=0,BN42>=0),"",BN42/BN124) -> 0.057689664 | BQ42: =+'N EERR RODEO'!K41 -> 0 | BR42: =IF(AND(BQ4=0,BQ42>=0), "",BQ42/BQ4) | BS42: =IF(AND(BQ124=0,BQ42>=0),"",BQ42/BQ124) | BT42: =IF(AND(BJ42=0,BQ42>0),100%,IF(AND(BJ42<0,BQ42=0),(BJ42-BQ42)/BJ42,IF(AND(BJ42>0,BQ42>0),(BQ42-BJ42)/BJ42,IF(AND(BJ42=0,BQ42=0),"",(BQ42-BJ42)/BJ42)))) | BU42: =+BN42+BQ42 -> 4398.05 | BV42: =IF(AND(BU4=0,BU42>=0), "",BU42/BU4) -> 0.026895728 | BW42: =IF(AND(BU124=0,BU42>=0),"",BU42/BU124) -> 0.057689664 | BX42: =+AZ42*9 -> 0 | BY42: =IF(AND(BX4=0,BX42>=0), "",BX42/BX4) | BZ42: =IF(AND(BX42=0,BU42>0),100%,IF(AND(BX42<0,BU42=0),(BX42-BU42)/BX42,IF(AND(BX42>0,BU42>0),(BU42-BX42)/BX42,IF(AND(BX42=0,BU42=0),"",(BU42-BX42)/BX42)))) -> 1 | CA42: =+'N EERR RODEO'!L41 -> 0 | CB42: =IF(AND(CA4=0,CA42>=0), "",CA42/CA4) | CC42: =IF(AND(CA124=0,CA42>=0),"",CA42/CA124) | CD42: =IF(AND(BQ42=0,CA42>0),100%,IF(AND(BQ42<0,CA42=0),(BQ42-CA42)/BQ42,IF(AND(BQ42>0,CA42>0),(CA42-BQ42)/BQ42,IF(AND(BQ42=0,CA42=0),"",(CA42-BQ42)/BQ42)))) | CE42: =+BU42+CA42 -> 4398.05 | CF42: =IF(AND(CE4=0,CE42>=0), "",CE42/CE4) -> 0.026895728 | CG42: =IF(AND(CE124=0,CE42>=0),"",CE42/CE124) -> 0.057689664 | CH42: =+'N EERR RODEO'!M41 -> 0 | CI42: =IF(AND(CH4=0,CH42>=0), "",CH42/CH4) | CJ42: =IF(AND(CH124=0,CH42>=0),"",CH42/CH124) | CK42: =IF(AND(CA42=0,CH42>0),100%,IF(AND(CA42<0,CH42=0),(CA42-CH42)/CA42,IF(AND(CA42>0,CH42>0),(CH42-CA42)/CA42,IF(AND(CA42=0,CH42=0),"",(CH42-CA42)/CA42)))) | CL42: =+CE42+CH42 -> 4398.05 | CM42: =IF(AND(CL4=0,CL42>=0), "",CL42/CL4) -> 0.026895728 | CN42: =IF(AND(CL124=0,CL42>=0),"",CL42/CL124) -> 0.057689664 | CO42: =+'N EERR RODEO'!N41 -> 0 | CP42: =IF(AND(CO4=0,CO42>=0), "",CO42/CO4) | CQ42: =IF(AND(CO124=0,CO42>=0),"",CO42/CO124) | CR42: =IF(AND(CH42=0,CO42>0),100%,IF(AND(CH42<0,CO42=0),(CH42-CO42)/CH42,IF(AND(CH42>0,CO42>0),(CO42-CH42)/CH42,IF(AND(CH42=0,CO42=0),"",(CO42-CH42)/CH42)))) | CS42: =+CL42+CO42 -> 4398.05 | CT42: =IF(AND(CS4=0,CS42>=0), "",CS42/CS4) -> 0.026895728 | CU42: =IF(AND(CS124=0,CS42>=0),"",CS42/CS124) -> 0.057689664 | CV42: =+AZ42*12 -> 0 | CW42: =IF(AND(CV4=0,CV42>=0), "",CV42/CV4) | CX42: =IF(AND(CV42=0,CS42>0),100%,IF(AND(CV42<0,CS42=0),(CV42-CS42)/CV42,IF(AND(CV42>0,CS42>0),(CS42-CV42)/CV42,IF(AND(CV42=0,CS42=0),"",(CS42-CV42)/CV42)))) -> 1
A43: Gastos de Condominio | B43: =+'N EERR RODEO'!B42 -> 0 | C43: =IF(AND(B4=0,B43>=0), "",B43/B4) | D43: =IF(AND(B124=0,B43>=0),"",B43/B124) | E43: =+'N EERR RODEO'!C42 -> 1879.61 | F43: =IF(AND(E4=0,E43>=0), "",E43/E4) -> 0.039213252 | G43: =IF(AND(E124=0,E43>=0),"",E43/E124) -> 0.060701487 | H43: =+'N EERR RODEO'!D42 -> 1956.16 | I43: =IF(AND(H4=0,H43>=0), "",H43/H4) -> 0.037996202 | J43: =IF(AND(H124=0,H43>=0),"",H43/H124) -> 0.10117359 | K43: =IF(AND(E43=0,H43>0),100%,IF(AND(E43<0,H43=0),(E43-H43)/E43,IF(AND(E43>0,H43>0),(H43-E43)/E43,IF(AND(E43=0,H43=0),"",(H43-E43)/E43)))) -> 0.040726534 | L43: =+E43+H43 -> 3835.77 | M43: =IF(AND(L4=0,L43>=0), "",L43/L4) -> 0.038582998 | N43: =IF(AND(L124=0,L43>=0),"",L43/L124) -> 0.076258611 | O43: =+'N EERR RODEO'!E42 -> 2149.12 | P43: =IF(AND(O4=0,O43>=0), "",O43/O4) -> 0.033524381 | Q43: =IF(AND(O124=0,O43>=0),"",O43/O124) -> 0.082859683 | R43: =IF(AND(H43=0,O43>0),100%,IF(AND(H43<0,O43=0),(H43-O43)/H43,IF(AND(H43>0,O43>0),(O43-H43)/H43,IF(AND(H43=0,O43=0),"",(O43-H43)/H43)))) -> 0.098642238 | S43: =+L43+O43 -> 5984.89 | T43: =IF(AND(S4=0,S43>=0), "",S43/S4) -> 0.036599851 | U43: =IF(AND(S124=0,S43>=0),"",S43/S124) -> 0.078504404 | W43: =IF(AND(V4=0,V43>=0), "",V43/V4) | X43: =IF(AND(V43=0,S43>0),100%,IF(AND(V43<0,S43=0),(V43-S43)/V43,IF(AND(V43>0,S43>0),(S43-V43)/V43,IF(AND(V43=0,S43=0),"",(S43-V43)/V43)))) -> 1 | Y43: =+'N EERR RODEO'!F42 -> 0 | Z43: =IF(AND(Y4=0,Y43>=0), "",Y43/Y4) | AA43: =IF(AND(Y124=0,Y43>=0),"",Y43/Y124) | AB43: =IF(AND(O43=0,Y43>0),100%,IF(AND(O43<0,Y43=0),(O43-Y43)/O43,IF(AND(O43>0,Y43>0),(Y43-O43)/O43,IF(AND(O43=0,Y43=0),"",(Y43-O43)/O43)))) -> -1 | AC43: =+S43+Y43 -> 5984.89 | AD43: =IF(AND(AC4=0,AC43>=0), "",AC43/AC4) -> 0.036599851 | AE43: =IF(AND(AC124=0,AC43>=0),"",AC43/AC124) -> 0.078504404 | AF43: =+'N EERR RODEO'!G42 -> 0 | AG43: =IF(AND(AF4=0,AF43>=0), "",AF43/AF4) | AH43: =IF(AND(AF124=0,AF43>=0),"",AF43/AF124) | AI43: =IF(AND(Y43=0,AF43>0),100%,IF(AND(Y43<0,AF43=0),(Y43-AF43)/Y43,IF(AND(Y43>0,AF43>0),(AF43-Y43)/Y43,IF(AND(Y43=0,AF43=0),"",(AF43-Y43)/Y43)))) | AJ43: =+AC43+AF43 -> 5984.89 | AK43: =IF(AND(AJ4=0,AJ43>=0), "",AJ43/AJ4) -> 0.036599851 | AL43: =IF(AND(AJ124=0,AJ43>=0),"",AJ43/AJ124) -> 0.078504404 | AM43: =+'N EERR RODEO'!H42 -> 0 | AN43: =IF(AND(AM4=0,AM43>=0), "",AM43/AM4) | AO43: =IF(AND(AM124=0,AM43>=0),"",AM43/AM124) | AP43: =IF(AND(AF43=0,AM43>0),100%,IF(AND(AF43<0,AM43=0),(AF43-AM43)/AF43,IF(AND(AF43>0,AM43>0),(AM43-AF43)/AF43,IF(AND(AF43=0,AM43=0),"",(AM43-AF43)/AF43)))) | AQ43: =+AJ43+AM43 -> 5984.89 | AR43: =IF(AND(AQ4=0,AQ43>=0), "",AQ43/AQ4) -> 0.036599851 | AS43: =IF(AND(AQ124=0,AQ43>=0),"",AQ43/AQ124) -> 0.078504404 | AT43: =+V43*2 -> 0 | AU43: =IF(AND(AT4=0,AT43>=0), "",AT43/AT4) | AV43: =IF(AND(AT43=0,AQ43>0),100%,IF(AND(AT43<0,AQ43=0),(AT43-AQ43)/AT43,IF(AND(AT43>0,AQ43>0),(AQ43-AT43)/AT43,IF(AND(AT43=0,AQ43=0),"",(AQ43-AT43)/AT43)))) -> 1 | AW43: =+AQ43/6 -> 997.48167 | AX43: =IF(AND(AW4=0,AW43>=0), "",AW43/AW4) -> 0.036599851 | AY43: =IF(AND(AW124=0,AW43>=0),"",AW43/AW124) -> 0.078504404 | AZ43: =+AT43/6 -> 0 | BA43: =IF(AND(AZ4=0,AZ43>=0), "",AZ43/AZ4) | BB43: =IF(AND(AZ43=0,AW43>0),100%,IF(AND(AZ43<0,AW43=0),(AZ43-AW43)/AZ43,IF(AND(AZ43>0,AW43>0),(AW43-AZ43)/AZ43,IF(AND(AZ43=0,AW43=0),"",(AW43-AZ43)/AZ43)))) -> 1 | BC43: =+'N EERR RODEO'!I42 -> 0 | BD43: =IF(AND(BC4=0,BC43>=0), "",BC43/BC4) | BE43: =IF(AND(BC124=0,BC43>=0),"",BC43/BC124) | BF43: =IF(AND(AM43=0,BC43>0),100%,IF(AND(AM43<0,BC43=0),(AM43-BC43)/AM43,IF(AND(AM43>0,BC43>0),(BC43-AM43)/AM43,IF(AND(AM43=0,BC43=0),"",(BC43-AM43)/AM43)))) | BG43: =+AQ43+BC43 -> 5984.89 | BH43: =IF(AND(BG4=0,BG43>=0), "",BG43/BG4) -> 0.036599851 | BI43: =IF(AND(BG124=0,BG43>=0),"",BG43/BG124) -> 0.078504404 | BJ43: =+'N EERR RODEO'!J42 -> 0 | BK43: =IF(AND(BJ4=0,BJ43>=0), "",BJ43/BJ4) | BL43: =IF(AND(BJ124=0,BJ43>=0),"",BJ43/BJ124) | BM43: =IF(AND(BC43=0,BJ43>0),100%,IF(AND(BC43<0,BJ43=0),(BC43-BJ43)/BC43,IF(AND(BC43>0,BJ43>0),(BJ43-BC43)/BC43,IF(AND(BC43=0,BJ43=0),"",(BJ43-BC43)/BC43)))) | BN43: =+BG43+BJ43 -> 5984.89 | BO43: =IF(AND(BN4=0,BN43>=0), "",BN43/BN4) -> 0.036599851 | BP43: =IF(AND(BN124=0,BN43>=0),"",BN43/BN124) -> 0.078504404 | BQ43: =+'N EERR RODEO'!K42 -> 0 | BR43: =IF(AND(BQ4=0,BQ43>=0), "",BQ43/BQ4) | BS43: =IF(AND(BQ124=0,BQ43>=0),"",BQ43/BQ124) | BT43: =IF(AND(BJ43=0,BQ43>0),100%,IF(AND(BJ43<0,BQ43=0),(BJ43-BQ43)/BJ43,IF(AND(BJ43>0,BQ43>0),(BQ43-BJ43)/BJ43,IF(AND(BJ43=0,BQ43=0),"",(BQ43-BJ43)/BJ43)))) | BU43: =+BN43+BQ43 -> 5984.89 | BV43: =IF(AND(BU4=0,BU43>=0), "",BU43/BU4) -> 0.036599851 | BW43: =IF(AND(BU124=0,BU43>=0),"",BU43/BU124) -> 0.078504404 | BX43: =+AZ43*9 -> 0 | BY43: =IF(AND(BX4=0,BX43>=0), "",BX43/BX4) | BZ43: =IF(AND(BX43=0,BU43>0),100%,IF(AND(BX43<0,BU43=0),(BX43-BU43)/BX43,IF(AND(BX43>0,BU43>0),(BU43-BX43)/BX43,IF(AND(BX43=0,BU43=0),"",(BU43-BX43)/BX43)))) -> 1 | CA43: =+'N EERR RODEO'!L42 -> 0 | CB43: =IF(AND(CA4=0,CA43>=0), "",CA43/CA4) | CC43: =IF(AND(CA124=0,CA43>=0),"",CA43/CA124) | CD43: =IF(AND(BQ43=0,CA43>0),100%,IF(AND(BQ43<0,CA43=0),(BQ43-CA43)/BQ43,IF(AND(BQ43>0,CA43>0),(CA43-BQ43)/BQ43,IF(AND(BQ43=0,CA43=0),"",(CA43-BQ43)/BQ43)))) | CE43: =+BU43+CA43 -> 5984.89 | CF43: =IF(AND(CE4=0,CE43>=0), "",CE43/CE4) -> 0.036599851 | CG43: =IF(AND(CE124=0,CE43>=0),"",CE43/CE124) -> 0.078504404 | CH43: =+'N EERR RODEO'!M42 -> 0 | CI43: =IF(AND(CH4=0,CH43>=0), "",CH43/CH4) | CJ43: =IF(AND(CH124=0,CH43>=0),"",CH43/CH124) | CK43: =IF(AND(CA43=0,CH43>0),100%,IF(AND(CA43<0,CH43=0),(CA43-CH43)/CA43,IF(AND(CA43>0,CH43>0),(CH43-CA43)/CA43,IF(AND(CA43=0,CH43=0),"",(CH43-CA43)/CA43)))) | CL43: =+CE43+CH43 -> 5984.89 | CM43: =IF(AND(CL4=0,CL43>=0), "",CL43/CL4) -> 0.036599851 | CN43: =IF(AND(CL124=0,CL43>=0),"",CL43/CL124) -> 0.078504404 | CO43: =+'N EERR RODEO'!N42 -> 0 | CP43: =IF(AND(CO4=0,CO43>=0), "",CO43/CO4) | CQ43: =IF(AND(CO124=0,CO43>=0),"",CO43/CO124) | CR43: =IF(AND(CH43=0,CO43>0),100%,IF(AND(CH43<0,CO43=0),(CH43-CO43)/CH43,IF(AND(CH43>0,CO43>0),(CO43-CH43)/CH43,IF(AND(CH43=0,CO43=0),"",(CO43-CH43)/CH43)))) | CS43: =+CL43+CO43 -> 5984.89 | CT43: =IF(AND(CS4=0,CS43>=0), "",CS43/CS4) -> 0.036599851 | CU43: =IF(AND(CS124=0,CS43>=0),"",CS43/CS124) -> 0.078504404 | CV43: =+AZ43*12 -> 0 | CW43: =IF(AND(CV4=0,CV43>=0), "",CV43/CV4) | CX43: =IF(AND(CV43=0,CS43>0),100%,IF(AND(CV43<0,CS43=0),(CV43-CS43)/CV43,IF(AND(CV43>0,CS43>0),(CS43-CV43)/CV43,IF(AND(CV43=0,CS43=0),"",(CS43-CV43)/CV43)))) -> 1
A44: Gastos de asistencia outsorsing | B44: =+'N EERR RODEO'!B43 -> 0 | C44: =IF(AND(B4=0,B44>=0), "",B44/B4) | D44: =IF(AND(B124=0,B44>=0),"",B44/B124) | E44: =+'N EERR RODEO'!C43 -> 965.72 | F44: =IF(AND(E4=0,E44>=0), "",E44/E4) -> 0.020147276 | G44: =IF(AND(E124=0,E44>=0),"",E44/E124) -> 0.031187661 | H44: =+'N EERR RODEO'!D43 -> 1362.08 | I44: =IF(AND(H4=0,H44>=0), "",H44/H4) -> 0.026456868 | J44: =IF(AND(H124=0,H44>=0),"",H44/H124) -> 0.07044747 | K44: =IF(AND(E44=0,H44>0),100%,IF(AND(E44<0,H44=0),(E44-H44)/E44,IF(AND(E44>0,H44>0),(H44-E44)/E44,IF(AND(E44=0,H44=0),"",(H44-E44)/E44)))) -> 0.41042952 | L44: =+E44+H44 -> 2327.8 | M44: =IF(AND(L4=0,L44>=0), "",L44/L4) -> 0.023414726 | N44: =IF(AND(L124=0,L44>=0),"",L44/L124) -> 0.04627879 | O44: =+'N EERR RODEO'!E43 -> 1434.12 | P44: =IF(AND(O4=0,O44>=0), "",O44/O4) -> 0.02237101 | Q44: =IF(AND(O124=0,O44>=0),"",O44/O124) -> 0.055292738 | R44: =IF(AND(H44=0,O44>0),100%,IF(AND(H44<0,O44=0),(H44-O44)/H44,IF(AND(H44>0,O44>0),(O44-H44)/H44,IF(AND(H44=0,O44=0),"",(O44-H44)/H44)))) -> 0.052889698 | S44: =+L44+O44 -> 3761.92 | T44: =IF(AND(S4=0,S44>=0), "",S44/S4) -> 0.023005554 | U44: =IF(AND(S124=0,S44>=0),"",S44/S124) -> 0.049345483 | W44: =IF(AND(V4=0,V44>=0), "",V44/V4) | X44: =IF(AND(V44=0,S44>0),100%,IF(AND(V44<0,S44=0),(V44-S44)/V44,IF(AND(V44>0,S44>0),(S44-V44)/V44,IF(AND(V44=0,S44=0),"",(S44-V44)/V44)))) -> 1 | Y44: =+'N EERR RODEO'!F43 -> 0 | Z44: =IF(AND(Y4=0,Y44>=0), "",Y44/Y4) | AA44: =IF(AND(Y124=0,Y44>=0),"",Y44/Y124) | AB44: =IF(AND(O44=0,Y44>0),100%,IF(AND(O44<0,Y44=0),(O44-Y44)/O44,IF(AND(O44>0,Y44>0),(Y44-O44)/O44,IF(AND(O44=0,Y44=0),"",(Y44-O44)/O44)))) -> -1 | AC44: =+S44+Y44 -> 3761.92 | AD44: =IF(AND(AC4=0,AC44>=0), "",AC44/AC4) -> 0.023005554 | AE44: =IF(AND(AC124=0,AC44>=0),"",AC44/AC124) -> 0.049345483 | AF44: =+'N EERR RODEO'!G43 -> 0 | AG44: =IF(AND(AF4=0,AF44>=0), "",AF44/AF4) | AH44: =IF(AND(AF124=0,AF44>=0),"",AF44/AF124) | AI44: =IF(AND(Y44=0,AF44>0),100%,IF(AND(Y44<0,AF44=0),(Y44-AF44)/Y44,IF(AND(Y44>0,AF44>0),(AF44-Y44)/Y44,IF(AND(Y44=0,AF44=0),"",(AF44-Y44)/Y44)))) | AJ44: =+AC44+AF44 -> 3761.92 | AK44: =IF(AND(AJ4=0,AJ44>=0), "",AJ44/AJ4) -> 0.023005554 | AL44: =IF(AND(AJ124=0,AJ44>=0),"",AJ44/AJ124) -> 0.049345483 | AM44: =+'N EERR RODEO'!H43 -> 0 | AN44: =IF(AND(AM4=0,AM44>=0), "",AM44/AM4) | AO44: =IF(AND(AM124=0,AM44>=0),"",AM44/AM124) | AP44: =IF(AND(AF44=0,AM44>0),100%,IF(AND(AF44<0,AM44=0),(AF44-AM44)/AF44,IF(AND(AF44>0,AM44>0),(AM44-AF44)/AF44,IF(AND(AF44=0,AM44=0),"",(AM44-AF44)/AF44)))) | AQ44: =+AJ44+AM44 -> 3761.92 | AR44: =IF(AND(AQ4=0,AQ44>=0), "",AQ44/AQ4) -> 0.023005554 | AS44: =IF(AND(AQ124=0,AQ44>=0),"",AQ44/AQ124) -> 0.049345483 | AT44: =+V44*2 -> 0 | AU44: =IF(AND(AT4=0,AT44>=0), "",AT44/AT4) | AV44: =IF(AND(AT44=0,AQ44>0),100%,IF(AND(AT44<0,AQ44=0),(AT44-AQ44)/AT44,IF(AND(AT44>0,AQ44>0),(AQ44-AT44)/AT44,IF(AND(AT44=0,AQ44=0),"",(AQ44-AT44)/AT44)))) -> 1 | AW44: =+AQ44/6 -> 626.98667 | AX44: =IF(AND(AW4=0,AW44>=0), "",AW44/AW4) -> 0.023005554 | AY44: =IF(AND(AW124=0,AW44>=0),"",AW44/AW124) -> 0.049345483 | AZ44: =+AT44/6 -> 0 | BA44: =IF(AND(AZ4=0,AZ44>=0), "",AZ44/AZ4) | BB44: =IF(AND(AZ44=0,AW44>0),100%,IF(AND(AZ44<0,AW44=0),(AZ44-AW44)/AZ44,IF(AND(AZ44>0,AW44>0),(AW44-AZ44)/AZ44,IF(AND(AZ44=0,AW44=0),"",(AW44-AZ44)/AZ44)))) -> 1 | BC44: =+'N EERR RODEO'!I43 -> 0 | BD44: =IF(AND(BC4=0,BC44>=0), "",BC44/BC4) | BE44: =IF(AND(BC124=0,BC44>=0),"",BC44/BC124) | BF44: =IF(AND(AM44=0,BC44>0),100%,IF(AND(AM44<0,BC44=0),(AM44-BC44)/AM44,IF(AND(AM44>0,BC44>0),(BC44-AM44)/AM44,IF(AND(AM44=0,BC44=0),"",(BC44-AM44)/AM44)))) | BG44: =+AQ44+BC44 -> 3761.92 | BH44: =IF(AND(BG4=0,BG44>=0), "",BG44/BG4) -> 0.023005554 | BI44: =IF(AND(BG124=0,BG44>=0),"",BG44/BG124) -> 0.049345483 | BJ44: =+'N EERR RODEO'!J43 -> 0 | BK44: =IF(AND(BJ4=0,BJ44>=0), "",BJ44/BJ4) | BL44: =IF(AND(BJ124=0,BJ44>=0),"",BJ44/BJ124) | BM44: =IF(AND(BC44=0,BJ44>0),100%,IF(AND(BC44<0,BJ44=0),(BC44-BJ44)/BC44,IF(AND(BC44>0,BJ44>0),(BJ44-BC44)/BC44,IF(AND(BC44=0,BJ44=0),"",(BJ44-BC44)/BC44)))) | BN44: =+BG44+BJ44 -> 3761.92 | BO44: =IF(AND(BN4=0,BN44>=0), "",BN44/BN4) -> 0.023005554 | BP44: =IF(AND(BN124=0,BN44>=0),"",BN44/BN124) -> 0.049345483 | BQ44: =+'N EERR RODEO'!K43 -> 0 | BR44: =IF(AND(BQ4=0,BQ44>=0), "",BQ44/BQ4) | BS44: =IF(AND(BQ124=0,BQ44>=0),"",BQ44/BQ124) | BT44: =IF(AND(BJ44=0,BQ44>0),100%,IF(AND(BJ44<0,BQ44=0),(BJ44-BQ44)/BJ44,IF(AND(BJ44>0,BQ44>0),(BQ44-BJ44)/BJ44,IF(AND(BJ44=0,BQ44=0),"",(BQ44-BJ44)/BJ44)))) | BU44: =+BN44+BQ44 -> 3761.92 | BV44: =IF(AND(BU4=0,BU44>=0), "",BU44/BU4) -> 0.023005554 | BW44: =IF(AND(BU124=0,BU44>=0),"",BU44/BU124) -> 0.049345483 | BX44: =+AZ44*9 -> 0 | BY44: =IF(AND(BX4=0,BX44>=0), "",BX44/BX4) | BZ44: =IF(AND(BX44=0,BU44>0),100%,IF(AND(BX44<0,BU44=0),(BX44-BU44)/BX44,IF(AND(BX44>0,BU44>0),(BU44-BX44)/BX44,IF(AND(BX44=0,BU44=0),"",(BU44-BX44)/BX44)))) -> 1 | CA44: =+'N EERR RODEO'!L43 -> 0 | CB44: =IF(AND(CA4=0,CA44>=0), "",CA44/CA4) | CC44: =IF(AND(CA124=0,CA44>=0),"",CA44/CA124) | CD44: =IF(AND(BQ44=0,CA44>0),100%,IF(AND(BQ44<0,CA44=0),(BQ44-CA44)/BQ44,IF(AND(BQ44>0,CA44>0),(CA44-BQ44)/BQ44,IF(AND(BQ44=0,CA44=0),"",(CA44-BQ44)/BQ44)))) | CE44: =+BU44+CA44 -> 3761.92 | CF44: =IF(AND(CE4=0,CE44>=0), "",CE44/CE4) -> 0.023005554 | CG44: =IF(AND(CE124=0,CE44>=0),"",CE44/CE124) -> 0.049345483 | CH44: =+'N EERR RODEO'!M43 -> 0 | CI44: =IF(AND(CH4=0,CH44>=0), "",CH44/CH4) | CJ44: =IF(AND(CH124=0,CH44>=0),"",CH44/CH124) | CK44: =IF(AND(CA44=0,CH44>0),100%,IF(AND(CA44<0,CH44=0),(CA44-CH44)/CA44,IF(AND(CA44>0,CH44>0),(CH44-CA44)/CA44,IF(AND(CA44=0,CH44=0),"",(CH44-CA44)/CA44)))) | CL44: =+CE44+CH44 -> 3761.92 | CM44: =IF(AND(CL4=0,CL44>=0), "",CL44/CL4) -> 0.023005554 | CN44: =IF(AND(CL124=0,CL44>=0),"",CL44/CL124) -> 0.049345483 | CO44: =+'N EERR RODEO'!N43 -> 0 | CP44: =IF(AND(CO4=0,CO44>=0), "",CO44/CO4) | CQ44: =IF(AND(CO124=0,CO44>=0),"",CO44/CO124) | CR44: =IF(AND(CH44=0,CO44>0),100%,IF(AND(CH44<0,CO44=0),(CH44-CO44)/CH44,IF(AND(CH44>0,CO44>0),(CO44-CH44)/CH44,IF(AND(CH44=0,CO44=0),"",(CO44-CH44)/CH44)))) | CS44: =+CL44+CO44 -> 3761.92 | CT44: =IF(AND(CS4=0,CS44>=0), "",CS44/CS4) -> 0.023005554 | CU44: =IF(AND(CS124=0,CS44>=0),"",CS44/CS124) -> 0.049345483 | CV44: =+AZ44*12 -> 0 | CW44: =IF(AND(CV4=0,CV44>=0), "",CV44/CV4) | CX44: =IF(AND(CV44=0,CS44>0),100%,IF(AND(CV44<0,CS44=0),(CV44-CS44)/CV44,IF(AND(CV44>0,CS44>0),(CS44-CV44)/CV44,IF(AND(CV44=0,CS44=0),"",(CS44-CV44)/CV44)))) -> 1
A45: Gastos de alquiler de bienes muebles | B45: =+'N EERR RODEO'!B44 -> 0 | C45: =IF(AND(B4=0,B45>=0), "",B45/B4) | D45: =IF(AND(B124=0,B45>=0),"",B45/B124) | E45: =+'N EERR RODEO'!C44 -> 122 | F45: =IF(AND(E4=0,E45>=0), "",E45/E4) -> 0.0025452178 | G45: =IF(AND(E124=0,E45>=0),"",E45/E124) -> 0.0039399564 | H45: =+'N EERR RODEO'!D44 -> 119.11 | I45: =IF(AND(H4=0,H45>=0), "",H45/H4) -> 0.0023135774 | J45: =IF(AND(H124=0,H45>=0),"",H45/H124) -> 0.0061604298 | K45: =IF(AND(E45=0,H45>0),100%,IF(AND(E45<0,H45=0),(E45-H45)/E45,IF(AND(E45>0,H45>0),(H45-E45)/E45,IF(AND(E45=0,H45=0),"",(H45-E45)/E45)))) -> -0.023688525 | L45: =+E45+H45 -> 241.11 | M45: =IF(AND(L4=0,L45>=0), "",L45/L4) -> 0.0024252618 | N45: =IF(AND(L124=0,L45>=0),"",L45/L124) -> 0.004793487 | O45: =+'N EERR RODEO'!E44 -> 122 | P45: =IF(AND(O4=0,O45>=0), "",O45/O4) -> 0.0019030927 | Q45: =IF(AND(O124=0,O45>=0),"",O45/O124) -> 0.0047037305 | R45: =IF(AND(H45=0,O45>0),100%,IF(AND(H45<0,O45=0),(H45-O45)/H45,IF(AND(H45>0,O45>0),(O45-H45)/H45,IF(AND(H45=0,O45=0),"",(O45-H45)/H45)))) -> 0.024263286 | S45: =+L45+O45 -> 363.11 | T45: =IF(AND(S4=0,S45>=0), "",S45/S4) -> 0.0022205541 | U45: =IF(AND(S124=0,S45>=0),"",S45/S124) -> 0.0047629504 | W45: =IF(AND(V4=0,V45>=0), "",V45/V4) | X45: =IF(AND(V45=0,S45>0),100%,IF(AND(V45<0,S45=0),(V45-S45)/V45,IF(AND(V45>0,S45>0),(S45-V45)/V45,IF(AND(V45=0,S45=0),"",(S45-V45)/V45)))) -> 1 | Y45: =+'N EERR RODEO'!F44 -> 0 | Z45: =IF(AND(Y4=0,Y45>=0), "",Y45/Y4) | AA45: =IF(AND(Y124=0,Y45>=0),"",Y45/Y124) | AB45: =IF(AND(O45=0,Y45>0),100%,IF(AND(O45<0,Y45=0),(O45-Y45)/O45,IF(AND(O45>0,Y45>0),(Y45-O45)/O45,IF(AND(O45=0,Y45=0),"",(Y45-O45)/O45)))) -> -1 | AC45: =+S45+Y45 -> 363.11 | AD45: =IF(AND(AC4=0,AC45>=0), "",AC45/AC4) -> 0.0022205541 | AE45: =IF(AND(AC124=0,AC45>=0),"",AC45/AC124) -> 0.0047629504 | AF45: =+'N EERR RODEO'!G44 -> 0 | AG45: =IF(AND(AF4=0,AF45>=0), "",AF45/AF4) | AH45: =IF(AND(AF124=0,AF45>=0),"",AF45/AF124) | AI45: =IF(AND(Y45=0,AF45>0),100%,IF(AND(Y45<0,AF45=0),(Y45-AF45)/Y45,IF(AND(Y45>0,AF45>0),(AF45-Y45)/Y45,IF(AND(Y45=0,AF45=0),"",(AF45-Y45)/Y45)))) | AJ45: =+AC45+AF45 -> 363.11 | AK45: =IF(AND(AJ4=0,AJ45>=0), "",AJ45/AJ4) -> 0.0022205541 | AL45: =IF(AND(AJ124=0,AJ45>=0),"",AJ45/AJ124) -> 0.0047629504 | AM45: =+'N EERR RODEO'!H44 -> 0 | AN45: =IF(AND(AM4=0,AM45>=0), "",AM45/AM4) | AO45: =IF(AND(AM124=0,AM45>=0),"",AM45/AM124) | AP45: =IF(AND(AF45=0,AM45>0),100%,IF(AND(AF45<0,AM45=0),(AF45-AM45)/AF45,IF(AND(AF45>0,AM45>0),(AM45-AF45)/AF45,IF(AND(AF45=0,AM45=0),"",(AM45-AF45)/AF45)))) | AQ45: =+AJ45+AM45 -> 363.11 | AR45: =IF(AND(AQ4=0,AQ45>=0), "",AQ45/AQ4) -> 0.0022205541 | AS45: =IF(AND(AQ124=0,AQ45>=0),"",AQ45/AQ124) -> 0.0047629504 | AT45: =+V45*2 -> 0 | AU45: =IF(AND(AT4=0,AT45>=0), "",AT45/AT4) | AV45: =IF(AND(AT45=0,AQ45>0),100%,IF(AND(AT45<0,AQ45=0),(AT45-AQ45)/AT45,IF(AND(AT45>0,AQ45>0),(AQ45-AT45)/AT45,IF(AND(AT45=0,AQ45=0),"",(AQ45-AT45)/AT45)))) -> 1 | AW45: =+AQ45/6 -> 60.518333 | AX45: =IF(AND(AW4=0,AW45>=0), "",AW45/AW4) -> 0.0022205541 | AY45: =IF(AND(AW124=0,AW45>=0),"",AW45/AW124) -> 0.0047629504 | AZ45: =+AT45/6 -> 0 | BA45: =IF(AND(AZ4=0,AZ45>=0), "",AZ45/AZ4) | BB45: =IF(AND(AZ45=0,AW45>0),100%,IF(AND(AZ45<0,AW45=0),(AZ45-AW45)/AZ45,IF(AND(AZ45>0,AW45>0),(AW45-AZ45)/AZ45,IF(AND(AZ45=0,AW45=0),"",(AW45-AZ45)/AZ45)))) -> 1 | BC45: =+'N EERR RODEO'!I44 -> 0 | BD45: =IF(AND(BC4=0,BC45>=0), "",BC45/BC4) | BE45: =IF(AND(BC124=0,BC45>=0),"",BC45/BC124) | BF45: =IF(AND(AM45=0,BC45>0),100%,IF(AND(AM45<0,BC45=0),(AM45-BC45)/AM45,IF(AND(AM45>0,BC45>0),(BC45-AM45)/AM45,IF(AND(AM45=0,BC45=0),"",(BC45-AM45)/AM45)))) | BG45: =+AQ45+BC45 -> 363.11 | BH45: =IF(AND(BG4=0,BG45>=0), "",BG45/BG4) -> 0.0022205541 | BI45: =IF(AND(BG124=0,BG45>=0),"",BG45/BG124) -> 0.0047629504 | BJ45: =+'N EERR RODEO'!J44 -> 0 | BK45: =IF(AND(BJ4=0,BJ45>=0), "",BJ45/BJ4) | BL45: =IF(AND(BJ124=0,BJ45>=0),"",BJ45/BJ124) | BM45: =IF(AND(BC45=0,BJ45>0),100%,IF(AND(BC45<0,BJ45=0),(BC45-BJ45)/BC45,IF(AND(BC45>0,BJ45>0),(BJ45-BC45)/BC45,IF(AND(BC45=0,BJ45=0),"",(BJ45-BC45)/BC45)))) | BN45: =+BG45+BJ45 -> 363.11 | BO45: =IF(AND(BN4=0,BN45>=0), "",BN45/BN4) -> 0.0022205541 | BP45: =IF(AND(BN124=0,BN45>=0),"",BN45/BN124) -> 0.0047629504 | BQ45: =+'N EERR RODEO'!K44 -> 0 | BR45: =IF(AND(BQ4=0,BQ45>=0), "",BQ45/BQ4) | BS45: =IF(AND(BQ124=0,BQ45>=0),"",BQ45/BQ124) | BT45: =IF(AND(BJ45=0,BQ45>0),100%,IF(AND(BJ45<0,BQ45=0),(BJ45-BQ45)/BJ45,IF(AND(BJ45>0,BQ45>0),(BQ45-BJ45)/BJ45,IF(AND(BJ45=0,BQ45=0),"",(BQ45-BJ45)/BJ45)))) | BU45: =+BN45+BQ45 -> 363.11 | BV45: =IF(AND(BU4=0,BU45>=0), "",BU45/BU4) -> 0.0022205541 | BW45: =IF(AND(BU124=0,BU45>=0),"",BU45/BU124) -> 0.0047629504 | BX45: =+AZ45*9 -> 0 | BY45: =IF(AND(BX4=0,BX45>=0), "",BX45/BX4) | BZ45: =IF(AND(BX45=0,BU45>0),100%,IF(AND(BX45<0,BU45=0),(BX45-BU45)/BX45,IF(AND(BX45>0,BU45>0),(BU45-BX45)/BX45,IF(AND(BX45=0,BU45=0),"",(BU45-BX45)/BX45)))) -> 1 | CA45: =+'N EERR RODEO'!L44 -> 0 | CB45: =IF(AND(CA4=0,CA45>=0), "",CA45/CA4) | CC45: =IF(AND(CA124=0,CA45>=0),"",CA45/CA124) | CD45: =IF(AND(BQ45=0,CA45>0),100%,IF(AND(BQ45<0,CA45=0),(BQ45-CA45)/BQ45,IF(AND(BQ45>0,CA45>0),(CA45-BQ45)/BQ45,IF(AND(BQ45=0,CA45=0),"",(CA45-BQ45)/BQ45)))) | CE45: =+BU45+CA45 -> 363.11 | CF45: =IF(AND(CE4=0,CE45>=0), "",CE45/CE4) -> 0.0022205541 | CG45: =IF(AND(CE124=0,CE45>=0),"",CE45/CE124) -> 0.0047629504 | CH45: =+'N EERR RODEO'!M44 -> 0 | CI45: =IF(AND(CH4=0,CH45>=0), "",CH45/CH4) | CJ45: =IF(AND(CH124=0,CH45>=0),"",CH45/CH124) | CK45: =IF(AND(CA45=0,CH45>0),100%,IF(AND(CA45<0,CH45=0),(CA45-CH45)/CA45,IF(AND(CA45>0,CH45>0),(CH45-CA45)/CA45,IF(AND(CA45=0,CH45=0),"",(CH45-CA45)/CA45)))) | CL45: =+CE45+CH45 -> 363.11 | CM45: =IF(AND(CL4=0,CL45>=0), "",CL45/CL4) -> 0.0022205541 | CN45: =IF(AND(CL124=0,CL45>=0),"",CL45/CL124) -> 0.0047629504 | CO45: =+'N EERR RODEO'!N44 -> 0 | CP45: =IF(AND(CO4=0,CO45>=0), "",CO45/CO4) | CQ45: =IF(AND(CO124=0,CO45>=0),"",CO45/CO124) | CR45: =IF(AND(CH45=0,CO45>0),100%,IF(AND(CH45<0,CO45=0),(CH45-CO45)/CH45,IF(AND(CH45>0,CO45>0),(CO45-CH45)/CH45,IF(AND(CH45=0,CO45=0),"",(CO45-CH45)/CH45)))) | CS45: =+CL45+CO45 -> 363.11 | CT45: =IF(AND(CS4=0,CS45>=0), "",CS45/CS4) -> 0.0022205541 | CU45: =IF(AND(CS124=0,CS45>=0),"",CS45/CS124) -> 0.0047629504 | CV45: =+AZ45*12 -> 0 | CW45: =IF(AND(CV4=0,CV45>=0), "",CV45/CV4) | CX45: =IF(AND(CV45=0,CS45>0),100%,IF(AND(CV45<0,CS45=0),(CV45-CS45)/CV45,IF(AND(CV45>0,CS45>0),(CS45-CV45)/CV45,IF(AND(CV45=0,CS45=0),"",(CS45-CV45)/CV45)))) -> 1
A46: Gastos de artículos de oficina | B46: =+'N EERR RODEO'!B45 -> 0 | C46: =IF(AND(B4=0,B46>=0), "",B46/B4) | D46: =IF(AND(B124=0,B46>=0),"",B46/B124) | E46: =+'N EERR RODEO'!C45 -> 34.95 | F46: =IF(AND(E4=0,E46>=0), "",E46/E4) -> 0.00072914231 | G46: =IF(AND(E124=0,E46>=0),"",E46/E124) -> 0.0011287006 | H46: =+'N EERR RODEO'!D45 -> 0 | I46: =IF(AND(H4=0,H46>=0), "",H46/H4) -> 0 | J46: =IF(AND(H124=0,H46>=0),"",H46/H124) -> 0 | K46: =IF(AND(E46=0,H46>0),100%,IF(AND(E46<0,H46=0),(E46-H46)/E46,IF(AND(E46>0,H46>0),(H46-E46)/E46,IF(AND(E46=0,H46=0),"",(H46-E46)/E46)))) -> -1 | L46: =+E46+H46 -> 34.95 | M46: =IF(AND(L4=0,L46>=0), "",L46/L4) -> 0.00035155282 | N46: =IF(AND(L124=0,L46>=0),"",L46/L124) -> 0.00069483792 | O46: =+'N EERR RODEO'!E45 -> 0 | P46: =IF(AND(O4=0,O46>=0), "",O46/O4) -> 0 | Q46: =IF(AND(O124=0,O46>=0),"",O46/O124) -> 0 | R46: =IF(AND(H46=0,O46>0),100%,IF(AND(H46<0,O46=0),(H46-O46)/H46,IF(AND(H46>0,O46>0),(O46-H46)/H46,IF(AND(H46=0,O46=0),"",(O46-H46)/H46)))) | S46: =+L46+O46 -> 34.95 | T46: =IF(AND(S4=0,S46>=0), "",S46/S4) -> 0.00021373238 | U46: =IF(AND(S124=0,S46>=0),"",S46/S124) -> 0.00045844266 | W46: =IF(AND(V4=0,V46>=0), "",V46/V4) | X46: =IF(AND(V46=0,S46>0),100%,IF(AND(V46<0,S46=0),(V46-S46)/V46,IF(AND(V46>0,S46>0),(S46-V46)/V46,IF(AND(V46=0,S46=0),"",(S46-V46)/V46)))) -> 1 | Y46: =+'N EERR RODEO'!F45 -> 0 | Z46: =IF(AND(Y4=0,Y46>=0), "",Y46/Y4) | AA46: =IF(AND(Y124=0,Y46>=0),"",Y46/Y124) | AB46: =IF(AND(O46=0,Y46>0),100%,IF(AND(O46<0,Y46=0),(O46-Y46)/O46,IF(AND(O46>0,Y46>0),(Y46-O46)/O46,IF(AND(O46=0,Y46=0),"",(Y46-O46)/O46)))) | AC46: =+S46+Y46 -> 34.95 | AD46: =IF(AND(AC4=0,AC46>=0), "",AC46/AC4) -> 0.00021373238 | AE46: =IF(AND(AC124=0,AC46>=0),"",AC46/AC124) -> 0.00045844266 | AF46: =+'N EERR RODEO'!G45 -> 0 | AG46: =IF(AND(AF4=0,AF46>=0), "",AF46/AF4) | AH46: =IF(AND(AF124=0,AF46>=0),"",AF46/AF124) | AI46: =IF(AND(Y46=0,AF46>0),100%,IF(AND(Y46<0,AF46=0),(Y46-AF46)/Y46,IF(AND(Y46>0,AF46>0),(AF46-Y46)/Y46,IF(AND(Y46=0,AF46=0),"",(AF46-Y46)/Y46)))) | AJ46: =+AC46+AF46 -> 34.95 | AK46: =IF(AND(AJ4=0,AJ46>=0), "",AJ46/AJ4) -> 0.00021373238 | AL46: =IF(AND(AJ124=0,AJ46>=0),"",AJ46/AJ124) -> 0.00045844266 | AM46: =+'N EERR RODEO'!H45 -> 0 | AN46: =IF(AND(AM4=0,AM46>=0), "",AM46/AM4) | AO46: =IF(AND(AM124=0,AM46>=0),"",AM46/AM124) | AP46: =IF(AND(AF46=0,AM46>0),100%,IF(AND(AF46<0,AM46=0),(AF46-AM46)/AF46,IF(AND(AF46>0,AM46>0),(AM46-AF46)/AF46,IF(AND(AF46=0,AM46=0),"",(AM46-AF46)/AF46)))) | AQ46: =+AJ46+AM46 -> 34.95 | AR46: =IF(AND(AQ4=0,AQ46>=0), "",AQ46/AQ4) -> 0.00021373238 | AS46: =IF(AND(AQ124=0,AQ46>=0),"",AQ46/AQ124) -> 0.00045844266 | AT46: =+V46*2 -> 0 | AU46: =IF(AND(AT4=0,AT46>=0), "",AT46/AT4) | AV46: =IF(AND(AT46=0,AQ46>0),100%,IF(AND(AT46<0,AQ46=0),(AT46-AQ46)/AT46,IF(AND(AT46>0,AQ46>0),(AQ46-AT46)/AT46,IF(AND(AT46=0,AQ46=0),"",(AQ46-AT46)/AT46)))) -> 1 | AW46: =+AQ46/6 -> 5.825 | AX46: =IF(AND(AW4=0,AW46>=0), "",AW46/AW4) -> 0.00021373238 | AY46: =IF(AND(AW124=0,AW46>=0),"",AW46/AW124) -> 0.00045844266 | AZ46: =+AT46/6 -> 0 | BA46: =IF(AND(AZ4=0,AZ46>=0), "",AZ46/AZ4) | BB46: =IF(AND(AZ46=0,AW46>0),100%,IF(AND(AZ46<0,AW46=0),(AZ46-AW46)/AZ46,IF(AND(AZ46>0,AW46>0),(AW46-AZ46)/AZ46,IF(AND(AZ46=0,AW46=0),"",(AW46-AZ46)/AZ46)))) -> 1 | BC46: =+'N EERR RODEO'!I45 -> 0 | BD46: =IF(AND(BC4=0,BC46>=0), "",BC46/BC4) | BE46: =IF(AND(BC124=0,BC46>=0),"",BC46/BC124) | BF46: =IF(AND(AM46=0,BC46>0),100%,IF(AND(AM46<0,BC46=0),(AM46-BC46)/AM46,IF(AND(AM46>0,BC46>0),(BC46-AM46)/AM46,IF(AND(AM46=0,BC46=0),"",(BC46-AM46)/AM46)))) | BG46: =+AQ46+BC46 -> 34.95 | BH46: =IF(AND(BG4=0,BG46>=0), "",BG46/BG4) -> 0.00021373238 | BI46: =IF(AND(BG124=0,BG46>=0),"",BG46/BG124) -> 0.00045844266 | BJ46: =+'N EERR RODEO'!J45 -> 0 | BK46: =IF(AND(BJ4=0,BJ46>=0), "",BJ46/BJ4) | BL46: =IF(AND(BJ124=0,BJ46>=0),"",BJ46/BJ124) | BM46: =IF(AND(BC46=0,BJ46>0),100%,IF(AND(BC46<0,BJ46=0),(BC46-BJ46)/BC46,IF(AND(BC46>0,BJ46>0),(BJ46-BC46)/BC46,IF(AND(BC46=0,BJ46=0),"",(BJ46-BC46)/BC46)))) | BN46: =+BG46+BJ46 -> 34.95 | BO46: =IF(AND(BN4=0,BN46>=0), "",BN46/BN4) -> 0.00021373238 | BP46: =IF(AND(BN124=0,BN46>=0),"",BN46/BN124) -> 0.00045844266 | BQ46: =+'N EERR RODEO'!K45 -> 0 | BR46: =IF(AND(BQ4=0,BQ46>=0), "",BQ46/BQ4) | BS46: =IF(AND(BQ124=0,BQ46>=0),"",BQ46/BQ124) | BT46: =IF(AND(BJ46=0,BQ46>0),100%,IF(AND(BJ46<0,BQ46=0),(BJ46-BQ46)/BJ46,IF(AND(BJ46>0,BQ46>0),(BQ46-BJ46)/BJ46,IF(AND(BJ46=0,BQ46=0),"",(BQ46-BJ46)/BJ46)))) | BU46: =+BN46+BQ46 -> 34.95 | BV46: =IF(AND(BU4=0,BU46>=0), "",BU46/BU4) -> 0.00021373238 | BW46: =IF(AND(BU124=0,BU46>=0),"",BU46/BU124) -> 0.00045844266 | BX46: =+AZ46*9 -> 0 | BY46: =IF(AND(BX4=0,BX46>=0), "",BX46/BX4) | BZ46: =IF(AND(BX46=0,BU46>0),100%,IF(AND(BX46<0,BU46=0),(BX46-BU46)/BX46,IF(AND(BX46>0,BU46>0),(BU46-BX46)/BX46,IF(AND(BX46=0,BU46=0),"",(BU46-BX46)/BX46)))) -> 1 | CA46: =+'N EERR RODEO'!L45 -> 0 | CB46: =IF(AND(CA4=0,CA46>=0), "",CA46/CA4) | CC46: =IF(AND(CA124=0,CA46>=0),"",CA46/CA124) | CD46: =IF(AND(BQ46=0,CA46>0),100%,IF(AND(BQ46<0,CA46=0),(BQ46-CA46)/BQ46,IF(AND(BQ46>0,CA46>0),(CA46-BQ46)/BQ46,IF(AND(BQ46=0,CA46=0),"",(CA46-BQ46)/BQ46)))) | CE46: =+BU46+CA46 -> 34.95 | CF46: =IF(AND(CE4=0,CE46>=0), "",CE46/CE4) -> 0.00021373238 | CG46: =IF(AND(CE124=0,CE46>=0),"",CE46/CE124) -> 0.00045844266 | CH46: =+'N EERR RODEO'!M45 -> 0 | CI46: =IF(AND(CH4=0,CH46>=0), "",CH46/CH4) | CJ46: =IF(AND(CH124=0,CH46>=0),"",CH46/CH124) | CK46: =IF(AND(CA46=0,CH46>0),100%,IF(AND(CA46<0,CH46=0),(CA46-CH46)/CA46,IF(AND(CA46>0,CH46>0),(CH46-CA46)/CA46,IF(AND(CA46=0,CH46=0),"",(CH46-CA46)/CA46)))) | CL46: =+CE46+CH46 -> 34.95 | CM46: =IF(AND(CL4=0,CL46>=0), "",CL46/CL4) -> 0.00021373238 | CN46: =IF(AND(CL124=0,CL46>=0),"",CL46/CL124) -> 0.00045844266 | CO46: =+'N EERR RODEO'!N45 -> 0 | CP46: =IF(AND(CO4=0,CO46>=0), "",CO46/CO4) | CQ46: =IF(AND(CO124=0,CO46>=0),"",CO46/CO124) | CR46: =IF(AND(CH46=0,CO46>0),100%,IF(AND(CH46<0,CO46=0),(CH46-CO46)/CH46,IF(AND(CH46>0,CO46>0),(CO46-CH46)/CH46,IF(AND(CH46=0,CO46=0),"",(CO46-CH46)/CH46)))) | CS46: =+CL46+CO46 -> 34.95 | CT46: =IF(AND(CS4=0,CS46>=0), "",CS46/CS4) -> 0.00021373238 | CU46: =IF(AND(CS124=0,CS46>=0),"",CS46/CS124) -> 0.00045844266 | CV46: =+AZ46*12 -> 0 | CW46: =IF(AND(CV4=0,CV46>=0), "",CV46/CV4) | CX46: =IF(AND(CV46=0,CS46>0),100%,IF(AND(CV46<0,CS46=0),(CV46-CS46)/CV46,IF(AND(CV46>0,CS46>0),(CS46-CV46)/CV46,IF(AND(CV46=0,CS46=0),"",(CS46-CV46)/CV46)))) -> 1
