Workbook

Sheet ESF RODEO
A2: ESTADO DE SITUACIÓN FINANCIERA
A3: PARTIDAS | B3: =IF(ISBLANK(A2),"",YEAR(TODAY())-1) -> 2025 | C3: Q1 | D3: Vari Rel. | E3: Q2 | F3: Vari Rel. | G3: Q3 | H3: Vari Rel. | I3: Q4 | J3: Vari Rel. | K3: Vari Rel. actual vs anterior
A4: ACTIVOS CORRIENTES | B4: =+B5+B14+B20+B23+B29+B33+B38 -> 0 | C4: =+C5+C14+C20+C23+C29+C33+C38 -> 85150 | D4: =IF(AND(B4=0,C4>0),100%,IF(AND(B4<0,C4>=0),(B4-C4)/B4,IF(AND(B4>0,C4>0),(C4-B4)/B4,IF(AND(B4=0,C4<=0),"",(C4-B4)/B4)))) -> 1 | E4: =+E5+E14+E20+E23+E29+E33+E38 -> 0 | F4: =IF(AND(C4=0,E4>0),100%,IF(AND(C4<0,E4>=0),(C4-E4)/C4,IF(AND(C4>0,E4>0),(E4-C4)/C4,IF(AND(C4=0,E4<=0),"",(E4-C4)/C4)))) -> -1 | G4: =+G5+G14+G20+G23+G29+G33+G38 -> 0 | H4: =IF(AND(E4=0,G4>0),100%,IF(AND(E4<0,G4>=0),(E4-G4)/E4,IF(AND(E4>0,G4>0),(G4-E4)/E4,IF(AND(E4=0,G4<=0),"",(G4-E4)/E4)))) | I4: =+I5+I14+I20+I23+I29+I33+I38 -> 0 | J4: =IF(AND(G4=0,I4>0),100%,IF(AND(G4<0,I4>=0),(G4-I4)/G4,IF(AND(G4>0,I4>0),(I4-G4)/G4,IF(AND(G4=0,I4<=0),"",(I4-G4)/G4)))) | K4: =IF(AND(B4=0,I4>0),100%,IF(AND(B4<0,I4>=0),(B4-I4)/B4,IF(AND(B4>0,I4>0),(I4-B4)/B4,IF(AND(B4=0,I4<=0),"",(I4-B4)/B4))))
A5: Efectivo y Equivalentes | B5: =+SUM(B6:B13) -> 0 | C5: =+SUM(C6:C13) -> 17700 | D5: =IF(AND(B5=0,C5>0),100%,IF(AND(B5<0,C5>=0),(B5-C5)/B5,IF(AND(B5>0,C5>0),(C5-B5)/B5,IF(AND(B5=0,C5<=0),"",(C5-B5)/B5)))) -> 1 | E5: =+SUM(E6:E13) -> 0 | F5: =IF(AND(C5=0,E5>0),100%,IF(AND(C5<0,E5>=0),(C5-E5)/C5,IF(AND(C5>0,E5>0),(E5-C5)/C5,IF(AND(C5=0,E5<=0),"",(E5-C5)/C5)))) -> -1 | G5: =+SUM(G6:G13) -> 0 | H5: =IF(AND(E5=0,G5>0),100%,IF(AND(E5<0,G5>=0),(E5-G5)/E5,IF(AND(E5>0,G5>0),(G5-E5)/E5,IF(AND(E5=0,G5<=0),"",(G5-E5)/E5)))) | I5: =+SUM(I6:I13) -> 0 | J5: =IF(AND(G5=0,I5>0),100%,IF(AND(G5<0,I5>=0),(G5-I5)/G5,IF(AND(G5>0,I5>0),(I5-G5)/G5,IF(AND(G5=0,I5<=0),"",(I5-G5)/G5)))) | K5: =IF(AND(B5=0,I5>0),100%,IF(AND(B5<0,I5>=0),(B5-I5)/B5,IF(AND(B5>0,I5>0),(I5-B5)/B5,IF(AND(B5=0,I5<=0),"",(I5-B5)/B5))))
A6: Cajas en Bs | B6: =+'N ESF'!B5 -> 0 | C6: =+'N ESF'!E5 -> 10 | D6: =IF(AND(B6=0,C6>0),100%,IF(AND(B6<0,C6>=0),(B6-C6)/B6,IF(AND(B6>0,C6>0),(C6-B6)/B6,IF(AND(B6=0,C6<=0),"",(C6-B6)/B6)))) -> 1 | E6: =+'N ESF'!H5 -> 0 | F6: =IF(AND(C6=0,E6>0),100%,IF(AND(C6<0,E6>=0),(C6-E6)/C6,IF(AND(C6>0,E6>0),(E6-C6)/C6,IF(AND(C6=0,E6<=0),"",(E6-C6)/C6)))) -> -1 | G6: =+'N ESF'!K5 -> 0 | H6: =IF(AND(E6=0,G6>0),100%,IF(AND(E6<0,G6>=0),(E6-G6)/E6,IF(AND(E6>0,G6>0),(G6-E6)/E6,IF(AND(E6=0,G6<=0),"",(G6-E6)/E6)))) | I6: =+'N ESF'!N5 -> 0 | J6: =IF(AND(G6=0,I6>0),100%,IF(AND(G6<0,I6>=0),(G6-I6)/G6,IF(AND(G6>0,I6>0),(I6-G6)/G6,IF(AND(G6=0,I6<=0),"",(I6-G6)/G6)))) | K6: =IF(AND(B6=0,I6>0),100%,IF(AND(B6<0,I6>=0),(B6-I6)/B6,IF(AND(B6>0,I6>0),(I6-B6)/B6,IF(AND(B6=0,I6<=0),"",(I6-B6)/B6))))
A7: Cajas en $ | B7: =+'N ESF'!B7 -> 0 | C7: =+'N ESF'!E7 -> 90 | D7: =IF(AND(B7=0,C7>0),100%,IF(AND(B7<0,C7>=0),(B7-C7)/B7,IF(AND(B7>0,C7>0),(C7-B7)/B7,IF(AND(B7=0,C7<=0),"",(C7-B7)/B7)))) -> 1 | E7: =+'N ESF'!H7 -> 0 | F7: =IF(AND(C7=0,E7>0),100%,IF(AND(C7<0,E7>=0),(C7-E7)/C7,IF(AND(C7>0,E7>0),(E7-C7)/C7,IF(AND(C7=0,E7<=0),"",(E7-C7)/C7)))) -> -1 | G7: =+'N ESF'!K7 -> 0 | H7: =IF(AND(E7=0,G7>0),100%,IF(AND(E7<0,G7>=0),(E7-G7)/E7,IF(AND(E7>0,G7>0),(G7-E7)/E7,IF(AND(E7=0,G7<=0),"",(G7-E7)/E7)))) | I7: =+'N ESF'!N7 -> 0 | J7: =IF(AND(G7=0,I7>0),100%,IF(AND(G7<0,I7>=0),(G7-I7)/G7,IF(AND(G7>0,I7>0),(I7-G7)/G7,IF(AND(G7=0,I7<=0),"",(I7-G7)/G7)))) | K7: =IF(AND(B7=0,I7>0),100%,IF(AND(B7<0,I7>=0),(B7-I7)/B7,IF(AND(B7>0,I7>0),(I7-B7)/B7,IF(AND(B7=0,I7<=0),"",(I7-B7)/B7))))
A8: Fondos en Bs | B8: =+'N ESF'!B11 -> 0 | C8: =+'N ESF'!E11 -> 350 | D8: =IF(AND(B8=0,C8>0),100%,IF(AND(B8<0,C8>=0),(B8-C8)/B8,IF(AND(B8>0,C8>0),(C8-B8)/B8,IF(AND(B8=0,C8<=0),"",(C8-B8)/B8)))) -> 1 | E8: =+'N ESF'!H11 -> 0 | F8: =IF(AND(C8=0,E8>0),100%,IF(AND(C8<0,E8>=0),(C8-E8)/C8,IF(AND(C8>0,E8>0),(E8-C8)/C8,IF(AND(C8=0,E8<=0),"",(E8-C8)/C8)))) -> -1 | G8: =+'N ESF'!K11 -> 0 | H8: =IF(AND(E8=0,G8>0),100%,IF(AND(E8<0,G8>=0),(E8-G8)/E8,IF(AND(E8>0,G8>0),(G8-E8)/E8,IF(AND(E8=0,G8<=0),"",(G8-E8)/E8)))) | I8: =+'N ESF'!N11 -> 0 | J8: =IF(AND(G8=0,I8>0),100%,IF(AND(G8<0,I8>=0),(G8-I8)/G8,IF(AND(G8>0,I8>0),(I8-G8)/G8,IF(AND(G8=0,I8<=0),"",(I8-G8)/G8)))) | K8: =IF(AND(B8=0,I8>0),100%,IF(AND(B8<0,I8>=0),(B8-I8)/B8,IF(AND(B8>0,I8>0),(I8-B8)/B8,IF(AND(B8=0,I8<=0),"",(I8-B8)/B8))))
A9: Fondos en $ | B9: =+'N ESF'!B17 -> 0 | C9: =+'N ESF'!E17 -> 3060 | D9: =IF(AND(B9=0,C9>0),100%,IF(AND(B9<0,C9>=0),(B9-C9)/B9,IF(AND(B9>0,C9>0),(C9-B9)/B9,IF(AND(B9=0,C9<=0),"",(C9-B9)/B9)))) -> 1 | E9: =+'N ESF'!H17 -> 0 | F9: =IF(AND(C9=0,E9>0),100%,IF(AND(C9<0,E9>=0),(C9-E9)/C9,IF(AND(C9>0,E9>0),(E9-C9)/C9,IF(AND(C9=0,E9<=0),"",(E9-C9)/C9)))) -> -1 | G9: =+'N ESF'!K17 -> 0 | H9: =IF(AND(E9=0,G9>0),100%,IF(AND(E9<0,G9>=0),(E9-G9)/E9,IF(AND(E9>0,G9>0),(G9-E9)/E9,IF(AND(E9=0,G9<=0),"",(G9-E9)/E9)))) | I9: =+'N ESF'!N17 -> 0 | J9: =IF(AND(G9=0,I9>0),100%,IF(AND(G9<0,I9>=0),(G9-I9)/G9,IF(AND(G9>0,I9>0),(I9-G9)/G9,IF(AND(G9=0,I9<=0),"",(I9-G9)/G9)))) | K9: =IF(AND(B9=0,I9>0),100%,IF(AND(B9<0,I9>=0),(B9-I9)/B9,IF(AND(B9>0,I9>0),(I9-B9)/B9,IF(AND(B9=0,I9<=0),"",(I9-B9)/B9))))
A10: Bancos en Bs | B10: =+'N ESF'!B35 -> 0 | C10: =+'N ESF'!E35 -> 3900 | D10: =IF(AND(B10=0,C10>0),100%,IF(AND(B10<0,C10>=0),(B10-C10)/B10,IF(AND(B10>0,C10>0),(C10-B10)/B10,IF(AND(B10=0,C10<=0),"",(C10-B10)/B10)))) -> 1 | E10: =+'N ESF'!H35 -> 0 | F10: =IF(AND(C10=0,E10>0),100%,IF(AND(C10<0,E10>=0),(C10-E10)/C10,IF(AND(C10>0,E10>0),(E10-C10)/C10,IF(AND(C10=0,E10<=0),"",(E10-C10)/C10)))) -> -1 | G10: =+'N ESF'!K35 -> 0 | H10: =IF(AND(E10=0,G10>0),100%,IF(AND(E10<0,G10>=0),(E10-G10)/E10,IF(AND(E10>0,G10>0),(G10-E10)/E10,IF(AND(E10=0,G10<=0),"",(G10-E10)/E10)))) | I10: =+'N ESF'!N35 -> 0 | J10: =IF(AND(G10=0,I10>0),100%,IF(AND(G10<0,I10>=0),(G10-I10)/G10,IF(AND(G10>0,I10>0),(I10-G10)/G10,IF(AND(G10=0,I10<=0),"",(I10-G10)/G10)))) | K10: =IF(AND(B10=0,I10>0),100%,IF(AND(B10<0,I10>=0),(B10-I10)/B10,IF(AND(B10>0,I10>0),(I10-B10)/B10,IF(AND(B10=0,I10<=0),"",(I10-B10)/B10))))
A11: Bancos en $ | B11: =+'N ESF'!B48 -> 0 | C11: =+'N ESF'!E48 -> 5850 | D11: =IF(AND(B11=0,C11>0),100%,IF(AND(B11<0,C11>=0),(B11-C11)/B11,IF(AND(B11>0,C11>0),(C11-B11)/B11,IF(AND(B11=0,C11<=0),"",(C11-B11)/B11)))) -> 1 | E11: =+'N ESF'!H48 -> 0 | F11: =IF(AND(C11=0,E11>0),100%,IF(AND(C11<0,E11>=0),(C11-E11)/C11,IF(AND(C11>0,E11>0),(E11-C11)/C11,IF(AND(C11=0,E11<=0),"",(E11-C11)/C11)))) -> -1 | G11: =+'N ESF'!K48 -> 0 | H11: =IF(AND(E11=0,G11>0),100%,IF(AND(E11<0,G11>=0),(E11-G11)/E11,IF(AND(E11>0,G11>0),(G11-E11)/E11,IF(AND(E11=0,G11<=0),"",(G11-E11)/E11)))) | I11: =+'N ESF'!N48 -> 0 | J11: =IF(AND(G11=0,I11>0),100%,IF(AND(G11<0,I11>=0),(G11-I11)/G11,IF(AND(G11>0,I11>0),(I11-G11)/G11,IF(AND(G11=0,I11<=0),"",(I11-G11)/G11)))) | K11: =IF(AND(B11=0,I11>0),100%,IF(AND(B11<0,I11>=0),(B11-I11)/B11,IF(AND(B11>0,I11>0),(I11-B11)/B11,IF(AND(B11=0,I11<=0),"",(I11-B11)/B11))))
A12: Bancos en transito en Bs | B12: =+'N ESF'!B62 -> 0 | C12: =+'N ESF'!E62 -> 2140 | D12: =IF(AND(B12=0,C12>0),100%,IF(AND(B12<0,C12>=0),(B12-C12)/B12,IF(AND(B12>0,C12>0),(C12-B12)/B12,IF(AND(B12=0,C12<=0),"",(C12-B12)/B12)))) -> 1 | E12: =+'N ESF'!H62 -> 0 | F12: =IF(AND(C12=0,E12>0),100%,IF(AND(C12<0,E12>=0),(C12-E12)/C12,IF(AND(C12>0,E12>0),(E12-C12)/C12,IF(AND(C12=0,E12<=0),"",(E12-C12)/C12)))) -> -1 | G12: =+'N ESF'!K62 -> 0 | H12: =IF(AND(E12=0,G12>0),100%,IF(AND(E12<0,G12>=0),(E12-G12)/E12,IF(AND(E12>0,G12>0),(G12-E12)/E12,IF(AND(E12=0,G12<=0),"",(G12-E12)/E12)))) | I12: =+'N ESF'!N62 -> 0 | J12: =IF(AND(G12=0,I12>0),100%,IF(AND(G12<0,I12>=0),(G12-I12)/G12,IF(AND(G12>0,I12>0),(I12-G12)/G12,IF(AND(G12=0,I12<=0),"",(I12-G12)/G12)))) | K12: =IF(AND(B12=0,I12>0),100%,IF(AND(B12<0,I12>=0),(B12-I12)/B12,IF(AND(B12>0,I12>0),(I12-B12)/B12,IF(AND(B12=0,I12<=0),"",(I12-B12)/B12))))
A13: Bancos en transito en $ | B13: =+'N ESF'!B67 -> 0 | C13: =+'N ESF'!E67 -> 2300 | D13: =IF(AND(B13=0,C13>0),100%,IF(AND(B13<0,C13>=0),(B13-C13)/B13,IF(AND(B13>0,C13>0),(C13-B13)/B13,IF(AND(B13=0,C13<=0),"",(C13-B13)/B13)))) -> 1 | E13: =+'N ESF'!H67 -> 0 | F13: =IF(AND(C13=0,E13>0),100%,IF(AND(C13<0,E13>=0),(C13-E13)/C13,IF(AND(C13>0,E13>0),(E13-C13)/C13,IF(AND(C13=0,E13<=0),"",(E13-C13)/C13)))) -> -1 | G13: =+'N ESF'!K67 -> 0 | H13: =IF(AND(E13=0,G13>0),100%,IF(AND(E13<0,G13>=0),(E13-G13)/E13,IF(AND(E13>0,G13>0),(G13-E13)/E13,IF(AND(E13=0,G13<=0),"",(G13-E13)/E13)))) | I13: =+'N ESF'!N67 -> 0 | J13: =IF(AND(G13=0,I13>0),100%,IF(AND(G13<0,I13>=0),(G13-I13)/G13,IF(AND(G13>0,I13>0),(I13-G13)/G13,IF(AND(G13=0,I13<=0),"",(I13-G13)/G13)))) | K13: =IF(AND(B13=0,I13>0),100%,IF(AND(B13<0,I13>=0),(B13-I13)/B13,IF(AND(B13>0,I13>0),(I13-B13)/B13,IF(AND(B13=0,I13<=0),"",(I13-B13)/B13))))
A14: Cuentas por Cobrar | B14: =+SUM(B15:B19) -> 0 | C14: =+SUM(C15:C19) -> 21460 | D14: =IF(AND(B14=0,C14>0),100%,IF(AND(B14<0,C14>=0),(B14-C14)/B14,IF(AND(B14>0,C14>0),(C14-B14)/B14,IF(AND(B14=0,C14<=0),"",(C14-B14)/B14)))) -> 1 | E14: =+SUM(E15:E19) -> 0 | F14: =IF(AND(C14=0,E14>0),100%,IF(AND(C14<0,E14>=0),(C14-E14)/C14,IF(AND(C14>0,E14>0),(E14-C14)/C14,IF(AND(C14=0,E14<=0),"",(E14-C14)/C14)))) -> -1 | G14: =+SUM(G15:G19) -> 0 | H14: =IF(AND(E14=0,G14>0),100%,IF(AND(E14<0,G14>=0),(E14-G14)/E14,IF(AND(E14>0,G14>0),(G14-E14)/E14,IF(AND(E14=0,G14<=0),"",(G14-E14)/E14)))) | I14: =+SUM(I15:I19) -> 0 | J14: =IF(AND(G14=0,I14>0),100%,IF(AND(G14<0,I14>=0),(G14-I14)/G14,IF(AND(G14>0,I14>0),(I14-G14)/G14,IF(AND(G14=0,I14<=0),"",(I14-G14)/G14)))) | K14: =IF(AND(B14=0,I14>0),100%,IF(AND(B14<0,I14>=0),(B14-I14)/B14,IF(AND(B14>0,I14>0),(I14-B14)/B14,IF(AND(B14=0,I14<=0),"",(I14-B14)/B14))))
A15: A clientes | B15: =+'N ESF'!B73 -> 0 | C15: =+'N ESF'!E73 -> 7860 | D15: =IF(AND(B15=0,C15>0),100%,IF(AND(B15<0,C15>=0),(B15-C15)/B15,IF(AND(B15>0,C15>0),(C15-B15)/B15,IF(AND(B15=0,C15<=0),"",(C15-B15)/B15)))) -> 1 | E15: =+'N ESF'!H73 -> 0 | F15: =IF(AND(C15=0,E15>0),100%,IF(AND(C15<0,E15>=0),(C15-E15)/C15,IF(AND(C15>0,E15>0),(E15-C15)/C15,IF(AND(C15=0,E15<=0),"",(E15-C15)/C15)))) -> -1 | G15: =+'N ESF'!K73 -> 0 | H15: =IF(AND(E15=0,G15>0),100%,IF(AND(E15<0,G15>=0),(E15-G15)/E15,IF(AND(E15>0,G15>0),(G15-E15)/E15,IF(AND(E15=0,G15<=0),"",(G15-E15)/E15)))) | I15: =+'N ESF'!N73 -> 0 | J15: =IF(AND(G15=0,I15>0),100%,IF(AND(G15<0,I15>=0),(G15-I15)/G15,IF(AND(G15>0,I15>0),(I15-G15)/G15,IF(AND(G15=0,I15<=0),"",(I15-G15)/G15)))) | K15: =IF(AND(B15=0,I15>0),100%,IF(AND(B15<0,I15>=0),(B15-I15)/B15,IF(AND(B15>0,I15>0),(I15-B15)/B15,IF(AND(B15=0,I15<=0),"",(I15-B15)/B15))))
A16: A empresas relacionadas del grupo | B16: =+'N ESF'!B86 -> 0 | C16: =+'N ESF'!E86 -> 2940 | D16: =IF(AND(B16=0,C16>0),100%,IF(AND(B16<0,C16>=0),(B16-C16)/B16,IF(AND(B16>0,C16>0),(C16-B16)/B16,IF(AND(B16=0,C16<=0),"",(C16-B16)/B16)))) -> 1 | E16: =+'N ESF'!H86 -> 0 | F16: =IF(AND(C16=0,E16>0),100%,IF(AND(C16<0,E16>=0),(C16-E16)/C16,IF(AND(C16>0,E16>0),(E16-C16)/C16,IF(AND(C16=0,E16<=0),"",(E16-C16)/C16)))) -> -1 | G16: =+'N ESF'!K86 -> 0 | H16: =IF(AND(E16=0,G16>0),100%,IF(AND(E16<0,G16>=0),(E16-G16)/E16,IF(AND(E16>0,G16>0),(G16-E16)/E16,IF(AND(E16=0,G16<=0),"",(G16-E16)/E16)))) | I16: =+'N ESF'!N86 -> 0 | J16: =IF(AND(G16=0,I16>0),100%,IF(AND(G16<0,I16>=0),(G16-I16)/G16,IF(AND(G16>0,I16>0),(I16-G16)/G16,IF(AND(G16=0,I16<=0),"",(I16-G16)/G16)))) | K16: =IF(AND(B16=0,I16>0),100%,IF(AND(B16<0,I16>=0),(B16-I16)/B16,IF(AND(B16>0,I16>0),(I16-B16)/B16,IF(AND(B16=0,I16<=0),"",(I16-B16)/B16))))
A17: A empresas externas del grupo | B17: =+'N ESF'!B92 -> 0 | C17: =+'N ESF'!E92 -> 3900 | D17: =IF(AND(B17=0,C17>0),100%,IF(AND(B17<0,C17>=0),(B17-C17)/B17,IF(AND(B17>0,C17>0),(C17-B17)/B17,IF(AND(B17=0,C17<=0),"",(C17-B17)/B17)))) -> 1 | E17: =+'N ESF'!H92 -> 0 | F17: =IF(AND(C17=0,E17>0),100%,IF(AND(C17<0,E17>=0),(C17-E17)/C17,IF(AND(C17>0,E17>0),(E17-C17)/C17,IF(AND(C17=0,E17<=0),"",(E17-C17)/C17)))) -> -1 | G17: =+'N ESF'!K92 -> 0 | H17: =IF(AND(E17=0,G17>0),100%,IF(AND(E17<0,G17>=0),(E17-G17)/E17,IF(AND(E17>0,G17>0),(G17-E17)/E17,IF(AND(E17=0,G17<=0),"",(G17-E17)/E17)))) | I17: =+'N ESF'!N92 -> 0 | J17: =IF(AND(G17=0,I17>0),100%,IF(AND(G17<0,I17>=0),(G17-I17)/G17,IF(AND(G17>0,I17>0),(I17-G17)/G17,IF(AND(G17=0,I17<=0),"",(I17-G17)/G17)))) | K17: =IF(AND(B17=0,I17>0),100%,IF(AND(B17<0,I17>=0),(B17-I17)/B17,IF(AND(B17>0,I17>0),(I17-B17)/B17,IF(AND(B17=0,I17<=0),"",(I17-B17)/B17))))
A18: A socios | B18: =+'N ESF'!B98 -> 0 | C18: =+'N ESF'!E98 -> 2460 | D18: =IF(AND(B18=0,C18>0),100%,IF(AND(B18<0,C18>=0),(B18-C18)/B18,IF(AND(B18>0,C18>0),(C18-B18)/B18,IF(AND(B18=0,C18<=0),"",(C18-B18)/B18)))) -> 1 | E18: =+'N ESF'!H98 -> 0 | F18: =IF(AND(C18=0,E18>0),100%,IF(AND(C18<0,E18>=0),(C18-E18)/C18,IF(AND(C18>0,E18>0),(E18-C18)/C18,IF(AND(C18=0,E18<=0),"",(E18-C18)/C18)))) -> -1 | G18: =+'N ESF'!K98 -> 0 | H18: =IF(AND(E18=0,G18>0),100%,IF(AND(E18<0,G18>=0),(E18-G18)/E18,IF(AND(E18>0,G18>0),(G18-E18)/E18,IF(AND(E18=0,G18<=0),"",(G18-E18)/E18)))) | I18: =+'N ESF'!N98 -> 0 | J18: =IF(AND(G18=0,I18>0),100%,IF(AND(G18<0,I18>=0),(G18-I18)/G18,IF(AND(G18>0,I18>0),(I18-G18)/G18,IF(AND(G18=0,I18<=0),"",(I18-G18)/G18)))) | K18: =IF(AND(B18=0,I18>0),100%,IF(AND(B18<0,I18>=0),(B18-I18)/B18,IF(AND(B18>0,I18>0),(I18-B18)/B18,IF(AND(B18=0,I18<=0),"",(I18-B18)/B18))))
A19: A empleados | B19: =+'N ESF'!B102 -> 0 | C19: =+'N ESF'!E102 -> 4300 | D19: =IF(AND(B19=0,C19>0),100%,IF(AND(B19<0,C19>=0),(B19-C19)/B19,IF(AND(B19>0,C19>0),(C19-B19)/B19,IF(AND(B19=0,C19<=0),"",(C19-B19)/B19)))) -> 1 | E19: =+'N ESF'!H102 -> 0 | F19: =IF(AND(C19=0,E19>0),100%,IF(AND(C19<0,E19>=0),(C19-E19)/C19,IF(AND(C19>0,E19>0),(E19-C19)/C19,IF(AND(C19=0,E19<=0),"",(E19-C19)/C19)))) -> -1 | G19: =+'N ESF'!K102 -> 0 | H19: =IF(AND(E19=0,G19>0),100%,IF(AND(E19<0,G19>=0),(E19-G19)/E19,IF(AND(E19>0,G19>0),(G19-E19)/E19,IF(AND(E19=0,G19<=0),"",(G19-E19)/E19)))) | I19: =+'N ESF'!N102 -> 0 | J19: =IF(AND(G19=0,I19>0),100%,IF(AND(G19<0,I19>=0),(G19-I19)/G19,IF(AND(G19>0,I19>0),(I19-G19)/G19,IF(AND(G19=0,I19<=0),"",(I19-G19)/G19)))) | K19: =IF(AND(B19=0,I19>0),100%,IF(AND(B19<0,I19>=0),(B19-I19)/B19,IF(AND(B19>0,I19>0),(I19-B19)/B19,IF(AND(B19=0,I19<=0),"",(I19-B19)/B19))))
A20: Otras Cuentas por Cobrar | B20: =+SUM(B21:B22) -> 0 | C20: =+SUM(C21:C22) -> 5490 | D20: =IF(AND(B20=0,C20>0),100%,IF(AND(B20<0,C20>=0),(B20-C20)/B20,IF(AND(B20>0,C20>0),(C20-B20)/B20,IF(AND(B20=0,C20<=0),"",(C20-B20)/B20)))) -> 1 | E20: =+SUM(E21:E22) -> 0 | F20: =IF(AND(C20=0,E20>0),100%,IF(AND(C20<0,E20>=0),(C20-E20)/C20,IF(AND(C20>0,E20>0),(E20-C20)/C20,IF(AND(C20=0,E20<=0),"",(E20-C20)/C20)))) -> -1 | G20: =+SUM(G21:G22) -> 0 | H20: =IF(AND(E20=0,G20>0),100%,IF(AND(E20<0,G20>=0),(E20-G20)/E20,IF(AND(E20>0,G20>0),(G20-E20)/E20,IF(AND(E20=0,G20<=0),"",(G20-E20)/E20)))) | I20: =+SUM(I21:I22) -> 0 | J20: =IF(AND(G20=0,I20>0),100%,IF(AND(G20<0,I20>=0),(G20-I20)/G20,IF(AND(G20>0,I20>0),(I20-G20)/G20,IF(AND(G20=0,I20<=0),"",(I20-G20)/G20)))) | K20: =IF(AND(B20=0,I20>0),100%,IF(AND(B20<0,I20>=0),(B20-I20)/B20,IF(AND(B20>0,I20>0),(I20-B20)/B20,IF(AND(B20=0,I20<=0),"",(I20-B20)/B20))))
A21: Otras cuentas por cobrar | B21: =+'N ESF'!B110 -> 0 | C21: =+'N ESF'!E110 -> 2700 | D21: =IF(AND(B21=0,C21>0),100%,IF(AND(B21<0,C21>=0),(B21-C21)/B21,IF(AND(B21>0,C21>0),(C21-B21)/B21,IF(AND(B21=0,C21<=0),"",(C21-B21)/B21)))) -> 1 | E21: =+'N ESF'!H110 -> 0 | F21: =IF(AND(C21=0,E21>0),100%,IF(AND(C21<0,E21>=0),(C21-E21)/C21,IF(AND(C21>0,E21>0),(E21-C21)/C21,IF(AND(C21=0,E21<=0),"",(E21-C21)/C21)))) -> -1 | G21: =+'N ESF'!K110 -> 0 | H21: =IF(AND(E21=0,G21>0),100%,IF(AND(E21<0,G21>=0),(E21-G21)/E21,IF(AND(E21>0,G21>0),(G21-E21)/E21,IF(AND(E21=0,G21<=0),"",(G21-E21)/E21)))) | I21: =+'N ESF'!N110 -> 0 | J21: =IF(AND(G21=0,I21>0),100%,IF(AND(G21<0,I21>=0),(G21-I21)/G21,IF(AND(G21>0,I21>0),(I21-G21)/G21,IF(AND(G21=0,I21<=0),"",(I21-G21)/G21)))) | K21: =IF(AND(B21=0,I21>0),100%,IF(AND(B21<0,I21>=0),(B21-I21)/B21,IF(AND(B21>0,I21>0),(I21-B21)/B21,IF(AND(B21=0,I21<=0),"",(I21-B21)/B21))))
A22: Por sociedades | B22: =+'N ESF'!B114 -> 0 | C22: =+'N ESF'!E114 -> 2790 | D22: =IF(AND(B22=0,C22>0),100%,IF(AND(B22<0,C22>=0),(B22-C22)/B22,IF(AND(B22>0,C22>0),(C22-B22)/B22,IF(AND(B22=0,C22<=0),"",(C22-B22)/B22)))) -> 1 | E22: =+'N ESF'!H114 -> 0 | F22: =IF(AND(C22=0,E22>0),100%,IF(AND(C22<0,E22>=0),(C22-E22)/C22,IF(AND(C22>0,E22>0),(E22-C22)/C22,IF(AND(C22=0,E22<=0),"",(E22-C22)/C22)))) -> -1 | G22: =+'N ESF'!K114 -> 0 | H22: =IF(AND(E22=0,G22>0),100%,IF(AND(E22<0,G22>=0),(E22-G22)/E22,IF(AND(E22>0,G22>0),(G22-E22)/E22,IF(AND(E22=0,G22<=0),"",(G22-E22)/E22)))) | I22: =+'N ESF'!N114 -> 0 | J22: =IF(AND(G22=0,I22>0),100%,IF(AND(G22<0,I22>=0),(G22-I22)/G22,IF(AND(G22>0,I22>0),(I22-G22)/G22,IF(AND(G22=0,I22<=0),"",(I22-G22)/G22)))) | K22: =IF(AND(B22=0,I22>0),100%,IF(AND(B22<0,I22>=0),(B22-I22)/B22,IF(AND(B22>0,I22>0),(I22-B22)/B22,IF(AND(B22=0,I22<=0),"",(I22-B22)/B22))))
A23: Préstamos por Cobrar | B23: =+SUM(B24:B28) -> 0 | C23: =+SUM(C24:C28) -> 15300 | D23: =IF(AND(B23=0,C23>0),100%,IF(AND(B23<0,C23>=0),(B23-C23)/B23,IF(AND(B23>0,C23>0),(C23-B23)/B23,IF(AND(B23=0,C23<=0),"",(C23-B23)/B23)))) -> 1 | E23: =+SUM(E24:E28) -> 0 | F23: =IF(AND(C23=0,E23>0),100%,IF(AND(C23<0,E23>=0),(C23-E23)/C23,IF(AND(C23>0,E23>0),(E23-C23)/C23,IF(AND(C23=0,E23<=0),"",(E23-C23)/C23)))) -> -1 | G23: =+SUM(G24:G28) -> 0 | H23: =IF(AND(E23=0,G23>0),100%,IF(AND(E23<0,G23>=0),(E23-G23)/E23,IF(AND(E23>0,G23>0),(G23-E23)/E23,IF(AND(E23=0,G23<=0),"",(G23-E23)/E23)))) | I23: =+SUM(I24:I28) -> 0 | J23: =IF(AND(G23=0,I23>0),100%,IF(AND(G23<0,I23>=0),(G23-I23)/G23,IF(AND(G23>0,I23>0),(I23-G23)/G23,IF(AND(G23=0,I23<=0),"",(I23-G23)/G23)))) | K23: =IF(AND(B23=0,I23>0),100%,IF(AND(B23<0,I23>=0),(B23-I23)/B23,IF(AND(B23>0,I23>0),(I23-B23)/B23,IF(AND(B23=0,I23<=0),"",(I23-B23)/B23))))
A24: A empresas relacionadas del grupo | B24: =+'N ESF'!B119 -> 0 | C24: =+'N ESF'!E119 -> 4850 | D24: =IF(AND(B24=0,C24>0),100%,IF(AND(B24<0,C24>=0),(B24-C24)/B24,IF(AND(B24>0,C24>0),(C24-B24)/B24,IF(AND(B24=0,C24<=0),"",(C24-B24)/B24)))) -> 1 | E24: =+'N ESF'!H119 -> 0 | F24: =IF(AND(C24=0,E24>0),100%,IF(AND(C24<0,E24>=0),(C24-E24)/C24,IF(AND(C24>0,E24>0),(E24-C24)/C24,IF(AND(C24=0,E24<=0),"",(E24-C24)/C24)))) -> -1 | G24: =+'N ESF'!K119 -> 0 | H24: =IF(AND(E24=0,G24>0),100%,IF(AND(E24<0,G24>=0),(E24-G24)/E24,IF(AND(E24>0,G24>0),(G24-E24)/E24,IF(AND(E24=0,G24<=0),"",(G24-E24)/E24)))) | I24: =+'N ESF'!N119 -> 0 | J24: =IF(AND(G24=0,I24>0),100%,IF(AND(G24<0,I24>=0),(G24-I24)/G24,IF(AND(G24>0,I24>0),(I24-G24)/G24,IF(AND(G24=0,I24<=0),"",(I24-G24)/G24)))) | K24: =IF(AND(B24=0,I24>0),100%,IF(AND(B24<0,I24>=0),(B24-I24)/B24,IF(AND(B24>0,I24>0),(I24-B24)/B24,IF(AND(B24=0,I24<=0),"",(I24-B24)/B24))))
A25: A empresas externas del grupo | B25: =+'N ESF'!B125 -> 0 | C25: =+'N ESF'!E125 -> 5100 | D25: =IF(AND(B25=0,C25>0),100%,IF(AND(B25<0,C25>=0),(B25-C25)/B25,IF(AND(B25>0,C25>0),(C25-B25)/B25,IF(AND(B25=0,C25<=0),"",(C25-B25)/B25)))) -> 1 | E25: =+'N ESF'!H125 -> 0 | F25: =IF(AND(C25=0,E25>0),100%,IF(AND(C25<0,E25>=0),(C25-E25)/C25,IF(AND(C25>0,E25>0),(E25-C25)/C25,IF(AND(C25=0,E25<=0),"",(E25-C25)/C25)))) -> -1 | G25: =+'N ESF'!K125 -> 0 | H25: =IF(AND(E25=0,G25>0),100%,IF(AND(E25<0,G25>=0),(E25-G25)/E25,IF(AND(E25>0,G25>0),(G25-E25)/E25,IF(AND(E25=0,G25<=0),"",(G25-E25)/E25)))) | I25: =+'N ESF'!N125 -> 0 | J25: =IF(AND(G25=0,I25>0),100%,IF(AND(G25<0,I25>=0),(G25-I25)/G25,IF(AND(G25>0,I25>0),(I25-G25)/G25,IF(AND(G25=0,I25<=0),"",(I25-G25)/G25)))) | K25: =IF(AND(B25=0,I25>0),100%,IF(AND(B25<0,I25>=0),(B25-I25)/B25,IF(AND(B25>0,I25>0),(I25-B25)/B25,IF(AND(B25=0,I25<=0),"",(I25-B25)/B25))))
A26: A socios | B26: =+'N ESF'!B131 -> 0 | C26: =+'N ESF'!E131 -> 3180 | D26: =IF(AND(B26=0,C26>0),100%,IF(AND(B26<0,C26>=0),(B26-C26)/B26,IF(AND(B26>0,C26>0),(C26-B26)/B26,IF(AND(B26=0,C26<=0),"",(C26-B26)/B26)))) -> 1 | E26: =+'N ESF'!H131 -> 0 | F26: =IF(AND(C26=0,E26>0),100%,IF(AND(C26<0,E26>=0),(C26-E26)/C26,IF(AND(C26>0,E26>0),(E26-C26)/C26,IF(AND(C26=0,E26<=0),"",(E26-C26)/C26)))) -> -1 | G26: =+'N ESF'!K131 -> 0 | H26: =IF(AND(E26=0,G26>0),100%,IF(AND(E26<0,G26>=0),(E26-G26)/E26,IF(AND(E26>0,G26>0),(G26-E26)/E26,IF(AND(E26=0,G26<=0),"",(G26-E26)/E26)))) | I26: =+'N ESF'!N131 -> 0 | J26: =IF(AND(G26=0,I26>0),100%,IF(AND(G26<0,I26>=0),(G26-I26)/G26,IF(AND(G26>0,I26>0),(I26-G26)/G26,IF(AND(G26=0,I26<=0),"",(I26-G26)/G26)))) | K26: =IF(AND(B26=0,I26>0),100%,IF(AND(B26<0,I26>=0),(B26-I26)/B26,IF(AND(B26>0,I26>0),(I26-B26)/B26,IF(AND(B26=0,I26<=0),"",(I26-B26)/B26))))
A27: A empleados | B27: =+'N ESF'!B135 -> 0 | C27: =+'N ESF'!E135 -> 1080 | D27: =IF(AND(B27=0,C27>0),100%,IF(AND(B27<0,C27>=0),(B27-C27)/B27,IF(AND(B27>0,C27>0),(C27-B27)/B27,IF(AND(B27=0,C27<=0),"",(C27-B27)/B27)))) -> 1 | E27: =+'N ESF'!H135 -> 0 | F27: =IF(AND(C27=0,E27>0),100%,IF(AND(C27<0,E27>=0),(C27-E27)/C27,IF(AND(C27>0,E27>0),(E27-C27)/C27,IF(AND(C27=0,E27<=0),"",(E27-C27)/C27)))) -> -1 | G27: =+'N ESF'!K135 -> 0 | H27: =IF(AND(E27=0,G27>0),100%,IF(AND(E27<0,G27>=0),(E27-G27)/E27,IF(AND(E27>0,G27>0),(G27-E27)/E27,IF(AND(E27=0,G27<=0),"",(G27-E27)/E27)))) | I27: =+'N ESF'!N135 -> 0 | J27: =IF(AND(G27=0,I27>0),100%,IF(AND(G27<0,I27>=0),(G27-I27)/G27,IF(AND(G27>0,I27>0),(I27-G27)/G27,IF(AND(G27=0,I27<=0),"",(I27-G27)/G27)))) | K27: =IF(AND(B27=0,I27>0),100%,IF(AND(B27<0,I27>=0),(B27-I27)/B27,IF(AND(B27>0,I27>0),(I27-B27)/B27,IF(AND(B27=0,I27<=0),"",(I27-B27)/B27))))
A28: A terceros | B28: =+'N ESF'!B137 -> 0 | C28: =+'N ESF'!E137 -> 1090 | D28: =IF(AND(B28=0,C28>0),100%,IF(AND(B28<0,C28>=0),(B28-C28)/B28,IF(AND(B28>0,C28>0),(C28-B28)/B28,IF(AND(B28=0,C28<=0),"",(C28-B28)/B28)))) -> 1 | E28: =+'N ESF'!H137 -> 0 | F28: =IF(AND(C28=0,E28>0),100%,IF(AND(C28<0,E28>=0),(C28-E28)/C28,IF(AND(C28>0,E28>0),(E28-C28)/C28,IF(AND(C28=0,E28<=0),"",(E28-C28)/C28)))) -> -1 | G28: =+'N ESF'!K137 -> 0 | H28: =IF(AND(E28=0,G28>0),100%,IF(AND(E28<0,G28>=0),(E28-G28)/E28,IF(AND(E28>0,G28>0),(G28-E28)/E28,IF(AND(E28=0,G28<=0),"",(G28-E28)/E28)))) | I28: =+'N ESF'!N137 -> 0 | J28: =IF(AND(G28=0,I28>0),100%,IF(AND(G28<0,I28>=0),(G28-I28)/G28,IF(AND(G28>0,I28>0),(I28-G28)/G28,IF(AND(G28=0,I28<=0),"",(I28-G28)/G28)))) | K28: =IF(AND(B28=0,I28>0),100%,IF(AND(B28<0,I28>=0),(B28-I28)/B28,IF(AND(B28>0,I28>0),(I28-B28)/B28,IF(AND(B28=0,I28<=0),"",(I28-B28)/B28))))
A29: Anticipos | B29: =+SUM(B30:B32) -> 0 | C29: =+SUM(C30:C32) -> 7910 | D29: =IF(AND(B29=0,C29>0),100%,IF(AND(B29<0,C29>=0),(B29-C29)/B29,IF(AND(B29>0,C29>0),(C29-B29)/B29,IF(AND(B29=0,C29<=0),"",(C29-B29)/B29)))) -> 1 | E29: =+SUM(E30:E32) -> 0 | F29: =IF(AND(C29=0,E29>0),100%,IF(AND(C29<0,E29>=0),(C29-E29)/C29,IF(AND(C29>0,E29>0),(E29-C29)/C29,IF(AND(C29=0,E29<=0),"",(E29-C29)/C29)))) -> -1 | G29: =+SUM(G30:G32) -> 0 | H29: =IF(AND(E29=0,G29>0),100%,IF(AND(E29<0,G29>=0),(E29-G29)/E29,IF(AND(E29>0,G29>0),(G29-E29)/E29,IF(AND(E29=0,G29<=0),"",(G29-E29)/E29)))) | I29: =+SUM(I30:I32) -> 0 | J29: =IF(AND(G29=0,I29>0),100%,IF(AND(G29<0,I29>=0),(G29-I29)/G29,IF(AND(G29>0,I29>0),(I29-G29)/G29,IF(AND(G29=0,I29<=0),"",(I29-G29)/G29)))) | K29: =IF(AND(B29=0,I29>0),100%,IF(AND(B29<0,I29>=0),(B29-I29)/B29,IF(AND(B29>0,I29>0),(I29-B29)/B29,IF(AND(B29=0,I29<=0),"",(I29-B29)/B29))))
A30: A proveedores | B30: =+'N ESF'!B140 -> 0 | C30: =+'N ESF'!E140 -> 2210 | D30: =IF(AND(B30=0,C30>0),100%,IF(AND(B30<0,C30>=0),(B30-C30)/B30,IF(AND(B30>0,C30>0),(C30-B30)/B30,IF(AND(B30=0,C30<=0),"",(C30-B30)/B30)))) -> 1 | E30: =+'N ESF'!H140 -> 0 | F30: =IF(AND(C30=0,E30>0),100%,IF(AND(C30<0,E30>=0),(C30-E30)/C30,IF(AND(C30>0,E30>0),(E30-C30)/C30,IF(AND(C30=0,E30<=0),"",(E30-C30)/C30)))) -> -1 | G30: =+'N ESF'!K140 -> 0 | H30: =IF(AND(E30=0,G30>0),100%,IF(AND(E30<0,G30>=0),(E30-G30)/E30,IF(AND(E30>0,G30>0),(G30-E30)/E30,IF(AND(E30=0,G30<=0),"",(G30-E30)/E30)))) | I30: =+'N ESF'!N140 -> 0 | J30: =IF(AND(G30=0,I30>0),100%,IF(AND(G30<0,I30>=0),(G30-I30)/G30,IF(AND(G30>0,I30>0),(I30-G30)/G30,IF(AND(G30=0,I30<=0),"",(I30-G30)/G30)))) | K30: =IF(AND(B30=0,I30>0),100%,IF(AND(B30<0,I30>=0),(B30-I30)/B30,IF(AND(B30>0,I30>0),(I30-B30)/B30,IF(AND(B30=0,I30<=0),"",(I30-B30)/B30))))
A31: A socios | B31: =+'N ESF'!B143 -> 0 | C31: =+'N ESF'!E143 -> 4540 | D31: =IF(AND(B31=0,C31>0),100%,IF(AND(B31<0,C31>=0),(B31-C31)/B31,IF(AND(B31>0,C31>0),(C31-B31)/B31,IF(AND(B31=0,C31<=0),"",(C31-B31)/B31)))) -> 1 | E31: =+'N ESF'!H143 -> 0 | F31: =IF(AND(C31=0,E31>0),100%,IF(AND(C31<0,E31>=0),(C31-E31)/C31,IF(AND(C31>0,E31>0),(E31-C31)/C31,IF(AND(C31=0,E31<=0),"",(E31-C31)/C31)))) -> -1 | G31: =+'N ESF'!K143 -> 0 | H31: =IF(AND(E31=0,G31>0),100%,IF(AND(E31<0,G31>=0),(E31-G31)/E31,IF(AND(E31>0,G31>0),(G31-E31)/E31,IF(AND(E31=0,G31<=0),"",(G31-E31)/E31)))) | I31: =+'N ESF'!N143 -> 0 | J31: =IF(AND(G31=0,I31>0),100%,IF(AND(G31<0,I31>=0),(G31-I31)/G31,IF(AND(G31>0,I31>0),(I31-G31)/G31,IF(AND(G31=0,I31<=0),"",(I31-G31)/G31)))) | K31: =IF(AND(B31=0,I31>0),100%,IF(AND(B31<0,I31>=0),(B31-I31)/B31,IF(AND(B31>0,I31>0),(I31-B31)/B31,IF(AND(B31=0,I31<=0),"",(I31-B31)/B31))))
A32: A empleados | B32: =+'N ESF'!B148 -> 0 | C32: =+'N ESF'!E148 -> 1160 | D32: =IF(AND(B32=0,C32>0),100%,IF(AND(B32<0,C32>=0),(B32-C32)/B32,IF(AND(B32>0,C32>0),(C32-B32)/B32,IF(AND(B32=0,C32<=0),"",(C32-B32)/B32)))) -> 1 | E32: =+'N ESF'!H148 -> 0 | F32: =IF(AND(C32=0,E32>0),100%,IF(AND(C32<0,E32>=0),(C32-E32)/C32,IF(AND(C32>0,E32>0),(E32-C32)/C32,IF(AND(C32=0,E32<=0),"",(E32-C32)/C32)))) -> -1 | G32: =+'N ESF'!K148 -> 0 | H32: =IF(AND(E32=0,G32>0),100%,IF(AND(E32<0,G32>=0),(E32-G32)/E32,IF(AND(E32>0,G32>0),(G32-E32)/E32,IF(AND(E32=0,G32<=0),"",(G32-E32)/E32)))) | I32: =+'N ESF'!N148 -> 0 | J32: =IF(AND(G32=0,I32>0),100%,IF(AND(G32<0,I32>=0),(G32-I32)/G32,IF(AND(G32>0,I32>0),(I32-G32)/G32,IF(AND(G32=0,I32<=0),"",(I32-G32)/G32)))) | K32: =IF(AND(B32=0,I32>0),100%,IF(AND(B32<0,I32>=0),(B32-I32)/B32,IF(AND(B32>0,I32>0),(I32-B32)/B32,IF(AND(B32=0,I32<=0),"",(I32-B32)/B32))))
A33: Inventarios | B33: =+SUM(B34:B37) -> 0 | C33: =+SUM(C34:C37) -> 7170 | D33: =IF(AND(B33=0,C33>0),100%,IF(AND(B33<0,C33>=0),(B33-C33)/B33,IF(AND(B33>0,C33>0),(C33-B33)/B33,IF(AND(B33=0,C33<=0),"",(C33-B33)/B33)))) -> 1 | E33: =+SUM(E34:E37) -> 0 | F33: =IF(AND(C33=0,E33>0),100%,IF(AND(C33<0,E33>=0),(C33-E33)/C33,IF(AND(C33>0,E33>0),(E33-C33)/C33,IF(AND(C33=0,E33<=0),"",(E33-C33)/C33)))) -> -1 | G33: =+SUM(G34:G37) -> 0 | H33: =IF(AND(E33=0,G33>0),100%,IF(AND(E33<0,G33>=0),(E33-G33)/E33,IF(AND(E33>0,G33>0),(G33-E33)/E33,IF(AND(E33=0,G33<=0),"",(G33-E33)/E33)))) | I33: =+SUM(I34:I37) -> 0 | J33: =IF(AND(G33=0,I33>0),100%,IF(AND(G33<0,I33>=0),(G33-I33)/G33,IF(AND(G33>0,I33>0),(I33-G33)/G33,IF(AND(G33=0,I33<=0),"",(I33-G33)/G33)))) | K33: =IF(AND(B33=0,I33>0),100%,IF(AND(B33<0,I33>=0),(B33-I33)/B33,IF(AND(B33>0,I33>0),(I33-B33)/B33,IF(AND(B33=0,I33<=0),"",(I33-B33)/B33))))
A34: De mercancía | B34: =+'N ESF'!B151 -> 0 | C34: =+'N ESF'!E151 -> 1170 | D34: =IF(AND(B34=0,C34>0),100%,IF(AND(B34<0,C34>=0),(B34-C34)/B34,IF(AND(B34>0,C34>0),(C34-B34)/B34,IF(AND(B34=0,C34<=0),"",(C34-B34)/B34)))) -> 1 | E34: =+'N ESF'!H151 -> 0 | F34: =IF(AND(C34=0,E34>0),100%,IF(AND(C34<0,E34>=0),(C34-E34)/C34,IF(AND(C34>0,E34>0),(E34-C34)/C34,IF(AND(C34=0,E34<=0),"",(E34-C34)/C34)))) -> -1 | G34: =+'N ESF'!K151 -> 0 | H34: =IF(AND(E34=0,G34>0),100%,IF(AND(E34<0,G34>=0),(E34-G34)/E34,IF(AND(E34>0,G34>0),(G34-E34)/E34,IF(AND(E34=0,G34<=0),"",(G34-E34)/E34)))) | I34: =+'N ESF'!N151 -> 0 | J34: =IF(AND(G34=0,I34>0),100%,IF(AND(G34<0,I34>=0),(G34-I34)/G34,IF(AND(G34>0,I34>0),(I34-G34)/G34,IF(AND(G34=0,I34<=0),"",(I34-G34)/G34)))) | K34: =IF(AND(B34=0,I34>0),100%,IF(AND(B34<0,I34>=0),(B34-I34)/B34,IF(AND(B34>0,I34>0),(I34-B34)/B34,IF(AND(B34=0,I34<=0),"",(I34-B34)/B34))))
A35: De suministros | B35: =+'N ESF'!B153 -> 0 | C35: =+'N ESF'!E153 -> 1180 | D35: =IF(AND(B35=0,C35>0),100%,IF(AND(B35<0,C35>=0),(B35-C35)/B35,IF(AND(B35>0,C35>0),(C35-B35)/B35,IF(AND(B35=0,C35<=0),"",(C35-B35)/B35)))) -> 1 | E35: =+'N ESF'!H153 -> 0 | F35: =IF(AND(C35=0,E35>0),100%,IF(AND(C35<0,E35>=0),(C35-E35)/C35,IF(AND(C35>0,E35>0),(E35-C35)/C35,IF(AND(C35=0,E35<=0),"",(E35-C35)/C35)))) -> -1 | G35: =+'N ESF'!K153 -> 0 | H35: =IF(AND(E35=0,G35>0),100%,IF(AND(E35<0,G35>=0),(E35-G35)/E35,IF(AND(E35>0,G35>0),(G35-E35)/E35,IF(AND(E35=0,G35<=0),"",(G35-E35)/E35)))) | I35: =+'N ESF'!N153 -> 0 | J35: =IF(AND(G35=0,I35>0),100%,IF(AND(G35<0,I35>=0),(G35-I35)/G35,IF(AND(G35>0,I35>0),(I35-G35)/G35,IF(AND(G35=0,I35<=0),"",(I35-G35)/G35)))) | K35: =IF(AND(B35=0,I35>0),100%,IF(AND(B35<0,I35>=0),(B35-I35)/B35,IF(AND(B35>0,I35>0),(I35-B35)/B35,IF(AND(B35=0,I35<=0),"",(I35-B35)/B35))))
A36: En tránsito | B36: =+'N ESF'!B155 -> 0 | C36: =+'N ESF'!E155 -> 2390 | D36: =IF(AND(B36=0,C36>0),100%,IF(AND(B36<0,C36>=0),(B36-C36)/B36,IF(AND(B36>0,C36>0),(C36-B36)/B36,IF(AND(B36=0,C36<=0),"",(C36-B36)/B36)))) -> 1 | E36: =+'N ESF'!H155 -> 0 | F36: =IF(AND(C36=0,E36>0),100%,IF(AND(C36<0,E36>=0),(C36-E36)/C36,IF(AND(C36>0,E36>0),(E36-C36)/C36,IF(AND(C36=0,E36<=0),"",(E36-C36)/C36)))) -> -1 | G36: =+'N ESF'!K155 -> 0 | H36: =IF(AND(E36=0,G36>0),100%,IF(AND(E36<0,G36>=0),(E36-G36)/E36,IF(AND(E36>0,G36>0),(G36-E36)/E36,IF(AND(E36=0,G36<=0),"",(G36-E36)/E36)))) | I36: =+'N ESF'!N155 -> 0 | J36: =IF(AND(G36=0,I36>0),100%,IF(AND(G36<0,I36>=0),(G36-I36)/G36,IF(AND(G36>0,I36>0),(I36-G36)/G36,IF(AND(G36=0,I36<=0),"",(I36-G36)/G36)))) | K36: =IF(AND(B36=0,I36>0),100%,IF(AND(B36<0,I36>=0),(B36-I36)/B36,IF(AND(B36>0,I36>0),(I36-B36)/B36,IF(AND(B36=0,I36<=0),"",(I36-B36)/B36))))
A37: A consignación | B37: =+'N ESF'!B158 -> 0 | C37: =+'N ESF'!E158 -> 2430 | D37: =IF(AND(B37=0,C37>0),100%,IF(AND(B37<0,C37>=0),(B37-C37)/B37,IF(AND(B37>0,C37>0),(C37-B37)/B37,IF(AND(B37=0,C37<=0),"",(C37-B37)/B37)))) -> 1 | E37: =+'N ESF'!H158 -> 0 | F37: =IF(AND(C37=0,E37>0),100%,IF(AND(C37<0,E37>=0),(C37-E37)/C37,IF(AND(C37>0,E37>0),(E37-C37)/C37,IF(AND(C37=0,E37<=0),"",(E37-C37)/C37)))) -> -1 | G37: =+'N ESF'!K158 -> 0 | H37: =IF(AND(E37=0,G37>0),100%,IF(AND(E37<0,G37>=0),(E37-G37)/E37,IF(AND(E37>0,G37>0),(G37-E37)/E37,IF(AND(E37=0,G37<=0),"",(G37-E37)/E37)))) | I37: =+'N ESF'!N158 -> 0 | J37: =IF(AND(G37=0,I37>0),100%,IF(AND(G37<0,I37>=0),(G37-I37)/G37,IF(AND(G37>0,I37>0),(I37-G37)/G37,IF(AND(G37=0,I37<=0),"",(I37-G37)/G37)))) | K37: =IF(AND(B37=0,I37>0),100%,IF(AND(B37<0,I37>=0),(B37-I37)/B37,IF(AND(B37>0,I37>0),(I37-B37)/B37,IF(AND(B37=0,I37<=0),"",(I37-B37)/B37))))
A38: Prepagados | B38: =+SUM(B39:B40) -> 0 | C38: =+SUM(C39:C40) -> 10120 | D38: =IF(AND(B38=0,C38>0),100%,IF(AND(B38<0,C38>=0),(B38-C38)/B38,IF(AND(B38>0,C38>0),(C38-B38)/B38,IF(AND(B38=0,C38<=0),"",(C38-B38)/B38)))) -> 1 | E38: =+SUM(E39:E40) -> 0 | F38: =IF(AND(C38=0,E38>0),100%,IF(AND(C38<0,E38>=0),(C38-E38)/C38,IF(AND(C38>0,E38>0),(E38-C38)/C38,IF(AND(C38=0,E38<=0),"",(E38-C38)/C38)))) -> -1 | G38: =+SUM(G39:G40) -> 0 | H38: =IF(AND(E38=0,G38>0),100%,IF(AND(E38<0,G38>=0),(E38-G38)/E38,IF(AND(E38>0,G38>0),(G38-E38)/E38,IF(AND(E38=0,G38<=0),"",(G38-E38)/E38)))) | I38: =+SUM(I39:I40) -> 0 | J38: =IF(AND(G38=0,I38>0),100%,IF(AND(G38<0,I38>=0),(G38-I38)/G38,IF(AND(G38>0,I38>0),(I38-G38)/G38,IF(AND(G38=0,I38<=0),"",(I38-G38)/G38)))) | K38: =IF(AND(B38=0,I38>0),100%,IF(AND(B38<0,I38>=0),(B38-I38)/B38,IF(AND(B38>0,I38>0),(I38-B38)/B38,IF(AND(B38=0,I38<=0),"",(I38-B38)/B38))))
A39: Impuestos | B39: =+'N ESF'!B162 -> 0 | C39: =+'N ESF'!E162 -> 6250 | D39: =IF(AND(B39=0,C39>0),100%,IF(AND(B39<0,C39>=0),(B39-C39)/B39,IF(AND(B39>0,C39>0),(C39-B39)/B39,IF(AND(B39=0,C39<=0),"",(C39-B39)/B39)))) -> 1 | E39: =+'N ESF'!H162 -> 0 | F39: =IF(AND(C39=0,E39>0),100%,IF(AND(C39<0,E39>=0),(C39-E39)/C39,IF(AND(C39>0,E39>0),(E39-C39)/C39,IF(AND(C39=0,E39<=0),"",(E39-C39)/C39)))) -> -1 | G39: =+'N ESF'!K162 -> 0 | H39: =IF(AND(E39=0,G39>0),100%,IF(AND(E39<0,G39>=0),(E39-G39)/E39,IF(AND(E39>0,G39>0),(G39-E39)/E39,IF(AND(E39=0,G39<=0),"",(G39-E39)/E39)))) | I39: =+'N ESF'!N162 -> 0 | J39: =IF(AND(G39=0,I39>0),100%,IF(AND(G39<0,I39>=0),(G39-I39)/G39,IF(AND(G39>0,I39>0),(I39-G39)/G39,IF(AND(G39=0,I39<=0),"",(I39-G39)/G39)))) | K39: =IF(AND(B39=0,I39>0),100%,IF(AND(B39<0,I39>=0),(B39-I39)/B39,IF(AND(B39>0,I39>0),(I39-B39)/B39,IF(AND(B39=0,I39<=0),"",(I39-B39)/B39))))
A40: Gastos pagados por anticipado | B40: =+'N ESF'!B168 -> 0 | C40: =+'N ESF'!E168 -> 3870 | D40: =IF(AND(B40=0,C40>0),100%,IF(AND(B40<0,C40>=0),(B40-C40)/B40,IF(AND(B40>0,C40>0),(C40-B40)/B40,IF(AND(B40=0,C40<=0),"",(C40-B40)/B40)))) -> 1 | E40: =+'N ESF'!H168 -> 0 | F40: =IF(AND(C40=0,E40>0),100%,IF(AND(C40<0,E40>=0),(C40-E40)/C40,IF(AND(C40>0,E40>0),(E40-C40)/C40,IF(AND(C40=0,E40<=0),"",(E40-C40)/C40)))) -> -1 | G40: =+'N ESF'!K168 -> 0 | H40: =IF(AND(E40=0,G40>0),100%,IF(AND(E40<0,G40>=0),(E40-G40)/E40,IF(AND(E40>0,G40>0),(G40-E40)/E40,IF(AND(E40=0,G40<=0),"",(G40-E40)/E40)))) | I40: =+'N ESF'!N168 -> 0 | J40: =IF(AND(G40=0,I40>0),100%,IF(AND(G40<0,I40>=0),(G40-I40)/G40,IF(AND(G40>0,I40>0),(I40-G40)/G40,IF(AND(G40=0,I40<=0),"",(I40-G40)/G40)))) | K40: =IF(AND(B40=0,I40>0),100%,IF(AND(B40<0,I40>=0),(B40-I40)/B40,IF(AND(B40>0,I40>0),(I40-B40)/B40,IF(AND(B40=0,I40<=0),"",(I40-B40)/B40))))
A41: ACTIVOS NO CORRIENTES | B41: =+B42+B48 -> 0 | C41: =+C42+C48 -> 187460 | D41: =IF(AND(B41=0,C41>0),100%,IF(AND(B41<0,C41>=0),(B41-C41)/B41,IF(AND(B41>0,C41>0),(C41-B41)/B41,IF(AND(B41=0,C41<=0),"",(C41-B41)/B41)))) -> 1 | E41: =+E42+E48 -> 0 | F41: =IF(AND(C41=0,E41>0),100%,IF(AND(C41<0,E41>=0),(C41-E41)/C41,IF(AND(C41>0,E41>0),(E41-C41)/C41,IF(AND(C41=0,E41<=0),"",(E41-C41)/C41)))) -> -1 | G41: =+G42+G48 -> 0 | H41: =IF(AND(E41=0,G41>0),100%,IF(AND(E41<0,G41>=0),(E41-G41)/E41,IF(AND(E41>0,G41>0),(G41-E41)/E41,IF(AND(E41=0,G41<=0),"",(G41-E41)/E41)))) | I41: =+I42+I48 -> 0 | J41: =IF(AND(G41=0,I41>0),100%,IF(AND(G41<0,I41>=0),(G41-I41)/G41,IF(AND(G41>0,I41>0),(I41-G41)/G41,IF(AND(G41=0,I41<=0),"",(I41-G41)/G41)))) | K41: =IF(AND(B41=0,I41>0),100%,IF(AND(B41<0,I41>=0),(B41-I41)/B41,IF(AND(B41>0,I41>0),(I41-B41)/B41,IF(AND(B41=0,I41<=0),"",(I41-B41)/B41))))
A42: Otros activos no corrientes | B42: =+SUM(B43:B47) -> 0 | C42: =+SUM(C43:C47) -> 74160 | D42: =IF(AND(B42=0,C42>0),100%,IF(AND(B42<0,C42>=0),(B42-C42)/B42,IF(AND(B42>0,C42>0),(C42-B42)/B42,IF(AND(B42=0,C42<=0),"",(C42-B42)/B42)))) -> 1 | E42: =+SUM(E43:E47) -> 0 | F42: =IF(AND(C42=0,E42>0),100%,IF(AND(C42<0,E42>=0),(C42-E42)/C42,IF(AND(C42>0,E42>0),(E42-C42)/C42,IF(AND(C42=0,E42<=0),"",(E42-C42)/C42)))) -> -1 | G42: =+SUM(G43:G47) -> 0 | H42: =IF(AND(E42=0,G42>0),100%,IF(AND(E42<0,G42>=0),(E42-G42)/E42,IF(AND(E42>0,G42>0),(G42-E42)/E42,IF(AND(E42=0,G42<=0),"",(G42-E42)/E42)))) | I42: =+SUM(I43:I47) -> 0 | J42: =IF(AND(G42=0,I42>0),100%,IF(AND(G42<0,I42>=0),(G42-I42)/G42,IF(AND(G42>0,I42>0),(I42-G42)/G42,IF(AND(G42=0,I42<=0),"",(I42-G42)/G42)))) | K42: =IF(AND(B42=0,I42>0),100%,IF(AND(B42<0,I42>=0),(B42-I42)/B42,IF(AND(B42>0,I42>0),(I42-B42)/B42,IF(AND(B42=0,I42<=0),"",(I42-B42)/B42))))
A43: Deudores comerciales a LP | B43: =+'N ESF'!B175 -> 0 | C43: =+'N ESF'!E175 -> 25110 | D43: =IF(AND(B43=0,C43>0),100%,IF(AND(B43<0,C43>=0),(B43-C43)/B43,IF(AND(B43>0,C43>0),(C43-B43)/B43,IF(AND(B43=0,C43<=0),"",(C43-B43)/B43)))) -> 1 | E43: =+'N ESF'!H175 -> 0 | F43: =IF(AND(C43=0,E43>0),100%,IF(AND(C43<0,E43>=0),(C43-E43)/C43,IF(AND(C43>0,E43>0),(E43-C43)/C43,IF(AND(C43=0,E43<=0),"",(E43-C43)/C43)))) -> -1 | G43: =+'N ESF'!K175 -> 0 | H43: =IF(AND(E43=0,G43>0),100%,IF(AND(E43<0,G43>=0),(E43-G43)/E43,IF(AND(E43>0,G43>0),(G43-E43)/E43,IF(AND(E43=0,G43<=0),"",(G43-E43)/E43)))) | I43: =+'N ESF'!N175 -> 0 | J43: =IF(AND(G43=0,I43>0),100%,IF(AND(G43<0,I43>=0),(G43-I43)/G43,IF(AND(G43>0,I43>0),(I43-G43)/G43,IF(AND(G43=0,I43<=0),"",(I43-G43)/G43)))) | K43: =IF(AND(B43=0,I43>0),100%,IF(AND(B43<0,I43>=0),(B43-I43)/B43,IF(AND(B43>0,I43>0),(I43-B43)/B43,IF(AND(B43=0,I43<=0),"",(I43-B43)/B43))))
A44: Otras cuentas por cobrar a LP | B44: =+'N ESF'!B194 -> 0 | C44: =+'N ESF'!E194 -> 9090 | D44: =IF(AND(B44=0,C44>0),100%,IF(AND(B44<0,C44>=0),(B44-C44)/B44,IF(AND(B44>0,C44>0),(C44-B44)/B44,IF(AND(B44=0,C44<=0),"",(C44-B44)/B44)))) -> 1 | E44: =+'N ESF'!H194 -> 0 | F44: =IF(AND(C44=0,E44>0),100%,IF(AND(C44<0,E44>=0),(C44-E44)/C44,IF(AND(C44>0,E44>0),(E44-C44)/C44,IF(AND(C44=0,E44<=0),"",(E44-C44)/C44)))) -> -1 | G44: =+'N ESF'!K194 -> 0 | H44: =IF(AND(E44=0,G44>0),100%,IF(AND(E44<0,G44>=0),(E44-G44)/E44,IF(AND(E44>0,G44>0),(G44-E44)/E44,IF(AND(E44=0,G44<=0),"",(G44-E44)/E44)))) | I44: =+'N ESF'!N194 -> 0 | J44: =IF(AND(G44=0,I44>0),100%,IF(AND(G44<0,I44>=0),(G44-I44)/G44,IF(AND(G44>0,I44>0),(I44-G44)/G44,IF(AND(G44=0,I44<=0),"",(I44-G44)/G44)))) | K44: =IF(AND(B44=0,I44>0),100%,IF(AND(B44<0,I44>=0),(B44-I44)/B44,IF(AND(B44>0,I44>0),(I44-B44)/B44,IF(AND(B44=0,I44<=0),"",(I44-B44)/B44))))
A45: Préstamos por cobrar LP | B45: =+'N ESF'!B201 -> 0 | C45: =+'N ESF'!E201 -> 24300 | D45: =IF(AND(B45=0,C45>0),100%,IF(AND(B45<0,C45>=0),(B45-C45)/B45,IF(AND(B45>0,C45>0),(C45-B45)/B45,IF(AND(B45=0,C45<=0),"",(C45-B45)/B45)))) -> 1 | E45: =+'N ESF'!H201 -> 0 | F45: =IF(AND(C45=0,E45>0),100%,IF(AND(C45<0,E45>=0),(C45-E45)/C45,IF(AND(C45>0,E45>0),(E45-C45)/C45,IF(AND(C45=0,E45<=0),"",(E45-C45)/C45)))) -> -1 | G45: =+'N ESF'!K201 -> 0 | H45: =IF(AND(E45=0,G45>0),100%,IF(AND(E45<0,G45>=0),(E45-G45)/E45,IF(AND(E45>0,G45>0),(G45-E45)/E45,IF(AND(E45=0,G45<=0),"",(G45-E45)/E45)))) | I45: =+'N ESF'!N201 -> 0 | J45: =IF(AND(G45=0,I45>0),100%,IF(AND(G45<0,I45>=0),(G45-I45)/G45,IF(AND(G45>0,I45>0),(I45-G45)/G45,IF(AND(G45=0,I45<=0),"",(I45-G45)/G45)))) | K45: =IF(AND(B45=0,I45>0),100%,IF(AND(B45<0,I45>=0),(B45-I45)/B45,IF(AND(B45>0,I45>0),(I45-B45)/B45,IF(AND(B45=0,I45<=0),"",(I45-B45)/B45))))
A46: Anticipos LP | B46: =+'N ESF'!B218 -> 0 | C46: =+'N ESF'!E218 -> 13880 | D46: =IF(AND(B46=0,C46>0),100%,IF(AND(B46<0,C46>=0),(B46-C46)/B46,IF(AND(B46>0,C46>0),(C46-B46)/B46,IF(AND(B46=0,C46<=0),"",(C46-B46)/B46)))) -> 1 | E46: =+'N ESF'!H218 -> 0 | F46: =IF(AND(C46=0,E46>0),100%,IF(AND(C46<0,E46>=0),(C46-E46)/C46,IF(AND(C46>0,E46>0),(E46-C46)/C46,IF(AND(C46=0,E46<=0),"",(E46-C46)/C46)))) -> -1 | G46: =+'N ESF'!K218 -> 0 | H46: =IF(AND(E46=0,G46>0),100%,IF(AND(E46<0,G46>=0),(E46-G46)/E46,IF(AND(E46>0,G46>0),(G46-E46)/E46,IF(AND(E46=0,G46<=0),"",(G46-E46)/E46)))) | I46: =+'N ESF'!N218 -> 0 | J46: =IF(AND(G46=0,I46>0),100%,IF(AND(G46<0,I46>=0),(G46-I46)/G46,IF(AND(G46>0,I46>0),(I46-G46)/G46,IF(AND(G46=0,I46<=0),"",(I46-G46)/G46)))) | K46: =IF(AND(B46=0,I46>0),100%,IF(AND(B46<0,I46>=0),(B46-I46)/B46,IF(AND(B46>0,I46>0),(I46-B46)/B46,IF(AND(B46=0,I46<=0),"",(I46-B46)/B46))))
A47: Propiedades de inversión | B47: =+'N ESF'!B227 -> 0 | C47: =+'N ESF'!E227 -> 1780 | D47: =IF(AND(B47=0,C47>0),100%,IF(AND(B47<0,C47>=0),(B47-C47)/B47,IF(AND(B47>0,C47>0),(C47-B47)/B47,IF(AND(B47=0,C47<=0),"",(C47-B47)/B47)))) -> 1 | E47: =+'N ESF'!H227 -> 0 | F47: =IF(AND(C47=0,E47>0),100%,IF(AND(C47<0,E47>=0),(C47-E47)/C47,IF(AND(C47>0,E47>0),(E47-C47)/C47,IF(AND(C47=0,E47<=0),"",(E47-C47)/C47)))) -> -1 | G47: =+'N ESF'!K227 -> 0 | H47: =IF(AND(E47=0,G47>0),100%,IF(AND(E47<0,G47>=0),(E47-G47)/E47,IF(AND(E47>0,G47>0),(G47-E47)/E47,IF(AND(E47=0,G47<=0),"",(G47-E47)/E47)))) | I47: =+'N ESF'!N227 -> 0 | J47: =IF(AND(G47=0,I47>0),100%,IF(AND(G47<0,I47>=0),(G47-I47)/G47,IF(AND(G47>0,I47>0),(I47-G47)/G47,IF(AND(G47=0,I47<=0),"",(I47-G47)/G47)))) | K47: =IF(AND(B47=0,I47>0),100%,IF(AND(B47<0,I47>=0),(B47-I47)/B47,IF(AND(B47>0,I47>0),(I47-B47)/B47,IF(AND(B47=0,I47<=0),"",(I47-B47)/B47))))
A48: Propiedades, Plantas y Equipos | B48: =+SUM(B49:B59) -> 0 | C48: =+SUM(C49:C59) -> 113300 | D48: =IF(AND(B48=0,C48>0),100%,IF(AND(B48<0,C48>=0),(B48-C48)/B48,IF(AND(B48>0,C48>0),(C48-B48)/B48,IF(AND(B48=0,C48<=0),"",(C48-B48)/B48)))) -> 1 | E48: =+SUM(E49:E59) -> 0 | F48: =IF(AND(C48=0,E48>0),100%,IF(AND(C48<0,E48>=0),(C48-E48)/C48,IF(AND(C48>0,E48>0),(E48-C48)/C48,IF(AND(C48=0,E48<=0),"",(E48-C48)/C48)))) -> -1 | G48: =+SUM(G49:G59) -> 0 | H48: =IF(AND(E48=0,G48>0),100%,IF(AND(E48<0,G48>=0),(E48-G48)/E48,IF(AND(E48>0,G48>0),(G48-E48)/E48,IF(AND(E48=0,G48<=0),"",(G48-E48)/E48)))) | I48: =+SUM(I49:I59) -> 0 | J48: =IF(AND(G48=0,I48>0),100%,IF(AND(G48<0,I48>=0),(G48-I48)/G48,IF(AND(G48>0,I48>0),(I48-G48)/G48,IF(AND(G48=0,I48<=0),"",(I48-G48)/G48)))) | K48: =IF(AND(B48=0,I48>0),100%,IF(AND(B48<0,I48>=0),(B48-I48)/B48,IF(AND(B48>0,I48>0),(I48-B48)/B48,IF(AND(B48=0,I48<=0),"",(I48-B48)/B48))))
A49: Terrenos | B49: =+'N ESF'!B230 -> 0 | C49: =+'N ESF'!E230 -> 3590 | D49: =IF(AND(B49=0,C49>0),100%,IF(AND(B49<0,C49>=0),(B49-C49)/B49,IF(AND(B49>0,C49>0),(C49-B49)/B49,IF(AND(B49=0,C49<=0),"",(C49-B49)/B49)))) -> 1 | E49: =+'N ESF'!H230 -> 0 | F49: =IF(AND(C49=0,E49>0),100%,IF(AND(C49<0,E49>=0),(C49-E49)/C49,IF(AND(C49>0,E49>0),(E49-C49)/C49,IF(AND(C49=0,E49<=0),"",(E49-C49)/C49)))) -> -1 | G49: =+'N ESF'!K230 -> 0 | H49: =IF(AND(E49=0,G49>0),100%,IF(AND(E49<0,G49>=0),(E49-G49)/E49,IF(AND(E49>0,G49>0),(G49-E49)/E49,IF(AND(E49=0,G49<=0),"",(G49-E49)/E49)))) | I49: =+'N ESF'!N230 -> 0 | J49: =IF(AND(G49=0,I49>0),100%,IF(AND(G49<0,I49>=0),(G49-I49)/G49,IF(AND(G49>0,I49>0),(I49-G49)/G49,IF(AND(G49=0,I49<=0),"",(I49-G49)/G49)))) | K49: =IF(AND(B49=0,I49>0),100%,IF(AND(B49<0,I49>=0),(B49-I49)/B49,IF(AND(B49>0,I49>0),(I49-B49)/B49,IF(AND(B49=0,I49<=0),"",(I49-B49)/B49))))
A50: Mobiliario y equipos | B50: =+'N ESF'!B233 -> 0 | C50: =+'N ESF'!E233 -> 5460 | D50: =IF(AND(B50=0,C50>0),100%,IF(AND(B50<0,C50>=0),(B50-C50)/B50,IF(AND(B50>0,C50>0),(C50-B50)/B50,IF(AND(B50=0,C50<=0),"",(C50-B50)/B50)))) -> 1 | E50: =+'N ESF'!H233 -> 0 | F50: =IF(AND(C50=0,E50>0),100%,IF(AND(C50<0,E50>=0),(C50-E50)/C50,IF(AND(C50>0,E50>0),(E50-C50)/C50,IF(AND(C50=0,E50<=0),"",(E50-C50)/C50)))) -> -1 | G50: =+'N ESF'!K233 -> 0 | H50: =IF(AND(E50=0,G50>0),100%,IF(AND(E50<0,G50>=0),(E50-G50)/E50,IF(AND(E50>0,G50>0),(G50-E50)/E50,IF(AND(E50=0,G50<=0),"",(G50-E50)/E50)))) | I50: =+'N ESF'!N233 -> 0 | J50: =IF(AND(G50=0,I50>0),100%,IF(AND(G50<0,I50>=0),(G50-I50)/G50,IF(AND(G50>0,I50>0),(I50-G50)/G50,IF(AND(G50=0,I50<=0),"",(I50-G50)/G50)))) | K50: =IF(AND(B50=0,I50>0),100%,IF(AND(B50<0,I50>=0),(B50-I50)/B50,IF(AND(B50>0,I50>0),(I50-B50)/B50,IF(AND(B50=0,I50<=0),"",(I50-B50)/B50))))
A51: Maquinaria y equipos | B51: =+'N ESF'!B237 -> 0 | C51: =+'N ESF'!E237 -> 5550 | D51: =IF(AND(B51=0,C51>0),100%,IF(AND(B51<0,C51>=0),(B51-C51)/B51,IF(AND(B51>0,C51>0),(C51-B51)/B51,IF(AND(B51=0,C51<=0),"",(C51-B51)/B51)))) -> 1 | E51: =+'N ESF'!H237 -> 0 | F51: =IF(AND(C51=0,E51>0),100%,IF(AND(C51<0,E51>=0),(C51-E51)/C51,IF(AND(C51>0,E51>0),(E51-C51)/C51,IF(AND(C51=0,E51<=0),"",(E51-C51)/C51)))) -> -1 | G51: =+'N ESF'!K237 -> 0 | H51: =IF(AND(E51=0,G51>0),100%,IF(AND(E51<0,G51>=0),(E51-G51)/E51,IF(AND(E51>0,G51>0),(G51-E51)/E51,IF(AND(E51=0,G51<=0),"",(G51-E51)/E51)))) | I51: =+'N ESF'!N237 -> 0 | J51: =IF(AND(G51=0,I51>0),100%,IF(AND(G51<0,I51>=0),(G51-I51)/G51,IF(AND(G51>0,I51>0),(I51-G51)/G51,IF(AND(G51=0,I51<=0),"",(I51-G51)/G51)))) | K51: =IF(AND(B51=0,I51>0),100%,IF(AND(B51<0,I51>=0),(B51-I51)/B51,IF(AND(B51>0,I51>0),(I51-B51)/B51,IF(AND(B51=0,I51<=0),"",(I51-B51)/B51))))
A52: Vehiculos | B52: =+'N ESF'!B241 -> 0 | C52: =+'N ESF'!E241 -> 41370 | D52: =IF(AND(B52=0,C52>0),100%,IF(AND(B52<0,C52>=0),(B52-C52)/B52,IF(AND(B52>0,C52>0),(C52-B52)/B52,IF(AND(B52=0,C52<=0),"",(C52-B52)/B52)))) -> 1 | E52: =+'N ESF'!H241 -> 0 | F52: =IF(AND(C52=0,E52>0),100%,IF(AND(C52<0,E52>=0),(C52-E52)/C52,IF(AND(C52>0,E52>0),(E52-C52)/C52,IF(AND(C52=0,E52<=0),"",(E52-C52)/C52)))) -> -1 | G52: =+'N ESF'!K241 -> 0 | H52: =IF(AND(E52=0,G52>0),100%,IF(AND(E52<0,G52>=0),(E52-G52)/E52,IF(AND(E52>0,G52>0),(G52-E52)/E52,IF(AND(E52=0,G52<=0),"",(G52-E52)/E52)))) | I52: =+'N ESF'!N241 -> 0 | J52: =IF(AND(G52=0,I52>0),100%,IF(AND(G52<0,I52>=0),(G52-I52)/G52,IF(AND(G52>0,I52>0),(I52-G52)/G52,IF(AND(G52=0,I52<=0),"",(I52-G52)/G52)))) | K52: =IF(AND(B52=0,I52>0),100%,IF(AND(B52<0,I52>=0),(B52-I52)/B52,IF(AND(B52>0,I52>0),(I52-B52)/B52,IF(AND(B52=0,I52<=0),"",(I52-B52)/B52))))
A53: Edificios y construcciones | B53: =+'N ESF'!B263 -> 0 | C53: =+'N ESF'!E263 -> 12630 | D53: =IF(AND(B53=0,C53>0),100%,IF(AND(B53<0,C53>=0),(B53-C53)/B53,IF(AND(B53>0,C53>0),(C53-B53)/B53,IF(AND(B53=0,C53<=0),"",(C53-B53)/B53)))) -> 1 | E53: =+'N ESF'!H263 -> 0 | F53: =IF(AND(C53=0,E53>0),100%,IF(AND(C53<0,E53>=0),(C53-E53)/C53,IF(AND(C53>0,E53>0),(E53-C53)/C53,IF(AND(C53=0,E53<=0),"",(E53-C53)/C53)))) -> -1 | G53: =+'N ESF'!K263 -> 0 | H53: =IF(AND(E53=0,G53>0),100%,IF(AND(E53<0,G53>=0),(E53-G53)/E53,IF(AND(E53>0,G53>0),(G53-E53)/E53,IF(AND(E53=0,G53<=0),"",(G53-E53)/E53)))) | I53: =+'N ESF'!N263 -> 0 | J53: =IF(AND(G53=0,I53>0),100%,IF(AND(G53<0,I53>=0),(G53-I53)/G53,IF(AND(G53>0,I53>0),(I53-G53)/G53,IF(AND(G53=0,I53<=0),"",(I53-G53)/G53)))) | K53: =IF(AND(B53=0,I53>0),100%,IF(AND(B53<0,I53>=0),(B53-I53)/B53,IF(AND(B53>0,I53>0),(I53-B53)/B53,IF(AND(B53=0,I53<=0),"",(I53-B53)/B53))))
A54: Materiales de eventos | B54: =+'N ESF'!B270 -> 0 | C54: =+'N ESF'!E270 -> 6450 | D54: =IF(AND(B54=0,C54>0),100%,IF(AND(B54<0,C54>=0),(B54-C54)/B54,IF(AND(B54>0,C54>0),(C54-B54)/B54,IF(AND(B54=0,C54<=0),"",(C54-B54)/B54)))) -> 1 | E54: =+'N ESF'!H270 -> 0 | F54: =IF(AND(C54=0,E54>0),100%,IF(AND(C54<0,E54>=0),(C54-E54)/C54,IF(AND(C54>0,E54>0),(E54-C54)/C54,IF(AND(C54=0,E54<=0),"",(E54-C54)/C54)))) -> -1 | G54: =+'N ESF'!K270 -> 0 | H54: =IF(AND(E54=0,G54>0),100%,IF(AND(E54<0,G54>=0),(E54-G54)/E54,IF(AND(E54>0,G54>0),(G54-E54)/E54,IF(AND(E54=0,G54<=0),"",(G54-E54)/E54)))) | I54: =+'N ESF'!N270 -> 0 | J54: =IF(AND(G54=0,I54>0),100%,IF(AND(G54<0,I54>=0),(G54-I54)/G54,IF(AND(G54>0,I54>0),(I54-G54)/G54,IF(AND(G54=0,I54<=0),"",(I54-G54)/G54)))) | K54: =IF(AND(B54=0,I54>0),100%,IF(AND(B54<0,I54>=0),(B54-I54)/B54,IF(AND(B54>0,I54>0),(I54-B54)/B54,IF(AND(B54=0,I54<=0),"",(I54-B54)/B54))))
A55: Herramientas | B55: =+'N ESF'!B274 -> 0 | C55: =+'N ESF'!E274 -> 6540 | D55: =IF(AND(B55=0,C55>0),100%,IF(AND(B55<0,C55>=0),(B55-C55)/B55,IF(AND(B55>0,C55>0),(C55-B55)/B55,IF(AND(B55=0,C55<=0),"",(C55-B55)/B55)))) -> 1 | E55: =+'N ESF'!H274 -> 0 | F55: =IF(AND(C55=0,E55>0),100%,IF(AND(C55<0,E55>=0),(C55-E55)/C55,IF(AND(C55>0,E55>0),(E55-C55)/C55,IF(AND(C55=0,E55<=0),"",(E55-C55)/C55)))) -> -1 | G55: =+'N ESF'!K274 -> 0 | H55: =IF(AND(E55=0,G55>0),100%,IF(AND(E55<0,G55>=0),(E55-G55)/E55,IF(AND(E55>0,G55>0),(G55-E55)/E55,IF(AND(E55=0,G55<=0),"",(G55-E55)/E55)))) | I55: =+'N ESF'!N274 -> 0 | J55: =IF(AND(G55=0,I55>0),100%,IF(AND(G55<0,I55>=0),(G55-I55)/G55,IF(AND(G55>0,I55>0),(I55-G55)/G55,IF(AND(G55=0,I55<=0),"",(I55-G55)/G55)))) | K55: =IF(AND(B55=0,I55>0),100%,IF(AND(B55<0,I55>=0),(B55-I55)/B55,IF(AND(B55>0,I55>0),(I55-B55)/B55,IF(AND(B55=0,I55<=0),"",(I55-B55)/B55))))
A56: Utensilios y equipos de cocina | B56: =+'N ESF'!B278 -> 0 | C56: =+'N ESF'!E278 -> 6630 | D56: =IF(AND(B56=0,C56>0),100%,IF(AND(B56<0,C56>=0),(B56-C56)/B56,IF(AND(B56>0,C56>0),(C56-B56)/B56,IF(AND(B56=0,C56<=0),"",(C56-B56)/B56)))) -> 1 | E56: =+'N ESF'!H278 -> 0 | F56: =IF(AND(C56=0,E56>0),100%,IF(AND(C56<0,E56>=0),(C56-E56)/C56,IF(AND(C56>0,E56>0),(E56-C56)/C56,IF(AND(C56=0,E56<=0),"",(E56-C56)/C56)))) -> -1 | G56: =+'N ESF'!K278 -> 0 | H56: =IF(AND(E56=0,G56>0),100%,IF(AND(E56<0,G56>=0),(E56-G56)/E56,IF(AND(E56>0,G56>0),(G56-E56)/E56,IF(AND(E56=0,G56<=0),"",(G56-E56)/E56)))) | I56: =+'N ESF'!N278 -> 0 | J56: =IF(AND(G56=0,I56>0),100%,IF(AND(G56<0,I56>=0),(G56-I56)/G56,IF(AND(G56>0,I56>0),(I56-G56)/G56,IF(AND(G56=0,I56<=0),"",(I56-G56)/G56)))) | K56: =IF(AND(B56=0,I56>0),100%,IF(AND(B56<0,I56>=0),(B56-I56)/B56,IF(AND(B56>0,I56>0),(I56-B56)/B56,IF(AND(B56=0,I56<=0),"",(I56-B56)/B56))))
A57: Equipamiento deportivo | B57: =+'N ESF'!B282 -> 0 | C57: =+'N ESF'!E282 -> 6720 | D57: =IF(AND(B57=0,C57>0),100%,IF(AND(B57<0,C57>=0),(B57-C57)/B57,IF(AND(B57>0,C57>0),(C57-B57)/B57,IF(AND(B57=0,C57<=0),"",(C57-B57)/B57)))) -> 1 | E57: =+'N ESF'!H282 -> 0 | F57: =IF(AND(C57=0,E57>0),100%,IF(AND(C57<0,E57>=0),(C57-E57)/C57,IF(AND(C57>0,E57>0),(E57-C57)/C57,IF(AND(C57=0,E57<=0),"",(E57-C57)/C57)))) -> -1 | G57: =+'N ESF'!K282 -> 0 | H57: =IF(AND(E57=0,G57>0),100%,IF(AND(E57<0,G57>=0),(E57-G57)/E57,IF(AND(E57>0,G57>0),(G57-E57)/E57,IF(AND(E57=0,G57<=0),"",(G57-E57)/E57)))) | I57: =+'N ESF'!N282 -> 0 | J57: =IF(AND(G57=0,I57>0),100%,IF(AND(G57<0,I57>=0),(G57-I57)/G57,IF(AND(G57>0,I57>0),(I57-G57)/G57,IF(AND(G57=0,I57<=0),"",(I57-G57)/G57)))) | K57: =IF(AND(B57=0,I57>0),100%,IF(AND(B57<0,I57>=0),(B57-I57)/B57,IF(AND(B57>0,I57>0),(I57-B57)/B57,IF(AND(B57=0,I57<=0),"",(I57-B57)/B57))))
A58: Mejoras a bienes arrendados | B58: =+'N ESF'!B286 -> 0 | C58: =+'N ESF'!E286 -> 6810 | D58: =IF(AND(B58=0,C58>0),100%,IF(AND(B58<0,C58>=0),(B58-C58)/B58,IF(AND(B58>0,C58>0),(C58-B58)/B58,IF(AND(B58=0,C58<=0),"",(C58-B58)/B58)))) -> 1 | E58: =+'N ESF'!H286 -> 0 | F58: =IF(AND(C58=0,E58>0),100%,IF(AND(C58<0,E58>=0),(C58-E58)/C58,IF(AND(C58>0,E58>0),(E58-C58)/C58,IF(AND(C58=0,E58<=0),"",(E58-C58)/C58)))) -> -1 | G58: =+'N ESF'!K286 -> 0 | H58: =IF(AND(E58=0,G58>0),100%,IF(AND(E58<0,G58>=0),(E58-G58)/E58,IF(AND(E58>0,G58>0),(G58-E58)/E58,IF(AND(E58=0,G58<=0),"",(G58-E58)/E58)))) | I58: =+'N ESF'!N286 -> 0 | J58: =IF(AND(G58=0,I58>0),100%,IF(AND(G58<0,I58>=0),(G58-I58)/G58,IF(AND(G58>0,I58>0),(I58-G58)/G58,IF(AND(G58=0,I58<=0),"",(I58-G58)/G58)))) | K58: =IF(AND(B58=0,I58>0),100%,IF(AND(B58<0,I58>=0),(B58-I58)/B58,IF(AND(B58>0,I58>0),(I58-B58)/B58,IF(AND(B58=0,I58<=0),"",(I58-B58)/B58))))
A59: Software Odoo y Crm | B59: =+'N ESF'!B290 -> 0 | C59: =+'N ESF'!E290 -> 11550 | D59: =IF(AND(B59=0,C59>0),100%,IF(AND(B59<0,C59>=0),(B59-C59)/B59,IF(AND(B59>0,C59>0),(C59-B59)/B59,IF(AND(B59=0,C59<=0),"",(C59-B59)/B59)))) -> 1 | E59: =+'N ESF'!H290 -> 0 | F59: =IF(AND(C59=0,E59>0),100%,IF(AND(C59<0,E59>=0),(C59-E59)/C59,IF(AND(C59>0,E59>0),(E59-C59)/C59,IF(AND(C59=0,E59<=0),"",(E59-C59)/C59)))) -> -1 | G59: =+'N ESF'!K290 -> 0 | H59: =IF(AND(E59=0,G59>0),100%,IF(AND(E59<0,G59>=0),(E59-G59)/E59,IF(AND(E59>0,G59>0),(G59-E59)/E59,IF(AND(E59=0,G59<=0),"",(G59-E59)/E59)))) | I59: =+'N ESF'!N290 -> 0 | J59: =IF(AND(G59=0,I59>0),100%,IF(AND(G59<0,I59>=0),(G59-I59)/G59,IF(AND(G59>0,I59>0),(I59-G59)/G59,IF(AND(G59=0,I59<=0),"",(I59-G59)/G59)))) | K59: =IF(AND(B59=0,I59>0),100%,IF(AND(B59<0,I59>=0),(B59-I59)/B59,IF(AND(B59>0,I59>0),(I59-B59)/B59,IF(AND(B59=0,I59<=0),"",(I59-B59)/B59))))
A60: TOTAL ACTIVOS | B60: =+B4+B41 -> 0 | C60: =+C4+C41 -> 272610 | D60: =IF(AND(B60=0,C60>0),100%,IF(AND(B60<0,C60>=0),(B60-C60)/B60,IF(AND(B60>0,C60>0),(C60-B60)/B60,IF(AND(B60=0,C60<=0),"",(C60-B60)/B60)))) -> 1 | E60: =+E4+E41 -> 0 | F60: =IF(AND(C60=0,E60>0),100%,IF(AND(C60<0,E60>=0),(C60-E60)/C60,IF(AND(C60>0,E60>0),(E60-C60)/C60,IF(AND(C60=0,E60<=0),"",(E60-C60)/C60)))) -> -1 | G60: =+G4+G41 -> 0 | H60: =IF(AND(E60=0,G60>0),100%,IF(AND(E60<0,G60>=0),(E60-G60)/E60,IF(AND(E60>0,G60>0),(G60-E60)/E60,IF(AND(E60=0,G60<=0),"",(G60-E60)/E60)))) | I60: =+I4+I41 -> 0 | J60: =IF(AND(G60=0,I60>0),100%,IF(AND(G60<0,I60>=0),(G60-I60)/G60,IF(AND(G60>0,I60>0),(I60-G60)/G60,IF(AND(G60=0,I60<=0),"",(I60-G60)/G60)))) | K60: =IF(AND(B60=0,I60>0),100%,IF(AND(B60<0,I60>=0),(B60-I60)/B60,IF(AND(B60>0,I60>0),(I60-B60)/B60,IF(AND(B60=0,I60<=0),"",(I60-B60)/B60))))
A61: PASIVOS CORRIENTES | B61: =+B62+B69+B78+B85+B89 -> 0 | C61: =+C62+C69+C78+C85+C89 -> 232000 | D61: =IF(AND(B61=0,C61>0),100%,IF(AND(B61<0,C61>=0),(B61-C61)/B61,IF(AND(B61>0,C61>0),(C61-B61)/B61,IF(AND(B61=0,C61<=0),"",(C61-B61)/B61)))) -> 1 | E61: =+E62+E69+E78+E85+E89 -> 0 | F61: =IF(AND(C61=0,E61>0),100%,IF(AND(C61<0,E61>=0),(C61-E61)/C61,IF(AND(C61>0,E61>0),(E61-C61)/C61,IF(AND(C61=0,E61<=0),"",(E61-C61)/C61)))) -> -1 | G61: =+G62+G69+G78+G85+G89 -> 0 | H61: =IF(AND(E61=0,G61>0),100%,IF(AND(E61<0,G61>=0),(E61-G61)/E61,IF(AND(E61>0,G61>0),(G61-E61)/E61,IF(AND(E61=0,G61<=0),"",(G61-E61)/E61)))) | I61: =+I62+I69+I78+I85+I89 -> 0 | J61: =IF(AND(G61=0,I61>0),100%,IF(AND(G61<0,I61>=0),(G61-I61)/G61,IF(AND(G61>0,I61>0),(I61-G61)/G61,IF(AND(G61=0,I61<=0),"",(I61-G61)/G61)))) | K61: =IF(AND(B61=0,I61>0),100%,IF(AND(B61<0,I61>=0),(B61-I61)/B61,IF(AND(B61>0,I61>0),(I61-B61)/B61,IF(AND(B61=0,I61<=0),"",(I61-B61)/B61))))
A62: Cuentas por Pagar | B62: =+SUM(B63:B68) -> 0 | C62: =+SUM(C63:C68) -> 198010 | D62: =IF(AND(B62=0,C62>0),100%,IF(AND(B62<0,C62>=0),(B62-C62)/B62,IF(AND(B62>0,C62>0),(C62-B62)/B62,IF(AND(B62=0,C62<=0),"",(C62-B62)/B62)))) -> 1 | E62: =+SUM(E63:E68) -> 0 | F62: =IF(AND(C62=0,E62>0),100%,IF(AND(C62<0,E62>=0),(C62-E62)/C62,IF(AND(C62>0,E62>0),(E62-C62)/C62,IF(AND(C62=0,E62<=0),"",(E62-C62)/C62)))) -> -1 | G62: =+SUM(G63:G68) -> 0 | H62: =IF(AND(E62=0,G62>0),100%,IF(AND(E62<0,G62>=0),(E62-G62)/E62,IF(AND(E62>0,G62>0),(G62-E62)/E62,IF(AND(E62=0,G62<=0),"",(G62-E62)/E62)))) | I62: =+SUM(I63:I68) -> 0 | J62: =IF(AND(G62=0,I62>0),100%,IF(AND(G62<0,I62>=0),(G62-I62)/G62,IF(AND(G62>0,I62>0),(I62-G62)/G62,IF(AND(G62=0,I62<=0),"",(I62-G62)/G62)))) | K62: =IF(AND(B62=0,I62>0),100%,IF(AND(B62<0,I62>=0),(B62-I62)/B62,IF(AND(B62>0,I62>0),(I62-B62)/B62,IF(AND(B62=0,I62<=0),"",(I62-B62)/B62))))
A63: A proveedores | B63: =+'N ESF'!B299 -> 0 | C63: =+'N ESF'!E299 -> 120000 | D63: =IF(AND(B63=0,C63>0),100%,IF(AND(B63<0,C63>=0),(B63-C63)/B63,IF(AND(B63>0,C63>0),(C63-B63)/B63,IF(AND(B63=0,C63<=0),"",(C63-B63)/B63)))) -> 1 | E63: =+'N ESF'!H299 -> 0 | F63: =IF(AND(C63=0,E63>0),100%,IF(AND(C63<0,E63>=0),(C63-E63)/C63,IF(AND(C63>0,E63>0),(E63-C63)/C63,IF(AND(C63=0,E63<=0),"",(E63-C63)/C63)))) -> -1 | G63: =+'N ESF'!K299 -> 0 | H63: =IF(AND(E63=0,G63>0),100%,IF(AND(E63<0,G63>=0),(E63-G63)/E63,IF(AND(E63>0,G63>0),(G63-E63)/E63,IF(AND(E63=0,G63<=0),"",(G63-E63)/E63)))) | I63: =+'N ESF'!N299 -> 0 | J63: =IF(AND(G63=0,I63>0),100%,IF(AND(G63<0,I63>=0),(G63-I63)/G63,IF(AND(G63>0,I63>0),(I63-G63)/G63,IF(AND(G63=0,I63<=0),"",(I63-G63)/G63)))) | K63: =IF(AND(B63=0,I63>0),100%,IF(AND(B63<0,I63>=0),(B63-I63)/B63,IF(AND(B63>0,I63>0),(I63-B63)/B63,IF(AND(B63=0,I63<=0),"",(I63-B63)/B63))))
A64: A empresas relacionadas del grupo | B64: =+'N ESF'!B303 -> 0 | C64: =+'N ESF'!E303 -> 76400 | D64: =IF(AND(B64=0,C64>0),100%,IF(AND(B64<0,C64>=0),(B64-C64)/B64,IF(AND(B64>0,C64>0),(C64-B64)/B64,IF(AND(B64=0,C64<=0),"",(C64-B64)/B64)))) -> 1 | E64: =+'N ESF'!H303 -> 0 | F64: =IF(AND(C64=0,E64>0),100%,IF(AND(C64<0,E64>=0),(C64-E64)/C64,IF(AND(C64>0,E64>0),(E64-C64)/C64,IF(AND(C64=0,E64<=0),"",(E64-C64)/C64)))) -> -1 | G64: =+'N ESF'!K303 -> 0 | H64: =IF(AND(E64=0,G64>0),100%,IF(AND(E64<0,G64>=0),(E64-G64)/E64,IF(AND(E64>0,G64>0),(G64-E64)/E64,IF(AND(E64=0,G64<=0),"",(G64-E64)/E64)))) | I64: =+'N ESF'!N303 -> 0 | J64: =IF(AND(G64=0,I64>0),100%,IF(AND(G64<0,I64>=0),(G64-I64)/G64,IF(AND(G64>0,I64>0),(I64-G64)/G64,IF(AND(G64=0,I64<=0),"",(I64-G64)/G64)))) | K64: =IF(AND(B64=0,I64>0),100%,IF(AND(B64<0,I64>=0),(B64-I64)/B64,IF(AND(B64>0,I64>0),(I64-B64)/B64,IF(AND(B64=0,I64<=0),"",(I64-B64)/B64))))
A65: A empresas externas del grupo | B65: =+'N ESF'!B308 -> 0 | C65: =+'N ESF'!E308 -> 350 | D65: =IF(AND(B65=0,C65>0),100%,IF(AND(B65<0,C65>=0),(B65-C65)/B65,IF(AND(B65>0,C65>0),(C65-B65)/B65,IF(AND(B65=0,C65<=0),"",(C65-B65)/B65)))) -> 1 | E65: =+'N ESF'!H308 -> 0 | F65: =IF(AND(C65=0,E65>0),100%,IF(AND(C65<0,E65>=0),(C65-E65)/C65,IF(AND(C65>0,E65>0),(E65-C65)/C65,IF(AND(C65=0,E65<=0),"",(E65-C65)/C65)))) -> -1 | G65: =+'N ESF'!K308 -> 0 | H65: =IF(AND(E65=0,G65>0),100%,IF(AND(E65<0,G65>=0),(E65-G65)/E65,IF(AND(E65>0,G65>0),(G65-E65)/E65,IF(AND(E65=0,G65<=0),"",(G65-E65)/E65)))) | I65: =+'N ESF'!N308 -> 0 | J65: =IF(AND(G65=0,I65>0),100%,IF(AND(G65<0,I65>=0),(G65-I65)/G65,IF(AND(G65>0,I65>0),(I65-G65)/G65,IF(AND(G65=0,I65<=0),"",(I65-G65)/G65)))) | K65: =IF(AND(B65=0,I65>0),100%,IF(AND(B65<0,I65>=0),(B65-I65)/B65,IF(AND(B65>0,I65>0),(I65-B65)/B65,IF(AND(B65=0,I65<=0),"",(I65-B65)/B65))))
A66: A socios | B66: =+'N ESF'!B314 -> 0 | C66: =+'N ESF'!E314 -> 330 | D66: =IF(AND(B66=0,C66>0),100%,IF(AND(B66<0,C66>=0),(B66-C66)/B66,IF(AND(B66>0,C66>0),(C66-B66)/B66,IF(AND(B66=0,C66<=0),"",(C66-B66)/B66)))) -> 1 | E66: =+'N ESF'!H314 -> 0 | F66: =IF(AND(C66=0,E66>0),100%,IF(AND(C66<0,E66>=0),(C66-E66)/C66,IF(AND(C66>0,E66>0),(E66-C66)/C66,IF(AND(C66=0,E66<=0),"",(E66-C66)/C66)))) -> -1 | G66: =+'N ESF'!K314 -> 0 | H66: =IF(AND(E66=0,G66>0),100%,IF(AND(E66<0,G66>=0),(E66-G66)/E66,IF(AND(E66>0,G66>0),(G66-E66)/E66,IF(AND(E66=0,G66<=0),"",(G66-E66)/E66)))) | I66: =+'N ESF'!N314 -> 0 | J66: =IF(AND(G66=0,I66>0),100%,IF(AND(G66<0,I66>=0),(G66-I66)/G66,IF(AND(G66>0,I66>0),(I66-G66)/G66,IF(AND(G66=0,I66<=0),"",(I66-G66)/G66)))) | K66: =IF(AND(B66=0,I66>0),100%,IF(AND(B66<0,I66>=0),(B66-I66)/B66,IF(AND(B66>0,I66>0),(I66-B66)/B66,IF(AND(B66=0,I66<=0),"",(I66-B66)/B66))))
A67: Cuentas por pagar TDC y TDC | B67: =+'N ESF'!B318 -> 0 | C67: =+'N ESF'!E318 -> 750 | D67: =IF(AND(B67=0,C67>0),100%,IF(AND(B67<0,C67>=0),(B67-C67)/B67,IF(AND(B67>0,C67>0),(C67-B67)/B67,IF(AND(B67=0,C67<=0),"",(C67-B67)/B67)))) -> 1 | E67: =+'N ESF'!H318 -> 0 | F67: =IF(AND(C67=0,E67>0),100%,IF(AND(C67<0,E67>=0),(C67-E67)/C67,IF(AND(C67>0,E67>0),(E67-C67)/C67,IF(AND(C67=0,E67<=0),"",(E67-C67)/C67)))) -> -1 | G67: =+'N ESF'!K318 -> 0 | H67: =IF(AND(E67=0,G67>0),100%,IF(AND(E67<0,G67>=0),(E67-G67)/E67,IF(AND(E67>0,G67>0),(G67-E67)/E67,IF(AND(E67=0,G67<=0),"",(G67-E67)/E67)))) | I67: =+'N ESF'!N318 -> 0 | J67: =IF(AND(G67=0,I67>0),100%,IF(AND(G67<0,I67>=0),(G67-I67)/G67,IF(AND(G67>0,I67>0),(I67-G67)/G67,IF(AND(G67=0,I67<=0),"",(I67-G67)/G67)))) | K67: =IF(AND(B67=0,I67>0),100%,IF(AND(B67<0,I67>=0),(B67-I67)/B67,IF(AND(B67>0,I67>0),(I67-B67)/B67,IF(AND(B67=0,I67<=0),"",(I67-B67)/B67))))
A68: A proveedores en consignación | B68: =+'N ESF'!B324 -> 0 | C68: =+'N ESF'!E324 -> 180 | D68: =IF(AND(B68=0,C68>0),100%,IF(AND(B68<0,C68>=0),(B68-C68)/B68,IF(AND(B68>0,C68>0),(C68-B68)/B68,IF(AND(B68=0,C68<=0),"",(C68-B68)/B68)))) -> 1 | E68: =+'N ESF'!H324 -> 0 | F68: =IF(AND(C68=0,E68>0),100%,IF(AND(C68<0,E68>=0),(C68-E68)/C68,IF(AND(C68>0,E68>0),(E68-C68)/C68,IF(AND(C68=0,E68<=0),"",(E68-C68)/C68)))) -> -1 | G68: =+'N ESF'!K324 -> 0 | H68: =IF(AND(E68=0,G68>0),100%,IF(AND(E68<0,G68>=0),(E68-G68)/E68,IF(AND(E68>0,G68>0),(G68-E68)/E68,IF(AND(E68=0,G68<=0),"",(G68-E68)/E68)))) | I68: =+'N ESF'!N324 -> 0 | J68: =IF(AND(G68=0,I68>0),100%,IF(AND(G68<0,I68>=0),(G68-I68)/G68,IF(AND(G68>0,I68>0),(I68-G68)/G68,IF(AND(G68=0,I68<=0),"",(I68-G68)/G68)))) | K68: =IF(AND(B68=0,I68>0),100%,IF(AND(B68<0,I68>=0),(B68-I68)/B68,IF(AND(B68>0,I68>0),(I68-B68)/B68,IF(AND(B68=0,I68<=0),"",(I68-B68)/B68))))
A69: Otras cuentas por pagar | B69: =+SUM(B70:B77) -> 0 | C69: =+SUM(C70:C77) -> 12600 | D69: =IF(AND(B69=0,C69>0),100%,IF(AND(B69<0,C69>=0),(B69-C69)/B69,IF(AND(B69>0,C69>0),(C69-B69)/B69,IF(AND(B69=0,C69<=0),"",(C69-B69)/B69)))) -> 1 | E69: =+SUM(E70:E77) -> 0 | F69: =IF(AND(C69=0,E69>0),100%,IF(AND(C69<0,E69>=0),(C69-E69)/C69,IF(AND(C69>0,E69>0),(E69-C69)/C69,IF(AND(C69=0,E69<=0),"",(E69-C69)/C69)))) -> -1 | G69: =+SUM(G70:G77) -> 0 | H69: =IF(AND(E69=0,G69>0),100%,IF(AND(E69<0,G69>=0),(E69-G69)/E69,IF(AND(E69>0,G69>0),(G69-E69)/E69,IF(AND(E69=0,G69<=0),"",(G69-E69)/E69)))) | I69: =+SUM(I70:I77) -> 0 | J69: =IF(AND(G69=0,I69>0),100%,IF(AND(G69<0,I69>=0),(G69-I69)/G69,IF(AND(G69>0,I69>0),(I69-G69)/G69,IF(AND(G69=0,I69<=0),"",(I69-G69)/G69)))) | K69: =IF(AND(B69=0,I69>0),100%,IF(AND(B69<0,I69>=0),(B69-I69)/B69,IF(AND(B69>0,I69>0),(I69-B69)/B69,IF(AND(B69=0,I69<=0),"",(I69-B69)/B69))))
A70: Otras cuentas por pagar | B70: =+'N ESF'!B327 -> 0 | C70: =+'N ESF'!E327 -> 600 | D70: =IF(AND(B70=0,C70>0),100%,IF(AND(B70<0,C70>=0),(B70-C70)/B70,IF(AND(B70>0,C70>0),(C70-B70)/B70,IF(AND(B70=0,C70<=0),"",(C70-B70)/B70)))) -> 1 | E70: =+'N ESF'!H327 -> 0 | F70: =IF(AND(C70=0,E70>0),100%,IF(AND(C70<0,E70>=0),(C70-E70)/C70,IF(AND(C70>0,E70>0),(E70-C70)/C70,IF(AND(C70=0,E70<=0),"",(E70-C70)/C70)))) -> -1 | G70: =+'N ESF'!K327 -> 0 | H70: =IF(AND(E70=0,G70>0),100%,IF(AND(E70<0,G70>=0),(E70-G70)/E70,IF(AND(E70>0,G70>0),(G70-E70)/E70,IF(AND(E70=0,G70<=0),"",(G70-E70)/E70)))) | I70: =+'N ESF'!N327 -> 0 | J70: =IF(AND(G70=0,I70>0),100%,IF(AND(G70<0,I70>=0),(G70-I70)/G70,IF(AND(G70>0,I70>0),(I70-G70)/G70,IF(AND(G70=0,I70<=0),"",(I70-G70)/G70)))) | K70: =IF(AND(B70=0,I70>0),100%,IF(AND(B70<0,I70>=0),(B70-I70)/B70,IF(AND(B70>0,I70>0),(I70-B70)/B70,IF(AND(B70=0,I70<=0),"",(I70-B70)/B70))))
A71: Descuentos a empleados por pagar | B71: =+'N ESF'!B331 -> 0 | C71: =+'N ESF'!E331 -> 940 | D71: =IF(AND(B71=0,C71>0),100%,IF(AND(B71<0,C71>=0),(B71-C71)/B71,IF(AND(B71>0,C71>0),(C71-B71)/B71,IF(AND(B71=0,C71<=0),"",(C71-B71)/B71)))) -> 1 | E71: =+'N ESF'!H331 -> 0 | F71: =IF(AND(C71=0,E71>0),100%,IF(AND(C71<0,E71>=0),(C71-E71)/C71,IF(AND(C71>0,E71>0),(E71-C71)/C71,IF(AND(C71=0,E71<=0),"",(E71-C71)/C71)))) -> -1 | G71: =+'N ESF'!K331 -> 0 | H71: =IF(AND(E71=0,G71>0),100%,IF(AND(E71<0,G71>=0),(E71-G71)/E71,IF(AND(E71>0,G71>0),(G71-E71)/E71,IF(AND(E71=0,G71<=0),"",(G71-E71)/E71)))) | I71: =+'N ESF'!N331 -> 0 | J71: =IF(AND(G71=0,I71>0),100%,IF(AND(G71<0,I71>=0),(G71-I71)/G71,IF(AND(G71>0,I71>0),(I71-G71)/G71,IF(AND(G71=0,I71<=0),"",(I71-G71)/G71)))) | K71: =IF(AND(B71=0,I71>0),100%,IF(AND(B71<0,I71>=0),(B71-I71)/B71,IF(AND(B71>0,I71>0),(I71-B71)/B71,IF(AND(B71=0,I71<=0),"",(I71-B71)/B71))))
A72: Sueldos y Salarios por pagar | B72: =+'N ESF'!B336 -> 0 | C72: =+'N ESF'!E336 -> 530 | D72: =IF(AND(B72=0,C72>0),100%,IF(AND(B72<0,C72>=0),(B72-C72)/B72,IF(AND(B72>0,C72>0),(C72-B72)/B72,IF(AND(B72=0,C72<=0),"",(C72-B72)/B72)))) -> 1 | E72: =+'N ESF'!H336 -> 0 | F72: =IF(AND(C72=0,E72>0),100%,IF(AND(C72<0,E72>=0),(C72-E72)/C72,IF(AND(C72>0,E72>0),(E72-C72)/C72,IF(AND(C72=0,E72<=0),"",(E72-C72)/C72)))) -> -1 | G72: =+'N ESF'!K336 -> 0 | H72: =IF(AND(E72=0,G72>0),100%,IF(AND(E72<0,G72>=0),(E72-G72)/E72,IF(AND(E72>0,G72>0),(G72-E72)/E72,IF(AND(E72=0,G72<=0),"",(G72-E72)/E72)))) | I72: =+'N ESF'!N336 -> 0 | J72: =IF(AND(G72=0,I72>0),100%,IF(AND(G72<0,I72>=0),(G72-I72)/G72,IF(AND(G72>0,I72>0),(I72-G72)/G72,IF(AND(G72=0,I72<=0),"",(I72-G72)/G72)))) | K72: =IF(AND(B72=0,I72>0),100%,IF(AND(B72<0,I72>=0),(B72-I72)/B72,IF(AND(B72>0,I72>0),(I72-B72)/B72,IF(AND(B72=0,I72<=0),"",(I72-B72)/B72))))
A73: Retenciones laborales a pagar | B73: =+'N ESF'!B339 -> 0 | C73: =+'N ESF'!E339 -> 1500 | D73: =IF(AND(B73=0,C73>0),100%,IF(AND(B73<0,C73>=0),(B73-C73)/B73,IF(AND(B73>0,C73>0),(C73-B73)/B73,IF(AND(B73=0,C73<=0),"",(C73-B73)/B73)))) -> 1 | E73: =+'N ESF'!H339 -> 0 | F73: =IF(AND(C73=0,E73>0),100%,IF(AND(C73<0,E73>=0),(C73-E73)/C73,IF(AND(C73>0,E73>0),(E73-C73)/C73,IF(AND(C73=0,E73<=0),"",(E73-C73)/C73)))) -> -1 | G73: =+'N ESF'!K339 -> 0 | H73: =IF(AND(E73=0,G73>0),100%,IF(AND(E73<0,G73>=0),(E73-G73)/E73,IF(AND(E73>0,G73>0),(G73-E73)/E73,IF(AND(E73=0,G73<=0),"",(G73-E73)/E73)))) | I73: =+'N ESF'!N339 -> 0 | J73: =IF(AND(G73=0,I73>0),100%,IF(AND(G73<0,I73>=0),(G73-I73)/G73,IF(AND(G73>0,I73>0),(I73-G73)/G73,IF(AND(G73=0,I73<=0),"",(I73-G73)/G73)))) | K73: =IF(AND(B73=0,I73>0),100%,IF(AND(B73<0,I73>=0),(B73-I73)/B73,IF(AND(B73>0,I73>0),(I73-B73)/B73,IF(AND(B73=0,I73<=0),"",(I73-B73)/B73))))
A74: Aportes patronales por pagar | B74: =+'N ESF'!B345 -> 0 | C74: =+'N ESF'!E345 -> 1380 | D74: =IF(AND(B74=0,C74>0),100%,IF(AND(B74<0,C74>=0),(B74-C74)/B74,IF(AND(B74>0,C74>0),(C74-B74)/B74,IF(AND(B74=0,C74<=0),"",(C74-B74)/B74)))) -> 1 | E74: =+'N ESF'!H345 -> 0 | F74: =IF(AND(C74=0,E74>0),100%,IF(AND(C74<0,E74>=0),(C74-E74)/C74,IF(AND(C74>0,E74>0),(E74-C74)/C74,IF(AND(C74=0,E74<=0),"",(E74-C74)/C74)))) -> -1 | G74: =+'N ESF'!K345 -> 0 | H74: =IF(AND(E74=0,G74>0),100%,IF(AND(E74<0,G74>=0),(E74-G74)/E74,IF(AND(E74>0,G74>0),(G74-E74)/E74,IF(AND(E74=0,G74<=0),"",(G74-E74)/E74)))) | I74: =+'N ESF'!N345 -> 0 | J74: =IF(AND(G74=0,I74>0),100%,IF(AND(G74<0,I74>=0),(G74-I74)/G74,IF(AND(G74>0,I74>0),(I74-G74)/G74,IF(AND(G74=0,I74<=0),"",(I74-G74)/G74)))) | K74: =IF(AND(B74=0,I74>0),100%,IF(AND(B74<0,I74>=0),(B74-I74)/B74,IF(AND(B74>0,I74>0),(I74-B74)/B74,IF(AND(B74=0,I74<=0),"",(I74-B74)/B74))))
A75: Intereses por pagar | B75: =+'N ESF'!B350 -> 0 | C75: =+'N ESF'!E350 -> 750 | D75: =IF(AND(B75=0,C75>0),100%,IF(AND(B75<0,C75>=0),(B75-C75)/B75,IF(AND(B75>0,C75>0),(C75-B75)/B75,IF(AND(B75=0,C75<=0),"",(C75-B75)/B75)))) -> 1 | E75: =+'N ESF'!H350 -> 0 | F75: =IF(AND(C75=0,E75>0),100%,IF(AND(C75<0,E75>=0),(C75-E75)/C75,IF(AND(C75>0,E75>0),(E75-C75)/C75,IF(AND(C75=0,E75<=0),"",(E75-C75)/C75)))) -> -1 | G75: =+'N ESF'!K350 -> 0 | H75: =IF(AND(E75=0,G75>0),100%,IF(AND(E75<0,G75>=0),(E75-G75)/E75,IF(AND(E75>0,G75>0),(G75-E75)/E75,IF(AND(E75=0,G75<=0),"",(G75-E75)/E75)))) | I75: =+'N ESF'!N350 -> 0 | J75: =IF(AND(G75=0,I75>0),100%,IF(AND(G75<0,I75>=0),(G75-I75)/G75,IF(AND(G75>0,I75>0),(I75-G75)/G75,IF(AND(G75=0,I75<=0),"",(I75-G75)/G75)))) | K75: =IF(AND(B75=0,I75>0),100%,IF(AND(B75<0,I75>=0),(B75-I75)/B75,IF(AND(B75>0,I75>0),(I75-B75)/B75,IF(AND(B75=0,I75<=0),"",(I75-B75)/B75))))
A76: Impuestos por pagar | B76: =+'N ESF'!B353 -> 0 | C76: =+'N ESF'!E353 -> 3870 | D76: =IF(AND(B76=0,C76>0),100%,IF(AND(B76<0,C76>=0),(B76-C76)/B76,IF(AND(B76>0,C76>0),(C76-B76)/B76,IF(AND(B76=0,C76<=0),"",(C76-B76)/B76)))) -> 1 | E76: =+'N ESF'!H353 -> 0 | F76: =IF(AND(C76=0,E76>0),100%,IF(AND(C76<0,E76>=0),(C76-E76)/C76,IF(AND(C76>0,E76>0),(E76-C76)/C76,IF(AND(C76=0,E76<=0),"",(E76-C76)/C76)))) -> -1 | G76: =+'N ESF'!K353 -> 0 | H76: =IF(AND(E76=0,G76>0),100%,IF(AND(E76<0,G76>=0),(E76-G76)/E76,IF(AND(E76>0,G76>0),(G76-E76)/E76,IF(AND(E76=0,G76<=0),"",(G76-E76)/E76)))) | I76: =+'N ESF'!N353 -> 0 | J76: =IF(AND(G76=0,I76>0),100%,IF(AND(G76<0,I76>=0),(G76-I76)/G76,IF(AND(G76>0,I76>0),(I76-G76)/G76,IF(AND(G76=0,I76<=0),"",(I76-G76)/G76)))) | K76: =IF(AND(B76=0,I76>0),100%,IF(AND(B76<0,I76>=0),(B76-I76)/B76,IF(AND(B76>0,I76>0),(I76-B76)/B76,IF(AND(B76=0,I76<=0),"",(I76-B76)/B76))))
A77: Dividendos por pagar | B77: =+'N ESF'!B363 -> 0 | C77: =+'N ESF'!E363 -> 3030 | D77: =IF(AND(B77=0,C77>0),100%,IF(AND(B77<0,C77>=0),(B77-C77)/B77,IF(AND(B77>0,C77>0),(C77-B77)/B77,IF(AND(B77=0,C77<=0),"",(C77-B77)/B77)))) -> 1 | E77: =+'N ESF'!H363 -> 0 | F77: =IF(AND(C77=0,E77>0),100%,IF(AND(C77<0,E77>=0),(C77-E77)/C77,IF(AND(C77>0,E77>0),(E77-C77)/C77,IF(AND(C77=0,E77<=0),"",(E77-C77)/C77)))) -> -1 | G77: =+'N ESF'!K363 -> 0 | H77: =IF(AND(E77=0,G77>0),100%,IF(AND(E77<0,G77>=0),(E77-G77)/E77,IF(AND(E77>0,G77>0),(G77-E77)/E77,IF(AND(E77=0,G77<=0),"",(G77-E77)/E77)))) | I77: =+'N ESF'!N363 -> 0 | J77: =IF(AND(G77=0,I77>0),100%,IF(AND(G77<0,I77>=0),(G77-I77)/G77,IF(AND(G77>0,I77>0),(I77-G77)/G77,IF(AND(G77=0,I77<=0),"",(I77-G77)/G77)))) | K77: =IF(AND(B77=0,I77>0),100%,IF(AND(B77<0,I77>=0),(B77-I77)/B77,IF(AND(B77>0,I77>0),(I77-B77)/B77,IF(AND(B77=0,I77<=0),"",(I77-B77)/B77))))
A78: Préstamos por Pagar | B78: =+SUM(B79:B84) -> 0 | C78: =+SUM(C79:C84) -> 14950 | D78: =IF(AND(B78=0,C78>0),100%,IF(AND(B78<0,C78>=0),(B78-C78)/B78,IF(AND(B78>0,C78>0),(C78-B78)/B78,IF(AND(B78=0,C78<=0),"",(C78-B78)/B78)))) -> 1 | E78: =+SUM(E79:E84) -> 0 | F78: =IF(AND(C78=0,E78>0),100%,IF(AND(C78<0,E78>=0),(C78-E78)/C78,IF(AND(C78>0,E78>0),(E78-C78)/C78,IF(AND(C78=0,E78<=0),"",(E78-C78)/C78)))) -> -1 | G78: =+SUM(G79:G84) -> 0 | H78: =IF(AND(E78=0,G78>0),100%,IF(AND(E78<0,G78>=0),(E78-G78)/E78,IF(AND(E78>0,G78>0),(G78-E78)/E78,IF(AND(E78=0,G78<=0),"",(G78-E78)/E78)))) | I78: =+SUM(I79:I84) -> 0 | J78: =IF(AND(G78=0,I78>0),100%,IF(AND(G78<0,I78>=0),(G78-I78)/G78,IF(AND(G78>0,I78>0),(I78-G78)/G78,IF(AND(G78=0,I78<=0),"",(I78-G78)/G78)))) | K78: =IF(AND(B78=0,I78>0),100%,IF(AND(B78<0,I78>=0),(B78-I78)/B78,IF(AND(B78>0,I78>0),(I78-B78)/B78,IF(AND(B78=0,I78<=0),"",(I78-B78)/B78))))
A79: A empresas relacionadas del grupo | B79: =+'N ESF'!B371 -> 0 | C79: =+'N ESF'!E371 -> 2220 | D79: =IF(AND(B79=0,C79>0),100%,IF(AND(B79<0,C79>=0),(B79-C79)/B79,IF(AND(B79>0,C79>0),(C79-B79)/B79,IF(AND(B79=0,C79<=0),"",(C79-B79)/B79)))) -> 1 | E79: =+'N ESF'!H371 -> 0 | F79: =IF(AND(C79=0,E79>0),100%,IF(AND(C79<0,E79>=0),(C79-E79)/C79,IF(AND(C79>0,E79>0),(E79-C79)/C79,IF(AND(C79=0,E79<=0),"",(E79-C79)/C79)))) -> -1 | G79: =+'N ESF'!K371 -> 0 | H79: =IF(AND(E79=0,G79>0),100%,IF(AND(E79<0,G79>=0),(E79-G79)/E79,IF(AND(E79>0,G79>0),(G79-E79)/E79,IF(AND(E79=0,G79<=0),"",(G79-E79)/E79)))) | I79: =+'N ESF'!N371 -> 0 | J79: =IF(AND(G79=0,I79>0),100%,IF(AND(G79<0,I79>=0),(G79-I79)/G79,IF(AND(G79>0,I79>0),(I79-G79)/G79,IF(AND(G79=0,I79<=0),"",(I79-G79)/G79)))) | K79: =IF(AND(B79=0,I79>0),100%,IF(AND(B79<0,I79>=0),(B79-I79)/B79,IF(AND(B79>0,I79>0),(I79-B79)/B79,IF(AND(B79=0,I79<=0),"",(I79-B79)/B79))))
A80: A empresas externas del grupo | B80: =+'N ESF'!B376 -> 0 | C80: =+'N ESF'!E376 -> 3000 | D80: =IF(AND(B80=0,C80>0),100%,IF(AND(B80<0,C80>=0),(B80-C80)/B80,IF(AND(B80>0,C80>0),(C80-B80)/B80,IF(AND(B80=0,C80<=0),"",(C80-B80)/B80)))) -> 1 | E80: =+'N ESF'!H376 -> 0 | F80: =IF(AND(C80=0,E80>0),100%,IF(AND(C80<0,E80>=0),(C80-E80)/C80,IF(AND(C80>0,E80>0),(E80-C80)/C80,IF(AND(C80=0,E80<=0),"",(E80-C80)/C80)))) -> -1 | G80: =+'N ESF'!K376 -> 0 | H80: =IF(AND(E80=0,G80>0),100%,IF(AND(E80<0,G80>=0),(E80-G80)/E80,IF(AND(E80>0,G80>0),(G80-E80)/E80,IF(AND(E80=0,G80<=0),"",(G80-E80)/E80)))) | I80: =+'N ESF'!N376 -> 0 | J80: =IF(AND(G80=0,I80>0),100%,IF(AND(G80<0,I80>=0),(G80-I80)/G80,IF(AND(G80>0,I80>0),(I80-G80)/G80,IF(AND(G80=0,I80<=0),"",(I80-G80)/G80)))) | K80: =IF(AND(B80=0,I80>0),100%,IF(AND(B80<0,I80>=0),(B80-I80)/B80,IF(AND(B80>0,I80>0),(I80-B80)/B80,IF(AND(B80=0,I80<=0),"",(I80-B80)/B80))))
A81: A socios | B81: =+'N ESF'!B382 -> 0 | C81: =+'N ESF'!E382 -> 1920 | D81: =IF(AND(B81=0,C81>0),100%,IF(AND(B81<0,C81>=0),(B81-C81)/B81,IF(AND(B81>0,C81>0),(C81-B81)/B81,IF(AND(B81=0,C81<=0),"",(C81-B81)/B81)))) -> 1 | E81: =+'N ESF'!H382 -> 0 | F81: =IF(AND(C81=0,E81>0),100%,IF(AND(C81<0,E81>=0),(C81-E81)/C81,IF(AND(C81>0,E81>0),(E81-C81)/C81,IF(AND(C81=0,E81<=0),"",(E81-C81)/C81)))) -> -1 | G81: =+'N ESF'!K382 -> 0 | H81: =IF(AND(E81=0,G81>0),100%,IF(AND(E81<0,G81>=0),(E81-G81)/E81,IF(AND(E81>0,G81>0),(G81-E81)/E81,IF(AND(E81=0,G81<=0),"",(G81-E81)/E81)))) | I81: =+'N ESF'!N382 -> 0 | J81: =IF(AND(G81=0,I81>0),100%,IF(AND(G81<0,I81>=0),(G81-I81)/G81,IF(AND(G81>0,I81>0),(I81-G81)/G81,IF(AND(G81=0,I81<=0),"",(I81-G81)/G81)))) | K81: =IF(AND(B81=0,I81>0),100%,IF(AND(B81<0,I81>=0),(B81-I81)/B81,IF(AND(B81>0,I81>0),(I81-B81)/B81,IF(AND(B81=0,I81<=0),"",(I81-B81)/B81))))
A82: A empleados | B82: =+'N ESF'!B386 -> 0 | C82: =+'N ESF'!E386 -> 660 | D82: =IF(AND(B82=0,C82>0),100%,IF(AND(B82<0,C82>=0),(B82-C82)/B82,IF(AND(B82>0,C82>0),(C82-B82)/B82,IF(AND(B82=0,C82<=0),"",(C82-B82)/B82)))) -> 1 | E82: =+'N ESF'!H386 -> 0 | F82: =IF(AND(C82=0,E82>0),100%,IF(AND(C82<0,E82>=0),(C82-E82)/C82,IF(AND(C82>0,E82>0),(E82-C82)/C82,IF(AND(C82=0,E82<=0),"",(E82-C82)/C82)))) -> -1 | G82: =+'N ESF'!K386 -> 0 | H82: =IF(AND(E82=0,G82>0),100%,IF(AND(E82<0,G82>=0),(E82-G82)/E82,IF(AND(E82>0,G82>0),(G82-E82)/E82,IF(AND(E82=0,G82<=0),"",(G82-E82)/E82)))) | I82: =+'N ESF'!N386 -> 0 | J82: =IF(AND(G82=0,I82>0),100%,IF(AND(G82<0,I82>=0),(G82-I82)/G82,IF(AND(G82>0,I82>0),(I82-G82)/G82,IF(AND(G82=0,I82<=0),"",(I82-G82)/G82)))) | K82: =IF(AND(B82=0,I82>0),100%,IF(AND(B82<0,I82>=0),(B82-I82)/B82,IF(AND(B82>0,I82>0),(I82-B82)/B82,IF(AND(B82=0,I82<=0),"",(I82-B82)/B82))))
A83: Prestamos bancarios por pagar | B83: =+'N ESF'!B388 -> 0 | C83: =+'N ESF'!E388 -> 6390 | D83: =IF(AND(B83=0,C83>0),100%,IF(AND(B83<0,C83>=0),(B83-C83)/B83,IF(AND(B83>0,C83>0),(C83-B83)/B83,IF(AND(B83=0,C83<=0),"",(C83-B83)/B83)))) -> 1 | E83: =+'N ESF'!H388 -> 0 | F83: =IF(AND(C83=0,E83>0),100%,IF(AND(C83<0,E83>=0),(C83-E83)/C83,IF(AND(C83>0,E83>0),(E83-C83)/C83,IF(AND(C83=0,E83<=0),"",(E83-C83)/C83)))) -> -1 | G83: =+'N ESF'!K388 -> 0 | H83: =IF(AND(E83=0,G83>0),100%,IF(AND(E83<0,G83>=0),(E83-G83)/E83,IF(AND(E83>0,G83>0),(G83-E83)/E83,IF(AND(E83=0,G83<=0),"",(G83-E83)/E83)))) | I83: =+'N ESF'!N388 -> 0 | J83: =IF(AND(G83=0,I83>0),100%,IF(AND(G83<0,I83>=0),(G83-I83)/G83,IF(AND(G83>0,I83>0),(I83-G83)/G83,IF(AND(G83=0,I83<=0),"",(I83-G83)/G83)))) | K83: =IF(AND(B83=0,I83>0),100%,IF(AND(B83<0,I83>=0),(B83-I83)/B83,IF(AND(B83>0,I83>0),(I83-B83)/B83,IF(AND(B83=0,I83<=0),"",(I83-B83)/B83))))
A84: Otros prestamos por pagar | B84: =+'N ESF'!B398 -> 0 | C84: =+'N ESF'!E398 -> 760 | D84: =IF(AND(B84=0,C84>0),100%,IF(AND(B84<0,C84>=0),(B84-C84)/B84,IF(AND(B84>0,C84>0),(C84-B84)/B84,IF(AND(B84=0,C84<=0),"",(C84-B84)/B84)))) -> 1 | E84: =+'N ESF'!H398 -> 0 | F84: =IF(AND(C84=0,E84>0),100%,IF(AND(C84<0,E84>=0),(C84-E84)/C84,IF(AND(C84>0,E84>0),(E84-C84)/C84,IF(AND(C84=0,E84<=0),"",(E84-C84)/C84)))) -> -1 | G84: =+'N ESF'!K398 -> 0 | H84: =IF(AND(E84=0,G84>0),100%,IF(AND(E84<0,G84>=0),(E84-G84)/E84,IF(AND(E84>0,G84>0),(G84-E84)/E84,IF(AND(E84=0,G84<=0),"",(G84-E84)/E84)))) | I84: =+'N ESF'!N398 -> 0 | J84: =IF(AND(G84=0,I84>0),100%,IF(AND(G84<0,I84>=0),(G84-I84)/G84,IF(AND(G84>0,I84>0),(I84-G84)/G84,IF(AND(G84=0,I84<=0),"",(I84-G84)/G84)))) | K84: =IF(AND(B84=0,I84>0),100%,IF(AND(B84<0,I84>=0),(B84-I84)/B84,IF(AND(B84>0,I84>0),(I84-B84)/B84,IF(AND(B84=0,I84<=0),"",(I84-B84)/B84))))
A85: Anticipos | B85: =+SUM(B86:B88) -> 0 | C85: =+SUM(C86:C88) -> 4770 | D85: =IF(AND(B85=0,C85>0),100%,IF(AND(B85<0,C85>=0),(B85-C85)/B85,IF(AND(B85>0,C85>0),(C85-B85)/B85,IF(AND(B85=0,C85<=0),"",(C85-B85)/B85)))) -> 1 | E85: =+SUM(E86:E88) -> 0 | F85: =IF(AND(C85=0,E85>0),100%,IF(AND(C85<0,E85>=0),(C85-E85)/C85,IF(AND(C85>0,E85>0),(E85-C85)/C85,IF(AND(C85=0,E85<=0),"",(E85-C85)/C85)))) -> -1 | G85: =+SUM(G86:G88) -> 0 | H85: =IF(AND(E85=0,G85>0),100%,IF(AND(E85<0,G85>=0),(E85-G85)/E85,IF(AND(E85>0,G85>0),(G85-E85)/E85,IF(AND(E85=0,G85<=0),"",(G85-E85)/E85)))) | I85: =+SUM(I86:I88) -> 0 | J85: =IF(AND(G85=0,I85>0),100%,IF(AND(G85<0,I85>=0),(G85-I85)/G85,IF(AND(G85>0,I85>0),(I85-G85)/G85,IF(AND(G85=0,I85<=0),"",(I85-G85)/G85)))) | K85: =IF(AND(B85=0,I85>0),100%,IF(AND(B85<0,I85>=0),(B85-I85)/B85,IF(AND(B85>0,I85>0),(I85-B85)/B85,IF(AND(B85=0,I85<=0),"",(I85-B85)/B85))))
A86: De clientes | B86: =+'N ESF'!B401 -> 0 | C86: =+'N ESF'!E401 -> 770 | D86: =IF(AND(B86=0,C86>0),100%,IF(AND(B86<0,C86>=0),(B86-C86)/B86,IF(AND(B86>0,C86>0),(C86-B86)/B86,IF(AND(B86=0,C86<=0),"",(C86-B86)/B86)))) -> 1 | E86: =+'N ESF'!H401 -> 0 | F86: =IF(AND(C86=0,E86>0),100%,IF(AND(C86<0,E86>=0),(C86-E86)/C86,IF(AND(C86>0,E86>0),(E86-C86)/C86,IF(AND(C86=0,E86<=0),"",(E86-C86)/C86)))) -> -1 | G86: =+'N ESF'!K401 -> 0 | H86: =IF(AND(E86=0,G86>0),100%,IF(AND(E86<0,G86>=0),(E86-G86)/E86,IF(AND(E86>0,G86>0),(G86-E86)/E86,IF(AND(E86=0,G86<=0),"",(G86-E86)/E86)))) | I86: =+'N ESF'!N401 -> 0 | J86: =IF(AND(G86=0,I86>0),100%,IF(AND(G86<0,I86>=0),(G86-I86)/G86,IF(AND(G86>0,I86>0),(I86-G86)/G86,IF(AND(G86=0,I86<=0),"",(I86-G86)/G86)))) | K86: =IF(AND(B86=0,I86>0),100%,IF(AND(B86<0,I86>=0),(B86-I86)/B86,IF(AND(B86>0,I86>0),(I86-B86)/B86,IF(AND(B86=0,I86<=0),"",(I86-B86)/B86))))
A87: De socios | B87: =+'N ESF'!B403 -> 0 | C87: =+'N ESF'!E403 -> 3180 | D87: =IF(AND(B87=0,C87>0),100%,IF(AND(B87<0,C87>=0),(B87-C87)/B87,IF(AND(B87>0,C87>0),(C87-B87)/B87,IF(AND(B87=0,C87<=0),"",(C87-B87)/B87)))) -> 1 | E87: =+'N ESF'!H403 -> 0 | F87: =IF(AND(C87=0,E87>0),100%,IF(AND(C87<0,E87>=0),(C87-E87)/C87,IF(AND(C87>0,E87>0),(E87-C87)/C87,IF(AND(C87=0,E87<=0),"",(E87-C87)/C87)))) -> -1 | G87: =+'N ESF'!K403 -> 0 | H87: =IF(AND(E87=0,G87>0),100%,IF(AND(E87<0,G87>=0),(E87-G87)/E87,IF(AND(E87>0,G87>0),(G87-E87)/E87,IF(AND(E87=0,G87<=0),"",(G87-E87)/E87)))) | I87: =+'N ESF'!N403 -> 0 | J87: =IF(AND(G87=0,I87>0),100%,IF(AND(G87<0,I87>=0),(G87-I87)/G87,IF(AND(G87>0,I87>0),(I87-G87)/G87,IF(AND(G87=0,I87<=0),"",(I87-G87)/G87)))) | K87: =IF(AND(B87=0,I87>0),100%,IF(AND(B87<0,I87>=0),(B87-I87)/B87,IF(AND(B87>0,I87>0),(I87-B87)/B87,IF(AND(B87=0,I87<=0),"",(I87-B87)/B87))))
A88: No reportados | B88: =+'N ESF'!B408 -> 0 | C88: =+'N ESF'!E408 -> 820 | D88: =IF(AND(B88=0,C88>0),100%,IF(AND(B88<0,C88>=0),(B88-C88)/B88,IF(AND(B88>0,C88>0),(C88-B88)/B88,IF(AND(B88=0,C88<=0),"",(C88-B88)/B88)))) -> 1 | E88: =+'N ESF'!H408 -> 0 | F88: =IF(AND(C88=0,E88>0),100%,IF(AND(C88<0,E88>=0),(C88-E88)/C88,IF(AND(C88>0,E88>0),(E88-C88)/C88,IF(AND(C88=0,E88<=0),"",(E88-C88)/C88)))) -> -1 | G88: =+'N ESF'!K408 -> 0 | H88: =IF(AND(E88=0,G88>0),100%,IF(AND(E88<0,G88>=0),(E88-G88)/E88,IF(AND(E88>0,G88>0),(G88-E88)/E88,IF(AND(E88=0,G88<=0),"",(G88-E88)/E88)))) | I88: =+'N ESF'!N408 -> 0 | J88: =IF(AND(G88=0,I88>0),100%,IF(AND(G88<0,I88>=0),(G88-I88)/G88,IF(AND(G88>0,I88>0),(I88-G88)/G88,IF(AND(G88=0,I88<=0),"",(I88-G88)/G88)))) | K88: =IF(AND(B88=0,I88>0),100%,IF(AND(B88<0,I88>=0),(B88-I88)/B88,IF(AND(B88>0,I88>0),(I88-B88)/B88,IF(AND(B88=0,I88<=0),"",(I88-B88)/B88))))
A89: Provisiones | B89: =+SUM(B90:B91) -> 0 | C89: =+SUM(C90:C91) -> 1670 | D89: =IF(AND(B89=0,C89>0),100%,IF(AND(B89<0,C89>=0),(B89-C89)/B89,IF(AND(B89>0,C89>0),(C89-B89)/B89,IF(AND(B89=0,C89<=0),"",(C89-B89)/B89)))) -> 1 | E89: =+SUM(E90:E91) -> 0 | F89: =IF(AND(C89=0,E89>0),100%,IF(AND(C89<0,E89>=0),(C89-E89)/C89,IF(AND(C89>0,E89>0),(E89-C89)/C89,IF(AND(C89=0,E89<=0),"",(E89-C89)/C89)))) -> -1 | G89: =+SUM(G90:G91) -> 0 | H89: =IF(AND(E89=0,G89>0),100%,IF(AND(E89<0,G89>=0),(E89-G89)/E89,IF(AND(E89>0,G89>0),(G89-E89)/E89,IF(AND(E89=0,G89<=0),"",(G89-E89)/E89)))) | I89: =+SUM(I90:I91) -> 0 | J89: =IF(AND(G89=0,I89>0),100%,IF(AND(G89<0,I89>=0),(G89-I89)/G89,IF(AND(G89>0,I89>0),(I89-G89)/G89,IF(AND(G89=0,I89<=0),"",(I89-G89)/G89)))) | K89: =IF(AND(B89=0,I89>0),100%,IF(AND(B89<0,I89>=0),(B89-I89)/B89,IF(AND(B89>0,I89>0),(I89-B89)/B89,IF(AND(B89=0,I89<=0),"",(I89-B89)/B89))))
A90: Provisiones para empleados | B90: =+'N ESF'!B411 -> 0 | C90: =+'N ESF'!E411 -> 1670 | D90: =IF(AND(B90=0,C90>0),100%,IF(AND(B90<0,C90>=0),(B90-C90)/B90,IF(AND(B90>0,C90>0),(C90-B90)/B90,IF(AND(B90=0,C90<=0),"",(C90-B90)/B90)))) -> 1 | E90: =+'N ESF'!H411 -> 0 | F90: =IF(AND(C90=0,E90>0),100%,IF(AND(C90<0,E90>=0),(C90-E90)/C90,IF(AND(C90>0,E90>0),(E90-C90)/C90,IF(AND(C90=0,E90<=0),"",(E90-C90)/C90)))) -> -1 | G90: =+'N ESF'!K411 -> 0 | H90: =IF(AND(E90=0,G90>0),100%,IF(AND(E90<0,G90>=0),(E90-G90)/E90,IF(AND(E90>0,G90>0),(G90-E90)/E90,IF(AND(E90=0,G90<=0),"",(G90-E90)/E90)))) | I90: =+'N ESF'!N411 -> 0 | J90: =IF(AND(G90=0,I90>0),100%,IF(AND(G90<0,I90>=0),(G90-I90)/G90,IF(AND(G90>0,I90>0),(I90-G90)/G90,IF(AND(G90=0,I90<=0),"",(I90-G90)/G90)))) | K90: =IF(AND(B90=0,I90>0),100%,IF(AND(B90<0,I90>=0),(B90-I90)/B90,IF(AND(B90>0,I90>0),(I90-B90)/B90,IF(AND(B90=0,I90<=0),"",(I90-B90)/B90))))
D91: =IF(AND(B91=0,C91>0),100%,IF(AND(B91<0,C91>=0),(B91-C91)/B91,IF(AND(B91>0,C91>0),(C91-B91)/B91,IF(AND(B91=0,C91<=0),"",(C91-B91)/B91)))) | F91: =IF(AND(C91=0,E91>0),100%,IF(AND(C91<0,E91>=0),(C91-E91)/C91,IF(AND(C91>0,E91>0),(E91-C91)/C91,IF(AND(C91=0,E91<=0),"",(E91-C91)/C91)))) | H91: =IF(AND(E91=0,G91>0),100%,IF(AND(E91<0,G91>=0),(E91-G91)/E91,IF(AND(E91>0,G91>0),(G91-E91)/E91,IF(AND(E91=0,G91<=0),"",(G91-E91)/E91)))) | J91: =IF(AND(G91=0,I91>0),100%,IF(AND(G91<0,I91>=0),(G91-I91)/G91,IF(AND(G91>0,I91>0),(I91-G91)/G91,IF(AND(G91=0,I91<=0),"",(I91-G91)/G91)))) | K91: =IF(AND(B91=0,I91>0),100%,IF(AND(B91<0,I91>=0),(B91-I91)/B91,IF(AND(B91>0,I91>0),(I91-B91)/B91,IF(AND(B91=0,I91<=0),"",(I91-B91)/B91))))
A92: PASIVOS NO CORRIENTES | B92: =+B93 -> 0 | C92: =+C93 -> 28710 | D92: =IF(AND(B92=0,C92>0),100%,IF(AND(B92<0,C92>=0),(B92-C92)/B92,IF(AND(B92>0,C92>0),(C92-B92)/B92,IF(AND(B92=0,C92<=0),"",(C92-B92)/B92)))) -> 1 | E92: =+E93 -> 0 | F92: =IF(AND(C92=0,E92>0),100%,IF(AND(C92<0,E92>=0),(C92-E92)/C92,IF(AND(C92>0,E92>0),(E92-C92)/C92,IF(AND(C92=0,E92<=0),"",(E92-C92)/C92)))) -> -1 | G92: =+G93 -> 0 | H92: =IF(AND(E92=0,G92>0),100%,IF(AND(E92<0,G92>=0),(E92-G92)/E92,IF(AND(E92>0,G92>0),(G92-E92)/E92,IF(AND(E92=0,G92<=0),"",(G92-E92)/E92)))) | I92: =+I93 -> 0 | J92: =IF(AND(G92=0,I92>0),100%,IF(AND(G92<0,I92>=0),(G92-I92)/G92,IF(AND(G92>0,I92>0),(I92-G92)/G92,IF(AND(G92=0,I92<=0),"",(I92-G92)/G92)))) | K92: =IF(AND(B92=0,I92>0),100%,IF(AND(B92<0,I92>=0),(B92-I92)/B92,IF(AND(B92>0,I92>0),(I92-B92)/B92,IF(AND(B92=0,I92<=0),"",(I92-B92)/B92))))
A93: Otras cuentas por pagar L.P. | B93: =+SUM(B94:B96) -> 0 | C93: =+SUM(C94:C96) -> 28710 | D93: =IF(AND(B93=0,C93>0),100%,IF(AND(B93<0,C93>=0),(B93-C93)/B93,IF(AND(B93>0,C93>0),(C93-B93)/B93,IF(AND(B93=0,C93<=0),"",(C93-B93)/B93)))) -> 1 | E93: =+SUM(E94:E96) -> 0 | F93: =IF(AND(C93=0,E93>0),100%,IF(AND(C93<0,E93>=0),(C93-E93)/C93,IF(AND(C93>0,E93>0),(E93-C93)/C93,IF(AND(C93=0,E93<=0),"",(E93-C93)/C93)))) -> -1 | G93: =+SUM(G94:G96) -> 0 | H93: =IF(AND(E93=0,G93>0),100%,IF(AND(E93<0,G93>=0),(E93-G93)/E93,IF(AND(E93>0,G93>0),(G93-E93)/E93,IF(AND(E93=0,G93<=0),"",(G93-E93)/E93)))) | I93: =+SUM(I94:I96) -> 0 | J93: =IF(AND(G93=0,I93>0),100%,IF(AND(G93<0,I93>=0),(G93-I93)/G93,IF(AND(G93>0,I93>0),(I93-G93)/G93,IF(AND(G93=0,I93<=0),"",(I93-G93)/G93)))) | K93: =IF(AND(B93=0,I93>0),100%,IF(AND(B93<0,I93>=0),(B93-I93)/B93,IF(AND(B93>0,I93>0),(I93-B93)/B93,IF(AND(B93=0,I93<=0),"",(I93-B93)/B93))))
A94: Intereses por pagar LP | B94: =+'N ESF'!B417 -> 0 | C94: =+'N ESF'!E417 -> 1710 | D94: =IF(AND(B94=0,C94>0),100%,IF(AND(B94<0,C94>=0),(B94-C94)/B94,IF(AND(B94>0,C94>0),(C94-B94)/B94,IF(AND(B94=0,C94<=0),"",(C94-B94)/B94)))) -> 1 | E94: =+'N ESF'!H417 -> 0 | F94: =IF(AND(C94=0,E94>0),100%,IF(AND(C94<0,E94>=0),(C94-E94)/C94,IF(AND(C94>0,E94>0),(E94-C94)/C94,IF(AND(C94=0,E94<=0),"",(E94-C94)/C94)))) -> -1 | G94: =+'N ESF'!K417 -> 0 | H94: =IF(AND(E94=0,G94>0),100%,IF(AND(E94<0,G94>=0),(E94-G94)/E94,IF(AND(E94>0,G94>0),(G94-E94)/E94,IF(AND(E94=0,G94<=0),"",(G94-E94)/E94)))) | I94: =+'N ESF'!N417 -> 0 | J94: =IF(AND(G94=0,I94>0),100%,IF(AND(G94<0,I94>=0),(G94-I94)/G94,IF(AND(G94>0,I94>0),(I94-G94)/G94,IF(AND(G94=0,I94<=0),"",(I94-G94)/G94)))) | K94: =IF(AND(B94=0,I94>0),100%,IF(AND(B94<0,I94>=0),(B94-I94)/B94,IF(AND(B94>0,I94>0),(I94-B94)/B94,IF(AND(B94=0,I94<=0),"",(I94-B94)/B94))))
A95: Prestamos por pagar LP | B95: =+'N ESF'!B420 -> 0 | C95: =+'N ESF'!E420 -> 23640 | D95: =IF(AND(B95=0,C95>0),100%,IF(AND(B95<0,C95>=0),(B95-C95)/B95,IF(AND(B95>0,C95>0),(C95-B95)/B95,IF(AND(B95=0,C95<=0),"",(C95-B95)/B95)))) -> 1 | E95: =+'N ESF'!H420 -> 0 | F95: =IF(AND(C95=0,E95>0),100%,IF(AND(C95<0,E95>=0),(C95-E95)/C95,IF(AND(C95>0,E95>0),(E95-C95)/C95,IF(AND(C95=0,E95<=0),"",(E95-C95)/C95)))) -> -1 | G95: =+'N ESF'!K420 -> 0 | H95: =IF(AND(E95=0,G95>0),100%,IF(AND(E95<0,G95>=0),(E95-G95)/E95,IF(AND(E95>0,G95>0),(G95-E95)/E95,IF(AND(E95=0,G95<=0),"",(G95-E95)/E95)))) | I95: =+'N ESF'!N420 -> 0 | J95: =IF(AND(G95=0,I95>0),100%,IF(AND(G95<0,I95>=0),(G95-I95)/G95,IF(AND(G95>0,I95>0),(I95-G95)/G95,IF(AND(G95=0,I95<=0),"",(I95-G95)/G95)))) | K95: =IF(AND(B95=0,I95>0),100%,IF(AND(B95<0,I95>=0),(B95-I95)/B95,IF(AND(B95>0,I95>0),(I95-B95)/B95,IF(AND(B95=0,I95<=0),"",(I95-B95)/B95))))
A96: Provisiones LP | B96: =+'N ESF'!B445 -> 0 | C96: =+'N ESF'!E445 -> 3360 | D96: =IF(AND(B96=0,C96>0),100%,IF(AND(B96<0,C96>=0),(B96-C96)/B96,IF(AND(B96>0,C96>0),(C96-B96)/B96,IF(AND(B96=0,C96<=0),"",(C96-B96)/B96)))) -> 1 | E96: =+'N ESF'!H445 -> 0 | F96: =IF(AND(C96=0,E96>0),100%,IF(AND(C96<0,E96>=0),(C96-E96)/C96,IF(AND(C96>0,E96>0),(E96-C96)/C96,IF(AND(C96=0,E96<=0),"",(E96-C96)/C96)))) -> -1 | G96: =+'N ESF'!K445 -> 0 | H96: =IF(AND(E96=0,G96>0),100%,IF(AND(E96<0,G96>=0),(E96-G96)/E96,IF(AND(E96>0,G96>0),(G96-E96)/E96,IF(AND(E96=0,G96<=0),"",(G96-E96)/E96)))) | I96: =+'N ESF'!N445 -> 0 | J96: =IF(AND(G96=0,I96>0),100%,IF(AND(G96<0,I96>=0),(G96-I96)/G96,IF(AND(G96>0,I96>0),(I96-G96)/G96,IF(AND(G96=0,I96<=0),"",(I96-G96)/G96)))) | K96: =IF(AND(B96=0,I96>0),100%,IF(AND(B96<0,I96>=0),(B96-I96)/B96,IF(AND(B96>0,I96>0),(I96-B96)/B96,IF(AND(B96=0,I96<=0),"",(I96-B96)/B96))))
D97: =IF(AND(B97=0,C97>0),100%,IF(AND(B97<0,C97>=0),(B97-C97)/B97,IF(AND(B97>0,C97>0),(C97-B97)/B97,IF(AND(B97=0,C97<=0),"",(C97-B97)/B97)))) | F97: =IF(AND(C97=0,E97>0),100%,IF(AND(C97<0,E97>=0),(C97-E97)/C97,IF(AND(C97>0,E97>0),(E97-C97)/C97,IF(AND(C97=0,E97<=0),"",(E97-C97)/C97)))) | H97: =IF(AND(E97=0,G97>0),100%,IF(AND(E97<0,G97>=0),(E97-G97)/E97,IF(AND(E97>0,G97>0),(G97-E97)/E97,IF(AND(E97=0,G97<=0),"",(G97-E97)/E97)))) | J97: =IF(AND(G97=0,I97>0),100%,IF(AND(G97<0,I97>=0),(G97-I97)/G97,IF(AND(G97>0,I97>0),(I97-G97)/G97,IF(AND(G97=0,I97<=0),"",(I97-G97)/G97)))) | K97: =IF(AND(B97=0,I97>0),100%,IF(AND(B97<0,I97>=0),(B97-I97)/B97,IF(AND(B97>0,I97>0),(I97-B97)/B97,IF(AND(B97=0,I97<=0),"",(I97-B97)/B97))))
A98: TOTAL PASIVOS | B98: =+B61+B92 -> 0 | C98: =+C61+C92 -> 260710 | D98: =IF(AND(B98=0,C98>0),100%,IF(AND(B98<0,C98>=0),(B98-C98)/B98,IF(AND(B98>0,C98>0),(C98-B98)/B98,IF(AND(B98=0,C98<=0),"",(C98-B98)/B98)))) -> 1 | E98: =+E61+E92 -> 0 | F98: =IF(AND(C98=0,E98>0),100%,IF(AND(C98<0,E98>=0),(C98-E98)/C98,IF(AND(C98>0,E98>0),(E98-C98)/C98,IF(AND(C98=0,E98<=0),"",(E98-C98)/C98)))) -> -1 | G98: =+G61+G92 -> 0 | H98: =IF(AND(E98=0,G98>0),100%,IF(AND(E98<0,G98>=0),(E98-G98)/E98,IF(AND(E98>0,G98>0),(G98-E98)/E98,IF(AND(E98=0,G98<=0),"",(G98-E98)/E98)))) | I98: =+I61+I92 -> 0 | J98: =IF(AND(G98=0,I98>0),100%,IF(AND(G98<0,I98>=0),(G98-I98)/G98,IF(AND(G98>0,I98>0),(I98-G98)/G98,IF(AND(G98=0,I98<=0),"",(I98-G98)/G98)))) | K98: =IF(AND(B98=0,I98>0),100%,IF(AND(B98<0,I98>=0),(B98-I98)/B98,IF(AND(B98>0,I98>0),(I98-B98)/B98,IF(AND(B98=0,I98<=0),"",(I98-B98)/B98))))
A99: PATRIMONIO | B99: =+SUM(B100:B104) -> 0 | C99: =+SUM(C100:C104) -> 9900 | D99: =IF(AND(B99=0,C99>0),100%,IF(AND(B99<0,C99>=0),(B99-C99)/B99,IF(AND(B99>0,C99>0),(C99-B99)/B99,IF(AND(B99=0,C99<=0),"",(C99-B99)/B99)))) -> 1 | E99: =+SUM(E100:E104) -> 3710 | F99: =IF(AND(C99=0,E99>0),100%,IF(AND(C99<0,E99>=0),(C99-E99)/C99,IF(AND(C99>0,E99>0),(E99-C99)/C99,IF(AND(C99=0,E99<=0),"",(E99-C99)/C99)))) -> -0.62525253 | G99: =+SUM(G100:G104) -> 3710 | H99: =IF(AND(E99=0,G99>0),100%,IF(AND(E99<0,G99>=0),(E99-G99)/E99,IF(AND(E99>0,G99>0),(G99-E99)/E99,IF(AND(E99=0,G99<=0),"",(G99-E99)/E99)))) -> 0 | I99: =+SUM(I100:I104) -> 3710 | J99: =IF(AND(G99=0,I99>0),100%,IF(AND(G99<0,I99>=0),(G99-I99)/G99,IF(AND(G99>0,I99>0),(I99-G99)/G99,IF(AND(G99=0,I99<=0),"",(I99-G99)/G99)))) -> 0 | K99: =IF(AND(B99=0,I99>0),100%,IF(AND(B99<0,I99>=0),(B99-I99)/B99,IF(AND(B99>0,I99>0),(I99-B99)/B99,IF(AND(B99=0,I99<=0),"",(I99-B99)/B99)))) -> 1
A100: Capital social | B100: =+'N ESF'!B452 -> 0 | C100: =+'N ESF'!E452 -> 1140 | D100: =IF(AND(B100=0,C100>0),100%,IF(AND(B100<0,C100>=0),(B100-C100)/B100,IF(AND(B100>0,C100>0),(C100-B100)/B100,IF(AND(B100=0,C100<=0),"",(C100-B100)/B100)))) -> 1 | E100: =+'N ESF'!H452 -> 0 | F100: =IF(AND(C100=0,E100>0),100%,IF(AND(C100<0,E100>=0),(C100-E100)/C100,IF(AND(C100>0,E100>0),(E100-C100)/C100,IF(AND(C100=0,E100<=0),"",(E100-C100)/C100)))) -> -1 | G100: =+'N ESF'!K452 -> 0 | H100: =IF(AND(E100=0,G100>0),100%,IF(AND(E100<0,G100>=0),(E100-G100)/E100,IF(AND(E100>0,G100>0),(G100-E100)/E100,IF(AND(E100=0,G100<=0),"",(G100-E100)/E100)))) | I100: =+'N ESF'!N452 -> 0 | J100: =IF(AND(G100=0,I100>0),100%,IF(AND(G100<0,I100>=0),(G100-I100)/G100,IF(AND(G100>0,I100>0),(I100-G100)/G100,IF(AND(G100=0,I100<=0),"",(I100-G100)/G100)))) | K100: =IF(AND(B100=0,I100>0),100%,IF(AND(B100<0,I100>=0),(B100-I100)/B100,IF(AND(B100>0,I100>0),(I100-B100)/B100,IF(AND(B100=0,I100<=0),"",(I100-B100)/B100))))
A101: Reservas legales y estatutarias | B101: =+'N ESF'!B454 -> 0 | C101: =+'N ESF'!E454 -> 1150 | D101: =IF(AND(B101=0,C101>0),100%,IF(AND(B101<0,C101>=0),(B101-C101)/B101,IF(AND(B101>0,C101>0),(C101-B101)/B101,IF(AND(B101=0,C101<=0),"",(C101-B101)/B101)))) -> 1 | E101: =+'N ESF'!H454 -> 0 | F101: =IF(AND(C101=0,E101>0),100%,IF(AND(C101<0,E101>=0),(C101-E101)/C101,IF(AND(C101>0,E101>0),(E101-C101)/C101,IF(AND(C101=0,E101<=0),"",(E101-C101)/C101)))) -> -1 | G101: =+'N ESF'!K454 -> 0 | H101: =IF(AND(E101=0,G101>0),100%,IF(AND(E101<0,G101>=0),(E101-G101)/E101,IF(AND(E101>0,G101>0),(G101-E101)/E101,IF(AND(E101=0,G101<=0),"",(G101-E101)/E101)))) | I101: =+'N ESF'!N454 -> 0 | J101: =IF(AND(G101=0,I101>0),100%,IF(AND(G101<0,I101>=0),(G101-I101)/G101,IF(AND(G101>0,I101>0),(I101-G101)/G101,IF(AND(G101=0,I101<=0),"",(I101-G101)/G101)))) | K101: =IF(AND(B101=0,I101>0),100%,IF(AND(B101<0,I101>=0),(B101-I101)/B101,IF(AND(B101>0,I101>0),(I101-B101)/B101,IF(AND(B101=0,I101<=0),"",(I101-B101)/B101))))
...

Sheet EERR RODEO
A2: ESTADO DE RESULTADOS
A3: PARTIDAS | B3: =IF(ISBLANK(A2),"",YEAR(TODAY())-1) -> 2025 | C3: % Vtas | D3: % Gastos | E3: ENE | F3: % Vtas | G3: % Gastos | H3: FEB | I3: % Vtas | J3: % Gastos | K3: Vari Rel. | L3: ACUM EJEC | M3: % Vtas | N3: % Gastos | O3: MAR | P3: % Vtas | Q3: % Gastos | R3: Vari Rel. | S3: ACUM EJEC | T3: % Vtas | U3: % Gastos | V3: ACUM PPTO | W3: % Vtas | X3: Var PPTO | Y3: ABR | Z3: % Vtas | AA3: % Gastos | AB3: Vari Rel. | AC3: ACUM EJEC | AD3: % Vtas | AE3: % Gastos | AF3: MAY | AG3: % Vtas | AH3: % Gastos | AI3: Vari Rel. | AJ3: ACUM EJEC | AK3: % Vtas | AL3: % Gastos | AM3: JUN | AN3: % Vtas | AO3: % Gastos | AP3: Vari Rel. | AQ3: ACUM EJEC | AR3: % Vtas | AS3: % Gastos | AT3: ACUM PPTO | AU3: % Vtas | AV3: Var PPTO | AW3: PROM 6 EJEC | AX3: % Vtas | AY3: % Gastos | AZ3: PROM 6 PPTO | BA3: % Vtas | BB3: Var PPTO | BC3: JUL | BD3: % Vtas | BE3: % Gastos | BF3: Vari Rel. | BG3: ACUM EJEC | BH3: % Vtas | BI3: % Gastos | BJ3: AGO | BK3: % Vtas | BL3: % Gastos | BM3: Vari Rel. | BN3: ACUM EJEC | BO3: % Vtas | BP3: % Gastos | BQ3: SEPT | BR3: % Vtas | BS3: % Gastos | BT3: Vari Rel. | BU3: ACUM EJEC | BV3: % Vtas | BW3: % Gastos | BX3: ACUM PPTO | BY3: % Vtas | BZ3: Var PPTO | CA3: OCT | CB3: % Vtas | CC3: % Gastos | CD3: Vari Rel. | CE3: ACUM EJEC | CF3: % Vtas | CG3: % Gastos | CH3: NOV | CI3: % Vtas | CJ3: % Gastos | CK3: Vari Rel. | CL3: ACUM EJEC | CM3: % Vtas | CN3: % Gastos | CO3: DIC | CP3: % Vtas | CQ3: % Gastos | CR3: Vari Rel. | CS3: 2025 | CT3: % Vtas | CU3: % Gastos | CV3: ACUM PPTO | CW3: % Vtas | CX3: Var PPTO
A4: Total Ingresos | B4: =+B5+B10+B15+B18 -> 0 | C4: =IF(AND(B4=0,B4>=0), "",B4/B4) | E4: =+E5+E10+E15+E18 -> 13800 | F4: =IF(AND(E4=0,E4>=0), "",E4/E4) -> 1 | H4: =+H5+H10+H15+H18 -> 0 | I4: =IF(AND(H4=0,H4>=0), "",H4/H4) | K4: =IF(AND(E4=0,H4>0),100%,IF(AND(E4<0,H4=0),(E4-H4)/E4,IF(AND(E4>0,H4>0),(H4-E4)/E4,IF(AND(E4=0,H4=0),"",(H4-E4)/E4)))) -> -1 | L4: =+L5+L10+L15+L18 -> 13800 | M4: =IF(AND(L4=0,L4>=0), "",L4/L4) -> 1 | O4: =+O5+O10+O15+O18 -> 0 | P4: =IF(AND(O4=0,O4>=0), "",O4/O4) | R4: =IF(AND(H4=0,O4>0),100%,IF(AND(H4<0,O4=0),(H4-O4)/H4,IF(AND(H4>0,O4>0),(O4-H4)/H4,IF(AND(H4=0,O4=0),"",(O4-H4)/H4)))) | S4: =+S5+S10+S15+S18 -> 13800 | T4: =IF(AND(S4=0,S4>=0), "",S4/S4) -> 1 | V4: =+V5+V10+V15+V18 -> 0 | W4: =IF(AND(V4=0,V4>=0), "",V4/V4) | X4: =IF(AND(V4=0,S4>0),100%,IF(AND(V4<0,S4=0),(V4-S4)/V4,IF(AND(V4>0,S4>0),(S4-V4)/V4,IF(AND(V4=0,S4=0),"",(S4-V4)/V4)))) -> 1 | Y4: =+Y5+Y10+Y15+Y18 -> 0 | Z4: =IF(AND(Y4=0,Y4>=0), "",Y4/Y4) | AB4: =IF(AND(O4=0,Y4>0),100%,IF(AND(O4<0,Y4=0),(O4-Y4)/O4,IF(AND(O4>0,Y4>0),(Y4-O4)/O4,IF(AND(O4=0,Y4=0),"",(Y4-O4)/O4)))) | AC4: =+AC5+AC10+AC15+AC18 -> 13800 | AD4: =IF(AND(AC4=0,AC4>=0), "",AC4/AC4) -> 1 | AF4: =+AF5+AF10+AF15+AF18 -> 0 | AG4: =IF(AND(AF4=0,AF4>=0), "",AF4/AF4) | AI4: =IF(AND(Y4=0,AF4>0),100%,IF(AND(Y4<0,AF4=0),(Y4-AF4)/Y4,IF(AND(Y4>0,AF4>0),(AF4-Y4)/Y4,IF(AND(Y4=0,AF4=0),"",(AF4-Y4)/Y4)))) | AJ4: =+AJ5+AJ10+AJ15+AJ18 -> 13800 | AK4: =IF(AND(AJ4=0,AJ4>=0), "",AJ4/AJ4) -> 1 | AM4: =+AM5+AM10+AM15+AM18 -> 0 | AN4: =IF(AND(AM4=0,AM4>=0), "",AM4/AM4) | AP4: =IF(AND(AF4=0,AM4>0),100%,IF(AND(AF4<0,AM4=0),(AF4-AM4)/AF4,IF(AND(AF4>0,AM4>0),(AM4-AF4)/AF4,IF(AND(AF4=0,AM4=0),"",(AM4-AF4)/AF4)))) | AQ4: =+AQ5+AQ10+AQ15+AQ18 -> 13800 | AR4: =IF(AND(AQ4=0,AQ4>=0), "",AQ4/AQ4) -> 1 | AT4: =+AT5+AT10+AT15+AT18 -> 0 | AU4: =IF(AND(AT4=0,AT4>=0), "",AT4/AT4) | AV4: =IF(AND(AT4=0,AQ4>0),100%,IF(AND(AT4<0,AQ4=0),(AT4-AQ4)/AT4,IF(AND(AT4>0,AQ4>0),(AQ4-AT4)/AT4,IF(AND(AT4=0,AQ4=0),"",(AQ4-AT4)/AT4)))) -> 1 | AW4: =+AW5+AW10+AW15+AW18 -> 2300 | AX4: =IF(AND(AW4=0,AW4>=0), "",AW4/AW4) -> 1 | AZ4: =+AZ5+AZ10+AZ15+AZ18 -> 0 | BA4: =IF(AND(AZ4=0,AZ4>=0), "",AZ4/AZ4) | BB4: =IF(AND(AZ4=0,AW4>0),100%,IF(AND(AZ4<0,AW4=0),(AZ4-AW4)/AZ4,IF(AND(AZ4>0,AW4>0),(AW4-AZ4)/AZ4,IF(AND(AZ4=0,AW4=0),"",(AW4-AZ4)/AZ4)))) -> 1 | BC4: =+BC5+BC10+BC15+BC18 -> 0 | BD4: =IF(AND(BC4=0,BC4>=0), "",BC4/BC4) | BF4: =IF(AND(AM4=0,BC4>0),100%,IF(AND(AM4<0,BC4=0),(AM4-BC4)/AM4,IF(AND(AM4>0,BC4>0),(BC4-AM4)/AM4,IF(AND(AM4=0,BC4=0),"",(BC4-AM4)/AM4)))) | BG4: =+BG5+BG10+BG15+BG18 -> 13800 | BH4: =IF(AND(BG4=0,BG4>=0), "",BG4/BG4) -> 1 | BJ4: =+BJ5+BJ10+BJ15+BJ18 -> 0 | BK4: =IF(AND(BJ4=0,BJ4>=0), "",BJ4/BJ4) | BM4: =IF(AND(BC4=0,BJ4>0),100%,IF(AND(BC4<0,BJ4=0),(BC4-BJ4)/BC4,IF(AND(BC4>0,BJ4>0),(BJ4-BC4)/BC4,IF(AND(BC4=0,BJ4=0),"",(BJ4-BC4)/BC4)))) | BN4: =+BN5+BN10+BN15+BN18 -> 13800 | BO4: =IF(AND(BN4=0,BN4>=0), "",BN4/BN4) -> 1 | BQ4: =+BQ5+BQ10+BQ15+BQ18 -> 0 | BR4: =IF(AND(BQ4=0,BQ4>=0), "",BQ4/BQ4) | BT4: =IF(AND(BJ4=0,BQ4>0),100%,IF(AND(BJ4<0,BQ4=0),(BJ4-BQ4)/BJ4,IF(AND(BJ4>0,BQ4>0),(BQ4-BJ4)/BJ4,IF(AND(BJ4=0,BQ4=0),"",(BQ4-BJ4)/BJ4)))) | BU4: =+BU5+BU10+BU15+BU18 -> 13800 | BV4: =IF(AND(BU4=0,BU4>=0), "",BU4/BU4) -> 1 | BX4: =+BX5+BX10+BX15+BX18 -> 0 | BY4: =IF(AND(BX4=0,BX4>=0), "",BX4/BX4) | BZ4: =IF(AND(BX4=0,BU4>0),100%,IF(AND(BX4<0,BU4=0),(BX4-BU4)/BX4,IF(AND(BX4>0,BU4>0),(BU4-BX4)/BX4,IF(AND(BX4=0,BU4=0),"",(BU4-BX4)/BX4)))) -> 1 | CA4: =+CA5+CA10+CA15+CA18 -> 0 | CB4: =IF(AND(CA4=0,CA4>=0), "",CA4/CA4) | CD4: =IF(AND(BQ4=0,CA4>0),100%,IF(AND(BQ4<0,CA4=0),(BQ4-CA4)/BQ4,IF(AND(BQ4>0,CA4>0),(CA4-BQ4)/BQ4,IF(AND(BQ4=0,CA4=0),"",(CA4-BQ4)/BQ4)))) | CE4: =+CE5+CE10+CE15+CE18 -> 13800 | CF4: =IF(AND(CE4=0,CE4>=0), "",CE4/CE4) -> 1 | CH4: =+CH5+CH10+CH15+CH18 -> 0 | CI4: =IF(AND(CH4=0,CH4>=0), "",CH4/CH4) | CK4: =IF(AND(CA4=0,CH4>0),100%,IF(AND(CA4<0,CH4=0),(CA4-CH4)/CA4,IF(AND(CA4>0,CH4>0),(CH4-CA4)/CA4,IF(AND(CA4=0,CH4=0),"",(CH4-CA4)/CA4)))) | CL4: =+CL5+CL10+CL15+CL18 -> 13800 | CM4: =IF(AND(CL4=0,CL4>=0), "",CL4/CL4) -> 1 | CO4: =+CO5+CO10+CO15+CO18 -> 0 | CP4: =IF(AND(CO4=0,CO4>=0), "",CO4/CO4) | CR4: =IF(AND(CH4=0,CO4>0),100%,IF(AND(CH4<0,CO4=0),(CH4-CO4)/CH4,IF(AND(CH4>0,CO4>0),(CO4-CH4)/CH4,IF(AND(CH4=0,CO4=0),"",(CO4-CH4)/CH4)))) | CS4: =+CS5+CS10+CS15+CS18 -> 13800 | CT4: =IF(AND(CS4=0,CS4>=0), "",CS4/CS4) -> 1 | CV4: =+CV5+CV10+CV15+CV18 -> 0 | CW4: =IF(AND(CV4=0,CV4>=0), "",CV4/CV4) | CX4: =IF(AND(CV4=0,CS4>0),100%,IF(AND(CV4<0,CS4=0),(CV4-CS4)/CV4,IF(AND(CV4>0,CS4>0),(CS4-CV4)/CV4,IF(AND(CV4=0,CS4=0),"",(CS4-CV4)/CV4)))) -> 1 | CY4: =+CS4/9 -> 1533.3333 | CZ4: =+B4/12 -> 0 | DA4: =+(CY4-CZ4)/CZ4 -> #DIV/0!
A5: Subtotal Ingresos por Venta de Mercancia | B5: =+B6+B7+B8 -> 0 | C5: =IF(AND(B4=0,B5>=0), "",B5/B4) | E5: =+E6+E7+E8 -> 13500 | F5: =IF(AND(E4=0,E5>=0), "",E5/E4) -> 0.97826087 | H5: =+H6+H7+H8 -> 0 | I5: =IF(AND(H4=0,H5>=0), "",H5/H4) | K5: =IF(AND(E5=0,H5>0),100%,IF(AND(E5<0,H5=0),(E5-H5)/E5,IF(AND(E5>0,H5>0),(H5-E5)/E5,IF(AND(E5=0,H5=0),"",(H5-E5)/E5)))) -> -1 | L5: =+L6+L7+L8 -> 13500 | M5: =IF(AND(L4=0,L5>=0), "",L5/L4) -> 0.97826087 | O5: =+O6+O7+O8 -> 0 | P5: =IF(AND(O4=0,O5>=0), "",O5/O4) | R5: =IF(AND(H5=0,O5>0),100%,IF(AND(H5<0,O5=0),(H5-O5)/H5,IF(AND(H5>0,O5>0),(O5-H5)/H5,IF(AND(H5=0,O5=0),"",(O5-H5)/H5)))) | S5: =+S6+S7+S8 -> 13500 | T5: =IF(AND(S4=0,S5>=0), "",S5/S4) -> 0.97826087 | V5: =+V6+V7+V8 -> 0 | W5: =IF(AND(V4=0,V5>=0), "",V5/V4) | X5: =IF(AND(V5=0,S5>0),100%,IF(AND(V5<0,S5=0),(V5-S5)/V5,IF(AND(V5>0,S5>0),(S5-V5)/V5,IF(AND(V5=0,S5=0),"",(S5-V5)/V5)))) -> 1 | Y5: =+Y6+Y7+Y8 -> 0 | Z5: =IF(AND(Y4=0,Y5>=0), "",Y5/Y4) | AB5: =IF(AND(O5=0,Y5>0),100%,IF(AND(O5<0,Y5=0),(O5-Y5)/O5,IF(AND(O5>0,Y5>0),(Y5-O5)/O5,IF(AND(O5=0,Y5=0),"",(Y5-O5)/O5)))) | AC5: =+AC6+AC7+AC8 -> 13500 | AD5: =IF(AND(AC4=0,AC5>=0), "",AC5/AC4) -> 0.97826087 | AF5: =+AF6+AF7+AF8 -> 0 | AG5: =IF(AND(AF4=0,AF5>=0), "",AF5/AF4) | AI5: =IF(AND(Y5=0,AF5>0),100%,IF(AND(Y5<0,AF5=0),(Y5-AF5)/Y5,IF(AND(Y5>0,AF5>0),(AF5-Y5)/Y5,IF(AND(Y5=0,AF5=0),"",(AF5-Y5)/Y5)))) | AJ5: =+AJ6+AJ7+AJ8 -> 13500 | AK5: =IF(AND(AJ4=0,AJ5>=0), "",AJ5/AJ4) -> 0.97826087 | AM5: =+AM6+AM7+AM8 -> 0 | AN5: =IF(AND(AM4=0,AM5>=0), "",AM5/AM4) | AP5: =IF(AND(AF5=0,AM5>0),100%,IF(AND(AF5<0,AM5=0),(AF5-AM5)/AF5,IF(AND(AF5>0,AM5>0),(AM5-AF5)/AF5,IF(AND(AF5=0,AM5=0),"",(AM5-AF5)/AF5)))) | AQ5: =+AQ6+AQ7+AQ8 -> 13500 | AR5: =IF(AND(AQ4=0,AQ5>=0), "",AQ5/AQ4) -> 0.97826087 | AT5: =+AT6+AT7+AT8 -> 0 | AU5: =IF(AND(AT4=0,AT5>=0), "",AT5/AT4) | AV5: =IF(AND(AT5=0,AQ5>0),100%,IF(AND(AT5<0,AQ5=0),(AT5-AQ5)/AT5,IF(AND(AT5>0,AQ5>0),(AQ5-AT5)/AT5,IF(AND(AT5=0,AQ5=0),"",(AQ5-AT5)/AT5)))) -> 1 | AW5: =+AW6+AW7+AW8 -> 2250 | AX5: =IF(AND(AW4=0,AW5>=0), "",AW5/AW4) -> 0.97826087 | AZ5: =+AZ6+AZ7+AZ8 -> 0 | BA5: =IF(AND(AZ4=0,AZ5>=0), "",AZ5/AZ4) | BB5: =IF(AND(AZ5=0,AW5>0),100%,IF(AND(AZ5<0,AW5=0),(AZ5-AW5)/AZ5,IF(AND(AZ5>0,AW5>0),(AW5-AZ5)/AZ5,IF(AND(AZ5=0,AW5=0),"",(AW5-AZ5)/AZ5)))) -> 1 | BC5: =+BC6+BC7+BC8 -> 0 | BD5: =IF(AND(BC4=0,BC5>=0), "",BC5/BC4) | BF5: =IF(AND(AM5=0,BC5>0),100%,IF(AND(AM5<0,BC5=0),(AM5-BC5)/AM5,IF(AND(AM5>0,BC5>0),(BC5-AM5)/AM5,IF(AND(AM5=0,BC5=0),"",(BC5-AM5)/AM5)))) | BG5: =+BG6+BG7+BG8 -> 13500 | BH5: =IF(AND(BG4=0,BG5>=0), "",BG5/BG4) -> 0.97826087 | BJ5: =+BJ6+BJ7+BJ8 -> 0 | BK5: =IF(AND(BJ4=0,BJ5>=0), "",BJ5/BJ4) | BM5: =IF(AND(BC5=0,BJ5>0),100%,IF(AND(BC5<0,BJ5=0),(BC5-BJ5)/BC5,IF(AND(BC5>0,BJ5>0),(BJ5-BC5)/BC5,IF(AND(BC5=0,BJ5=0),"",(BJ5-BC5)/BC5)))) | BN5: =+BN6+BN7+BN8 -> 13500 | BO5: =IF(AND(BN4=0,BN5>=0), "",BN5/BN4) -> 0.97826087 | BQ5: =+BQ6+BQ7+BQ8 -> 0 | BR5: =IF(AND(BQ4=0,BQ5>=0), "",BQ5/BQ4) | BT5: =IF(AND(BJ5=0,BQ5>0),100%,IF(AND(BJ5<0,BQ5=0),(BJ5-BQ5)/BJ5,IF(AND(BJ5>0,BQ5>0),(BQ5-BJ5)/BJ5,IF(AND(BJ5=0,BQ5=0),"",(BQ5-BJ5)/BJ5)))) | BU5: =+BU6+BU7+BU8 -> 13500 | BV5: =IF(AND(BU4=0,BU5>=0), "",BU5/BU4) -> 0.97826087 | BX5: =+BX6+BX7+BX8 -> 0 | BY5: =IF(AND(BX4=0,BX5>=0), "",BX5/BX4) | BZ5: =IF(AND(BX5=0,BU5>0),100%,IF(AND(BX5<0,BU5=0),(BX5-BU5)/BX5,IF(AND(BX5>0,BU5>0),(BU5-BX5)/BX5,IF(AND(BX5=0,BU5=0),"",(BU5-BX5)/BX5)))) -> 1 | CA5: =+CA6+CA7+CA8 -> 0 | CB5: =IF(AND(CA4=0,CA5>=0), "",CA5/CA4) | CD5: =IF(AND(BQ5=0,CA5>0),100%,IF(AND(BQ5<0,CA5=0),(BQ5-CA5)/BQ5,IF(AND(BQ5>0,CA5>0),(CA5-BQ5)/BQ5,IF(AND(BQ5=0,CA5=0),"",(CA5-BQ5)/BQ5)))) | CE5: =+CE6+CE7+CE8 -> 13500 | CF5: =IF(AND(CE4=0,CE5>=0), "",CE5/CE4) -> 0.97826087 | CH5: =+CH6+CH7+CH8 -> 0 | CI5: =IF(AND(CH4=0,CH5>=0), "",CH5/CH4) | CK5: =IF(AND(CA5=0,CH5>0),100%,IF(AND(CA5<0,CH5=0),(CA5-CH5)/CA5,IF(AND(CA5>0,CH5>0),(CH5-CA5)/CA5,IF(AND(CA5=0,CH5=0),"",(CH5-CA5)/CA5)))) | CL5: =+CL6+CL7+CL8 -> 13500 | CM5: =IF(AND(CL4=0,CL5>=0), "",CL5/CL4) -> 0.97826087 | CO5: =+CO6+CO7+CO8 -> 0 | CP5: =IF(AND(CO4=0,CO5>=0), "",CO5/CO4) | CR5: =IF(AND(CH5=0,CO5>0),100%,IF(AND(CH5<0,CO5=0),(CH5-CO5)/CH5,IF(AND(CH5>0,CO5>0),(CO5-CH5)/CH5,IF(AND(CH5=0,CO5=0),"",(CO5-CH5)/CH5)))) | CS5: =+CS6+CS7+CS8 -> 13500 | CT5: =IF(AND(CS4=0,CS5>=0), "",CS5/CS4) -> 0.97826087 | CV5: =+CV6+CV7+CV8 -> 0 | CW5: =IF(AND(CV4=0,CV5>=0), "",CV5/CV4) | CX5: =IF(AND(CV5=0,CS5>0),100%,IF(AND(CV5<0,CS5=0),(CV5-CS5)/CV5,IF(AND(CV5>0,CS5>0),(CS5-CV5)/CV5,IF(AND(CV5=0,CS5=0),"",(CS5-CV5)/CV5)))) -> 1
A6: Ingresos por venta de mercancía | B6: =+'N EERR'!B6 -> 0 | C6: =IF(AND(B4=0,B6>=0), "",B6/B4) | E6: =+'N EERR'!C6 -> 15000 | F6: =IF(AND(E4=0,E6>=0), "",E6/E4) -> 1.0869565 | H6: =+'N EERR'!D6 -> 0 | I6: =IF(AND(H4=0,H6>=0), "",H6/H4) | K6: =IF(AND(E6=0,H6>0),100%,IF(AND(E6<0,H6=0),(E6-H6)/E6,IF(AND(E6>0,H6>0),(H6-E6)/E6,IF(AND(E6=0,H6=0),"",(H6-E6)/E6)))) -> -1 | L6: =+E6+H6 -> 15000 | M6: =IF(AND(L4=0,L6>=0), "",L6/L4) -> 1.0869565 | O6: =+'N EERR'!E6 -> 0 | P6: =IF(AND(O4=0,O6>=0), "",O6/O4) | R6: =IF(AND(H6=0,O6>0),100%,IF(AND(H6<0,O6=0),(H6-O6)/H6,IF(AND(H6>0,O6>0),(O6-H6)/H6,IF(AND(H6=0,O6=0),"",(O6-H6)/H6)))) | S6: =+L6+O6 -> 15000 | T6: =IF(AND(S4=0,S6>=0), "",S6/S4) -> 1.0869565 | W6: =IF(AND(V4=0,V6>=0), "",V6/V4) | X6: =IF(AND(V6=0,S6>0),100%,IF(AND(V6<0,S6=0),(V6-S6)/V6,IF(AND(V6>0,S6>0),(S6-V6)/V6,IF(AND(V6=0,S6=0),"",(S6-V6)/V6)))) -> 1 | Y6: =+'N EERR'!F6 -> 0 | Z6: =IF(AND(Y4=0,Y6>=0), "",Y6/Y4) | AB6: =IF(AND(O6=0,Y6>0),100%,IF(AND(O6<0,Y6=0),(O6-Y6)/O6,IF(AND(O6>0,Y6>0),(Y6-O6)/O6,IF(AND(O6=0,Y6=0),"",(Y6-O6)/O6)))) | AC6: =+S6+Y6 -> 15000 | AD6: =IF(AND(AC4=0,AC6>=0), "",AC6/AC4) -> 1.0869565 | AF6: =+'N EERR'!G6 -> 0 | AG6: =IF(AND(AF4=0,AF6>=0), "",AF6/AF4) | AI6: =IF(AND(Y6=0,AF6>0),100%,IF(AND(Y6<0,AF6=0),(Y6-AF6)/Y6,IF(AND(Y6>0,AF6>0),(AF6-Y6)/Y6,IF(AND(Y6=0,AF6=0),"",(AF6-Y6)/Y6)))) | AJ6: =+AC6+AF6 -> 15000 | AK6: =IF(AND(AJ4=0,AJ6>=0), "",AJ6/AJ4) -> 1.0869565 | AM6: =+'N EERR'!H6 -> 0 | AN6: =IF(AND(AM4=0,AM6>=0), "",AM6/AM4) | AP6: =IF(AND(AF6=0,AM6>0),100%,IF(AND(AF6<0,AM6=0),(AF6-AM6)/AF6,IF(AND(AF6>0,AM6>0),(AM6-AF6)/AF6,IF(AND(AF6=0,AM6=0),"",(AM6-AF6)/AF6)))) | AQ6: =+AJ6+AM6 -> 15000 | AR6: =IF(AND(AQ4=0,AQ6>=0), "",AQ6/AQ4) -> 1.0869565 | AT6: =+V6*2 -> 0 | AU6: =IF(AND(AT4=0,AT6>=0), "",AT6/AT4) | AV6: =IF(AND(AT6=0,AQ6>0),100%,IF(AND(AT6<0,AQ6=0),(AT6-AQ6)/AT6,IF(AND(AT6>0,AQ6>0),(AQ6-AT6)/AT6,IF(AND(AT6=0,AQ6=0),"",(AQ6-AT6)/AT6)))) -> 1 | AW6: =+AQ6/6 -> 2500 | AX6: =IF(AND(AW4=0,AW6>=0), "",AW6/AW4) -> 1.0869565 | AZ6: =+AT6/6 -> 0 | BA6: =IF(AND(AZ4=0,AZ6>=0), "",AZ6/AZ4) | BB6: =IF(AND(AZ6=0,AW6>0),100%,IF(AND(AZ6<0,AW6=0),(AZ6-AW6)/AZ6,IF(AND(AZ6>0,AW6>0),(AW6-AZ6)/AZ6,IF(AND(AZ6=0,AW6=0),"",(AW6-AZ6)/AZ6)))) -> 1 | BC6: =+'N EERR'!I6 -> 0 | BD6: =IF(AND(BC4=0,BC6>=0), "",BC6/BC4) | BF6: =IF(AND(AM6=0,BC6>0),100%,IF(AND(AM6<0,BC6=0),(AM6-BC6)/AM6,IF(AND(AM6>0,BC6>0),(BC6-AM6)/AM6,IF(AND(AM6=0,BC6=0),"",(BC6-AM6)/AM6)))) | BG6: =+AQ6+BC6 -> 15000 | BH6: =IF(AND(BG4=0,BG6>=0), "",BG6/BG4) -> 1.0869565 | BJ6: =+'N EERR'!J6 -> 0 | BK6: =IF(AND(BJ4=0,BJ6>=0), "",BJ6/BJ4) | BM6: =IF(AND(BC6=0,BJ6>0),100%,IF(AND(BC6<0,BJ6=0),(BC6-BJ6)/BC6,IF(AND(BC6>0,BJ6>0),(BJ6-BC6)/BC6,IF(AND(BC6=0,BJ6=0),"",(BJ6-BC6)/BC6)))) | BN6: =+BG6+BJ6 -> 15000 | BO6: =IF(AND(BN4=0,BN6>=0), "",BN6/BN4) -> 1.0869565 | BQ6: =+'N EERR'!K6 -> 0 | BR6: =IF(AND(BQ4=0,BQ6>=0), "",BQ6/BQ4) | BT6: =IF(AND(BJ6=0,BQ6>0),100%,IF(AND(BJ6<0,BQ6=0),(BJ6-BQ6)/BJ6,IF(AND(BJ6>0,BQ6>0),(BQ6-BJ6)/BJ6,IF(AND(BJ6=0,BQ6=0),"",(BQ6-BJ6)/BJ6)))) | BU6: =+BN6+BQ6 -> 15000 | BV6: =IF(AND(BU4=0,BU6>=0), "",BU6/BU4) -> 1.0869565 | BX6: =+AZ6*9 -> 0 | BY6: =IF(AND(BX4=0,BX6>=0), "",BX6/BX4) | BZ6: =IF(AND(BX6=0,BU6>0),100%,IF(AND(BX6<0,BU6=0),(BX6-BU6)/BX6,IF(AND(BX6>0,BU6>0),(BU6-BX6)/BX6,IF(AND(BX6=0,BU6=0),"",(BU6-BX6)/BX6)))) -> 1 | CA6: =+'N EERR'!L6 -> 0 | CB6: =IF(AND(CA4=0,CA6>=0), "",CA6/CA4) | CD6: =IF(AND(BQ6=0,CA6>0),100%,IF(AND(BQ6<0,CA6=0),(BQ6-CA6)/BQ6,IF(AND(BQ6>0,CA6>0),(CA6-BQ6)/BQ6,IF(AND(BQ6=0,CA6=0),"",(CA6-BQ6)/BQ6)))) | CE6: =+BU6+CA6 -> 15000 | CF6: =IF(AND(CE4=0,CE6>=0), "",CE6/CE4) -> 1.0869565 | CH6: =+'N EERR'!M6 -> 0 | CI6: =IF(AND(CH4=0,CH6>=0), "",CH6/CH4) | CK6: =IF(AND(CA6=0,CH6>0),100%,IF(AND(CA6<0,CH6=0),(CA6-CH6)/CA6,IF(AND(CA6>0,CH6>0),(CH6-CA6)/CA6,IF(AND(CA6=0,CH6=0),"",(CH6-CA6)/CA6)))) | CL6: =+CE6+CH6 -> 15000 | CM6: =IF(AND(CL4=0,CL6>=0), "",CL6/CL4) -> 1.0869565 | CO6: =+'N EERR'!N6 -> 0 | CP6: =IF(AND(CO4=0,CO6>=0), "",CO6/CO4) | CR6: =IF(AND(CH6=0,CO6>0),100%,IF(AND(CH6<0,CO6=0),(CH6-CO6)/CH6,IF(AND(CH6>0,CO6>0),(CO6-CH6)/CH6,IF(AND(CH6=0,CO6=0),"",(CO6-CH6)/CH6)))) | CS6: =+CL6+CO6 -> 15000 | CT6: =IF(AND(CS4=0,CS6>=0), "",CS6/CS4) -> 1.0869565 | CV6: =+AZ6*12 -> 0 | CW6: =IF(AND(CV4=0,CV6>=0), "",CV6/CV4) | CX6: =IF(AND(CV6=0,CS6>0),100%,IF(AND(CV6<0,CS6=0),(CV6-CS6)/CV6,IF(AND(CV6>0,CS6>0),(CS6-CV6)/CV6,IF(AND(CV6=0,CS6=0),"",(CS6-CV6)/CV6)))) -> 1
A7: Devoluciones sobre ventas | B7: =+'N EERR'!B7 -> 0 | C7: =IF(AND(B4=0,B7>=0), "",B7/B4) | E7: =+'N EERR'!C7 -> -500 | F7: =IF(AND(E4=0,E7>=0), "",E7/E4) -> -0.036231884 | H7: =+'N EERR'!D7 -> 0 | I7: =IF(AND(H4=0,H7>=0), "",H7/H4) | K7: =IF(AND(E7=0,H7>0),100%,IF(AND(E7<0,H7=0),(E7-H7)/E7,IF(AND(E7>0,H7>0),(H7-E7)/E7,IF(AND(E7=0,H7=0),"",(H7-E7)/E7)))) -> 1 | L7: =+E7+H7 -> -500 | M7: =IF(AND(L4=0,L7>=0), "",L7/L4) -> -0.036231884 | O7: =+'N EERR'!E7 -> 0 | P7: =IF(AND(O4=0,O7>=0), "",O7/O4) | R7: =IF(AND(H7=0,O7>0),100%,IF(AND(H7<0,O7=0),(H7-O7)/H7,IF(AND(H7>0,O7>0),(O7-H7)/H7,IF(AND(H7=0,O7=0),"",(O7-H7)/H7)))) | S7: =+L7+O7 -> -500 | T7: =IF(AND(S4=0,S7>=0), "",S7/S4) -> -0.036231884 | W7: =IF(AND(V4=0,V7>=0), "",V7/V4) | X7: =IF(AND(V7=0,S7>0),100%,IF(AND(V7<0,S7=0),(V7-S7)/V7,IF(AND(V7>0,S7>0),(S7-V7)/V7,IF(AND(V7=0,S7=0),"",(S7-V7)/V7)))) -> #DIV/0! | Y7: =+'N EERR'!F7 -> 0 | Z7: =IF(AND(Y4=0,Y7>=0), "",Y7/Y4) | AB7: =IF(AND(O7=0,Y7>0),100%,IF(AND(O7<0,Y7=0),(O7-Y7)/O7,IF(AND(O7>0,Y7>0),(Y7-O7)/O7,IF(AND(O7=0,Y7=0),"",(Y7-O7)/O7)))) | AC7: =+S7+Y7 -> -500 | AD7: =IF(AND(AC4=0,AC7>=0), "",AC7/AC4) -> -0.036231884 | AF7: =+'N EERR'!G7 -> 0 | AG7: =IF(AND(AF4=0,AF7>=0), "",AF7/AF4) | AI7: =IF(AND(Y7=0,AF7>0),100%,IF(AND(Y7<0,AF7=0),(Y7-AF7)/Y7,IF(AND(Y7>0,AF7>0),(AF7-Y7)/Y7,IF(AND(Y7=0,AF7=0),"",(AF7-Y7)/Y7)))) | AJ7: =+AC7+AF7 -> -500 | AK7: =IF(AND(AJ4=0,AJ7>=0), "",AJ7/AJ4) -> -0.036231884 | AM7: =+'N EERR'!H7 -> 0 | AN7: =IF(AND(AM4=0,AM7>=0), "",AM7/AM4) | AP7: =IF(AND(AF7=0,AM7>0),100%,IF(AND(AF7<0,AM7=0),(AF7-AM7)/AF7,IF(AND(AF7>0,AM7>0),(AM7-AF7)/AF7,IF(AND(AF7=0,AM7=0),"",(AM7-AF7)/AF7)))) | AQ7: =+AJ7+AM7 -> -500 | AR7: =IF(AND(AQ4=0,AQ7>=0), "",AQ7/AQ4) -> -0.036231884 | AT7: =+V7*2 -> 0 | AU7: =IF(AND(AT4=0,AT7>=0), "",AT7/AT4) | AV7: =IF(AND(AT7=0,AQ7>0),100%,IF(AND(AT7<0,AQ7=0),(AT7-AQ7)/AT7,IF(AND(AT7>0,AQ7>0),(AQ7-AT7)/AT7,IF(AND(AT7=0,AQ7=0),"",(AQ7-AT7)/AT7)))) -> #DIV/0! | AW7: =+AQ7/6 -> -83.333333 | AX7: =IF(AND(AW4=0,AW7>=0), "",AW7/AW4) -> -0.036231884 | AZ7: =+AT7/6 -> 0 | BA7: =IF(AND(AZ4=0,AZ7>=0), "",AZ7/AZ4) | BB7: =IF(AND(AZ7=0,AW7>0),100%,IF(AND(AZ7<0,AW7=0),(AZ7-AW7)/AZ7,IF(AND(AZ7>0,AW7>0),(AW7-AZ7)/AZ7,IF(AND(AZ7=0,AW7=0),"",(AW7-AZ7)/AZ7)))) -> #DIV/0! | BC7: =+'N EERR'!I7 -> 0 | BD7: =IF(AND(BC4=0,BC7>=0), "",BC7/BC4) | BF7: =IF(AND(AM7=0,BC7>0),100%,IF(AND(AM7<0,BC7=0),(AM7-BC7)/AM7,IF(AND(AM7>0,BC7>0),(BC7-AM7)/AM7,IF(AND(AM7=0,BC7=0),"",(BC7-AM7)/AM7)))) | BG7: =+AQ7+BC7 -> -500 | BH7: =IF(AND(BG4=0,BG7>=0), "",BG7/BG4) -> -0.036231884 | BJ7: =+'N EERR'!J7 -> 0 | BK7: =IF(AND(BJ4=0,BJ7>=0), "",BJ7/BJ4) | BM7: =IF(AND(BC7=0,BJ7>0),100%,IF(AND(BC7<0,BJ7=0),(BC7-BJ7)/BC7,IF(AND(BC7>0,BJ7>0),(BJ7-BC7)/BC7,IF(AND(BC7=0,BJ7=0),"",(BJ7-BC7)/BC7)))) | BN7: =+BG7+BJ7 -> -500 | BO7: =IF(AND(BN4=0,BN7>=0), "",BN7/BN4) -> -0.036231884 | BQ7: =+'N EERR'!K7 -> 0 | BR7: =IF(AND(BQ4=0,BQ7>=0), "",BQ7/BQ4) | BT7: =IF(AND(BJ7=0,BQ7>0),100%,IF(AND(BJ7<0,BQ7=0),(BJ7-BQ7)/BJ7,IF(AND(BJ7>0,BQ7>0),(BQ7-BJ7)/BJ7,IF(AND(BJ7=0,BQ7=0),"",(BQ7-BJ7)/BJ7)))) | BU7: =+BN7+BQ7 -> -500 | BV7: =IF(AND(BU4=0,BU7>=0), "",BU7/BU4) -> -0.036231884 | BX7: =+AZ7*9 -> 0 | BY7: =IF(AND(BX4=0,BX7>=0), "",BX7/BX4) | BZ7: =IF(AND(BX7=0,BU7>0),100%,IF(AND(BX7<0,BU7=0),(BX7-BU7)/BX7,IF(AND(BX7>0,BU7>0),(BU7-BX7)/BX7,IF(AND(BX7=0,BU7=0),"",(BU7-BX7)/BX7)))) -> #DIV/0! | CA7: =+'N EERR'!L7 -> 0 | CB7: =IF(AND(CA4=0,CA7>=0), "",CA7/CA4) | CD7: =IF(AND(BQ7=0,CA7>0),100%,IF(AND(BQ7<0,CA7=0),(BQ7-CA7)/BQ7,IF(AND(BQ7>0,CA7>0),(CA7-BQ7)/BQ7,IF(AND(BQ7=0,CA7=0),"",(CA7-BQ7)/BQ7)))) | CE7: =+BU7+CA7 -> -500 | CF7: =IF(AND(CE4=0,CE7>=0), "",CE7/CE4) -> -0.036231884 | CH7: =+'N EERR'!M7 -> 0 | CI7: =IF(AND(CH4=0,CH7>=0), "",CH7/CH4) | CK7: =IF(AND(CA7=0,CH7>0),100%,IF(AND(CA7<0,CH7=0),(CA7-CH7)/CA7,IF(AND(CA7>0,CH7>0),(CH7-CA7)/CA7,IF(AND(CA7=0,CH7=0),"",(CH7-CA7)/CA7)))) | CL7: =+CE7+CH7 -> -500 | CM7: =IF(AND(CL4=0,CL7>=0), "",CL7/CL4) -> -0.036231884 | CO7: =+'N EERR'!N7 -> 0 | CP7: =IF(AND(CO4=0,CO7>=0), "",CO7/CO4) | CR7: =IF(AND(CH7=0,CO7>0),100%,IF(AND(CH7<0,CO7=0),(CH7-CO7)/CH7,IF(AND(CH7>0,CO7>0),(CO7-CH7)/CH7,IF(AND(CH7=0,CO7=0),"",(CO7-CH7)/CH7)))) | CS7: =+CL7+CO7 -> -500 | CT7: =IF(AND(CS4=0,CS7>=0), "",CS7/CS4) -> -0.036231884 | CV7: =+AZ7*12 -> 0 | CW7: =IF(AND(CV4=0,CV7>=0), "",CV7/CV4) | CX7: =IF(AND(CV7=0,CS7>0),100%,IF(AND(CV7<0,CS7=0),(CV7-CS7)/CV7,IF(AND(CV7>0,CS7>0),(CS7-CV7)/CV7,IF(AND(CV7=0,CS7=0),"",(CS7-CV7)/CV7)))) -> #DIV/0!
A8: Descuentos sobre ventas | B8: =+'N EERR'!B8+'N EERR'!B9 -> 0 | C8: =IF(AND(B5=0,B8>=0), "",B8/B5) | E8: =+'N EERR'!C8+'N EERR'!C9 -> -1000 | F8: =IF(AND(E5=0,E8>=0), "",E8/E5) -> -0.074074074 | H8: =+'N EERR'!D8+'N EERR'!D9 -> 0 | I8: =IF(AND(H5=0,H8>=0), "",H8/H5) | K8: =IF(AND(E8=0,H8>0),100%,IF(AND(E8<0,H8=0),(E8-H8)/E8,IF(AND(E8>0,H8>0),(H8-E8)/E8,IF(AND(E8=0,H8=0),"",(H8-E8)/E8)))) -> 1 | L8: =+E8+H8 -> -1000 | M8: =IF(AND(L5=0,L8>=0), "",L8/L5) -> -0.074074074 | O8: =+'N EERR'!E8+'N EERR'!E9 -> 0 | P8: =IF(AND(O5=0,O8>=0), "",O8/O5) | R8: =IF(AND(H8=0,O8>0),100%,IF(AND(H8<0,O8=0),(H8-O8)/H8,IF(AND(H8>0,O8>0),(O8-H8)/H8,IF(AND(H8=0,O8=0),"",(O8-H8)/H8)))) | S8: =+L8+O8 -> -1000 | T8: =IF(AND(S5=0,S8>=0), "",S8/S5) -> -0.074074074 | W8: =IF(AND(V5=0,V8>=0), "",V8/V5) | X8: =IF(AND(V8=0,S8>0),100%,IF(AND(V8<0,S8=0),(V8-S8)/V8,IF(AND(V8>0,S8>0),(S8-V8)/V8,IF(AND(V8=0,S8=0),"",(S8-V8)/V8)))) -> #DIV/0! | Y8: =+'N EERR'!F8+'N EERR'!F9 -> 0 | Z8: =IF(AND(Y5=0,Y8>=0), "",Y8/Y5) | AB8: =IF(AND(O8=0,Y8>0),100%,IF(AND(O8<0,Y8=0),(O8-Y8)/O8,IF(AND(O8>0,Y8>0),(Y8-O8)/O8,IF(AND(O8=0,Y8=0),"",(Y8-O8)/O8)))) | AC8: =+S8+Y8 -> -1000 | AD8: =IF(AND(AC5=0,AC8>=0), "",AC8/AC5) -> -0.074074074 | AF8: =+'N EERR'!G8+'N EERR'!G9 -> 0 | AG8: =IF(AND(AF5=0,AF8>=0), "",AF8/AF5) | AI8: =IF(AND(Y8=0,AF8>0),100%,IF(AND(Y8<0,AF8=0),(Y8-AF8)/Y8,IF(AND(Y8>0,AF8>0),(AF8-Y8)/Y8,IF(AND(Y8=0,AF8=0),"",(AF8-Y8)/Y8)))) | AJ8: =+AC8+AF8 -> -1000 | AK8: =IF(AND(AJ5=0,AJ8>=0), "",AJ8/AJ5) -> -0.074074074 | AM8: =+'N EERR'!H8+'N EERR'!H9 -> 0 | AN8: =IF(AND(AM5=0,AM8>=0), "",AM8/AM5) | AP8: =IF(AND(AF8=0,AM8>0),100%,IF(AND(AF8<0,AM8=0),(AF8-AM8)/AF8,IF(AND(AF8>0,AM8>0),(AM8-AF8)/AF8,IF(AND(AF8=0,AM8=0),"",(AM8-AF8)/AF8)))) | AQ8: =+AJ8+AM8 -> -1000 | AR8: =IF(AND(AQ5=0,AQ8>=0), "",AQ8/AQ5) -> -0.074074074 | AT8: =+V8*2 -> 0 | AU8: =IF(AND(AT5=0,AT8>=0), "",AT8/AT5) | AV8: =IF(AND(AT8=0,AQ8>0),100%,IF(AND(AT8<0,AQ8=0),(AT8-AQ8)/AT8,IF(AND(AT8>0,AQ8>0),(AQ8-AT8)/AT8,IF(AND(AT8=0,AQ8=0),"",(AQ8-AT8)/AT8)))) -> #DIV/0! | AW8: =+AQ8/6 -> -166.66667 | AX8: =IF(AND(AW5=0,AW8>=0), "",AW8/AW5) -> -0.074074074 | AZ8: =+AT8/6 -> 0 | BA8: =IF(AND(AZ5=0,AZ8>=0), "",AZ8/AZ5) | BB8: =IF(AND(AZ8=0,AW8>0),100%,IF(AND(AZ8<0,AW8=0),(AZ8-AW8)/AZ8,IF(AND(AZ8>0,AW8>0),(AW8-AZ8)/AZ8,IF(AND(AZ8=0,AW8=0),"",(AW8-AZ8)/AZ8)))) -> #DIV/0! | BC8: =+'N EERR'!I8+'N EERR'!I9 -> 0 | BD8: =IF(AND(BC5=0,BC8>=0), "",BC8/BC5) | BF8: =IF(AND(AM8=0,BC8>0),100%,IF(AND(AM8<0,BC8=0),(AM8-BC8)/AM8,IF(AND(AM8>0,BC8>0),(BC8-AM8)/AM8,IF(AND(AM8=0,BC8=0),"",(BC8-AM8)/AM8)))) | BG8: =+AQ8+BC8 -> -1000 | BH8: =IF(AND(BG5=0,BG8>=0), "",BG8/BG5) -> -0.074074074 | BJ8: =+'N EERR'!J8+'N EERR'!J9 -> 0 | BK8: =IF(AND(BJ5=0,BJ8>=0), "",BJ8/BJ5) | BM8: =IF(AND(BC8=0,BJ8>0),100%,IF(AND(BC8<0,BJ8=0),(BC8-BJ8)/BC8,IF(AND(BC8>0,BJ8>0),(BJ8-BC8)/BC8,IF(AND(BC8=0,BJ8=0),"",(BJ8-BC8)/BC8)))) | BN8: =+BG8+BJ8 -> -1000 | BO8: =IF(AND(BN5=0,BN8>=0), "",BN8/BN5) -> -0.074074074 | BQ8: =+'N EERR'!K8+'N EERR'!K9 -> 0 | BR8: =IF(AND(BQ5=0,BQ8>=0), "",BQ8/BQ5) | BT8: =IF(AND(BJ8=0,BQ8>0),100%,IF(AND(BJ8<0,BQ8=0),(BJ8-BQ8)/BJ8,IF(AND(BJ8>0,BQ8>0),(BQ8-BJ8)/BJ8,IF(AND(BJ8=0,BQ8=0),"",(BQ8-BJ8)/BJ8)))) | BU8: =+BN8+BQ8 -> -1000 | BV8: =IF(AND(BU5=0,BU8>=0), "",BU8/BU5) -> -0.074074074 | BX8: =+AZ8*9 -> 0 | BY8: =IF(AND(BX5=0,BX8>=0), "",BX8/BX5) | BZ8: =IF(AND(BX8=0,BU8>0),100%,IF(AND(BX8<0,BU8=0),(BX8-BU8)/BX8,IF(AND(BX8>0,BU8>0),(BU8-BX8)/BX8,IF(AND(BX8=0,BU8=0),"",(BU8-BX8)/BX8)))) -> #DIV/0! | CA8: =+'N EERR'!L8+'N EERR'!L9 -> 0 | CB8: =IF(AND(CA5=0,CA8>=0), "",CA8/CA5) | CD8: =IF(AND(BQ8=0,CA8>0),100%,IF(AND(BQ8<0,CA8=0),(BQ8-CA8)/BQ8,IF(AND(BQ8>0,CA8>0),(CA8-BQ8)/BQ8,IF(AND(BQ8=0,CA8=0),"",(CA8-BQ8)/BQ8)))) | CE8: =+BU8+CA8 -> -1000 | CF8: =IF(AND(CE5=0,CE8>=0), "",CE8/CE5) -> -0.074074074 | CH8: =+'N EERR'!M8+'N EERR'!M9 -> 0 | CI8: =IF(AND(CH5=0,CH8>=0), "",CH8/CH5) | CK8: =IF(AND(CA8=0,CH8>0),100%,IF(AND(CA8<0,CH8=0),(CA8-CH8)/CA8,IF(AND(CA8>0,CH8>0),(CH8-CA8)/CA8,IF(AND(CA8=0,CH8=0),"",(CH8-CA8)/CA8)))) | CL8: =+CE8+CH8 -> -1000 | CM8: =IF(AND(CL5=0,CL8>=0), "",CL8/CL5) -> -0.074074074 | CO8: =+'N EERR'!N8+'N EERR'!N9 -> 0 | CP8: =IF(AND(CO5=0,CO8>=0), "",CO8/CO5) | CR8: =IF(AND(CH8=0,CO8>0),100%,IF(AND(CH8<0,CO8=0),(CH8-CO8)/CH8,IF(AND(CH8>0,CO8>0),(CO8-CH8)/CH8,IF(AND(CH8=0,CO8=0),"",(CO8-CH8)/CH8)))) | CS8: =+CL8+CO8 -> -1000 | CT8: =IF(AND(CS5=0,CS8>=0), "",CS8/CS5) -> -0.074074074 | CV8: =+AZ8*12 -> 0 | CW8: =IF(AND(CV5=0,CV8>=0), "",CV8/CV5) | CX8: =IF(AND(CV8=0,CS8>0),100%,IF(AND(CV8<0,CS8=0),(CV8-CS8)/CV8,IF(AND(CV8>0,CS8>0),(CS8-CV8)/CV8,IF(AND(CV8=0,CS8=0),"",(CS8-CV8)/CV8)))) -> #DIV/0!
K9: =IF(AND(E9=0,H9>0),100%,IF(AND(E9<0,H9=0),(E9-H9)/E9,IF(AND(E9>0,H9>0),(H9-E9)/E9,IF(AND(E9=0,H9=0),"",(H9-E9)/E9)))) | R9: =IF(AND(H9=0,O9>0),100%,IF(AND(H9<0,O9=0),(H9-O9)/H9,IF(AND(H9>0,O9>0),(O9-H9)/H9,IF(AND(H9=0,O9=0),"",(O9-H9)/H9)))) | X9: =IF(AND(V9=0,S9>0),100%,IF(AND(V9<0,S9=0),(V9-S9)/V9,IF(AND(V9>0,S9>0),(S9-V9)/V9,IF(AND(V9=0,S9=0),"",(S9-V9)/V9)))) | AB9: =IF(AND(O9=0,Y9>0),100%,IF(AND(O9<0,Y9=0),(O9-Y9)/O9,IF(AND(O9>0,Y9>0),(Y9-O9)/O9,IF(AND(O9=0,Y9=0),"",(Y9-O9)/O9)))) | AI9: =IF(AND(Y9=0,AF9>0),100%,IF(AND(Y9<0,AF9=0),(Y9-AF9)/Y9,IF(AND(Y9>0,AF9>0),(AF9-Y9)/Y9,IF(AND(Y9=0,AF9=0),"",(AF9-Y9)/Y9)))) | AJ9: =+AC9+AF9 -> 0 | AP9: =IF(AND(AF9=0,AM9>0),100%,IF(AND(AF9<0,AM9=0),(AF9-AM9)/AF9,IF(AND(AF9>0,AM9>0),(AM9-AF9)/AF9,IF(AND(AF9=0,AM9=0),"",(AM9-AF9)/AF9)))) | AQ9: =+AJ9+AM9 -> 0 | AT9: =+V9*2 -> 0 | AV9: =IF(AND(AT9=0,AQ9>0),100%,IF(AND(AT9<0,AQ9=0),(AT9-AQ9)/AT9,IF(AND(AT9>0,AQ9>0),(AQ9-AT9)/AT9,IF(AND(AT9=0,AQ9=0),"",(AQ9-AT9)/AT9)))) | AZ9: =+AT9/6 -> 0 | BB9: =IF(AND(AZ9=0,AW9>0),100%,IF(AND(AZ9<0,AW9=0),(AZ9-AW9)/AZ9,IF(AND(AZ9>0,AW9>0),(AW9-AZ9)/AZ9,IF(AND(AZ9=0,AW9=0),"",(AW9-AZ9)/AZ9)))) | BF9: =IF(AND(AM9=0,BC9>0),100%,IF(AND(AM9<0,BC9=0),(AM9-BC9)/AM9,IF(AND(AM9>0,BC9>0),(BC9-AM9)/AM9,IF(AND(AM9=0,BC9=0),"",(BC9-AM9)/AM9)))) | BG9: =+AQ9+BC9 -> 0 | BM9: =IF(AND(BC9=0,BJ9>0),100%,IF(AND(BC9<0,BJ9=0),(BC9-BJ9)/BC9,IF(AND(BC9>0,BJ9>0),(BJ9-BC9)/BC9,IF(AND(BC9=0,BJ9=0),"",(BJ9-BC9)/BC9)))) | BN9: =+BG9+BJ9 -> 0 | BT9: =IF(AND(BJ9=0,BQ9>0),100%,IF(AND(BJ9<0,BQ9=0),(BJ9-BQ9)/BJ9,IF(AND(BJ9>0,BQ9>0),(BQ9-BJ9)/BJ9,IF(AND(BJ9=0,BQ9=0),"",(BQ9-BJ9)/BJ9)))) | BU9: =+BN9+BQ9 -> 0 | BX9: =+AZ9*9 -> 0 | BZ9: =IF(AND(BX9=0,BU9>0),100%,IF(AND(BX9<0,BU9=0),(BX9-BU9)/BX9,IF(AND(BX9>0,BU9>0),(BU9-BX9)/BX9,IF(AND(BX9=0,BU9=0),"",(BU9-BX9)/BX9)))) | CD9: =IF(AND(BQ9=0,CA9>0),100%,IF(AND(BQ9<0,CA9=0),(BQ9-CA9)/BQ9,IF(AND(BQ9>0,CA9>0),(CA9-BQ9)/BQ9,IF(AND(BQ9=0,CA9=0),"",(CA9-BQ9)/BQ9)))) | CK9: =IF(AND(CA9=0,CH9>0),100%,IF(AND(CA9<0,CH9=0),(CA9-CH9)/CA9,IF(AND(CA9>0,CH9>0),(CH9-CA9)/CA9,IF(AND(CA9=0,CH9=0),"",(CH9-CA9)/CA9)))) | CL9: =+CE9+CH9 -> 0 | CR9: =IF(AND(CH9=0,CO9>0),100%,IF(AND(CH9<0,CO9=0),(CH9-CO9)/CH9,IF(AND(CH9>0,CO9>0),(CO9-CH9)/CH9,IF(AND(CH9=0,CO9=0),"",(CO9-CH9)/CH9)))) | CS9: =+CL9+CO9 -> 0 | CV9: =+AZ9*12 -> 0 | CX9: =IF(AND(CV9=0,CS9>0),100%,IF(AND(CV9<0,CS9=0),(CV9-CS9)/CV9,IF(AND(CV9>0,CS9>0),(CS9-CV9)/CV9,IF(AND(CV9=0,CS9=0),"",(CS9-CV9)/CV9))))
A10: Subtotal Ingresos por Servicios | B10: =SUM(B11:B14) -> 0 | C10: =IF(AND(B4=0,B10>=0), "",B10/B4) | E10: =SUM(E11:E14) -> 200 | F10: =IF(AND(E4=0,E10>=0), "",E10/E4) -> 0.014492754 | H10: =SUM(H11:H14) -> 0 | I10: =IF(AND(H4=0,H10>=0), "",H10/H4) | K10: =IF(AND(E10=0,H10>0),100%,IF(AND(E10<0,H10=0),(E10-H10)/E10,IF(AND(E10>0,H10>0),(H10-E10)/E10,IF(AND(E10=0,H10=0),"",(H10-E10)/E10)))) -> -1 | L10: =SUM(L11:L14) -> 200 | M10: =IF(AND(L4=0,L10>=0), "",L10/L4) -> 0.014492754 | O10: =SUM(O11:O14) -> 0 | P10: =IF(AND(O4=0,O10>=0), "",O10/O4) | R10: =IF(AND(H10=0,O10>0),100%,IF(AND(H10<0,O10=0),(H10-O10)/H10,IF(AND(H10>0,O10>0),(O10-H10)/H10,IF(AND(H10=0,O10=0),"",(O10-H10)/H10)))) | S10: =SUM(S11:S14) -> 200 | T10: =IF(AND(S4=0,S10>=0), "",S10/S4) -> 0.014492754 | V10: =SUM(V11:V14) -> 0 | W10: =IF(AND(V4=0,V10>=0), "",V10/V4) | X10: =IF(AND(V10=0,S10>0),100%,IF(AND(V10<0,S10=0),(V10-S10)/V10,IF(AND(V10>0,S10>0),(S10-V10)/V10,IF(AND(V10=0,S10=0),"",(S10-V10)/V10)))) -> 1 | Y10: =SUM(Y11:Y14) -> 0 | Z10: =IF(AND(Y4=0,Y10>=0), "",Y10/Y4) | AB10: =IF(AND(O10=0,Y10>0),100%,IF(AND(O10<0,Y10=0),(O10-Y10)/O10,IF(AND(O10>0,Y10>0),(Y10-O10)/O10,IF(AND(O10=0,Y10=0),"",(Y10-O10)/O10)))) | AC10: =SUM(AC11:AC14) -> 200 | AD10: =IF(AND(AC4=0,AC10>=0), "",AC10/AC4) -> 0.014492754 | AF10: =SUM(AF11:AF14) -> 0 | AG10: =IF(AND(AF4=0,AF10>=0), "",AF10/AF4) | AI10: =IF(AND(Y10=0,AF10>0),100%,IF(AND(Y10<0,AF10=0),(Y10-AF10)/Y10,IF(AND(Y10>0,AF10>0),(AF10-Y10)/Y10,IF(AND(Y10=0,AF10=0),"",(AF10-Y10)/Y10)))) | AJ10: =SUM(AJ11:AJ14) -> 200 | AK10: =IF(AND(AJ4=0,AJ10>=0), "",AJ10/AJ4) -> 0.014492754 | AM10: =SUM(AM11:AM14) -> 0 | AN10: =IF(AND(AM4=0,AM10>=0), "",AM10/AM4) | AP10: =IF(AND(AF10=0,AM10>0),100%,IF(AND(AF10<0,AM10=0),(AF10-AM10)/AF10,IF(AND(AF10>0,AM10>0),(AM10-AF10)/AF10,IF(AND(AF10=0,AM10=0),"",(AM10-AF10)/AF10)))) | AQ10: =SUM(AQ11:AQ14) -> 200 | AR10: =IF(AND(AQ4=0,AQ10>=0), "",AQ10/AQ4) -> 0.014492754 | AT10: =SUM(AT11:AT14) -> 0 | AU10: =IF(AND(AT4=0,AT10>=0), "",AT10/AT4) | AV10: =IF(AND(AT10=0,AQ10>0),100%,IF(AND(AT10<0,AQ10=0),(AT10-AQ10)/AT10,IF(AND(AT10>0,AQ10>0),(AQ10-AT10)/AT10,IF(AND(AT10=0,AQ10=0),"",(AQ10-AT10)/AT10)))) -> 1 | AW10: =SUM(AW11:AW14) -> 33.333333 | AX10: =IF(AND(AW4=0,AW10>=0), "",AW10/AW4) -> 0.014492754 | AZ10: =SUM(AZ11:AZ14) -> 0 | BA10: =IF(AND(AZ4=0,AZ10>=0), "",AZ10/AZ4) | BB10: =IF(AND(AZ10=0,AW10>0),100%,IF(AND(AZ10<0,AW10=0),(AZ10-AW10)/AZ10,IF(AND(AZ10>0,AW10>0),(AW10-AZ10)/AZ10,IF(AND(AZ10=0,AW10=0),"",(AW10-AZ10)/AZ10)))) -> 1 | BC10: =SUM(BC11:BC14) -> 0 | BD10: =IF(AND(BC4=0,BC10>=0), "",BC10/BC4) | BF10: =IF(AND(AM10=0,BC10>0),100%,IF(AND(AM10<0,BC10=0),(AM10-BC10)/AM10,IF(AND(AM10>0,BC10>0),(BC10-AM10)/AM10,IF(AND(AM10=0,BC10=0),"",(BC10-AM10)/AM10)))) | BG10: =SUM(BG11:BG14) -> 200 | BH10: =IF(AND(BG4=0,BG10>=0), "",BG10/BG4) -> 0.014492754 | BJ10: =SUM(BJ11:BJ14) -> 0 | BK10: =IF(AND(BJ4=0,BJ10>=0), "",BJ10/BJ4) | BM10: =IF(AND(BC10=0,BJ10>0),100%,IF(AND(BC10<0,BJ10=0),(BC10-BJ10)/BC10,IF(AND(BC10>0,BJ10>0),(BJ10-BC10)/BC10,IF(AND(BC10=0,BJ10=0),"",(BJ10-BC10)/BC10)))) | BN10: =SUM(BN11:BN14) -> 200 | BO10: =IF(AND(BN4=0,BN10>=0), "",BN10/BN4) -> 0.014492754 | BQ10: =SUM(BQ11:BQ14) -> 0 | BR10: =IF(AND(BQ4=0,BQ10>=0), "",BQ10/BQ4) | BT10: =IF(AND(BJ10=0,BQ10>0),100%,IF(AND(BJ10<0,BQ10=0),(BJ10-BQ10)/BJ10,IF(AND(BJ10>0,BQ10>0),(BQ10-BJ10)/BJ10,IF(AND(BJ10=0,BQ10=0),"",(BQ10-BJ10)/BJ10)))) | BU10: =SUM(BU11:BU14) -> 200 | BV10: =IF(AND(BU4=0,BU10>=0), "",BU10/BU4) -> 0.014492754 | BX10: =SUM(BX11:BX14) -> 0 | BY10: =IF(AND(BX4=0,BX10>=0), "",BX10/BX4) | BZ10: =IF(AND(BX10=0,BU10>0),100%,IF(AND(BX10<0,BU10=0),(BX10-BU10)/BX10,IF(AND(BX10>0,BU10>0),(BU10-BX10)/BX10,IF(AND(BX10=0,BU10=0),"",(BU10-BX10)/BX10)))) -> 1 | CA10: =SUM(CA11:CA14) -> 0 | CB10: =IF(AND(CA4=0,CA10>=0), "",CA10/CA4) | CD10: =IF(AND(BQ10=0,CA10>0),100%,IF(AND(BQ10<0,CA10=0),(BQ10-CA10)/BQ10,IF(AND(BQ10>0,CA10>0),(CA10-BQ10)/BQ10,IF(AND(BQ10=0,CA10=0),"",(CA10-BQ10)/BQ10)))) | CE10: =SUM(CE11:CE14) -> 200 | CF10: =IF(AND(CE4=0,CE10>=0), "",CE10/CE4) -> 0.014492754 | CH10: =SUM(CH11:CH14) -> 0 | CI10: =IF(AND(CH4=0,CH10>=0), "",CH10/CH4) | CK10: =IF(AND(CA10=0,CH10>0),100%,IF(AND(CA10<0,CH10=0),(CA10-CH10)/CA10,IF(AND(CA10>0,CH10>0),(CH10-CA10)/CA10,IF(AND(CA10=0,CH10=0),"",(CH10-CA10)/CA10)))) | CL10: =SUM(CL11:CL14) -> 200 | CM10: =IF(AND(CL4=0,CL10>=0), "",CL10/CL4) -> 0.014492754 | CO10: =SUM(CO11:CO14) -> 0 | CP10: =IF(AND(CO4=0,CO10>=0), "",CO10/CO4) | CR10: =IF(AND(CH10=0,CO10>0),100%,IF(AND(CH10<0,CO10=0),(CH10-CO10)/CH10,IF(AND(CH10>0,CO10>0),(CO10-CH10)/CH10,IF(AND(CH10=0,CO10=0),"",(CO10-CH10)/CH10)))) | CS10: =SUM(CS11:CS14) -> 200 | CT10: =IF(AND(CS4=0,CS10>=0), "",CS10/CS4) -> 0.014492754 | CV10: =SUM(CV11:CV14) -> 0 | CW10: =IF(AND(CV4=0,CV10>=0), "",CV10/CV4) | CX10: =IF(AND(CV10=0,CS10>0),100%,IF(AND(CV10<0,CS10=0),(CV10-CS10)/CV10,IF(AND(CV10>0,CS10>0),(CS10-CV10)/CV10,IF(AND(CV10=0,CS10=0),"",(CS10-CV10)/CV10)))) -> 1
A11: Ingresos por servicios del café | B11: =+'N EERR'!B10 -> 0 | C11: =IF(AND(B4=0,B11>=0), "",B11/B4) | E11: =+'N EERR'!C10 -> 50 | F11: =IF(AND(E4=0,E11>=0), "",E11/E4) -> 0.0036231884 | H11: =+'N EERR'!D10 -> 0 | I11: =IF(AND(H4=0,H11>=0), "",H11/H4) | K11: =IF(AND(E11=0,H11>0),100%,IF(AND(E11<0,H11=0),(E11-H11)/E11,IF(AND(E11>0,H11>0),(H11-E11)/E11,IF(AND(E11=0,H11=0),"",(H11-E11)/E11)))) -> -1 | L11: =+E11+H11 -> 50 | M11: =IF(AND(L4=0,L11>=0), "",L11/L4) -> 0.0036231884 | O11: =+'N EERR'!E10 -> 0 | P11: =IF(AND(O4=0,O11>=0), "",O11/O4) | R11: =IF(AND(H11=0,O11>0),100%,IF(AND(H11<0,O11=0),(H11-O11)/H11,IF(AND(H11>0,O11>0),(O11-H11)/H11,IF(AND(H11=0,O11=0),"",(O11-H11)/H11)))) | S11: =+L11+O11 -> 50 | T11: =IF(AND(S4=0,S11>=0), "",S11/S4) -> 0.0036231884 | W11: =IF(AND(V4=0,V11>=0), "",V11/V4) | X11: =IF(AND(V11=0,S11>0),100%,IF(AND(V11<0,S11=0),(V11-S11)/V11,IF(AND(V11>0,S11>0),(S11-V11)/V11,IF(AND(V11=0,S11=0),"",(S11-V11)/V11)))) -> 1 | Y11: =+'N EERR'!F10 -> 0 | Z11: =IF(AND(Y4=0,Y11>=0), "",Y11/Y4) | AB11: =IF(AND(O11=0,Y11>0),100%,IF(AND(O11<0,Y11=0),(O11-Y11)/O11,IF(AND(O11>0,Y11>0),(Y11-O11)/O11,IF(AND(O11=0,Y11=0),"",(Y11-O11)/O11)))) | AC11: =+S11+Y11 -> 50 | AD11: =IF(AND(AC4=0,AC11>=0), "",AC11/AC4) -> 0.0036231884 | AF11: =+'N EERR'!G10 -> 0 | AG11: =IF(AND(AF4=0,AF11>=0), "",AF11/AF4) | AI11: =IF(AND(Y11=0,AF11>0),100%,IF(AND(Y11<0,AF11=0),(Y11-AF11)/Y11,IF(AND(Y11>0,AF11>0),(AF11-Y11)/Y11,IF(AND(Y11=0,AF11=0),"",(AF11-Y11)/Y11)))) | AJ11: =+AC11+AF11 -> 50 | AK11: =IF(AND(AJ4=0,AJ11>=0), "",AJ11/AJ4) -> 0.0036231884 | AM11: =+'N EERR'!H10 -> 0 | AN11: =IF(AND(AM4=0,AM11>=0), "",AM11/AM4) | AP11: =IF(AND(AF11=0,AM11>0),100%,IF(AND(AF11<0,AM11=0),(AF11-AM11)/AF11,IF(AND(AF11>0,AM11>0),(AM11-AF11)/AF11,IF(AND(AF11=0,AM11=0),"",(AM11-AF11)/AF11)))) | AQ11: =+AJ11+AM11 -> 50 | AR11: =IF(AND(AQ4=0,AQ11>=0), "",AQ11/AQ4) -> 0.0036231884 | AT11: =+V11*2 -> 0 | AU11: =IF(AND(AT4=0,AT11>=0), "",AT11/AT4) | AV11: =IF(AND(AT11=0,AQ11>0),100%,IF(AND(AT11<0,AQ11=0),(AT11-AQ11)/AT11,IF(AND(AT11>0,AQ11>0),(AQ11-AT11)/AT11,IF(AND(AT11=0,AQ11=0),"",(AQ11-AT11)/AT11)))) -> 1 | AW11: =+AQ11/6 -> 8.3333333 | AX11: =IF(AND(AW4=0,AW11>=0), "",AW11/AW4) -> 0.0036231884 | AZ11: =+AT11/6 -> 0 | BA11: =IF(AND(AZ4=0,AZ11>=0), "",AZ11/AZ4) | BB11: =IF(AND(AZ11=0,AW11>0),100%,IF(AND(AZ11<0,AW11=0),(AZ11-AW11)/AZ11,IF(AND(AZ11>0,AW11>0),(AW11-AZ11)/AZ11,IF(AND(AZ11=0,AW11=0),"",(AW11-AZ11)/AZ11)))) -> 1 | BC11: =+'N EERR'!I10 -> 0 | BD11: =IF(AND(BC4=0,BC11>=0), "",BC11/BC4) | BF11: =IF(AND(AM11=0,BC11>0),100%,IF(AND(AM11<0,BC11=0),(AM11-BC11)/AM11,IF(AND(AM11>0,BC11>0),(BC11-AM11)/AM11,IF(AND(AM11=0,BC11=0),"",(BC11-AM11)/AM11)))) | BG11: =+AQ11+BC11 -> 50 | BH11: =IF(AND(BG4=0,BG11>=0), "",BG11/BG4) -> 0.0036231884 | BJ11: =+'N EERR'!J10 -> 0 | BK11: =IF(AND(BJ4=0,BJ11>=0), "",BJ11/BJ4) | BM11: =IF(AND(BC11=0,BJ11>0),100%,IF(AND(BC11<0,BJ11=0),(BC11-BJ11)/BC11,IF(AND(BC11>0,BJ11>0),(BJ11-BC11)/BC11,IF(AND(BC11=0,BJ11=0),"",(BJ11-BC11)/BC11)))) | BN11: =+BG11+BJ11 -> 50 | BO11: =IF(AND(BN4=0,BN11>=0), "",BN11/BN4) -> 0.0036231884 | BQ11: =+'N EERR'!K10 -> 0 | BR11: =IF(AND(BQ4=0,BQ11>=0), "",BQ11/BQ4) | BT11: =IF(AND(BJ11=0,BQ11>0),100%,IF(AND(BJ11<0,BQ11=0),(BJ11-BQ11)/BJ11,IF(AND(BJ11>0,BQ11>0),(BQ11-BJ11)/BJ11,IF(AND(BJ11=0,BQ11=0),"",(BQ11-BJ11)/BJ11)))) | BU11: =+BN11+BQ11 -> 50 | BV11: =IF(AND(BU4=0,BU11>=0), "",BU11/BU4) -> 0.0036231884 | BX11: =+AZ11*9 -> 0 | BY11: =IF(AND(BX4=0,BX11>=0), "",BX11/BX4) | BZ11: =IF(AND(BX11=0,BU11>0),100%,IF(AND(BX11<0,BU11=0),(BX11-BU11)/BX11,IF(AND(BX11>0,BU11>0),(BU11-BX11)/BX11,IF(AND(BX11=0,BU11=0),"",(BU11-BX11)/BX11)))) -> 1 | CA11: =+'N EERR'!L10 -> 0 | CB11: =IF(AND(CA4=0,CA11>=0), "",CA11/CA4) | CD11: =IF(AND(BQ11=0,CA11>0),100%,IF(AND(BQ11<0,CA11=0),(BQ11-CA11)/BQ11,IF(AND(BQ11>0,CA11>0),(CA11-BQ11)/BQ11,IF(AND(BQ11=0,CA11=0),"",(CA11-BQ11)/BQ11)))) | CE11: =+BU11+CA11 -> 50 | CF11: =IF(AND(CE4=0,CE11>=0), "",CE11/CE4) -> 0.0036231884 | CH11: =+'N EERR'!M10 -> 0 | CI11: =IF(AND(CH4=0,CH11>=0), "",CH11/CH4) | CK11: =IF(AND(CA11=0,CH11>0),100%,IF(AND(CA11<0,CH11=0),(CA11-CH11)/CA11,IF(AND(CA11>0,CH11>0),(CH11-CA11)/CA11,IF(AND(CA11=0,CH11=0),"",(CH11-CA11)/CA11)))) | CL11: =+CE11+CH11 -> 50 | CM11: =IF(AND(CL4=0,CL11>=0), "",CL11/CL4) -> 0.0036231884 | CO11: =+'N EERR'!N10 -> 0 | CP11: =IF(AND(CO4=0,CO11>=0), "",CO11/CO4) | CR11: =IF(AND(CH11=0,CO11>0),100%,IF(AND(CH11<0,CO11=0),(CH11-CO11)/CH11,IF(AND(CH11>0,CO11>0),(CO11-CH11)/CH11,IF(AND(CH11=0,CO11=0),"",(CO11-CH11)/CH11)))) | CS11: =+CL11+CO11 -> 50 | CT11: =IF(AND(CS4=0,CS11>=0), "",CS11/CS4) -> 0.0036231884 | CV11: =+AZ11*12 -> 0 | CW11: =IF(AND(CV4=0,CV11>=0), "",CV11/CV4) | CX11: =IF(AND(CV11=0,CS11>0),100%,IF(AND(CV11<0,CS11=0),(CV11-CS11)/CV11,IF(AND(CV11>0,CS11>0),(CS11-CV11)/CV11,IF(AND(CV11=0,CS11=0),"",(CS11-CV11)/CV11)))) -> 1
A12: Ingresos por zona FIT | B12: =+'N EERR'!B11 -> 0 | C12: =IF(AND(B4=0,B12>=0), "",B12/B4) | E12: =+'N EERR'!C11 -> 50 | F12: =IF(AND(E4=0,E12>=0), "",E12/E4) -> 0.0036231884 | H12: =+'N EERR'!D11 -> 0 | I12: =IF(AND(H4=0,H12>=0), "",H12/H4) | K12: =IF(AND(E12=0,H12>0),100%,IF(AND(E12<0,H12=0),(E12-H12)/E12,IF(AND(E12>0,H12>0),(H12-E12)/E12,IF(AND(E12=0,H12=0),"",(H12-E12)/E12)))) -> -1 | L12: =+E12+H12 -> 50 | M12: =IF(AND(L4=0,L12>=0), "",L12/L4) -> 0.0036231884 | O12: =+'N EERR'!E11 -> 0 | P12: =IF(AND(O4=0,O12>=0), "",O12/O4) | R12: =IF(AND(H12=0,O12>0),100%,IF(AND(H12<0,O12=0),(H12-O12)/H12,IF(AND(H12>0,O12>0),(O12-H12)/H12,IF(AND(H12=0,O12=0),"",(O12-H12)/H12)))) | S12: =+L12+O12 -> 50 | T12: =IF(AND(S4=0,S12>=0), "",S12/S4) -> 0.0036231884 | W12: =IF(AND(V4=0,V12>=0), "",V12/V4) | X12: =IF(AND(V12=0,S12>0),100%,IF(AND(V12<0,S12=0),(V12-S12)/V12,IF(AND(V12>0,S12>0),(S12-V12)/V12,IF(AND(V12=0,S12=0),"",(S12-V12)/V12)))) -> 1 | Y12: =+'N EERR'!F11 -> 0 | Z12: =IF(AND(Y4=0,Y12>=0), "",Y12/Y4) | AB12: =IF(AND(O12=0,Y12>0),100%,IF(AND(O12<0,Y12=0),(O12-Y12)/O12,IF(AND(O12>0,Y12>0),(Y12-O12)/O12,IF(AND(O12=0,Y12=0),"",(Y12-O12)/O12)))) | AC12: =+S12+Y12 -> 50 | AD12: =IF(AND(AC4=0,AC12>=0), "",AC12/AC4) -> 0.0036231884 | AF12: =+'N EERR'!G11 -> 0 | AG12: =IF(AND(AF4=0,AF12>=0), "",AF12/AF4) | AI12: =IF(AND(Y12=0,AF12>0),100%,IF(AND(Y12<0,AF12=0),(Y12-AF12)/Y12,IF(AND(Y12>0,AF12>0),(AF12-Y12)/Y12,IF(AND(Y12=0,AF12=0),"",(AF12-Y12)/Y12)))) | AJ12: =+AC12+AF12 -> 50 | AK12: =IF(AND(AJ4=0,AJ12>=0), "",AJ12/AJ4) -> 0.0036231884 | AM12: =+'N EERR'!H11 -> 0 | AN12: =IF(AND(AM4=0,AM12>=0), "",AM12/AM4) | AP12: =IF(AND(AF12=0,AM12>0),100%,IF(AND(AF12<0,AM12=0),(AF12-AM12)/AF12,IF(AND(AF12>0,AM12>0),(AM12-AF12)/AF12,IF(AND(AF12=0,AM12=0),"",(AM12-AF12)/AF12)))) | AQ12: =+AJ12+AM12 -> 50 | AR12: =IF(AND(AQ4=0,AQ12>=0), "",AQ12/AQ4) -> 0.0036231884 | AT12: =+V12*2 -> 0 | AU12: =IF(AND(AT4=0,AT12>=0), "",AT12/AT4) | AV12: =IF(AND(AT12=0,AQ12>0),100%,IF(AND(AT12<0,AQ12=0),(AT12-AQ12)/AT12,IF(AND(AT12>0,AQ12>0),(AQ12-AT12)/AT12,IF(AND(AT12=0,AQ12=0),"",(AQ12-AT12)/AT12)))) -> 1 | AW12: =+AQ12/6 -> 8.3333333 | AX12: =IF(AND(AW4=0,AW12>=0), "",AW12/AW4) -> 0.0036231884 | AZ12: =+AT12/6 -> 0 | BA12: =IF(AND(AZ4=0,AZ12>=0), "",AZ12/AZ4) | BB12: =IF(AND(AZ12=0,AW12>0),100%,IF(AND(AZ12<0,AW12=0),(AZ12-AW12)/AZ12,IF(AND(AZ12>0,AW12>0),(AW12-AZ12)/AZ12,IF(AND(AZ12=0,AW12=0),"",(AW12-AZ12)/AZ12)))) -> 1 | BC12: =+'N EERR'!I11 -> 0 | BD12: =IF(AND(BC4=0,BC12>=0), "",BC12/BC4) | BF12: =IF(AND(AM12=0,BC12>0),100%,IF(AND(AM12<0,BC12=0),(AM12-BC12)/AM12,IF(AND(AM12>0,BC12>0),(BC12-AM12)/AM12,IF(AND(AM12=0,BC12=0),"",(BC12-AM12)/AM12)))) | BG12: =+AQ12+BC12 -> 50 | BH12: =IF(AND(BG4=0,BG12>=0), "",BG12/BG4) -> 0.0036231884 | BJ12: =+'N EERR'!J11 -> 0 | BK12: =IF(AND(BJ4=0,BJ12>=0), "",BJ12/BJ4) | BM12: =IF(AND(BC12=0,BJ12>0),100%,IF(AND(BC12<0,BJ12=0),(BC12-BJ12)/BC12,IF(AND(BC12>0,BJ12>0),(BJ12-BC12)/BC12,IF(AND(BC12=0,BJ12=0),"",(BJ12-BC12)/BC12)))) | BN12: =+BG12+BJ12 -> 50 | BO12: =IF(AND(BN4=0,BN12>=0), "",BN12/BN4) -> 0.0036231884 | BQ12: =+'N EERR'!K11 -> 0 | BR12: =IF(AND(BQ4=0,BQ12>=0), "",BQ12/BQ4) | BT12: =IF(AND(BJ12=0,BQ12>0),100%,IF(AND(BJ12<0,BQ12=0),(BJ12-BQ12)/BJ12,IF(AND(BJ12>0,BQ12>0),(BQ12-BJ12)/BJ12,IF(AND(BJ12=0,BQ12=0),"",(BQ12-BJ12)/BJ12)))) | BU12: =+BN12+BQ12 -> 50 | BV12: =IF(AND(BU4=0,BU12>=0), "",BU12/BU4) -> 0.0036231884 | BX12: =+AZ12*9 -> 0 | BY12: =IF(AND(BX4=0,BX12>=0), "",BX12/BX4) | BZ12: =IF(AND(BX12=0,BU12>0),100%,IF(AND(BX12<0,BU12=0),(BX12-BU12)/BX12,IF(AND(BX12>0,BU12>0),(BU12-BX12)/BX12,IF(AND(BX12=0,BU12=0),"",(BU12-BX12)/BX12)))) -> 1 | CA12: =+'N EERR'!L11 -> 0 | CB12: =IF(AND(CA4=0,CA12>=0), "",CA12/CA4) | CD12: =IF(AND(BQ12=0,CA12>0),100%,IF(AND(BQ12<0,CA12=0),(BQ12-CA12)/BQ12,IF(AND(BQ12>0,CA12>0),(CA12-BQ12)/BQ12,IF(AND(BQ12=0,CA12=0),"",(CA12-BQ12)/BQ12)))) | CE12: =+BU12+CA12 -> 50 | CF12: =IF(AND(CE4=0,CE12>=0), "",CE12/CE4) -> 0.0036231884 | CH12: =+'N EERR'!M11 -> 0 | CI12: =IF(AND(CH4=0,CH12>=0), "",CH12/CH4) | CK12: =IF(AND(CA12=0,CH12>0),100%,IF(AND(CA12<0,CH12=0),(CA12-CH12)/CA12,IF(AND(CA12>0,CH12>0),(CH12-CA12)/CA12,IF(AND(CA12=0,CH12=0),"",(CH12-CA12)/CA12)))) | CL12: =+CE12+CH12 -> 50 | CM12: =IF(AND(CL4=0,CL12>=0), "",CL12/CL4) -> 0.0036231884 | CO12: =+'N EERR'!N11 -> 0 | CP12: =IF(AND(CO4=0,CO12>=0), "",CO12/CO4) | CR12: =IF(AND(CH12=0,CO12>0),100%,IF(AND(CH12<0,CO12=0),(CH12-CO12)/CH12,IF(AND(CH12>0,CO12>0),(CO12-CH12)/CH12,IF(AND(CH12=0,CO12=0),"",(CO12-CH12)/CH12)))) | CS12: =+CL12+CO12 -> 50 | CT12: =IF(AND(CS4=0,CS12>=0), "",CS12/CS4) -> 0.0036231884 | CV12: =+AZ12*12 -> 0 | CW12: =IF(AND(CV4=0,CV12>=0), "",CV12/CV4) | CX12: =IF(AND(CV12=0,CS12>0),100%,IF(AND(CV12<0,CS12=0),(CV12-CS12)/CV12,IF(AND(CV12>0,CS12>0),(CS12-CV12)/CV12,IF(AND(CV12=0,CS12=0),"",(CS12-CV12)/CV12)))) -> 1
A13: Ingresos por fletes | B13: =+'N EERR'!B12 -> 0 | C13: =IF(AND(B4=0,B13>=0), "",B13/B4) | E13: =+'N EERR'!C12 -> 50 | F13: =IF(AND(E4=0,E13>=0), "",E13/E4) -> 0.0036231884 | H13: =+'N EERR'!D12 -> 0 | I13: =IF(AND(H4=0,H13>=0), "",H13/H4) | K13: =IF(AND(E13=0,H13>0),100%,IF(AND(E13<0,H13=0),(E13-H13)/E13,IF(AND(E13>0,H13>0),(H13-E13)/E13,IF(AND(E13=0,H13=0),"",(H13-E13)/E13)))) -> -1 | L13: =+E13+H13 -> 50 | M13: =IF(AND(L4=0,L13>=0), "",L13/L4) -> 0.0036231884 | O13: =+'N EERR'!E12 -> 0 | P13: =IF(AND(O4=0,O13>=0), "",O13/O4) | R13: =IF(AND(H13=0,O13>0),100%,IF(AND(H13<0,O13=0),(H13-O13)/H13,IF(AND(H13>0,O13>0),(O13-H13)/H13,IF(AND(H13=0,O13=0),"",(O13-H13)/H13)))) | S13: =+L13+O13 -> 50 | T13: =IF(AND(S4=0,S13>=0), "",S13/S4) -> 0.0036231884 | W13: =IF(AND(V4=0,V13>=0), "",V13/V4) | X13: =IF(AND(V13=0,S13>0),100%,IF(AND(V13<0,S13=0),(V13-S13)/V13,IF(AND(V13>0,S13>0),(S13-V13)/V13,IF(AND(V13=0,S13=0),"",(S13-V13)/V13)))) -> 1 | Y13: =+'N EERR'!F12 -> 0 | Z13: =IF(AND(Y4=0,Y13>=0), "",Y13/Y4) | AB13: =IF(AND(O13=0,Y13>0),100%,IF(AND(O13<0,Y13=0),(O13-Y13)/O13,IF(AND(O13>0,Y13>0),(Y13-O13)/O13,IF(AND(O13=0,Y13=0),"",(Y13-O13)/O13)))) | AC13: =+S13+Y13 -> 50 | AD13: =IF(AND(AC4=0,AC13>=0), "",AC13/AC4) -> 0.0036231884 | AF13: =+'N EERR'!G12 -> 0 | AG13: =IF(AND(AF4=0,AF13>=0), "",AF13/AF4) | AI13: =IF(AND(Y13=0,AF13>0),100%,IF(AND(Y13<0,AF13=0),(Y13-AF13)/Y13,IF(AND(Y13>0,AF13>0),(AF13-Y13)/Y13,IF(AND(Y13=0,AF13=0),"",(AF13-Y13)/Y13)))) | AJ13: =+AC13+AF13 -> 50 | AK13: =IF(AND(AJ4=0,AJ13>=0), "",AJ13/AJ4) -> 0.0036231884 | AM13: =+'N EERR'!H12 -> 0 | AN13: =IF(AND(AM4=0,AM13>=0), "",AM13/AM4) | AP13: =IF(AND(AF13=0,AM13>0),100%,IF(AND(AF13<0,AM13=0),(AF13-AM13)/AF13,IF(AND(AF13>0,AM13>0),(AM13-AF13)/AF13,IF(AND(AF13=0,AM13=0),"",(AM13-AF13)/AF13)))) | AQ13: =+AJ13+AM13 -> 50 | AR13: =IF(AND(AQ4=0,AQ13>=0), "",AQ13/AQ4) -> 0.0036231884 | AT13: =+V13*2 -> 0 | AU13: =IF(AND(AT4=0,AT13>=0), "",AT13/AT4) | AV13: =IF(AND(AT13=0,AQ13>0),100%,IF(AND(AT13<0,AQ13=0),(AT13-AQ13)/AT13,IF(AND(AT13>0,AQ13>0),(AQ13-AT13)/AT13,IF(AND(AT13=0,AQ13=0),"",(AQ13-AT13)/AT13)))) -> 1 | AW13: =+AQ13/6 -> 8.3333333 | AX13: =IF(AND(AW4=0,AW13>=0), "",AW13/AW4) -> 0.0036231884 | AZ13: =+AT13/6 -> 0 | BA13: =IF(AND(AZ4=0,AZ13>=0), "",AZ13/AZ4) | BB13: =IF(AND(AZ13=0,AW13>0),100%,IF(AND(AZ13<0,AW13=0),(AZ13-AW13)/AZ13,IF(AND(AZ13>0,AW13>0),(AW13-AZ13)/AZ13,IF(AND(AZ13=0,AW13=0),"",(AW13-AZ13)/AZ13)))) -> 1 | BC13: =+'N EERR'!I12 -> 0 | BD13: =IF(AND(BC4=0,BC13>=0), "",BC13/BC4) | BF13: =IF(AND(AM13=0,BC13>0),100%,IF(AND(AM13<0,BC13=0),(AM13-BC13)/AM13,IF(AND(AM13>0,BC13>0),(BC13-AM13)/AM13,IF(AND(AM13=0,BC13=0),"",(BC13-AM13)/AM13)))) | BG13: =+AQ13+BC13 -> 50 | BH13: =IF(AND(BG4=0,BG13>=0), "",BG13/BG4) -> 0.0036231884 | BJ13: =+'N EERR'!J12 -> 0 | BK13: =IF(AND(BJ4=0,BJ13>=0), "",BJ13/BJ4) | BM13: =IF(AND(BC13=0,BJ13>0),100%,IF(AND(BC13<0,BJ13=0),(BC13-BJ13)/BC13,IF(AND(BC13>0,BJ13>0),(BJ13-BC13)/BC13,IF(AND(BC13=0,BJ13=0),"",(BJ13-BC13)/BC13)))) | BN13: =+BG13+BJ13 -> 50 | BO13: =IF(AND(BN4=0,BN13>=0), "",BN13/BN4) -> 0.0036231884 | BQ13: =+'N EERR'!K12 -> 0 | BR13: =IF(AND(BQ4=0,BQ13>=0), "",BQ13/BQ4) | BT13: =IF(AND(BJ13=0,BQ13>0),100%,IF(AND(BJ13<0,BQ13=0),(BJ13-BQ13)/BJ13,IF(AND(BJ13>0,BQ13>0),(BQ13-BJ13)/BJ13,IF(AND(BJ13=0,BQ13=0),"",(BQ13-BJ13)/BJ13)))) | BU13: =+BN13+BQ13 -> 50 | BV13: =IF(AND(BU4=0,BU13>=0), "",BU13/BU4) -> 0.0036231884 | BX13: =+AZ13*9 -> 0 | BY13: =IF(AND(BX4=0,BX13>=0), "",BX13/BX4) | BZ13: =IF(AND(BX13=0,BU13>0),100%,IF(AND(BX13<0,BU13=0),(BX13-BU13)/BX13,IF(AND(BX13>0,BU13>0),(BU13-BX13)/BX13,IF(AND(BX13=0,BU13=0),"",(BU13-BX13)/BX13)))) -> 1 | CA13: =+'N EERR'!L12 -> 0 | CB13: =IF(AND(CA4=0,CA13>=0), "",CA13/CA4) | CD13: =IF(AND(BQ13=0,CA13>0),100%,IF(AND(BQ13<0,CA13=0),(BQ13-CA13)/BQ13,IF(AND(BQ13>0,CA13>0),(CA13-BQ13)/BQ13,IF(AND(BQ13=0,CA13=0),"",(CA13-BQ13)/BQ13)))) | CE13: =+BU13+CA13 -> 50 | CF13: =IF(AND(CE4=0,CE13>=0), "",CE13/CE4) -> 0.0036231884 | CH13: =+'N EERR'!M12 -> 0 | CI13: =IF(AND(CH4=0,CH13>=0), "",CH13/CH4) | CK13: =IF(AND(CA13=0,CH13>0),100%,IF(AND(CA13<0,CH13=0),(CA13-CH13)/CA13,IF(AND(CA13>0,CH13>0),(CH13-CA13)/CA13,IF(AND(CA13=0,CH13=0),"",(CH13-CA13)/CA13)))) | CL13: =+CE13+CH13 -> 50 | CM13: =IF(AND(CL4=0,CL13>=0), "",CL13/CL4) -> 0.0036231884 | CO13: =+'N EERR'!N12 -> 0 | CP13: =IF(AND(CO4=0,CO13>=0), "",CO13/CO4) | CR13: =IF(AND(CH13=0,CO13>0),100%,IF(AND(CH13<0,CO13=0),(CH13-CO13)/CH13,IF(AND(CH13>0,CO13>0),(CO13-CH13)/CH13,IF(AND(CH13=0,CO13=0),"",(CO13-CH13)/CH13)))) | CS13: =+CL13+CO13 -> 50 | CT13: =IF(AND(CS4=0,CS13>=0), "",CS13/CS4) -> 0.0036231884 | CV13: =+AZ13*12 -> 0 | CW13: =IF(AND(CV4=0,CV13>=0), "",CV13/CV4) | CX13: =IF(AND(CV13=0,CS13>0),100%,IF(AND(CV13<0,CS13=0),(CV13-CS13)/CV13,IF(AND(CV13>0,CS13>0),(CS13-CV13)/CV13,IF(AND(CV13=0,CS13=0),"",(CS13-CV13)/CV13)))) -> 1
A14: Ingresos por otros servicios | B14: =+'N EERR'!B13 -> 0 | C14: =IF(AND(B4=0,B14>=0),,B14/B4) -> 0 | E14: =+'N EERR'!C13 -> 50 | F14: =IF(AND(E4=0,E14>=0),,E14/E4) -> 0.0036231884 | H14: =+'N EERR'!D13 -> 0 | I14: =IF(AND(H4=0,H14>=0),,H14/H4) -> 0 | K14: =IF(AND(E14=0,H14>0),100%,IF(AND(E14<0,H14=0),(E14-H14)/E14,IF(AND(E14>0,H14>0),(H14-E14)/E14,IF(AND(E14=0,H14=0),0,(H14-E14)/E14)))) -> -1 | L14: =+E14+H14 -> 50 | M14: =IF(AND(L4=0,L14>=0),,L14/L4) -> 0.0036231884 | O14: =+'N EERR'!E13 -> 0 | P14: =IF(AND(O4=0,O14>=0),,O14/O4) -> 0 | R14: =IF(AND(H14=0,O14>0),100%,IF(AND(H14<0,O14=0),(H14-O14)/H14,IF(AND(H14>0,O14>0),(O14-H14)/H14,IF(AND(H14=0,O14=0),0,(O14-H14)/H14)))) -> 0 | S14: =+L14+O14 -> 50 | T14: =IF(AND(S4=0,S14>=0),,S14/S4) -> 0.0036231884 | V14: =+'[1]MAYOR EERR'!V14+'[1]EVENTOS EERR'!V14+'[1]TERRACOTA EERR'!V14+'[1]UCAFE EERR'!V14 -> 0 | W14: =IF(AND(V4=0,V14>=0),,V14/V4) -> 0 | X14: =IF(AND(V14=0,S14>0),100%,IF(AND(V14<0,S14=0),(V14-S14)/V14,IF(AND(V14>0,S14>0),(S14-V14)/V14,IF(AND(V14=0,S14=0),0,(S14-V14)/V14)))) -> 1 | Y14: =+'N EERR'!F13 -> 0 | Z14: =IF(AND(Y4=0,Y14>=0),,Y14/Y4) -> 0 | AB14: =IF(AND(O14=0,Y14>0),100%,IF(AND(O14<0,Y14=0),(O14-Y14)/O14,IF(AND(O14>0,Y14>0),(Y14-O14)/O14,IF(AND(O14=0,Y14=0),0,(Y14-O14)/O14)))) -> 0 | AC14: =+S14+Y14 -> 50 | AD14: =IF(AND(AC4=0,AC14>=0),,AC14/AC4) -> 0.0036231884 | AF14: =+'N EERR'!G13 -> 0 | AG14: =IF(AND(AF4=0,AF14>=0),,AF14/AF4) -> 0 | AI14: =IF(AND(V14=0,AF14>0),100%,IF(AND(V14<0,AF14=0),(V14-AF14)/V14,IF(AND(V14>0,AF14>0),(AF14-V14)/V14,IF(AND(V14=0,AF14=0),0,(AF14-V14)/V14)))) -> 0 | AJ14: =+AC14+AF14 -> 50 | AK14: =IF(AND(AJ4=0,AJ14>=0),,AJ14/AJ4) -> 0.0036231884 | AM14: =+'N EERR'!H13 -> 0 | AN14: =IF(AND(AM4=0,AM14>=0),,AM14/AM4) -> 0 | AP14: =IF(AND(AC14=0,AM14>0),100%,IF(AND(AC14<0,AM14=0),(AC14-AM14)/AC14,IF(AND(AC14>0,AM14>0),(AM14-AC14)/AC14,IF(AND(AC14=0,AM14=0),0,(AM14-AC14)/AC14)))) -> -1 | AQ14: =+AJ14+AM14 -> 50 | AR14: =IF(AND(AQ4=0,AQ14>=0),,AQ14/AQ4) -> 0.0036231884 | AT14: =+V14*2 -> 0 | AU14: =IF(AND(AT4=0,AT14>=0),,AT14/AT4) -> 0 | AV14: =IF(AND(AT14=0,AQ14>0),100%,IF(AND(AT14<0,AQ14=0),(AT14-AQ14)/AT14,IF(AND(AT14>0,AQ14>0),(AQ14-AT14)/AT14,IF(AND(AT14=0,AQ14=0),0,(AQ14-AT14)/AT14)))) -> 1 | AW14: =+AQ14/6 -> 8.3333333 | AX14: =IF(AND(AW4=0,AW14>=0),,AW14/AW4) -> 0.0036231884 | AZ14: =+AT14/6 -> 0 | BA14: =IF(AND(AZ4=0,AZ14>=0),,AZ14/AZ4) -> 0 | BB14: =IF(AND(AZ14=0,AW14>0),100%,IF(AND(AZ14<0,AW14=0),(AZ14-AW14)/AZ14,IF(AND(AZ14>0,AW14>0),(AW14-AZ14)/AZ14,IF(AND(AZ14=0,AW14=0),0,(AW14-AZ14)/AZ14)))) -> 1 | BC14: =+'N EERR'!I13 -> 0 | BD14: =IF(AND(BC4=0,BC14>=0),,BC14/BC4) -> 0 | BF14: =IF(AND(AM14=0,BC14>0),100%,IF(AND(AM14<0,BC14=0),(AM14-BC14)/AM14,IF(AND(AM14>0,BC14>0),(BC14-AM14)/AM14,IF(AND(AM14=0,BC14=0),0,(BC14-AM14)/AM14)))) -> 0 | BG14: =+AQ14+BC14 -> 50 | BH14: =IF(AND(BG4=0,BG14>=0),,BG14/BG4) -> 0.0036231884 | BJ14: =+'N EERR'!J13 -> 0 | BK14: =IF(AND(BJ4=0,BJ14>=0),,BJ14/BJ4) -> 0 | BM14: =IF(AND(BC14=0,BJ14>0),100%,IF(AND(BC14<0,BJ14=0),(BC14-BJ14)/BC14,IF(AND(BC14>0,BJ14>0),(BJ14-BC14)/BC14,IF(AND(BC14=0,BJ14=0),0,(BJ14-BC14)/BC14)))) -> 0 | BN14: =+BG14+BJ14 -> 50 | BO14: =IF(AND(BN4=0,BN14>=0),,BN14/BN4) -> 0.0036231884 | BQ14: =+'N EERR'!K13 -> 0 | BR14: =IF(AND(BQ4=0,BQ14>=0),,BQ14/BQ4) -> 0 | BT14: =IF(AND(BJ14=0,BQ14>0),100%,IF(AND(BJ14<0,BQ14=0),(BJ14-BQ14)/BJ14,IF(AND(BJ14>0,BQ14>0),(BQ14-BJ14)/BJ14,IF(AND(BJ14=0,BQ14=0),0,(BQ14-BJ14)/BJ14)))) -> 0 | BU14: =+BN14+BQ14 -> 50 | BV14: =IF(AND(BU4=0,BU14>=0),,BU14/BU4) -> 0.0036231884 | BX14: =+AZ14*9 -> 0 | BY14: =IF(AND(BX4=0,BX14>=0),,BX14/BX4) -> 0 | BZ14: =IF(AND(BX14=0,BU14>0),100%,IF(AND(BX14<0,BU14=0),(BX14-BU14)/BX14,IF(AND(BX14>0,BU14>0),(BU14-BX14)/BX14,IF(AND(BX14=0,BU14=0),0,(BU14-BX14)/BX14)))) -> 1 | CA14: =+'N EERR'!L13 -> 0 | CB14: =IF(AND(CA4=0,CA14>=0),,CA14/CA4) -> 0 | CD14: =IF(AND(BQ14=0,CA14>0),100%,IF(AND(BQ14<0,CA14=0),(BQ14-CA14)/BQ14,IF(AND(BQ14>0,CA14>0),(CA14-BQ14)/BQ14,IF(AND(BQ14=0,CA14=0),0,(CA14-BQ14)/BQ14)))) -> 0 | CE14: =+BU14+CA14 -> 50 | CF14: =IF(AND(CE4=0,CE14>=0),,CE14/CE4) -> 0.0036231884 | CH14: =+'N EERR'!M13 -> 0 | CI14: =IF(AND(CH4=0,CH14>=0),,CH14/CH4) -> 0 | CK14: =IF(AND(CA14=0,CH14>0),100%,IF(AND(CA14<0,CH14=0),(CA14-CH14)/CA14,IF(AND(CA14>0,CH14>0),(CH14-CA14)/CA14,IF(AND(CA14=0,CH14=0),0,(CH14-CA14)/CA14)))) -> 0 | CL14: =+CE14+CH14 -> 50 | CM14: =IF(AND(CL4=0,CL14>=0),,CL14/CL4) -> 0.0036231884 | CO14: =+'N EERR'!N13 -> 0 | CP14: =IF(AND(CO4=0,CO14>=0),,CO14/CO4) -> 0 | CR14: =IF(AND(CH14=0,CO14>0),100%,IF(AND(CH14<0,CO14=0),(CH14-CO14)/CH14,IF(AND(CH14>0,CO14>0),(CO14-CH14)/CH14,IF(AND(CH14=0,CO14=0),0,(CO14-CH14)/CH14)))) -> 0 | CS14: =+CL14+CO14 -> 50 | CT14: =IF(AND(CS4=0,CS14>=0),,CS14/CS4) -> 0.0036231884 | CV14: =+AZ14*12 -> 0 | CW14: =IF(AND(CV4=0,CV14>=0),,CV14/CV4) -> 0 | CX14: =IF(AND(CV14=0,CS14>0),100%,IF(AND(CV14<0,CS14=0),(CV14-CS14)/CV14,IF(AND(CV14>0,CS14>0),(CS14-CV14)/CV14,IF(AND(CV14=0,CS14=0),0,(CS14-CV14)/CV14)))) -> 1
A15: Subtotal Ingresos por Eventos | B15: =SUM(B16:B17) -> 0 | C15: =IF(AND(B4=0,B15>=0), "",B15/B4) | E15: =SUM(E16:E17) -> 50 | F15: =IF(AND(E4=0,E15>=0), "",E15/E4) -> 0.0036231884 | H15: =SUM(H16:H17) -> 0 | I15: =IF(AND(H4=0,H15>=0), "",H15/H4) | K15: =IF(AND(E15=0,H15>0),100%,IF(AND(E15<0,H15=0),(E15-H15)/E15,IF(AND(E15>0,H15>0),(H15-E15)/E15,IF(AND(E15=0,H15=0),"",(H15-E15)/E15)))) -> -1 | L15: =SUM(L16:L17) -> 50 | M15: =IF(AND(L4=0,L15>=0), "",L15/L4) -> 0.0036231884 | O15: =SUM(O16:O17) -> 0 | P15: =IF(AND(O4=0,O15>=0), "",O15/O4) | R15: =IF(AND(H15=0,O15>0),100%,IF(AND(H15<0,O15=0),(H15-O15)/H15,IF(AND(H15>0,O15>0),(O15-H15)/H15,IF(AND(H15=0,O15=0),"",(O15-H15)/H15)))) | S15: =SUM(S16:S17) -> 50 | T15: =IF(AND(S4=0,S15>=0), "",S15/S4) -> 0.0036231884 | V15: =SUM(V16:V17) -> 0 | W15: =IF(AND(V4=0,V15>=0), "",V15/V4) | X15: =IF(AND(V15=0,S15>0),100%,IF(AND(V15<0,S15=0),(V15-S15)/V15,IF(AND(V15>0,S15>0),(S15-V15)/V15,IF(AND(V15=0,S15=0),"",(S15-V15)/V15)))) -> 1 | Y15: =SUM(Y16:Y17) -> 0 | Z15: =IF(AND(Y4=0,Y15>=0), "",Y15/Y4) | AB15: =IF(AND(O15=0,Y15>0),100%,IF(AND(O15<0,Y15=0),(O15-Y15)/O15,IF(AND(O15>0,Y15>0),(Y15-O15)/O15,IF(AND(O15=0,Y15=0),"",(Y15-O15)/O15)))) | AC15: =SUM(AC16:AC17) -> 50 | AD15: =IF(AND(AC4=0,AC15>=0), "",AC15/AC4) -> 0.0036231884 | AF15: =SUM(AF16:AF17) -> 0 | AG15: =IF(AND(AF4=0,AF15>=0), "",AF15/AF4) | AI15: =IF(AND(Y15=0,AF15>0),100%,IF(AND(Y15<0,AF15=0),(Y15-AF15)/Y15,IF(AND(Y15>0,AF15>0),(AF15-Y15)/Y15,IF(AND(Y15=0,AF15=0),"",(AF15-Y15)/Y15)))) | AJ15: =SUM(AJ16:AJ17) -> 50 | AK15: =IF(AND(AJ4=0,AJ15>=0), "",AJ15/AJ4) -> 0.0036231884 | AM15: =SUM(AM16:AM17) -> 0 | AN15: =IF(AND(AM4=0,AM15>=0), "",AM15/AM4) | AP15: =IF(AND(AF15=0,AM15>0),100%,IF(AND(AF15<0,AM15=0),(AF15-AM15)/AF15,IF(AND(AF15>0,AM15>0),(AM15-AF15)/AF15,IF(AND(AF15=0,AM15=0),"",(AM15-AF15)/AF15)))) | AQ15: =SUM(AQ16:AQ17) -> 50 | AR15: =IF(AND(AQ4=0,AQ15>=0), "",AQ15/AQ4) -> 0.0036231884 | AT15: =SUM(AT16:AT17) -> 0 | AU15: =IF(AND(AT4=0,AT15>=0), "",AT15/AT4) | AV15: =IF(AND(AT15=0,AQ15>0),100%,IF(AND(AT15<0,AQ15=0),(AT15-AQ15)/AT15,IF(AND(AT15>0,AQ15>0),(AQ15-AT15)/AT15,IF(AND(AT15=0,AQ15=0),"",(AQ15-AT15)/AT15)))) -> 1 | AW15: =SUM(AW16:AW17) -> 8.3333333 | AX15: =IF(AND(AW4=0,AW15>=0), "",AW15/AW4) -> 0.0036231884 | AZ15: =SUM(AZ16:AZ17) -> 0 | BA15: =IF(AND(AZ4=0,AZ15>=0), "",AZ15/AZ4) | BB15: =IF(AND(AZ15=0,AW15>0),100%,IF(AND(AZ15<0,AW15=0),(AZ15-AW15)/AZ15,IF(AND(AZ15>0,AW15>0),(AW15-AZ15)/AZ15,IF(AND(AZ15=0,AW15=0),"",(AW15-AZ15)/AZ15)))) -> 1 | BC15: =SUM(BC16:BC17) -> 0 | BD15: =IF(AND(BC4=0,BC15>=0), "",BC15/BC4) | BF15: =IF(AND(AM15=0,BC15>0),100%,IF(AND(AM15<0,BC15=0),(AM15-BC15)/AM15,IF(AND(AM15>0,BC15>0),(BC15-AM15)/AM15,IF(AND(AM15=0,BC15=0),"",(BC15-AM15)/AM15)))) | BG15: =SUM(BG16:BG17) -> 50 | BH15: =IF(AND(BG4=0,BG15>=0), "",BG15/BG4) -> 0.0036231884 | BJ15: =SUM(BJ16:BJ17) -> 0 | BK15: =IF(AND(BJ4=0,BJ15>=0), "",BJ15/BJ4) | BM15: =IF(AND(BC15=0,BJ15>0),100%,IF(AND(BC15<0,BJ15=0),(BC15-BJ15)/BC15,IF(AND(BC15>0,BJ15>0),(BJ15-BC15)/BC15,IF(AND(BC15=0,BJ15=0),"",(BJ15-BC15)/BC15)))) | BN15: =SUM(BN16:BN17) -> 50 | BO15: =IF(AND(BN4=0,BN15>=0), "",BN15/BN4) -> 0.0036231884 | BQ15: =SUM(BQ16:BQ17) -> 0 | BR15: =IF(AND(BQ4=0,BQ15>=0), "",BQ15/BQ4) | BT15: =IF(AND(BJ15=0,BQ15>0),100%,IF(AND(BJ15<0,BQ15=0),(BJ15-BQ15)/BJ15,IF(AND(BJ15>0,BQ15>0),(BQ15-BJ15)/BJ15,IF(AND(BJ15=0,BQ15=0),"",(BQ15-BJ15)/BJ15)))) | BU15: =SUM(BU16:BU17) -> 50 | BV15: =IF(AND(BU4=0,BU15>=0), "",BU15/BU4) -> 0.0036231884 | BX15: =SUM(BX16:BX17) -> 0 | BY15: =IF(AND(BX4=0,BX15>=0), "",BX15/BX4) | BZ15: =IF(AND(BX15=0,BU15>0),100%,IF(AND(BX15<0,BU15=0),(BX15-BU15)/BX15,IF(AND(BX15>0,BU15>0),(BU15-BX15)/BX15,IF(AND(BX15=0,BU15=0),"",(BU15-BX15)/BX15)))) -> 1 | CA15: =SUM(CA16:CA17) -> 0 | CB15: =IF(AND(CA4=0,CA15>=0), "",CA15/CA4) | CD15: =IF(AND(BQ15=0,CA15>0),100%,IF(AND(BQ15<0,CA15=0),(BQ15-CA15)/BQ15,IF(AND(BQ15>0,CA15>0),(CA15-BQ15)/BQ15,IF(AND(BQ15=0,CA15=0),"",(CA15-BQ15)/BQ15)))) | CE15: =SUM(CE16:CE17) -> 50 | CF15: =IF(AND(CE4=0,CE15>=0), "",CE15/CE4) -> 0.0036231884 | CH15: =SUM(CH16:CH17) -> 0 | CI15: =IF(AND(CH4=0,CH15>=0), "",CH15/CH4) | CK15: =IF(AND(CA15=0,CH15>0),100%,IF(AND(CA15<0,CH15=0),(CA15-CH15)/CA15,IF(AND(CA15>0,CH15>0),(CH15-CA15)/CA15,IF(AND(CA15=0,CH15=0),"",(CH15-CA15)/CA15)))) | CL15: =SUM(CL16:CL17) -> 50 | CM15: =IF(AND(CL4=0,CL15>=0), "",CL15/CL4) -> 0.0036231884 | CO15: =SUM(CO16:CO17) -> 0 | CP15: =IF(AND(CO4=0,CO15>=0), "",CO15/CO4) | CR15: =IF(AND(CH15=0,CO15>0),100%,IF(AND(CH15<0,CO15=0),(CH15-CO15)/CH15,IF(AND(CH15>0,CO15>0),(CO15-CH15)/CH15,IF(AND(CH15=0,CO15=0),"",(CO15-CH15)/CH15)))) | CS15: =SUM(CS16:CS17) -> 50 | CT15: =IF(AND(CS4=0,CS15>=0), "",CS15/CS4) -> 0.0036231884 | CV15: =SUM(CV16:CV17) -> 0 | CW15: =IF(AND(CV4=0,CV15>=0), "",CV15/CV4) | CX15: =IF(AND(CV15=0,CS15>0),100%,IF(AND(CV15<0,CS15=0),(CV15-CS15)/CV15,IF(AND(CV15>0,CS15>0),(CS15-CV15)/CV15,IF(AND(CV15=0,CS15=0),"",(CS15-CV15)/CV15)))) -> 1
A16: Ingresos por eventos | B16: =+'N EERR'!B14 -> 0 | C16: =IF(AND(B4=0,B16>=0), "",B16/B4) | E16: =+'N EERR'!C14 -> 50 | F16: =IF(AND(E4=0,E16>=0), "",E16/E4) -> 0.0036231884 | H16: =+'N EERR'!D14 -> 0 | I16: =IF(AND(H4=0,H16>=0), "",H16/H4) | K16: =IF(AND(E16=0,H16>0),100%,IF(AND(E16<0,H16=0),(E16-H16)/E16,IF(AND(E16>0,H16>0),(H16-E16)/E16,IF(AND(E16=0,H16=0),"",(H16-E16)/E16)))) -> -1 | L16: =+E16+H16 -> 50 | M16: =IF(AND(L4=0,L16>=0), "",L16/L4) -> 0.0036231884 | O16: =+'N EERR'!E14 -> 0 | P16: =IF(AND(O4=0,O16>=0), "",O16/O4) | R16: =IF(AND(H16=0,O16>0),100%,IF(AND(H16<0,O16=0),(H16-O16)/H16,IF(AND(H16>0,O16>0),(O16-H16)/H16,IF(AND(H16=0,O16=0),"",(O16-H16)/H16)))) | S16: =+L16+O16 -> 50 | T16: =IF(AND(S4=0,S16>=0), "",S16/S4) -> 0.0036231884 | W16: =IF(AND(V4=0,V16>=0), "",V16/V4) | X16: =IF(AND(V16=0,S16>0),100%,IF(AND(V16<0,S16=0),(V16-S16)/V16,IF(AND(V16>0,S16>0),(S16-V16)/V16,IF(AND(V16=0,S16=0),"",(S16-V16)/V16)))) -> 1 | Y16: =+'N EERR'!F14 -> 0 | Z16: =IF(AND(Y4=0,Y16>=0), "",Y16/Y4) | AB16: =IF(AND(O16=0,Y16>0),100%,IF(AND(O16<0,Y16=0),(O16-Y16)/O16,IF(AND(O16>0,Y16>0),(Y16-O16)/O16,IF(AND(O16=0,Y16=0),"",(Y16-O16)/O16)))) | AC16: =+S16+Y16 -> 50 | AD16: =IF(AND(AC4=0,AC16>=0), "",AC16/AC4) -> 0.0036231884 | AF16: =+'N EERR'!G14 -> 0 | AG16: =IF(AND(AF4=0,AF16>=0), "",AF16/AF4) | AI16: =IF(AND(Y16=0,AF16>0),100%,IF(AND(Y16<0,AF16=0),(Y16-AF16)/Y16,IF(AND(Y16>0,AF16>0),(AF16-Y16)/Y16,IF(AND(Y16=0,AF16=0),"",(AF16-Y16)/Y16)))) | AJ16: =+AC16+AF16 -> 50 | AK16: =IF(AND(AJ4=0,AJ16>=0), "",AJ16/AJ4) -> 0.0036231884 | AM16: =+'N EERR'!H14 -> 0 | AN16: =IF(AND(AM4=0,AM16>=0), "",AM16/AM4) | AP16: =IF(AND(AF16=0,AM16>0),100%,IF(AND(AF16<0,AM16=0),(AF16-AM16)/AF16,IF(AND(AF16>0,AM16>0),(AM16-AF16)/AF16,IF(AND(AF16=0,AM16=0),"",(AM16-AF16)/AF16)))) | AQ16: =+AJ16+AM16 -> 50 | AR16: =IF(AND(AQ4=0,AQ16>=0), "",AQ16/AQ4) -> 0.0036231884 | AT16: =+V16*2 -> 0 | AU16: =IF(AND(AT4=0,AT16>=0), "",AT16/AT4) | AV16: =IF(AND(AT16=0,AQ16>0),100%,IF(AND(AT16<0,AQ16=0),(AT16-AQ16)/AT16,IF(AND(AT16>0,AQ16>0),(AQ16-AT16)/AT16,IF(AND(AT16=0,AQ16=0),"",(AQ16-AT16)/AT16)))) -> 1 | AW16: =+AQ16/6 -> 8.3333333 | AX16: =IF(AND(AW4=0,AW16>=0), "",AW16/AW4) -> 0.0036231884 | AZ16: =+AT16/6 -> 0 | BA16: =IF(AND(AZ4=0,AZ16>=0), "",AZ16/AZ4) | BB16: =IF(AND(AZ16=0,AW16>0),100%,IF(AND(AZ16<0,AW16=0),(AZ16-AW16)/AZ16,IF(AND(AZ16>0,AW16>0),(AW16-AZ16)/AZ16,IF(AND(AZ16=0,AW16=0),"",(AW16-AZ16)/AZ16)))) -> 1 | BC16: =+'N EERR'!I14 -> 0 | BD16: =IF(AND(BC4=0,BC16>=0), "",BC16/BC4) | BF16: =IF(AND(AM16=0,BC16>0),100%,IF(AND(AM16<0,BC16=0),(AM16-BC16)/AM16,IF(AND(AM16>0,BC16>0),(BC16-AM16)/AM16,IF(AND(AM16=0,BC16=0),"",(BC16-AM16)/AM16)))) | BG16: =+AQ16+BC16 -> 50 | BH16: =IF(AND(BG4=0,BG16>=0), "",BG16/BG4) -> 0.0036231884 | BJ16: =+'N EERR'!J14 -> 0 | BK16: =IF(AND(BJ4=0,BJ16>=0), "",BJ16/BJ4) | BM16: =IF(AND(BC16=0,BJ16>0),100%,IF(AND(BC16<0,BJ16=0),(BC16-BJ16)/BC16,IF(AND(BC16>0,BJ16>0),(BJ16-BC16)/BC16,IF(AND(BC16=0,BJ16=0),"",(BJ16-BC16)/BC16)))) | BN16: =+BG16+BJ16 -> 50 | BO16: =IF(AND(BN4=0,BN16>=0), "",BN16/BN4) -> 0.0036231884 | BQ16: =+'N EERR'!K14 -> 0 | BR16: =IF(AND(BQ4=0,BQ16>=0), "",BQ16/BQ4) | BT16: =IF(AND(BJ16=0,BQ16>0),100%,IF(AND(BJ16<0,BQ16=0),(BJ16-BQ16)/BJ16,IF(AND(BJ16>0,BQ16>0),(BQ16-BJ16)/BJ16,IF(AND(BJ16=0,BQ16=0),"",(BQ16-BJ16)/BJ16)))) | BU16: =+BN16+BQ16 -> 50 | BV16: =IF(AND(BU4=0,BU16>=0), "",BU16/BU4) -> 0.0036231884 | BX16: =+AZ16*9 -> 0 | BY16: =IF(AND(BX4=0,BX16>=0), "",BX16/BX4) | BZ16: =IF(AND(BX16=0,BU16>0),100%,IF(AND(BX16<0,BU16=0),(BX16-BU16)/BX16,IF(AND(BX16>0,BU16>0),(BU16-BX16)/BX16,IF(AND(BX16=0,BU16=0),"",(BU16-BX16)/BX16)))) -> 1 | CA16: =+'N EERR'!L14 -> 0 | CB16: =IF(AND(CA4=0,CA16>=0), "",CA16/CA4) | CD16: =IF(AND(BQ16=0,CA16>0),100%,IF(AND(BQ16<0,CA16=0),(BQ16-CA16)/BQ16,IF(AND(BQ16>0,CA16>0),(CA16-BQ16)/BQ16,IF(AND(BQ16=0,CA16=0),"",(CA16-BQ16)/BQ16)))) | CE16: =+BU16+CA16 -> 50 | CF16: =IF(AND(CE4=0,CE16>=0), "",CE16/CE4) -> 0.0036231884 | CH16: =+'N EERR'!M14 -> 0 | CI16: =IF(AND(CH4=0,CH16>=0), "",CH16/CH4) | CK16: =IF(AND(CA16=0,CH16>0),100%,IF(AND(CA16<0,CH16=0),(CA16-CH16)/CA16,IF(AND(CA16>0,CH16>0),(CH16-CA16)/CA16,IF(AND(CA16=0,CH16=0),"",(CH16-CA16)/CA16)))) | CL16: =+CE16+CH16 -> 50 | CM16: =IF(AND(CL4=0,CL16>=0), "",CL16/CL4) -> 0.0036231884 | CO16: =+'N EERR'!N14 -> 0 | CP16: =IF(AND(CO4=0,CO16>=0), "",CO16/CO4) | CR16: =IF(AND(CH16=0,CO16>0),100%,IF(AND(CH16<0,CO16=0),(CH16-CO16)/CH16,IF(AND(CH16>0,CO16>0),(CO16-CH16)/CH16,IF(AND(CH16=0,CO16=0),"",(CO16-CH16)/CH16)))) | CS16: =+CL16+CO16 -> 50 | CT16: =IF(AND(CS4=0,CS16>=0), "",CS16/CS4) -> 0.0036231884 | CV16: =+AZ16*12 -> 0 | CW16: =IF(AND(CV4=0,CV16>=0), "",CV16/CV4) | CX16: =IF(AND(CV16=0,CS16>0),100%,IF(AND(CV16<0,CS16=0),(CV16-CS16)/CV16,IF(AND(CV16>0,CS16>0),(CS16-CV16)/CV16,IF(AND(CV16=0,CS16=0),"",(CS16-CV16)/CV16)))) -> 1
K17: =IF(AND(E17=0,H17>0),100%,IF(AND(E17<0,H17=0),(E17-H17)/E17,IF(AND(E17>0,H17>0),(H17-E17)/E17,IF(AND(E17=0,H17=0),"",(H17-E17)/E17)))) | R17: =IF(AND(H17=0,O17>0),100%,IF(AND(H17<0,O17=0),(H17-O17)/H17,IF(AND(H17>0,O17>0),(O17-H17)/H17,IF(AND(H17=0,O17=0),"",(O17-H17)/H17)))) | X17: =IF(AND(V17=0,S17>0),100%,IF(AND(V17<0,S17=0),(V17-S17)/V17,IF(AND(V17>0,S17>0),(S17-V17)/V17,IF(AND(V17=0,S17=0),"",(S17-V17)/V17)))) | AB17: =IF(AND(O17=0,Y17>0),100%,IF(AND(O17<0,Y17=0),(O17-Y17)/O17,IF(AND(O17>0,Y17>0),(Y17-O17)/O17,IF(AND(O17=0,Y17=0),"",(Y17-O17)/O17)))) | AI17: =IF(AND(Y17=0,AF17>0),100%,IF(AND(Y17<0,AF17=0),(Y17-AF17)/Y17,IF(AND(Y17>0,AF17>0),(AF17-Y17)/Y17,IF(AND(Y17=0,AF17=0),"",(AF17-Y17)/Y17)))) | AJ17: =+AC17+AF17 -> 0 | AP17: =IF(AND(AF17=0,AM17>0),100%,IF(AND(AF17<0,AM17=0),(AF17-AM17)/AF17,IF(AND(AF17>0,AM17>0),(AM17-AF17)/AF17,IF(AND(AF17=0,AM17=0),"",(AM17-AF17)/AF17)))) | AQ17: =+AJ17+AM17 -> 0 | AT17: =+V17*2 -> 0 | AV17: =IF(AND(AT17=0,AQ17>0),100%,IF(AND(AT17<0,AQ17=0),(AT17-AQ17)/AT17,IF(AND(AT17>0,AQ17>0),(AQ17-AT17)/AT17,IF(AND(AT17=0,AQ17=0),"",(AQ17-AT17)/AT17)))) | AW17: =+AQ17/6 -> 0 | AZ17: =+AT17/6 -> 0 | BB17: =IF(AND(AZ17=0,AW17>0),100%,IF(AND(AZ17<0,AW17=0),(AZ17-AW17)/AZ17,IF(AND(AZ17>0,AW17>0),(AW17-AZ17)/AZ17,IF(AND(AZ17=0,AW17=0),"",(AW17-AZ17)/AZ17)))) | BF17: =IF(AND(AM17=0,BC17>0),100%,IF(AND(AM17<0,BC17=0),(AM17-BC17)/AM17,IF(AND(AM17>0,BC17>0),(BC17-AM17)/AM17,IF(AND(AM17=0,BC17=0),"",(BC17-AM17)/AM17)))) | BG17: =+AQ17+BC17 -> 0 | BM17: =IF(AND(BC17=0,BJ17>0),100%,IF(AND(BC17<0,BJ17=0),(BC17-BJ17)/BC17,IF(AND(BC17>0,BJ17>0),(BJ17-BC17)/BC17,IF(AND(BC17=0,BJ17=0),"",(BJ17-BC17)/BC17)))) | BN17: =+BG17+BJ17 -> 0 | BT17: =IF(AND(BJ17=0,BQ17>0),100%,IF(AND(BJ17<0,BQ17=0),(BJ17-BQ17)/BJ17,IF(AND(BJ17>0,BQ17>0),(BQ17-BJ17)/BJ17,IF(AND(BJ17=0,BQ17=0),"",(BQ17-BJ17)/BJ17)))) | BU17: =+BN17+BQ17 -> 0 | BX17: =+AZ17*9 -> 0 | BZ17: =IF(AND(BX17=0,BU17>0),100%,IF(AND(BX17<0,BU17=0),(BX17-BU17)/BX17,IF(AND(BX17>0,BU17>0),(BU17-BX17)/BX17,IF(AND(BX17=0,BU17=0),"",(BU17-BX17)/BX17)))) | CD17: =IF(AND(BQ17=0,CA17>0),100%,IF(AND(BQ17<0,CA17=0),(BQ17-CA17)/BQ17,IF(AND(BQ17>0,CA17>0),(CA17-BQ17)/BQ17,IF(AND(BQ17=0,CA17=0),"",(CA17-BQ17)/BQ17)))) | CK17: =IF(AND(CA17=0,CH17>0),100%,IF(AND(CA17<0,CH17=0),(CA17-CH17)/CA17,IF(AND(CA17>0,CH17>0),(CH17-CA17)/CA17,IF(AND(CA17=0,CH17=0),"",(CH17-CA17)/CA17)))) | CL17: =+CE17+CH17 -> 0 | CR17: =IF(AND(CH17=0,CO17>0),100%,IF(AND(CH17<0,CO17=0),(CH17-CO17)/CH17,IF(AND(CH17>0,CO17>0),(CO17-CH17)/CH17,IF(AND(CH17=0,CO17=0),"",(CO17-CH17)/CH17)))) | CS17: =+CL17+CO17 -> 0 | CV17: =+AZ17*12 -> 0 | CX17: =IF(AND(CV17=0,CS17>0),100%,IF(AND(CV17<0,CS17=0),(CV17-CS17)/CV17,IF(AND(CV17>0,CS17>0),(CS17-CV17)/CV17,IF(AND(CV17=0,CS17=0),"",(CS17-CV17)/CV17))))
A18: Subtotal Ingresos por Taller | B18: =SUM(B19:B20) -> 0 | C18: =IF(AND(B4=0,B18>=0), "",B18/B4) | E18: =SUM(E19:E20) -> 50 | F18: =IF(AND(E4=0,E18>=0), "",E18/E4) -> 0.0036231884 | H18: =SUM(H19:H20) -> 0 | I18: =IF(AND(H4=0,H18>=0), "",H18/H4) | K18: =IF(AND(E18=0,H18>0),100%,IF(AND(E18<0,H18=0),(E18-H18)/E18,IF(AND(E18>0,H18>0),(H18-E18)/E18,IF(AND(E18=0,H18=0),"",(H18-E18)/E18)))) -> -1 | L18: =SUM(L19:L20) -> 50 | M18: =IF(AND(L4=0,L18>=0), "",L18/L4) -> 0.0036231884 | O18: =SUM(O19:O20) -> 0 | P18: =IF(AND(O4=0,O18>=0), "",O18/O4) | R18: =IF(AND(H18=0,O18>0),100%,IF(AND(H18<0,O18=0),(H18-O18)/H18,IF(AND(H18>0,O18>0),(O18-H18)/H18,IF(AND(H18=0,O18=0),"",(O18-H18)/H18)))) | S18: =SUM(S19:S20) -> 50 | T18: =IF(AND(S4=0,S18>=0), "",S18/S4) -> 0.0036231884 | V18: =SUM(V19:V20) -> 0 | W18: =IF(AND(V4=0,V18>=0), "",V18/V4) | X18: =IF(AND(V18=0,S18>0),100%,IF(AND(V18<0,S18=0),(V18-S18)/V18,IF(AND(V18>0,S18>0),(S18-V18)/V18,IF(AND(V18=0,S18=0),"",(S18-V18)/V18)))) -> 1 | Y18: =SUM(Y19:Y20) -> 0 | Z18: =IF(AND(Y4=0,Y18>=0), "",Y18/Y4) | AB18: =IF(AND(O18=0,Y18>0),100%,IF(AND(O18<0,Y18=0),(O18-Y18)/O18,IF(AND(O18>0,Y18>0),(Y18-O18)/O18,IF(AND(O18=0,Y18=0),"",(Y18-O18)/O18)))) | AC18: =SUM(AC19:AC20) -> 50 | AD18: =IF(AND(AC4=0,AC18>=0), "",AC18/AC4) -> 0.0036231884 | AF18: =SUM(AF19:AF20) -> 0 | AG18: =IF(AND(AF4=0,AF18>=0), "",AF18/AF4) | AI18: =IF(AND(Y18=0,AF18>0),100%,IF(AND(Y18<0,AF18=0),(Y18-AF18)/Y18,IF(AND(Y18>0,AF18>0),(AF18-Y18)/Y18,IF(AND(Y18=0,AF18=0),"",(AF18-Y18)/Y18)))) | AJ18: =SUM(AJ19:AJ20) -> 50 | AK18: =IF(AND(AJ4=0,AJ18>=0), "",AJ18/AJ4) -> 0.0036231884 | AM18: =SUM(AM19:AM20) -> 0 | AN18: =IF(AND(AM4=0,AM18>=0), "",AM18/AM4) | AP18: =IF(AND(AF18=0,AM18>0),100%,IF(AND(AF18<0,AM18=0),(AF18-AM18)/AF18,IF(AND(AF18>0,AM18>0),(AM18-AF18)/AF18,IF(AND(AF18=0,AM18=0),"",(AM18-AF18)/AF18)))) | AQ18: =SUM(AQ19:AQ20) -> 50 | AR18: =IF(AND(AQ4=0,AQ18>=0), "",AQ18/AQ4) -> 0.0036231884 | AT18: =SUM(AT19:AT20) -> 0 | AU18: =IF(AND(AT4=0,AT18>=0), "",AT18/AT4) | AV18: =IF(AND(AT18=0,AQ18>0),100%,IF(AND(AT18<0,AQ18=0),(AT18-AQ18)/AT18,IF(AND(AT18>0,AQ18>0),(AQ18-AT18)/AT18,IF(AND(AT18=0,AQ18=0),"",(AQ18-AT18)/AT18)))) -> 1 | AW18: =SUM(AW19:AW20) -> 8.3333333 | AX18: =IF(AND(AW4=0,AW18>=0), "",AW18/AW4) -> 0.0036231884 | AZ18: =SUM(AZ19:AZ20) -> 0 | BA18: =IF(AND(AZ4=0,AZ18>=0), "",AZ18/AZ4) | BB18: =IF(AND(AZ18=0,AW18>0),100%,IF(AND(AZ18<0,AW18=0),(AZ18-AW18)/AZ18,IF(AND(AZ18>0,AW18>0),(AW18-AZ18)/AZ18,IF(AND(AZ18=0,AW18=0),"",(AW18-AZ18)/AZ18)))) -> 1 | BC18: =SUM(BC19:BC20) -> 0 | BD18: =IF(AND(BC4=0,BC18>=0), "",BC18/BC4) | BF18: =IF(AND(AM18=0,BC18>0),100%,IF(AND(AM18<0,BC18=0),(AM18-BC18)/AM18,IF(AND(AM18>0,BC18>0),(BC18-AM18)/AM18,IF(AND(AM18=0,BC18=0),"",(BC18-AM18)/AM18)))) | BG18: =SUM(BG19:BG20) -> 50 | BH18: =IF(AND(BG4=0,BG18>=0), "",BG18/BG4) -> 0.0036231884 | BJ18: =SUM(BJ19:BJ20) -> 0 | BK18: =IF(AND(BJ4=0,BJ18>=0), "",BJ18/BJ4) | BM18: =IF(AND(BC18=0,BJ18>0),100%,IF(AND(BC18<0,BJ18=0),(BC18-BJ18)/BC18,IF(AND(BC18>0,BJ18>0),(BJ18-BC18)/BC18,IF(AND(BC18=0,BJ18=0),"",(BJ18-BC18)/BC18)))) | BN18: =SUM(BN19:BN20) -> 50 | BO18: =IF(AND(BN4=0,BN18>=0), "",BN18/BN4) -> 0.0036231884 | BQ18: =SUM(BQ19:BQ20) -> 0 | BR18: =IF(AND(BQ4=0,BQ18>=0), "",BQ18/BQ4) | BT18: =IF(AND(BJ18=0,BQ18>0),100%,IF(AND(BJ18<0,BQ18=0),(BJ18-BQ18)/BJ18,IF(AND(BJ18>0,BQ18>0),(BQ18-BJ18)/BJ18,IF(AND(BJ18=0,BQ18=0),"",(BQ18-BJ18)/BJ18)))) | BU18: =SUM(BU19:BU20) -> 50 | BV18: =IF(AND(BU4=0,BU18>=0), "",BU18/BU4) -> 0.0036231884 | BX18: =SUM(BX19:BX20) -> 0 | BY18: =IF(AND(BX4=0,BX18>=0), "",BX18/BX4) | BZ18: =IF(AND(BX18=0,BU18>0),100%,IF(AND(BX18<0,BU18=0),(BX18-BU18)/BX18,IF(AND(BX18>0,BU18>0),(BU18-BX18)/BX18,IF(AND(BX18=0,BU18=0),"",(BU18-BX18)/BX18)))) -> 1 | CA18: =SUM(CA19:CA20) -> 0 | CB18: =IF(AND(CA4=0,CA18>=0), "",CA18/CA4) | CD18: =IF(AND(BQ18=0,CA18>0),100%,IF(AND(BQ18<0,CA18=0),(BQ18-CA18)/BQ18,IF(AND(BQ18>0,CA18>0),(CA18-BQ18)/BQ18,IF(AND(BQ18=0,CA18=0),"",(CA18-BQ18)/BQ18)))) | CE18: =SUM(CE19:CE20) -> 50 | CF18: =IF(AND(CE4=0,CE18>=0), "",CE18/CE4) -> 0.0036231884 | CH18: =SUM(CH19:CH20) -> 0 | CI18: =IF(AND(CH4=0,CH18>=0), "",CH18/CH4) | CK18: =IF(AND(CA18=0,CH18>0),100%,IF(AND(CA18<0,CH18=0),(CA18-CH18)/CA18,IF(AND(CA18>0,CH18>0),(CH18-CA18)/CA18,IF(AND(CA18=0,CH18=0),"",(CH18-CA18)/CA18)))) | CL18: =SUM(CL19:CL20) -> 50 | CM18: =IF(AND(CL4=0,CL18>=0), "",CL18/CL4) -> 0.0036231884 | CO18: =SUM(CO19:CO20) -> 0 | CP18: =IF(AND(CO4=0,CO18>=0), "",CO18/CO4) | CR18: =IF(AND(CH18=0,CO18>0),100%,IF(AND(CH18<0,CO18=0),(CH18-CO18)/CH18,IF(AND(CH18>0,CO18>0),(CO18-CH18)/CH18,IF(AND(CH18=0,CO18=0),"",(CO18-CH18)/CH18)))) | CS18: =SUM(CS19:CS20) -> 50 | CT18: =IF(AND(CS4=0,CS18>=0), "",CS18/CS4) -> 0.0036231884 | CV18: =SUM(CV19:CV20) -> 0 | CW18: =IF(AND(CV4=0,CV18>=0), "",CV18/CV4) | CX18: =IF(AND(CV18=0,CS18>0),100%,IF(AND(CV18<0,CS18=0),(CV18-CS18)/CV18,IF(AND(CV18>0,CS18>0),(CS18-CV18)/CV18,IF(AND(CV18=0,CS18=0),"",(CS18-CV18)/CV18)))) -> 1
A19: Ingresos por taller | B19: =+'N EERR'!B15 -> 0 | C19: =IF(AND(B4=0,B19>=0), "",B19/B4) | E19: =+'N EERR'!C15 -> 50 | F19: =IF(AND(E4=0,E19>=0), "",E19/E4) -> 0.0036231884 | H19: =+'N EERR'!D15 -> 0 | I19: =IF(AND(H4=0,H19>=0), "",H19/H4) | K19: =IF(AND(E19=0,H19>0),100%,IF(AND(E19<0,H19=0),(E19-H19)/E19,IF(AND(E19>0,H19>0),(H19-E19)/E19,IF(AND(E19=0,H19=0),"",(H19-E19)/E19)))) -> -1 | L19: =+E19+H19 -> 50 | M19: =IF(AND(L4=0,L19>=0), "",L19/L4) -> 0.0036231884 | O19: =+'N EERR'!E15 -> 0 | P19: =IF(AND(O4=0,O19>=0), "",O19/O4) | R19: =IF(AND(H19=0,O19>0),100%,IF(AND(H19<0,O19=0),(H19-O19)/H19,IF(AND(H19>0,O19>0),(O19-H19)/H19,IF(AND(H19=0,O19=0),"",(O19-H19)/H19)))) | S19: =+L19+O19 -> 50 | T19: =IF(AND(S4=0,S19>=0), "",S19/S4) -> 0.0036231884 | W19: =IF(AND(V4=0,V19>=0), "",V19/V4) | X19: =IF(AND(V19=0,S19>0),100%,IF(AND(V19<0,S19=0),(V19-S19)/V19,IF(AND(V19>0,S19>0),(S19-V19)/V19,IF(AND(V19=0,S19=0),"",(S19-V19)/V19)))) -> 1 | Y19: =+'N EERR'!F15 -> 0 | Z19: =IF(AND(Y4=0,Y19>=0), "",Y19/Y4) | AB19: =IF(AND(O19=0,Y19>0),100%,IF(AND(O19<0,Y19=0),(O19-Y19)/O19,IF(AND(O19>0,Y19>0),(Y19-O19)/O19,IF(AND(O19=0,Y19=0),"",(Y19-O19)/O19)))) | AC19: =+S19+Y19 -> 50 | AD19: =IF(AND(AC4=0,AC19>=0), "",AC19/AC4) -> 0.0036231884 | AF19: =+'N EERR'!G15 -> 0 | AG19: =IF(AND(AF4=0,AF19>=0), "",AF19/AF4) | AI19: =IF(AND(Y19=0,AF19>0),100%,IF(AND(Y19<0,AF19=0),(Y19-AF19)/Y19,IF(AND(Y19>0,AF19>0),(AF19-Y19)/Y19,IF(AND(Y19=0,AF19=0),"",(AF19-Y19)/Y19)))) | AJ19: =+AC19+AF19 -> 50 | AK19: =IF(AND(AJ4=0,AJ19>=0), "",AJ19/AJ4) -> 0.0036231884 | AM19: =+'N EERR'!H15 -> 0 | AN19: =IF(AND(AM4=0,AM19>=0), "",AM19/AM4) | AP19: =IF(AND(AF19=0,AM19>0),100%,IF(AND(AF19<0,AM19=0),(AF19-AM19)/AF19,IF(AND(AF19>0,AM19>0),(AM19-AF19)/AF19,IF(AND(AF19=0,AM19=0),"",(AM19-AF19)/AF19)))) | AQ19: =+AJ19+AM19 -> 50 | AR19: =IF(AND(AQ4=0,AQ19>=0), "",AQ19/AQ4) -> 0.0036231884 | AT19: =+V19*2 -> 0 | AU19: =IF(AND(AT4=0,AT19>=0), "",AT19/AT4) | AV19: =IF(AND(AT19=0,AQ19>0),100%,IF(AND(AT19<0,AQ19=0),(AT19-AQ19)/AT19,IF(AND(AT19>0,AQ19>0),(AQ19-AT19)/AT19,IF(AND(AT19=0,AQ19=0),"",(AQ19-AT19)/AT19)))) -> 1 | AW19: =+AQ19/6 -> 8.3333333 | AX19: =IF(AND(AW4=0,AW19>=0), "",AW19/AW4) -> 0.0036231884 | AZ19: =+AT19/6 -> 0 | BA19: =IF(AND(AZ4=0,AZ19>=0), "",AZ19/AZ4) | BB19: =IF(AND(AZ19=0,AW19>0),100%,IF(AND(AZ19<0,AW19=0),(AZ19-AW19)/AZ19,IF(AND(AZ19>0,AW19>0),(AW19-AZ19)/AZ19,IF(AND(AZ19=0,AW19=0),"",(AW19-AZ19)/AZ19)))) -> 1 | BC19: =+'N EERR'!I15 -> 0 | BD19: =IF(AND(BC4=0,BC19>=0), "",BC19/BC4) | BF19: =IF(AND(AM19=0,BC19>0),100%,IF(AND(AM19<0,BC19=0),(AM19-BC19)/AM19,IF(AND(AM19>0,BC19>0),(BC19-AM19)/AM19,IF(AND(AM19=0,BC19=0),"",(BC19-AM19)/AM19)))) | BG19: =+AQ19+BC19 -> 50 | BH19: =IF(AND(BG4=0,BG19>=0), "",BG19/BG4) -> 0.0036231884 | BJ19: =+'N EERR'!J15 -> 0 | BK19: =IF(AND(BJ4=0,BJ19>=0), "",BJ19/BJ4) | BM19: =IF(AND(BC19=0,BJ19>0),100%,IF(AND(BC19<0,BJ19=0),(BC19-BJ19)/BC19,IF(AND(BC19>0,BJ19>0),(BJ19-BC19)/BC19,IF(AND(BC19=0,BJ19=0),"",(BJ19-BC19)/BC19)))) | BN19: =+BG19+BJ19 -> 50 | BO19: =IF(AND(BN4=0,BN19>=0), "",BN19/BN4) -> 0.0036231884 | BQ19: =+'N EERR'!K15 -> 0 | BR19: =IF(AND(BQ4=0,BQ19>=0), "",BQ19/BQ4) | BT19: =IF(AND(BJ19=0,BQ19>0),100%,IF(AND(BJ19<0,BQ19=0),(BJ19-BQ19)/BJ19,IF(AND(BJ19>0,BQ19>0),(BQ19-BJ19)/BJ19,IF(AND(BJ19=0,BQ19=0),"",(BQ19-BJ19)/BJ19)))) | BU19: =+BN19+BQ19 -> 50 | BV19: =IF(AND(BU4=0,BU19>=0), "",BU19/BU4) -> 0.0036231884 | BX19: =+AZ19*9 -> 0 | BY19: =IF(AND(BX4=0,BX19>=0), "",BX19/BX4) | BZ19: =IF(AND(BX19=0,BU19>0),100%,IF(AND(BX19<0,BU19=0),(BX19-BU19)/BX19,IF(AND(BX19>0,BU19>0),(BU19-BX19)/BX19,IF(AND(BX19=0,BU19=0),"",(BU19-BX19)/BX19)))) -> 1 | CA19: =+'N EERR'!L15 -> 0 | CB19: =IF(AND(CA4=0,CA19>=0), "",CA19/CA4) | CD19: =IF(AND(BQ19=0,CA19>0),100%,IF(AND(BQ19<0,CA19=0),(BQ19-CA19)/BQ19,IF(AND(BQ19>0,CA19>0),(CA19-BQ19)/BQ19,IF(AND(BQ19=0,CA19=0),"",(CA19-BQ19)/BQ19)))) | CE19: =+BU19+CA19 -> 50 | CF19: =IF(AND(CE4=0,CE19>=0), "",CE19/CE4) -> 0.0036231884 | CH19: =+'N EERR'!M15 -> 0 | CI19: =IF(AND(CH4=0,CH19>=0), "",CH19/CH4) | CK19: =IF(AND(CA19=0,CH19>0),100%,IF(AND(CA19<0,CH19=0),(CA19-CH19)/CA19,IF(AND(CA19>0,CH19>0),(CH19-CA19)/CA19,IF(AND(CA19=0,CH19=0),"",(CH19-CA19)/CA19)))) | CL19: =+CE19+CH19 -> 50 | CM19: =IF(AND(CL4=0,CL19>=0), "",CL19/CL4) -> 0.0036231884 | CO19: =+'N EERR'!N15 -> 0 | CP19: =IF(AND(CO4=0,CO19>=0), "",CO19/CO4) | CR19: =IF(AND(CH19=0,CO19>0),100%,IF(AND(CH19<0,CO19=0),(CH19-CO19)/CH19,IF(AND(CH19>0,CO19>0),(CO19-CH19)/CH19,IF(AND(CH19=0,CO19=0),"",(CO19-CH19)/CH19)))) | CS19: =+CL19+CO19 -> 50 | CT19: =IF(AND(CS4=0,CS19>=0), "",CS19/CS4) -> 0.0036231884 | CV19: =+AZ19*12 -> 0 | CW19: =IF(AND(CV4=0,CV19>=0), "",CV19/CV4) | CX19: =IF(AND(CV19=0,CS19>0),100%,IF(AND(CV19<0,CS19=0),(CV19-CS19)/CV19,IF(AND(CV19>0,CS19>0),(CS19-CV19)/CV19,IF(AND(CV19=0,CS19=0),"",(CS19-CV19)/CV19)))) -> 1
K20: =IF(AND(E20=0,H20>0),100%,IF(AND(E20<0,H20=0),(E20-H20)/E20,IF(AND(E20>0,H20>0),(H20-E20)/E20,IF(AND(E20=0,H20=0),"",(H20-E20)/E20)))) | R20: =IF(AND(H20=0,O20>0),100%,IF(AND(H20<0,O20=0),(H20-O20)/H20,IF(AND(H20>0,O20>0),(O20-H20)/H20,IF(AND(H20=0,O20=0),"",(O20-H20)/H20)))) | X20: =IF(AND(V20=0,S20>0),100%,IF(AND(V20<0,S20=0),(V20-S20)/V20,IF(AND(V20>0,S20>0),(S20-V20)/V20,IF(AND(V20=0,S20=0),"",(S20-V20)/V20)))) | AB20: =IF(AND(O20=0,Y20>0),100%,IF(AND(O20<0,Y20=0),(O20-Y20)/O20,IF(AND(O20>0,Y20>0),(Y20-O20)/O20,IF(AND(O20=0,Y20=0),"",(Y20-O20)/O20)))) | AI20: =IF(AND(Y20=0,AF20>0),100%,IF(AND(Y20<0,AF20=0),(Y20-AF20)/Y20,IF(AND(Y20>0,AF20>0),(AF20-Y20)/Y20,IF(AND(Y20=0,AF20=0),"",(AF20-Y20)/Y20)))) | AJ20: =+AC20+AF20 -> 0 | AP20: =IF(AND(AF20=0,AM20>0),100%,IF(AND(AF20<0,AM20=0),(AF20-AM20)/AF20,IF(AND(AF20>0,AM20>0),(AM20-AF20)/AF20,IF(AND(AF20=0,AM20=0),"",(AM20-AF20)/AF20)))) | AQ20: =+AJ20+AM20 -> 0 | AT20: =+V20*2 -> 0 | AV20: =IF(AND(AT20=0,AQ20>0),100%,IF(AND(AT20<0,AQ20=0),(AT20-AQ20)/AT20,IF(AND(AT20>0,AQ20>0),(AQ20-AT20)/AT20,IF(AND(AT20=0,AQ20=0),"",(AQ20-AT20)/AT20)))) | AW20: =+AQ20/6 -> 0 | AZ20: =+AT20/6 -> 0 | BB20: =IF(AND(AZ20=0,AW20>0),100%,IF(AND(AZ20<0,AW20=0),(AZ20-AW20)/AZ20,IF(AND(AZ20>0,AW20>0),(AW20-AZ20)/AZ20,IF(AND(AZ20=0,AW20=0),"",(AW20-AZ20)/AZ20)))) | BF20: =IF(AND(AM20=0,BC20>0),100%,IF(AND(AM20<0,BC20=0),(AM20-BC20)/AM20,IF(AND(AM20>0,BC20>0),(BC20-AM20)/AM20,IF(AND(AM20=0,BC20=0),"",(BC20-AM20)/AM20)))) | BG20: =+AQ20+BC20 -> 0 | BM20: =IF(AND(BC20=0,BJ20>0),100%,IF(AND(BC20<0,BJ20=0),(BC20-BJ20)/BC20,IF(AND(BC20>0,BJ20>0),(BJ20-BC20)/BC20,IF(AND(BC20=0,BJ20=0),"",(BJ20-BC20)/BC20)))) | BN20: =+BG20+BJ20 -> 0 | BT20: =IF(AND(BJ20=0,BQ20>0),100%,IF(AND(BJ20<0,BQ20=0),(BJ20-BQ20)/BJ20,IF(AND(BJ20>0,BQ20>0),(BQ20-BJ20)/BJ20,IF(AND(BJ20=0,BQ20=0),"",(BQ20-BJ20)/BJ20)))) | BU20: =+BN20+BQ20 -> 0 | BX20: =+AZ20*9 -> 0 | BZ20: =IF(AND(BX20=0,BU20>0),100%,IF(AND(BX20<0,BU20=0),(BX20-BU20)/BX20,IF(AND(BX20>0,BU20>0),(BU20-BX20)/BX20,IF(AND(BX20=0,BU20=0),"",(BU20-BX20)/BX20)))) | CD20: =IF(AND(BQ20=0,CA20>0),100%,IF(AND(BQ20<0,CA20=0),(BQ20-CA20)/BQ20,IF(AND(BQ20>0,CA20>0),(CA20-BQ20)/BQ20,IF(AND(BQ20=0,CA20=0),"",(CA20-BQ20)/BQ20)))) | CK20: =IF(AND(CA20=0,CH20>0),100%,IF(AND(CA20<0,CH20=0),(CA20-CH20)/CA20,IF(AND(CA20>0,CH20>0),(CH20-CA20)/CA20,IF(AND(CA20=0,CH20=0),"",(CH20-CA20)/CA20)))) | CL20: =+CE20+CH20 -> 0 | CR20: =IF(AND(CH20=0,CO20>0),100%,IF(AND(CH20<0,CO20=0),(CH20-CO20)/CH20,IF(AND(CH20>0,CO20>0),(CO20-CH20)/CH20,IF(AND(CH20=0,CO20=0),"",(CO20-CH20)/CH20)))) | CS20: =+CL20+CO20 -> 0 | CV20: =+AZ20*12 -> 0 | CX20: =IF(AND(CV20=0,CS20>0),100%,IF(AND(CV20<0,CS20=0),(CV20-CS20)/CV20,IF(AND(CV20>0,CS20>0),(CS20-CV20)/CV20,IF(AND(CV20=0,CS20=0),"",(CS20-CV20)/CV20))))
K21: =IF(AND(E21=0,H21>0),100%,IF(AND(E21<0,H21=0),(E21-H21)/E21,IF(AND(E21>0,H21>0),(H21-E21)/E21,IF(AND(E21=0,H21=0),"",(H21-E21)/E21)))) | R21: =IF(AND(H21=0,O21>0),100%,IF(AND(H21<0,O21=0),(H21-O21)/H21,IF(AND(H21>0,O21>0),(O21-H21)/H21,IF(AND(H21=0,O21=0),"",(O21-H21)/H21)))) | X21: =IF(AND(V21=0,S21>0),100%,IF(AND(V21<0,S21=0),(V21-S21)/V21,IF(AND(V21>0,S21>0),(S21-V21)/V21,IF(AND(V21=0,S21=0),"",(S21-V21)/V21)))) | AB21: =IF(AND(O21=0,Y21>0),100%,IF(AND(O21<0,Y21=0),(O21-Y21)/O21,IF(AND(O21>0,Y21>0),(Y21-O21)/O21,IF(AND(O21=0,Y21=0),"",(Y21-O21)/O21)))) | AI21: =IF(AND(Y21=0,AF21>0),100%,IF(AND(Y21<0,AF21=0),(Y21-AF21)/Y21,IF(AND(Y21>0,AF21>0),(AF21-Y21)/Y21,IF(AND(Y21=0,AF21=0),"",(AF21-Y21)/Y21)))) | AJ21: =+AC21+AF21 -> 0 | AP21: =IF(AND(AF21=0,AM21>0),100%,IF(AND(AF21<0,AM21=0),(AF21-AM21)/AF21,IF(AND(AF21>0,AM21>0),(AM21-AF21)/AF21,IF(AND(AF21=0,AM21=0),"",(AM21-AF21)/AF21)))) | AQ21: =+AJ21+AM21 -> 0 | AT21: =+V21*2 -> 0 | AV21: =IF(AND(AT21=0,AQ21>0),100%,IF(AND(AT21<0,AQ21=0),(AT21-AQ21)/AT21,IF(AND(AT21>0,AQ21>0),(AQ21-AT21)/AT21,IF(AND(AT21=0,AQ21=0),"",(AQ21-AT21)/AT21)))) | AW21: =+AQ21/6 -> 0 | AZ21: =+AT21/6 -> 0 | BB21: =IF(AND(AZ21=0,AW21>0),100%,IF(AND(AZ21<0,AW21=0),(AZ21-AW21)/AZ21,IF(AND(AZ21>0,AW21>0),(AW21-AZ21)/AZ21,IF(AND(AZ21=0,AW21=0),"",(AW21-AZ21)/AZ21)))) | BF21: =IF(AND(AM21=0,BC21>0),100%,IF(AND(AM21<0,BC21=0),(AM21-BC21)/AM21,IF(AND(AM21>0,BC21>0),(BC21-AM21)/AM21,IF(AND(AM21=0,BC21=0),"",(BC21-AM21)/AM21)))) | BG21: =+AQ21+BC21 -> 0 | BM21: =IF(AND(BC21=0,BJ21>0),100%,IF(AND(BC21<0,BJ21=0),(BC21-BJ21)/BC21,IF(AND(BC21>0,BJ21>0),(BJ21-BC21)/BC21,IF(AND(BC21=0,BJ21=0),"",(BJ21-BC21)/BC21)))) | BN21: =+BG21+BJ21 -> 0 | BT21: =IF(AND(BJ21=0,BQ21>0),100%,IF(AND(BJ21<0,BQ21=0),(BJ21-BQ21)/BJ21,IF(AND(BJ21>0,BQ21>0),(BQ21-BJ21)/BJ21,IF(AND(BJ21=0,BQ21=0),"",(BQ21-BJ21)/BJ21)))) | BU21: =+BN21+BQ21 -> 0 | BX21: =+AZ21*9 -> 0 | BZ21: =IF(AND(BX21=0,BU21>0),100%,IF(AND(BX21<0,BU21=0),(BX21-BU21)/BX21,IF(AND(BX21>0,BU21>0),(BU21-BX21)/BX21,IF(AND(BX21=0,BU21=0),"",(BU21-BX21)/BX21)))) | CD21: =IF(AND(BQ21=0,CA21>0),100%,IF(AND(BQ21<0,CA21=0),(BQ21-CA21)/BQ21,IF(AND(BQ21>0,CA21>0),(CA21-BQ21)/BQ21,IF(AND(BQ21=0,CA21=0),"",(CA21-BQ21)/BQ21)))) | CK21: =IF(AND(CA21=0,CH21>0),100%,IF(AND(CA21<0,CH21=0),(CA21-CH21)/CA21,IF(AND(CA21>0,CH21>0),(CH21-CA21)/CA21,IF(AND(CA21=0,CH21=0),"",(CH21-CA21)/CA21)))) | CL21: =+CE21+CH21 -> 0 | CR21: =IF(AND(CH21=0,CO21>0),100%,IF(AND(CH21<0,CO21=0),(CH21-CO21)/CH21,IF(AND(CH21>0,CO21>0),(CO21-CH21)/CH21,IF(AND(CH21=0,CO21=0),"",(CO21-CH21)/CH21)))) | CS21: =+CL21+CO21 -> 0 | CV21: =+AZ21*12 -> 0 | CX21: =IF(AND(CV21=0,CS21>0),100%,IF(AND(CV21<0,CS21=0),(CV21-CS21)/CV21,IF(AND(CV21>0,CS21>0),(CS21-CV21)/CV21,IF(AND(CV21=0,CS21=0),"",(CS21-CV21)/CV21))))
A22: Total Costo de Ventas | B22: =+B23+B26+B29 -> 0 | C22: =IF(AND(B4=0,B22>=0), "",B22/B4) | E22: =+E23+E26+E29 -> 9050 | F22: =IF(AND(E4=0,E22>=0), "",E22/E4) -> 0.6557971 | H22: =+H23+H26+H29 -> 0 | I22: =IF(AND(H4=0,H22>=0), "",H22/H4) | K22: =IF(AND(E22=0,H22>0),100%,IF(AND(E22<0,H22=0),(E22-H22)/E22,IF(AND(E22>0,H22>0),(H22-E22)/E22,IF(AND(E22=0,H22=0),"",(H22-E22)/E22)))) -> -1 | L22: =+L23+L26+L29 -> 9050 | M22: =IF(AND(L4=0,L22>=0), "",L22/L4) -> 0.6557971 | O22: =+O23+O26+O29 -> 0 | P22: =IF(AND(O4=0,O22>=0), "",O22/O4) | R22: =IF(AND(H22=0,O22>0),100%,IF(AND(H22<0,O22=0),(H22-O22)/H22,IF(AND(H22>0,O22>0),(O22-H22)/H22,IF(AND(H22=0,O22=0),"",(O22-H22)/H22)))) | S22: =+S23+S26+S29 -> 9050 | T22: =IF(AND(S4=0,S22>=0), "",S22/S4) -> 0.6557971 | V22: =+V23+V26+V29 -> 0 | W22: =IF(AND(V4=0,V22>=0), "",V22/V4) | X22: =IF(AND(V22=0,S22>0),100%,IF(AND(V22<0,S22=0),(V22-S22)/V22,IF(AND(V22>0,S22>0),(S22-V22)/V22,IF(AND(V22=0,S22=0),"",(S22-V22)/V22)))) -> 1 | Y22: =+Y23+Y26+Y29 -> 0 | Z22: =IF(AND(Y4=0,Y22>=0), "",Y22/Y4) | AB22: =IF(AND(O22=0,Y22>0),100%,IF(AND(O22<0,Y22=0),(O22-Y22)/O22,IF(AND(O22>0,Y22>0),(Y22-O22)/O22,IF(AND(O22=0,Y22=0),"",(Y22-O22)/O22)))) | AC22: =+AC23+AC26+AC29 -> 9050 | AD22: =IF(AND(AC4=0,AC22>=0), "",AC22/AC4) -> 0.6557971 | AF22: =+AF23+AF26+AF29 -> 0 | AG22: =IF(AND(AF4=0,AF22>=0), "",AF22/AF4) | AI22: =IF(AND(Y22=0,AF22>0),100%,IF(AND(Y22<0,AF22=0),(Y22-AF22)/Y22,IF(AND(Y22>0,AF22>0),(AF22-Y22)/Y22,IF(AND(Y22=0,AF22=0),"",(AF22-Y22)/Y22)))) | AJ22: =+AJ23+AJ26+AJ29 -> 9050 | AK22: =IF(AND(AJ4=0,AJ22>=0), "",AJ22/AJ4) -> 0.6557971 | AM22: =+AM23+AM26+AM29 -> 0 | AN22: =IF(AND(AM4=0,AM22>=0), "",AM22/AM4) | AP22: =IF(AND(AF22=0,AM22>0),100%,IF(AND(AF22<0,AM22=0),(AF22-AM22)/AF22,IF(AND(AF22>0,AM22>0),(AM22-AF22)/AF22,IF(AND(AF22=0,AM22=0),"",(AM22-AF22)/AF22)))) | AQ22: =+AQ23+AQ26+AQ29 -> 9050 | AR22: =IF(AND(AQ4=0,AQ22>=0), "",AQ22/AQ4) -> 0.6557971 | AT22: =+AT23+AT26+AT29 -> 0 | AU22: =IF(AND(AT4=0,AT22>=0), "",AT22/AT4) | AV22: =IF(AND(AT22=0,AQ22>0),100%,IF(AND(AT22<0,AQ22=0),(AT22-AQ22)/AT22,IF(AND(AT22>0,AQ22>0),(AQ22-AT22)/AT22,IF(AND(AT22=0,AQ22=0),"",(AQ22-AT22)/AT22)))) -> 1 | AW22: =+AW23+AW26+AW29 -> 1508.3333 | AX22: =IF(AND(AW4=0,AW22>=0), "",AW22/AW4) -> 0.6557971 | AZ22: =+AZ23+AZ26+AZ29 -> 0 | BA22: =IF(AND(AZ4=0,AZ22>=0), "",AZ22/AZ4) | BB22: =IF(AND(AZ22=0,AW22>0),100%,IF(AND(AZ22<0,AW22=0),(AZ22-AW22)/AZ22,IF(AND(AZ22>0,AW22>0),(AW22-AZ22)/AZ22,IF(AND(AZ22=0,AW22=0),"",(AW22-AZ22)/AZ22)))) -> 1 | BC22: =+BC23+BC26+BC29 -> 0 | BD22: =IF(AND(BC4=0,BC22>=0), "",BC22/BC4) | BF22: =IF(AND(AM22=0,BC22>0),100%,IF(AND(AM22<0,BC22=0),(AM22-BC22)/AM22,IF(AND(AM22>0,BC22>0),(BC22-AM22)/AM22,IF(AND(AM22=0,BC22=0),"",(BC22-AM22)/AM22)))) | BG22: =+BG23+BG26+BG29 -> 9050 | BH22: =IF(AND(BG4=0,BG22>=0), "",BG22/BG4) -> 0.6557971 | BJ22: =+BJ23+BJ26+BJ29 -> 0 | BK22: =IF(AND(BJ4=0,BJ22>=0), "",BJ22/BJ4) | BM22: =IF(AND(BC22=0,BJ22>0),100%,IF(AND(BC22<0,BJ22=0),(BC22-BJ22)/BC22,IF(AND(BC22>0,BJ22>0),(BJ22-BC22)/BC22,IF(AND(BC22=0,BJ22=0),"",(BJ22-BC22)/BC22)))) | BN22: =+BN23+BN26+BN29 -> 9050 | BO22: =IF(AND(BN4=0,BN22>=0), "",BN22/BN4) -> 0.6557971 | BQ22: =+BQ23+BQ26+BQ29 -> 0 | BR22: =IF(AND(BQ4=0,BQ22>=0), "",BQ22/BQ4) | BT22: =IF(AND(BJ22=0,BQ22>0),100%,IF(AND(BJ22<0,BQ22=0),(BJ22-BQ22)/BJ22,IF(AND(BJ22>0,BQ22>0),(BQ22-BJ22)/BJ22,IF(AND(BJ22=0,BQ22=0),"",(BQ22-BJ22)/BJ22)))) | BU22: =+BU23+BU26+BU29 -> 9050 | BV22: =IF(AND(BU4=0,BU22>=0), "",BU22/BU4) -> 0.6557971 | BX22: =+BX23+BX26+BX29 -> 0 | BY22: =IF(AND(BX4=0,BX22>=0), "",BX22/BX4) | BZ22: =IF(AND(BX22=0,BU22>0),100%,IF(AND(BX22<0,BU22=0),(BX22-BU22)/BX22,IF(AND(BX22>0,BU22>0),(BU22-BX22)/BX22,IF(AND(BX22=0,BU22=0),"",(BU22-BX22)/BX22)))) -> 1 | CA22: =+CA23+CA26+CA29 -> 0 | CB22: =IF(AND(CA4=0,CA22>=0), "",CA22/CA4) | CD22: =IF(AND(BQ22=0,CA22>0),100%,IF(AND(BQ22<0,CA22=0),(BQ22-CA22)/BQ22,IF(AND(BQ22>0,CA22>0),(CA22-BQ22)/BQ22,IF(AND(BQ22=0,CA22=0),"",(CA22-BQ22)/BQ22)))) | CE22: =+CE23+CE26+CE29 -> 9050 | CF22: =IF(AND(CE4=0,CE22>=0), "",CE22/CE4) -> 0.6557971 | CH22: =+CH23+CH26+CH29 -> 0 | CI22: =IF(AND(CH4=0,CH22>=0), "",CH22/CH4) | CK22: =IF(AND(CA22=0,CH22>0),100%,IF(AND(CA22<0,CH22=0),(CA22-CH22)/CA22,IF(AND(CA22>0,CH22>0),(CH22-CA22)/CA22,IF(AND(CA22=0,CH22=0),"",(CH22-CA22)/CA22)))) | CL22: =+CL23+CL26+CL29 -> 9050 | CM22: =IF(AND(CL4=0,CL22>=0), "",CL22/CL4) -> 0.6557971 | CO22: =+CO23+CO26+CO29 -> 0 | CP22: =IF(AND(CO4=0,CO22>=0), "",CO22/CO4) | CR22: =IF(AND(CH22=0,CO22>0),100%,IF(AND(CH22<0,CO22=0),(CH22-CO22)/CH22,IF(AND(CH22>0,CO22>0),(CO22-CH22)/CH22,IF(AND(CH22=0,CO22=0),"",(CO22-CH22)/CH22)))) | CS22: =+CS23+CS26+CS29 -> 9050 | CT22: =IF(AND(CS4=0,CS22>=0), "",CS22/CS4) -> 0.6557971 | CV22: =+CV23+CV26+CV29 -> 0 | CW22: =IF(AND(CV4=0,CV22>=0), "",CV22/CV4) | CX22: =IF(AND(CV22=0,CS22>0),100%,IF(AND(CV22<0,CS22=0),(CV22-CS22)/CV22,IF(AND(CV22>0,CS22>0),(CS22-CV22)/CV22,IF(AND(CV22=0,CS22=0),"",(CS22-CV22)/CV22)))) -> 1
A23: Subtotal Costo de Ventas por Mercancia | B23: =SUM(B24:B25) -> 0 | C23: =IF(AND(B5=0,B23>=0), "",B23/B5) | E23: =SUM(E24:E25) -> 9000 | F23: =IF(AND(E5=0,E23>=0), "",E23/E5) -> 0.66666667 | H23: =SUM(H24:H25) -> 0 | I23: =IF(AND(H5=0,H23>=0), "",H23/H5) | K23: =IF(AND(E23=0,H23>0),100%,IF(AND(E23<0,H23=0),(E23-H23)/E23,IF(AND(E23>0,H23>0),(H23-E23)/E23,IF(AND(E23=0,H23=0),"",(H23-E23)/E23)))) -> -1 | L23: =SUM(L24:L25) -> 9000 | M23: =IF(AND(L5=0,L23>=0), "",L23/L5) -> 0.66666667 | O23: =SUM(O24:O25) -> 0 | P23: =IF(AND(O5=0,O23>=0), "",O23/O5) | R23: =IF(AND(H23=0,O23>0),100%,IF(AND(H23<0,O23=0),(H23-O23)/H23,IF(AND(H23>0,O23>0),(O23-H23)/H23,IF(AND(H23=0,O23=0),"",(O23-H23)/H23)))) | S23: =SUM(S24:S25) -> 9000 | T23: =IF(AND(S5=0,S23>=0), "",S23/S5) -> 0.66666667 | V23: =SUM(V24:V25) -> 0 | W23: =IF(AND(V5=0,V23>=0), "",V23/V5) | X23: =IF(AND(V23=0,S23>0),100%,IF(AND(V23<0,S23=0),(V23-S23)/V23,IF(AND(V23>0,S23>0),(S23-V23)/V23,IF(AND(V23=0,S23=0),"",(S23-V23)/V23)))) -> 1 | Y23: =SUM(Y24:Y25) -> 0 | Z23: =IF(AND(Y5=0,Y23>=0), "",Y23/Y5) | AB23: =IF(AND(O23=0,Y23>0),100%,IF(AND(O23<0,Y23=0),(O23-Y23)/O23,IF(AND(O23>0,Y23>0),(Y23-O23)/O23,IF(AND(O23=0,Y23=0),"",(Y23-O23)/O23)))) | AC23: =SUM(AC24:AC25) -> 9000 | AD23: =IF(AND(AC5=0,AC23>=0), "",AC23/AC5) -> 0.66666667 | AF23: =SUM(AF24:AF25) -> 0 | AG23: =IF(AND(AF5=0,AF23>=0), "",AF23/AF5) | AI23: =IF(AND(Y23=0,AF23>0),100%,IF(AND(Y23<0,AF23=0),(Y23-AF23)/Y23,IF(AND(Y23>0,AF23>0),(AF23-Y23)/Y23,IF(AND(Y23=0,AF23=0),"",(AF23-Y23)/Y23)))) | AJ23: =SUM(AJ24:AJ25) -> 9000 | AK23: =IF(AND(AJ5=0,AJ23>=0), "",AJ23/AJ5) -> 0.66666667 | AM23: =SUM(AM24:AM25) -> 0 | AN23: =IF(AND(AM5=0,AM23>=0), "",AM23/AM5) | AP23: =IF(AND(AF23=0,AM23>0),100%,IF(AND(AF23<0,AM23=0),(AF23-AM23)/AF23,IF(AND(AF23>0,AM23>0),(AM23-AF23)/AF23,IF(AND(AF23=0,AM23=0),"",(AM23-AF23)/AF23)))) | AQ23: =SUM(AQ24:AQ25) -> 9000 | AR23: =IF(AND(AQ5=0,AQ23>=0), "",AQ23/AQ5) -> 0.66666667 | AT23: =SUM(AT24:AT25) -> 0 | AU23: =IF(AND(AT5=0,AT23>=0), "",AT23/AT5) | AV23: =IF(AND(AT23=0,AQ23>0),100%,IF(AND(AT23<0,AQ23=0),(AT23-AQ23)/AT23,IF(AND(AT23>0,AQ23>0),(AQ23-AT23)/AT23,IF(AND(AT23=0,AQ23=0),"",(AQ23-AT23)/AT23)))) -> 1 | AW23: =SUM(AW24:AW25) -> 1500 | AX23: =IF(AND(AW5=0,AW23>=0), "",AW23/AW5) -> 0.66666667 | AZ23: =SUM(AZ24:AZ25) -> 0 | BA23: =IF(AND(AZ5=0,AZ23>=0), "",AZ23/AZ5) | BB23: =IF(AND(AZ23=0,AW23>0),100%,IF(AND(AZ23<0,AW23=0),(AZ23-AW23)/AZ23,IF(AND(AZ23>0,AW23>0),(AW23-AZ23)/AZ23,IF(AND(AZ23=0,AW23=0),"",(AW23-AZ23)/AZ23)))) -> 1 | BC23: =SUM(BC24:BC25) -> 0 | BD23: =IF(AND(BC5=0,BC23>=0), "",BC23/BC5) | BF23: =IF(AND(AM23=0,BC23>0),100%,IF(AND(AM23<0,BC23=0),(AM23-BC23)/AM23,IF(AND(AM23>0,BC23>0),(BC23-AM23)/AM23,IF(AND(AM23=0,BC23=0),"",(BC23-AM23)/AM23)))) | BG23: =SUM(BG24:BG25) -> 9000 | BH23: =IF(AND(BG5=0,BG23>=0), "",BG23/BG5) -> 0.66666667 | BJ23: =SUM(BJ24:BJ25) -> 0 | BK23: =IF(AND(BJ5=0,BJ23>=0), "",BJ23/BJ5) | BM23: =IF(AND(BC23=0,BJ23>0),100%,IF(AND(BC23<0,BJ23=0),(BC23-BJ23)/BC23,IF(AND(BC23>0,BJ23>0),(BJ23-BC23)/BC23,IF(AND(BC23=0,BJ23=0),"",(BJ23-BC23)/BC23)))) | BN23: =SUM(BN24:BN25) -> 9000 | BO23: =IF(AND(BN5=0,BN23>=0), "",BN23/BN5) -> 0.66666667 | BQ23: =SUM(BQ24:BQ25) -> 0 | BR23: =IF(AND(BQ5=0,BQ23>=0), "",BQ23/BQ5) | BT23: =IF(AND(BJ23=0,BQ23>0),100%,IF(AND(BJ23<0,BQ23=0),(BJ23-BQ23)/BJ23,IF(AND(BJ23>0,BQ23>0),(BQ23-BJ23)/BJ23,IF(AND(BJ23=0,BQ23=0),"",(BQ23-BJ23)/BJ23)))) | BU23: =SUM(BU24:BU25) -> 9000 | BV23: =IF(AND(BU5=0,BU23>=0), "",BU23/BU5) -> 0.66666667 | BX23: =SUM(BX24:BX25) -> 0 | BY23: =IF(AND(BX5=0,BX23>=0), "",BX23/BX5) | BZ23: =IF(AND(BX23=0,BU23>0),100%,IF(AND(BX23<0,BU23=0),(BX23-BU23)/BX23,IF(AND(BX23>0,BU23>0),(BU23-BX23)/BX23,IF(AND(BX23=0,BU23=0),"",(BU23-BX23)/BX23)))) -> 1 | CA23: =SUM(CA24:CA25) -> 0 | CB23: =IF(AND(CA5=0,CA23>=0), "",CA23/CA5) | CD23: =IF(AND(BQ23=0,CA23>0),100%,IF(AND(BQ23<0,CA23=0),(BQ23-CA23)/BQ23,IF(AND(BQ23>0,CA23>0),(CA23-BQ23)/BQ23,IF(AND(BQ23=0,CA23=0),"",(CA23-BQ23)/BQ23)))) | CE23: =SUM(CE24:CE25) -> 9000 | CF23: =IF(AND(CE5=0,CE23>=0), "",CE23/CE5) -> 0.66666667 | CH23: =SUM(CH24:CH25) -> 0 | CI23: =IF(AND(CH5=0,CH23>=0), "",CH23/CH5) | CK23: =IF(AND(CA23=0,CH23>0),100%,IF(AND(CA23<0,CH23=0),(CA23-CH23)/CA23,IF(AND(CA23>0,CH23>0),(CH23-CA23)/CA23,IF(AND(CA23=0,CH23=0),"",(CH23-CA23)/CA23)))) | CL23: =SUM(CL24:CL25) -> 9000 | CM23: =IF(AND(CL5=0,CL23>=0), "",CL23/CL5) -> 0.66666667 | CO23: =SUM(CO24:CO25) -> 0 | CP23: =IF(AND(CO5=0,CO23>=0), "",CO23/CO5) | CR23: =IF(AND(CH23=0,CO23>0),100%,IF(AND(CH23<0,CO23=0),(CH23-CO23)/CH23,IF(AND(CH23>0,CO23>0),(CO23-CH23)/CH23,IF(AND(CH23=0,CO23=0),"",(CO23-CH23)/CH23)))) | CS23: =SUM(CS24:CS25) -> 9000 | CT23: =IF(AND(CS5=0,CS23>=0), "",CS23/CS5) -> 0.66666667 | CV23: =SUM(CV24:CV25) -> 0 | CW23: =IF(AND(CV5=0,CV23>=0), "",CV23/CV5) | CX23: =IF(AND(CV23=0,CS23>0),100%,IF(AND(CV23<0,CS23=0),(CV23-CS23)/CV23,IF(AND(CV23>0,CS23>0),(CS23-CV23)/CV23,IF(AND(CV23=0,CS23=0),"",(CS23-CV23)/CV23)))) -> 1
A24: Costo de venta por mercancía | B24: =+'N EERR'!B30 -> 0 | C24: =IF(AND(B5=0,B24>=0), "",B24/B5) | E24: =+'N EERR'!C30 -> 9000 | F24: =IF(AND(E5=0,E24>=0), "",E24/E5) -> 0.66666667 | H24: =+'N EERR'!D30 -> 0 | I24: =IF(AND(H5=0,H24>=0), "",H24/H5) | K24: =IF(AND(E24=0,H24>0),100%,IF(AND(E24<0,H24=0),(E24-H24)/E24,IF(AND(E24>0,H24>0),(H24-E24)/E24,IF(AND(E24=0,H24=0),"",(H24-E24)/E24)))) -> -1 | L24: =+E24+H24 -> 9000 | M24: =IF(AND(L5=0,L24>=0), "",L24/L5) -> 0.66666667 | O24: =+'N EERR'!E30 -> 0 | P24: =IF(AND(O5=0,O24>=0), "",O24/O5) | R24: =IF(AND(H24=0,O24>0),100%,IF(AND(H24<0,O24=0),(H24-O24)/H24,IF(AND(H24>0,O24>0),(O24-H24)/H24,IF(AND(H24=0,O24=0),"",(O24-H24)/H24)))) | S24: =+L24+O24 -> 9000 | T24: =IF(AND(S5=0,S24>=0), "",S24/S5) -> 0.66666667 | V24: =+V6*66.71% -> 0 | W24: =IF(AND(V5=0,V24>=0), "",V24/V5) | X24: =IF(AND(V24=0,S24>0),100%,IF(AND(V24<0,S24=0),(V24-S24)/V24,IF(AND(V24>0,S24>0),(S24-V24)/V24,IF(AND(V24=0,S24=0),"",(S24-V24)/V24)))) -> 1 | Y24: =+'N EERR'!F30 -> 0 | Z24: =IF(AND(Y5=0,Y24>=0), "",Y24/Y5) | AB24: =IF(AND(O24=0,Y24>0),100%,IF(AND(O24<0,Y24=0),(O24-Y24)/O24,IF(AND(O24>0,Y24>0),(Y24-O24)/O24,IF(AND(O24=0,Y24=0),"",(Y24-O24)/O24)))) | AC24: =+S24+Y24 -> 9000 | AD24: =IF(AND(AC5=0,AC24>=0), "",AC24/AC5) -> 0.66666667 | AF24: =+'N EERR'!G30 -> 0 | AG24: =IF(AND(AF5=0,AF24>=0), "",AF24/AF5) | AI24: =IF(AND(Y24=0,AF24>0),100%,IF(AND(Y24<0,AF24=0),(Y24-AF24)/Y24,IF(AND(Y24>0,AF24>0),(AF24-Y24)/Y24,IF(AND(Y24=0,AF24=0),"",(AF24-Y24)/Y24)))) | AJ24: =+AC24+AF24 -> 9000 | AK24: =IF(AND(AJ5=0,AJ24>=0), "",AJ24/AJ5) -> 0.66666667 | AM24: =+'N EERR'!H30 -> 0 | AN24: =IF(AND(AM5=0,AM24>=0), "",AM24/AM5) | AP24: =IF(AND(AF24=0,AM24>0),100%,IF(AND(AF24<0,AM24=0),(AF24-AM24)/AF24,IF(AND(AF24>0,AM24>0),(AM24-AF24)/AF24,IF(AND(AF24=0,AM24=0),"",(AM24-AF24)/AF24)))) | AQ24: =+AJ24+AM24 -> 9000 | AR24: =IF(AND(AQ5=0,AQ24>=0), "",AQ24/AQ5) -> 0.66666667 | AT24: =+V24*2 -> 0 | AU24: =IF(AND(AT5=0,AT24>=0), "",AT24/AT5) | AV24: =IF(AND(AT24=0,AQ24>0),100%,IF(AND(AT24<0,AQ24=0),(AT24-AQ24)/AT24,IF(AND(AT24>0,AQ24>0),(AQ24-AT24)/AT24,IF(AND(AT24=0,AQ24=0),"",(AQ24-AT24)/AT24)))) -> 1 | AW24: =+AQ24/6 -> 1500 | AX24: =IF(AND(AW5=0,AW24>=0), "",AW24/AW5) -> 0.66666667 | AZ24: =+AT24/6 -> 0 | BA24: =IF(AND(AZ5=0,AZ24>=0), "",AZ24/AZ5) | BB24: =IF(AND(AZ24=0,AW24>0),100%,IF(AND(AZ24<0,AW24=0),(AZ24-AW24)/AZ24,IF(AND(AZ24>0,AW24>0),(AW24-AZ24)/AZ24,IF(AND(AZ24=0,AW24=0),"",(AW24-AZ24)/AZ24)))) -> 1 | BC24: =+'N EERR'!I30 -> 0 | BD24: =IF(AND(BC5=0,BC24>=0), "",BC24/BC5) | BF24: =IF(AND(AM24=0,BC24>0),100%,IF(AND(AM24<0,BC24=0),(AM24-BC24)/AM24,IF(AND(AM24>0,BC24>0),(BC24-AM24)/AM24,IF(AND(AM24=0,BC24=0),"",(BC24-AM24)/AM24)))) | BG24: =+AQ24+BC24 -> 9000 | BH24: =IF(AND(BG5=0,BG24>=0), "",BG24/BG5) -> 0.66666667 | BJ24: =+'N EERR'!J30 -> 0 | BK24: =IF(AND(BJ5=0,BJ24>=0), "",BJ24/BJ5) | BM24: =IF(AND(BC24=0,BJ24>0),100%,IF(AND(BC24<0,BJ24=0),(BC24-BJ24)/BC24,IF(AND(BC24>0,BJ24>0),(BJ24-BC24)/BC24,IF(AND(BC24=0,BJ24=0),"",(BJ24-BC24)/BC24)))) | BN24: =+BG24+BJ24 -> 9000 | BO24: =IF(AND(BN5=0,BN24>=0), "",BN24/BN5) -> 0.66666667 | BQ24: =+'N EERR'!K30 -> 0 | BR24: =IF(AND(BQ5=0,BQ24>=0), "",BQ24/BQ5) | BT24: =IF(AND(BJ24=0,BQ24>0),100%,IF(AND(BJ24<0,BQ24=0),(BJ24-BQ24)/BJ24,IF(AND(BJ24>0,BQ24>0),(BQ24-BJ24)/BJ24,IF(AND(BJ24=0,BQ24=0),"",(BQ24-BJ24)/BJ24)))) | BU24: =+BN24+BQ24 -> 9000 | BV24: =IF(AND(BU5=0,BU24>=0), "",BU24/BU5) -> 0.66666667 | BX24: =+AZ24*9 -> 0 | BY24: =IF(AND(BX5=0,BX24>=0), "",BX24/BX5) | BZ24: =IF(AND(BX24=0,BU24>0),100%,IF(AND(BX24<0,BU24=0),(BX24-BU24)/BX24,IF(AND(BX24>0,BU24>0),(BU24-BX24)/BX24,IF(AND(BX24=0,BU24=0),"",(BU24-BX24)/BX24)))) -> 1 | CA24: =+'N EERR'!L30 -> 0 | CB24: =IF(AND(CA5=0,CA24>=0), "",CA24/CA5) | CD24: =IF(AND(BQ24=0,CA24>0),100%,IF(AND(BQ24<0,CA24=0),(BQ24-CA24)/BQ24,IF(AND(BQ24>0,CA24>0),(CA24-BQ24)/BQ24,IF(AND(BQ24=0,CA24=0),"",(CA24-BQ24)/BQ24)))) | CE24: =+BU24+CA24 -> 9000 | CF24: =IF(AND(CE5=0,CE24>=0), "",CE24/CE5) -> 0.66666667 | CH24: =+'N EERR'!M30 -> 0 | CI24: =IF(AND(CH5=0,CH24>=0), "",CH24/CH5) | CK24: =IF(AND(CA24=0,CH24>0),100%,IF(AND(CA24<0,CH24=0),(CA24-CH24)/CA24,IF(AND(CA24>0,CH24>0),(CH24-CA24)/CA24,IF(AND(CA24=0,CH24=0),"",(CH24-CA24)/CA24)))) | CL24: =+CE24+CH24 -> 9000 | CM24: =IF(AND(CL5=0,CL24>=0), "",CL24/CL5) -> 0.66666667 | CO24: =+'N EERR'!N30 -> 0 | CP24: =IF(AND(CO5=0,CO24>=0), "",CO24/CO5) | CR24: =IF(AND(CH24=0,CO24>0),100%,IF(AND(CH24<0,CO24=0),(CH24-CO24)/CH24,IF(AND(CH24>0,CO24>0),(CO24-CH24)/CH24,IF(AND(CH24=0,CO24=0),"",(CO24-CH24)/CH24)))) | CS24: =+CL24+CO24 -> 9000 | CT24: =IF(AND(CS5=0,CS24>=0), "",CS24/CS5) -> 0.66666667 | CV24: =+AZ24*12 -> 0 | CW24: =IF(AND(CV5=0,CV24>=0), "",CV24/CV5) | CX24: =IF(AND(CV24=0,CS24>0),100%,IF(AND(CV24<0,CS24=0),(CV24-CS24)/CV24,IF(AND(CV24>0,CS24>0),(CS24-CV24)/CV24,IF(AND(CV24=0,CS24=0),"",(CS24-CV24)/CV24)))) -> 1
K25: =IF(AND(E25=0,H25>0),100%,IF(AND(E25<0,H25=0),(E25-H25)/E25,IF(AND(E25>0,H25>0),(H25-E25)/E25,IF(AND(E25=0,H25=0),"",(H25-E25)/E25)))) | R25: =IF(AND(H25=0,O25>0),100%,IF(AND(H25<0,O25=0),(H25-O25)/H25,IF(AND(H25>0,O25>0),(O25-H25)/H25,IF(AND(H25=0,O25=0),"",(O25-H25)/H25)))) | X25: =IF(AND(V25=0,S25>0),100%,IF(AND(V25<0,S25=0),(V25-S25)/V25,IF(AND(V25>0,S25>0),(S25-V25)/V25,IF(AND(V25=0,S25=0),"",(S25-V25)/V25)))) | AB25: =IF(AND(O25=0,Y25>0),100%,IF(AND(O25<0,Y25=0),(O25-Y25)/O25,IF(AND(O25>0,Y25>0),(Y25-O25)/O25,IF(AND(O25=0,Y25=0),"",(Y25-O25)/O25)))) | AI25: =IF(AND(Y25=0,AF25>0),100%,IF(AND(Y25<0,AF25=0),(Y25-AF25)/Y25,IF(AND(Y25>0,AF25>0),(AF25-Y25)/Y25,IF(AND(Y25=0,AF25=0),"",(AF25-Y25)/Y25)))) | AJ25: =+AC25+AF25 -> 0 | AP25: =IF(AND(AF25=0,AM25>0),100%,IF(AND(AF25<0,AM25=0),(AF25-AM25)/AF25,IF(AND(AF25>0,AM25>0),(AM25-AF25)/AF25,IF(AND(AF25=0,AM25=0),"",(AM25-AF25)/AF25)))) | AQ25: =+AJ25+AM25 -> 0 | AT25: =+V25*2 -> 0 | AV25: =IF(AND(AT25=0,AQ25>0),100%,IF(AND(AT25<0,AQ25=0),(AT25-AQ25)/AT25,IF(AND(AT25>0,AQ25>0),(AQ25-AT25)/AT25,IF(AND(AT25=0,AQ25=0),"",(AQ25-AT25)/AT25)))) | AW25: =+AQ25/6 -> 0 | AZ25: =+AT25/6 -> 0 | BB25: =IF(AND(AZ25=0,AW25>0),100%,IF(AND(AZ25<0,AW25=0),(AZ25-AW25)/AZ25,IF(AND(AZ25>0,AW25>0),(AW25-AZ25)/AZ25,IF(AND(AZ25=0,AW25=0),"",(AW25-AZ25)/AZ25)))) | BF25: =IF(AND(AM25=0,BC25>0),100%,IF(AND(AM25<0,BC25=0),(AM25-BC25)/AM25,IF(AND(AM25>0,BC25>0),(BC25-AM25)/AM25,IF(AND(AM25=0,BC25=0),"",(BC25-AM25)/AM25)))) | BG25: =+AQ25+BC25 -> 0 | BM25: =IF(AND(BC25=0,BJ25>0),100%,IF(AND(BC25<0,BJ25=0),(BC25-BJ25)/BC25,IF(AND(BC25>0,BJ25>0),(BJ25-BC25)/BC25,IF(AND(BC25=0,BJ25=0),"",(BJ25-BC25)/BC25)))) | BN25: =+BG25+BJ25 -> 0 | BT25: =IF(AND(BJ25=0,BQ25>0),100%,IF(AND(BJ25<0,BQ25=0),(BJ25-BQ25)/BJ25,IF(AND(BJ25>0,BQ25>0),(BQ25-BJ25)/BJ25,IF(AND(BJ25=0,BQ25=0),"",(BQ25-BJ25)/BJ25)))) | BU25: =+BN25+BQ25 -> 0 | BX25: =+AZ25*9 -> 0 | BZ25: =IF(AND(BX25=0,BU25>0),100%,IF(AND(BX25<0,BU25=0),(BX25-BU25)/BX25,IF(AND(BX25>0,BU25>0),(BU25-BX25)/BX25,IF(AND(BX25=0,BU25=0),"",(BU25-BX25)/BX25)))) | CD25: =IF(AND(BQ25=0,CA25>0),100%,IF(AND(BQ25<0,CA25=0),(BQ25-CA25)/BQ25,IF(AND(BQ25>0,CA25>0),(CA25-BQ25)/BQ25,IF(AND(BQ25=0,CA25=0),"",(CA25-BQ25)/BQ25)))) | CK25: =IF(AND(CA25=0,CH25>0),100%,IF(AND(CA25<0,CH25=0),(CA25-CH25)/CA25,IF(AND(CA25>0,CH25>0),(CH25-CA25)/CA25,IF(AND(CA25=0,CH25=0),"",(CH25-CA25)/CA25)))) | CL25: =+CE25+CH25 -> 0 | CR25: =IF(AND(CH25=0,CO25>0),100%,IF(AND(CH25<0,CO25=0),(CH25-CO25)/CH25,IF(AND(CH25>0,CO25>0),(CO25-CH25)/CH25,IF(AND(CH25=0,CO25=0),"",(CO25-CH25)/CH25)))) | CS25: =+CL25+CO25 -> 0 | CV25: =+AZ25*12 -> 0 | CX25: =IF(AND(CV25=0,CS25>0),100%,IF(AND(CV25<0,CS25=0),(CV25-CS25)/CV25,IF(AND(CV25>0,CS25>0),(CS25-CV25)/CV25,IF(AND(CV25=0,CS25=0),"",(CS25-CV25)/CV25))))
A26: Subtotal Costo de Ventas por Servicios | B26: =SUM(B27:B28) -> 0 | C26: =IF(AND(B10=0,B26>=0), "",B26/B10) | E26: =SUM(E27:E28) -> 20 | F26: =IF(AND(E10=0,E26>=0), "",E26/E10) -> 0.1 | H26: =SUM(H27:H28) -> 0 | I26: =IF(AND(H10=0,H26>=0), "",H26/H10) | K26: =IF(AND(E26=0,H26>0),100%,IF(AND(E26<0,H26=0),(E26-H26)/E26,IF(AND(E26>0,H26>0),(H26-E26)/E26,IF(AND(E26=0,H26=0),"",(H26-E26)/E26)))) -> -1 | L26: =SUM(L27:L28) -> 20 | M26: =IF(AND(L10=0,L26>=0), "",L26/L10) -> 0.1 | O26: =SUM(O27:O28) -> 0 | P26: =IF(AND(O10=0,O26>=0), "",O26/O10) | R26: =IF(AND(H26=0,O26>0),100%,IF(AND(H26<0,O26=0),(H26-O26)/H26,IF(AND(H26>0,O26>0),(O26-H26)/H26,IF(AND(H26=0,O26=0),"",(O26-H26)/H26)))) | S26: =SUM(S27:S28) -> 20 | T26: =IF(AND(S10=0,S26>=0), "",S26/S10) -> 0.1 | V26: =SUM(V27:V28) -> 0 | W26: =IF(AND(V10=0,V26>=0), "",V26/V10) | X26: =IF(AND(V26=0,S26>0),100%,IF(AND(V26<0,S26=0),(V26-S26)/V26,IF(AND(V26>0,S26>0),(S26-V26)/V26,IF(AND(V26=0,S26=0),"",(S26-V26)/V26)))) -> 1 | Y26: =SUM(Y27:Y28) -> 0 | Z26: =IF(AND(Y10=0,Y26>=0), "",Y26/Y10) | AB26: =IF(AND(O26=0,Y26>0),100%,IF(AND(O26<0,Y26=0),(O26-Y26)/O26,IF(AND(O26>0,Y26>0),(Y26-O26)/O26,IF(AND(O26=0,Y26=0),"",(Y26-O26)/O26)))) | AC26: =SUM(AC27:AC28) -> 20 | AD26: =IF(AND(AC10=0,AC26>=0), "",AC26/AC10) -> 0.1 | AF26: =SUM(AF27:AF28) -> 0 | AG26: =IF(AND(AF10=0,AF26>=0), "",AF26/AF10) | AI26: =IF(AND(Y26=0,AF26>0),100%,IF(AND(Y26<0,AF26=0),(Y26-AF26)/Y26,IF(AND(Y26>0,AF26>0),(AF26-Y26)/Y26,IF(AND(Y26=0,AF26=0),"",(AF26-Y26)/Y26)))) | AJ26: =SUM(AJ27:AJ28) -> 20 | AK26: =IF(AND(AJ10=0,AJ26>=0), "",AJ26/AJ10) -> 0.1 | AM26: =SUM(AM27:AM28) -> 0 | AN26: =IF(AND(AM10=0,AM26>=0), "",AM26/AM10) | AP26: =IF(AND(AF26=0,AM26>0),100%,IF(AND(AF26<0,AM26=0),(AF26-AM26)/AF26,IF(AND(AF26>0,AM26>0),(AM26-AF26)/AF26,IF(AND(AF26=0,AM26=0),"",(AM26-AF26)/AF26)))) | AQ26: =SUM(AQ27:AQ28) -> 20 | AR26: =IF(AND(AQ10=0,AQ26>=0), "",AQ26/AQ10) -> 0.1 | AT26: =SUM(AT27:AT28) -> 0 | AU26: =IF(AND(AT10=0,AT26>=0), "",AT26/AT10) | AV26: =IF(AND(AT26=0,AQ26>0),100%,IF(AND(AT26<0,AQ26=0),(AT26-AQ26)/AT26,IF(AND(AT26>0,AQ26>0),(AQ26-AT26)/AT26,IF(AND(AT26=0,AQ26=0),"",(AQ26-AT26)/AT26)))) -> 1 | AW26: =SUM(AW27:AW28) -> 3.3333333 | AX26: =IF(AND(AW10=0,AW26>=0), "",AW26/AW10) -> 0.1 | AZ26: =SUM(AZ27:AZ28) -> 0 | BA26: =IF(AND(AZ10=0,AZ26>=0), "",AZ26/AZ10) | BB26: =IF(AND(AZ26=0,AW26>0),100%,IF(AND(AZ26<0,AW26=0),(AZ26-AW26)/AZ26,IF(AND(AZ26>0,AW26>0),(AW26-AZ26)/AZ26,IF(AND(AZ26=0,AW26=0),"",(AW26-AZ26)/AZ26)))) -> 1 | BC26: =SUM(BC27:BC28) -> 0 | BD26: =IF(AND(BC10=0,BC26>=0), "",BC26/BC10) | BF26: =IF(AND(AM26=0,BC26>0),100%,IF(AND(AM26<0,BC26=0),(AM26-BC26)/AM26,IF(AND(AM26>0,BC26>0),(BC26-AM26)/AM26,IF(AND(AM26=0,BC26=0),"",(BC26-AM26)/AM26)))) | BG26: =SUM(BG27:BG28) -> 20 | BH26: =IF(AND(BG10=0,BG26>=0), "",BG26/BG10) -> 0.1 | BJ26: =SUM(BJ27:BJ28) -> 0 | BK26: =IF(AND(BJ10=0,BJ26>=0), "",BJ26/BJ10) | BM26: =IF(AND(BC26=0,BJ26>0),100%,IF(AND(BC26<0,BJ26=0),(BC26-BJ26)/BC26,IF(AND(BC26>0,BJ26>0),(BJ26-BC26)/BC26,IF(AND(BC26=0,BJ26=0),"",(BJ26-BC26)/BC26)))) | BN26: =SUM(BN27:BN28) -> 20 | BO26: =IF(AND(BN10=0,BN26>=0), "",BN26/BN10) -> 0.1 | BQ26: =SUM(BQ27:BQ28) -> 0 | BR26: =IF(AND(BQ10=0,BQ26>=0), "",BQ26/BQ10) | BT26: =IF(AND(BJ26=0,BQ26>0),100%,IF(AND(BJ26<0,BQ26=0),(BJ26-BQ26)/BJ26,IF(AND(BJ26>0,BQ26>0),(BQ26-BJ26)/BJ26,IF(AND(BJ26=0,BQ26=0),"",(BQ26-BJ26)/BJ26)))) | BU26: =SUM(BU27:BU28) -> 20 | BV26: =IF(AND(BU10=0,BU26>=0), "",BU26/BU10) -> 0.1 | BX26: =SUM(BX27:BX28) -> 0 | BY26: =IF(AND(BX10=0,BX26>=0), "",BX26/BX10) | BZ26: =IF(AND(BX26=0,BU26>0),100%,IF(AND(BX26<0,BU26=0),(BX26-BU26)/BX26,IF(AND(BX26>0,BU26>0),(BU26-BX26)/BX26,IF(AND(BX26=0,BU26=0),"",(BU26-BX26)/BX26)))) -> 1 | CA26: =SUM(CA27:CA28) -> 0 | CB26: =IF(AND(CA10=0,CA26>=0), "",CA26/CA10) | CD26: =IF(AND(BQ26=0,CA26>0),100%,IF(AND(BQ26<0,CA26=0),(BQ26-CA26)/BQ26,IF(AND(BQ26>0,CA26>0),(CA26-BQ26)/BQ26,IF(AND(BQ26=0,CA26=0),"",(CA26-BQ26)/BQ26)))) | CE26: =SUM(CE27:CE28) -> 20 | CF26: =IF(AND(CE10=0,CE26>=0), "",CE26/CE10) -> 0.1 | CH26: =SUM(CH27:CH28) -> 0 | CI26: =IF(AND(CH10=0,CH26>=0), "",CH26/CH10) | CK26: =IF(AND(CA26=0,CH26>0),100%,IF(AND(CA26<0,CH26=0),(CA26-CH26)/CA26,IF(AND(CA26>0,CH26>0),(CH26-CA26)/CA26,IF(AND(CA26=0,CH26=0),"",(CH26-CA26)/CA26)))) | CL26: =SUM(CL27:CL28) -> 20 | CM26: =IF(AND(CL10=0,CL26>=0), "",CL26/CL10) -> 0.1 | CO26: =SUM(CO27:CO28) -> 0 | CP26: =IF(AND(CO10=0,CO26>=0), "",CO26/CO10) | CR26: =IF(AND(CH26=0,CO26>0),100%,IF(AND(CH26<0,CO26=0),(CH26-CO26)/CH26,IF(AND(CH26>0,CO26>0),(CO26-CH26)/CH26,IF(AND(CH26=0,CO26=0),"",(CO26-CH26)/CH26)))) | CS26: =SUM(CS27:CS28) -> 20 | CT26: =IF(AND(CS10=0,CS26>=0), "",CS26/CS10) -> 0.1 | CV26: =SUM(CV27:CV28) -> 0 | CW26: =IF(AND(CV10=0,CV26>=0), "",CV26/CV10) | CX26: =IF(AND(CV26=0,CS26>0),100%,IF(AND(CV26<0,CS26=0),(CV26-CS26)/CV26,IF(AND(CV26>0,CS26>0),(CS26-CV26)/CV26,IF(AND(CV26=0,CS26=0),"",(CS26-CV26)/CV26)))) -> 1
A27: Costo de venta por servicio del café | B27: =+'N EERR'!B31 -> 0 | C27: =IF(AND(B10=0,B27>=0), "",B27/B10) | E27: =+'N EERR'!C31 -> 20 | F27: =IF(AND(E10=0,E27>=0), "",E27/E10) -> 0.1 | H27: =+'N EERR'!D31 -> 0 | I27: =IF(AND(H10=0,H27>=0), "",H27/H10) | K27: =IF(AND(E27=0,H27>0),100%,IF(AND(E27<0,H27=0),(E27-H27)/E27,IF(AND(E27>0,H27>0),(H27-E27)/E27,IF(AND(E27=0,H27=0),"",(H27-E27)/E27)))) -> -1 | L27: =+E27+H27 -> 20 | M27: =IF(AND(L10=0,L27>=0), "",L27/L10) -> 0.1 | O27: =+'N EERR'!E31 -> 0 | P27: =IF(AND(O10=0,O27>=0), "",O27/O10) | R27: =IF(AND(H27=0,O27>0),100%,IF(AND(H27<0,O27=0),(H27-O27)/H27,IF(AND(H27>0,O27>0),(O27-H27)/H27,IF(AND(H27=0,O27=0),"",(O27-H27)/H27)))) | S27: =+L27+O27 -> 20 | T27: =IF(AND(S10=0,S27>=0), "",S27/S10) -> 0.1 | W27: =IF(AND(V10=0,V27>=0), "",V27/V10) | X27: =IF(AND(V27=0,S27>0),100%,IF(AND(V27<0,S27=0),(V27-S27)/V27,IF(AND(V27>0,S27>0),(S27-V27)/V27,IF(AND(V27=0,S27=0),"",(S27-V27)/V27)))) -> 1 | Y27: =+'N EERR'!F31 -> 0 | Z27: =IF(AND(Y10=0,Y27>=0), "",Y27/Y10) | AB27: =IF(AND(O27=0,Y27>0),100%,IF(AND(O27<0,Y27=0),(O27-Y27)/O27,IF(AND(O27>0,Y27>0),(Y27-O27)/O27,IF(AND(O27=0,Y27=0),"",(Y27-O27)/O27)))) | AC27: =+S27+Y27 -> 20 | AD27: =IF(AND(AC10=0,AC27>=0), "",AC27/AC10) -> 0.1 | AF27: =+'N EERR'!G31 -> 0 | AG27: =IF(AND(AF10=0,AF27>=0), "",AF27/AF10) | AI27: =IF(AND(Y27=0,AF27>0),100%,IF(AND(Y27<0,AF27=0),(Y27-AF27)/Y27,IF(AND(Y27>0,AF27>0),(AF27-Y27)/Y27,IF(AND(Y27=0,AF27=0),"",(AF27-Y27)/Y27)))) | AJ27: =+AC27+AF27 -> 20 | AK27: =IF(AND(AJ10=0,AJ27>=0), "",AJ27/AJ10) -> 0.1 | AM27: =+'N EERR'!H31 -> 0 | AN27: =IF(AND(AM10=0,AM27>=0), "",AM27/AM10) | AP27: =IF(AND(AF27=0,AM27>0),100%,IF(AND(AF27<0,AM27=0),(AF27-AM27)/AF27,IF(AND(AF27>0,AM27>0),(AM27-AF27)/AF27,IF(AND(AF27=0,AM27=0),"",(AM27-AF27)/AF27)))) | AQ27: =+AJ27+AM27 -> 20 | AR27: =IF(AND(AQ10=0,AQ27>=0), "",AQ27/AQ10) -> 0.1 | AT27: =+V27*2 -> 0 | AU27: =IF(AND(AT10=0,AT27>=0), "",AT27/AT10) | AV27: =IF(AND(AT27=0,AQ27>0),100%,IF(AND(AT27<0,AQ27=0),(AT27-AQ27)/AT27,IF(AND(AT27>0,AQ27>0),(AQ27-AT27)/AT27,IF(AND(AT27=0,AQ27=0),"",(AQ27-AT27)/AT27)))) -> 1 | AW27: =+AQ27/6 -> 3.3333333 | AX27: =IF(AND(AW10=0,AW27>=0), "",AW27/AW10) -> 0.1 | AZ27: =+AT27/6 -> 0 | BA27: =IF(AND(AZ10=0,AZ27>=0), "",AZ27/AZ10) | BB27: =IF(AND(AZ27=0,AW27>0),100%,IF(AND(AZ27<0,AW27=0),(AZ27-AW27)/AZ27,IF(AND(AZ27>0,AW27>0),(AW27-AZ27)/AZ27,IF(AND(AZ27=0,AW27=0),"",(AW27-AZ27)/AZ27)))) -> 1 | BC27: =+'N EERR'!I31 -> 0 | BD27: =IF(AND(BC10=0,BC27>=0), "",BC27/BC10) | BF27: =IF(AND(AM27=0,BC27>0),100%,IF(AND(AM27<0,BC27=0),(AM27-BC27)/AM27,IF(AND(AM27>0,BC27>0),(BC27-AM27)/AM27,IF(AND(AM27=0,BC27=0),"",(BC27-AM27)/AM27)))) | BG27: =+AQ27+BC27 -> 20 | BH27: =IF(AND(BG10=0,BG27>=0), "",BG27/BG10) -> 0.1 | BJ27: =+'N EERR'!J31 -> 0 | BK27: =IF(AND(BJ10=0,BJ27>=0), "",BJ27/BJ10) | BM27: =IF(AND(BC27=0,BJ27>0),100%,IF(AND(BC27<0,BJ27=0),(BC27-BJ27)/BC27,IF(AND(BC27>0,BJ27>0),(BJ27-BC27)/BC27,IF(AND(BC27=0,BJ27=0),"",(BJ27-BC27)/BC27)))) | BN27: =+BG27+BJ27 -> 20 | BO27: =IF(AND(BN10=0,BN27>=0), "",BN27/BN10) -> 0.1 | BQ27: =+'N EERR'!K31 -> 0 | BR27: =IF(AND(BQ10=0,BQ27>=0), "",BQ27/BQ10) | BT27: =IF(AND(BJ27=0,BQ27>0),100%,IF(AND(BJ27<0,BQ27=0),(BJ27-BQ27)/BJ27,IF(AND(BJ27>0,BQ27>0),(BQ27-BJ27)/BJ27,IF(AND(BJ27=0,BQ27=0),"",(BQ27-BJ27)/BJ27)))) | BU27: =+BN27+BQ27 -> 20 | BV27: =IF(AND(BU10=0,BU27>=0), "",BU27/BU10) -> 0.1 | BX27: =+AZ27*9 -> 0 | BY27: =IF(AND(BX10=0,BX27>=0), "",BX27/BX10) | BZ27: =IF(AND(BX27=0,BU27>0),100%,IF(AND(BX27<0,BU27=0),(BX27-BU27)/BX27,IF(AND(BX27>0,BU27>0),(BU27-BX27)/BX27,IF(AND(BX27=0,BU27=0),"",(BU27-BX27)/BX27)))) -> 1 | CA27: =+'N EERR'!L31 -> 0 | CB27: =IF(AND(CA10=0,CA27>=0), "",CA27/CA10) | CD27: =IF(AND(BQ27=0,CA27>0),100%,IF(AND(BQ27<0,CA27=0),(BQ27-CA27)/BQ27,IF(AND(BQ27>0,CA27>0),(CA27-BQ27)/BQ27,IF(AND(BQ27=0,CA27=0),"",(CA27-BQ27)/BQ27)))) | CE27: =+BU27+CA27 -> 20 | CF27: =IF(AND(CE10=0,CE27>=0), "",CE27/CE10) -> 0.1 | CH27: =+'N EERR'!M31 -> 0 | CI27: =IF(AND(CH10=0,CH27>=0), "",CH27/CH10) | CK27: =IF(AND(CA27=0,CH27>0),100%,IF(AND(CA27<0,CH27=0),(CA27-CH27)/CA27,IF(AND(CA27>0,CH27>0),(CH27-CA27)/CA27,IF(AND(CA27=0,CH27=0),"",(CH27-CA27)/CA27)))) | CL27: =+CE27+CH27 -> 20 | CM27: =IF(AND(CL10=0,CL27>=0), "",CL27/CL10) -> 0.1 | CO27: =+'N EERR'!N31 -> 0 | CP27: =IF(AND(CO10=0,CO27>=0), "",CO27/CO10) | CR27: =IF(AND(CH27=0,CO27>0),100%,IF(AND(CH27<0,CO27=0),(CH27-CO27)/CH27,IF(AND(CH27>0,CO27>0),(CO27-CH27)/CH27,IF(AND(CH27=0,CO27=0),"",(CO27-CH27)/CH27)))) | CS27: =+CL27+CO27 -> 20 | CT27: =IF(AND(CS10=0,CS27>=0), "",CS27/CS10) -> 0.1 | CV27: =+AZ27*12 -> 0 | CW27: =IF(AND(CV10=0,CV27>=0), "",CV27/CV10) | CX27: =IF(AND(CV27=0,CS27>0),100%,IF(AND(CV27<0,CS27=0),(CV27-CS27)/CV27,IF(AND(CV27>0,CS27>0),(CS27-CV27)/CV27,IF(AND(CV27=0,CS27=0),"",(CS27-CV27)/CV27)))) -> 1
K28: =IF(AND(E28=0,H28>0),100%,IF(AND(E28<0,H28=0),(E28-H28)/E28,IF(AND(E28>0,H28>0),(H28-E28)/E28,IF(AND(E28=0,H28=0),"",(H28-E28)/E28)))) | R28: =IF(AND(H28=0,O28>0),100%,IF(AND(H28<0,O28=0),(H28-O28)/H28,IF(AND(H28>0,O28>0),(O28-H28)/H28,IF(AND(H28=0,O28=0),"",(O28-H28)/H28)))) | X28: =IF(AND(V28=0,S28>0),100%,IF(AND(V28<0,S28=0),(V28-S28)/V28,IF(AND(V28>0,S28>0),(S28-V28)/V28,IF(AND(V28=0,S28=0),"",(S28-V28)/V28)))) | AB28: =IF(AND(O28=0,Y28>0),100%,IF(AND(O28<0,Y28=0),(O28-Y28)/O28,IF(AND(O28>0,Y28>0),(Y28-O28)/O28,IF(AND(O28=0,Y28=0),"",(Y28-O28)/O28)))) | AI28: =IF(AND(Y28=0,AF28>0),100%,IF(AND(Y28<0,AF28=0),(Y28-AF28)/Y28,IF(AND(Y28>0,AF28>0),(AF28-Y28)/Y28,IF(AND(Y28=0,AF28=0),"",(AF28-Y28)/Y28)))) | AJ28: =+AC28+AF28 -> 0 | AP28: =IF(AND(AF28=0,AM28>0),100%,IF(AND(AF28<0,AM28=0),(AF28-AM28)/AF28,IF(AND(AF28>0,AM28>0),(AM28-AF28)/AF28,IF(AND(AF28=0,AM28=0),"",(AM28-AF28)/AF28)))) | AQ28: =+AJ28+AM28 -> 0 | AT28: =+V28*2 -> 0 | AV28: =IF(AND(AT28=0,AQ28>0),100%,IF(AND(AT28<0,AQ28=0),(AT28-AQ28)/AT28,IF(AND(AT28>0,AQ28>0),(AQ28-AT28)/AT28,IF(AND(AT28=0,AQ28=0),"",(AQ28-AT28)/AT28)))) | AW28: =+AQ28/6 -> 0 | AZ28: =+AT28/6 -> 0 | BB28: =IF(AND(AZ28=0,AW28>0),100%,IF(AND(AZ28<0,AW28=0),(AZ28-AW28)/AZ28,IF(AND(AZ28>0,AW28>0),(AW28-AZ28)/AZ28,IF(AND(AZ28=0,AW28=0),"",(AW28-AZ28)/AZ28)))) | BF28: =IF(AND(AM28=0,BC28>0),100%,IF(AND(AM28<0,BC28=0),(AM28-BC28)/AM28,IF(AND(AM28>0,BC28>0),(BC28-AM28)/AM28,IF(AND(AM28=0,BC28=0),"",(BC28-AM28)/AM28)))) | BG28: =+AQ28+BC28 -> 0 | BM28: =IF(AND(BC28=0,BJ28>0),100%,IF(AND(BC28<0,BJ28=0),(BC28-BJ28)/BC28,IF(AND(BC28>0,BJ28>0),(BJ28-BC28)/BC28,IF(AND(BC28=0,BJ28=0),"",(BJ28-BC28)/BC28)))) | BN28: =+BG28+BJ28 -> 0 | BT28: =IF(AND(BJ28=0,BQ28>0),100%,IF(AND(BJ28<0,BQ28=0),(BJ28-BQ28)/BJ28,IF(AND(BJ28>0,BQ28>0),(BQ28-BJ28)/BJ28,IF(AND(BJ28=0,BQ28=0),"",(BQ28-BJ28)/BJ28)))) | BU28: =+BN28+BQ28 -> 0 | BX28: =+AZ28*9 -> 0 | BZ28: =IF(AND(BX28=0,BU28>0),100%,IF(AND(BX28<0,BU28=0),(BX28-BU28)/BX28,IF(AND(BX28>0,BU28>0),(BU28-BX28)/BX28,IF(AND(BX28=0,BU28=0),"",(BU28-BX28)/BX28)))) | CD28: =IF(AND(BQ28=0,CA28>0),100%,IF(AND(BQ28<0,CA28=0),(BQ28-CA28)/BQ28,IF(AND(BQ28>0,CA28>0),(CA28-BQ28)/BQ28,IF(AND(BQ28=0,CA28=0),"",(CA28-BQ28)/BQ28)))) | CK28: =IF(AND(CA28=0,CH28>0),100%,IF(AND(CA28<0,CH28=0),(CA28-CH28)/CA28,IF(AND(CA28>0,CH28>0),(CH28-CA28)/CA28,IF(AND(CA28=0,CH28=0),"",(CH28-CA28)/CA28)))) | CL28: =+CE28+CH28 -> 0 | CR28: =IF(AND(CH28=0,CO28>0),100%,IF(AND(CH28<0,CO28=0),(CH28-CO28)/CH28,IF(AND(CH28>0,CO28>0),(CO28-CH28)/CH28,IF(AND(CH28=0,CO28=0),"",(CO28-CH28)/CH28)))) | CS28: =+CL28+CO28 -> 0 | CV28: =+AZ28*12 -> 0 | CX28: =IF(AND(CV28=0,CS28>0),100%,IF(AND(CV28<0,CS28=0),(CV28-CS28)/CV28,IF(AND(CV28>0,CS28>0),(CS28-CV28)/CV28,IF(AND(CV28=0,CS28=0),"",(CS28-CV28)/CV28))))
